Workbook

Sheet Data
B2: Database
D4: Categories | AA4: Stock performance | AK4: Earnings | CT4: P/E | EP4: Calendarization
AK6: 2 | AL6: > Input 1 for GAAP earnings, 2 for Adjusted earnings | ES6: GAAP | FS6: Adjusted
F8: Categories | P8: Subcategories | AK8: IS_COMP_NET_INCOME_GAAP | AZ8: IS_COMP_NET_INCOME_ADJUST | BO8: Calendarized | BZ8: Earnings growth ($) | CD8: Earnings growth (%) | CH8: Consensus revisions (%) | CN8: Consensus revisions ($) | ES8: Fiscal | FH8: Calendar | FS8: Fiscal | GH8: Calendar
F9: =COUNTIFS(F11:F510,"yes") -> 6 | G9: =COUNTIFS(G11:G510,"yes") -> 48 | H9: =COUNTIFS(H11:H510,"yes") -> 7 | I9: =COUNTIFS(I11:I510,"yes") -> 11 | AA9: Market cap ($b) | AE9: $Δ Mkt cap | AH9: Stock returns | AK9: 2024 | AL9: 2025 | AN9: 2026 | AO9: 2026 | AP9: 2026 | AR9: 2027 | AS9: 2027 | AT9: 2027 | AV9: 2028 | AW9: 2028 | AX9: 2028 | AZ9: 2024 | BA9: 2025 | BC9: 2026 | BD9: 2026 | BE9: 2026 | BG9: 2027 | BH9: 2027 | BI9: 2027 | BK9: 2028 | BL9: 2028 | BM9: 2028 | BO9: 2024 | BP9: 2025 | BR9: 2026 | BS9: 2026 | BT9: 2026 | BV9: 2027 | BW9: 2027 | BX9: 2027 | BZ9: 2025 | CA9: =BZ9+1 -> 2026 | CB9: =CA9+1 -> 2027 | CD9: 2025 | CE9: =CD9+1 -> 2026 | CF9: =CE9+1 -> 2027 | CH9: =BS9 -> 2026 | CI9: =BT9 -> 2026 | CK9: =BW9 -> 2027 | CL9: =BX9 -> 2027 | CN9: =BS9 -> 2026 | CO9: =BT9 -> 2026 | CQ9: =BW9 -> 2027 | CR9: =BX9 -> 2027 | CT9: NTM net income estimates | DR9: Market cap | ES9: 2024 | ET9: 2025 | EX9: 2026 | FB9: 2027 | FF9: 2028 | FH9: 2024 | FI9: 2025 | FM9: 2026 | FQ9: 2027 | FS9: 2024 | FT9: 2025 | FX9: 2026 | GB9: 2027 | GF9: 2028 | GH9: 2024 | GI9: 2025 | GM9: 2026 | GQ9: 2027
B10: Tickers | C10: Name | D10: Is compounder? | F10: AI Buildout Funders | G10: AI Capex Beneficiaries | H10: Infrastructure SW | I10: Application SW | J10: Other | K10: =F10 -> AI Buildout Funders | L10: =G10 -> AI Capex Beneficiaries | M10: =H10 -> Infrastructure SW | N10: =I10 -> Application SW | P10: AI capex - Sub categories | Q10: Digital Semis | R10: Memory | S10: Semicap | T10: Analog/MCU | U10: Power | V10: Electric/Cooling | W10: Hardware/Components | X10: Design | Y10: Construction | AA10: 46023 | AB10: 46112 | AC10: 46171 | AE10: YTD | AF10: QTD | AH10: YTD | AI10: QTD | AN10: =$AA$10 -> 46023 | AO10: =$AB$10 -> 46112 | AP10: =$AC$10 -> 46171 | AR10: =$AA$10 -> 46023 | AS10: =$AB$10 -> 46112 | AT10: =$AC$10 -> 46171 | AV10: =$AA$10 -> 46023 | AW10: =$AB$10 -> 46112 | AX10: =$AC$10 -> 46171 | BC10: =$AA$10 -> 46023 | BD10: =$AB$10 -> 46112 | BE10: =$AC$10 -> 46171 | BG10: =$AA$10 -> 46023 | BH10: =$AB$10 -> 46112 | BI10: =$AC$10 -> 46171 | BK10: =$AA$10 -> 46023 | BL10: =$AB$10 -> 46112 | BM10: =$AC$10 -> 46171 | BO10: Actual | BP10: Actual | BR10: =$AA$10 -> 46023 | BS10: =$AB$10 -> 46112 | BT10: =$AC$10 -> 46171 | BV10: =$AA$10 -> 46023 | BW10: =$AB$10 -> 46112 | BX10: =$AC$10 -> 46171 | BZ10: Actual | CA10: Est. | CB10: Est. | CD10: Actual | CE10: Est. | CF10: Est. | CH10: =$BS$10 -> 46112 | CI10: =$BT$10 -> 46171 | CK10: =$BS$10 -> 46112 | CL10: =$BT$10 -> 46171 | CN10: =$BS$10 -> 46112 | CO10: =$BT$10 -> 46171 | CQ10: =$BS$10 -> 46112 | CR10: =$BT$10 -> 46171 | CT10: =$BT$10 -> 46171 | CU10: 46112 | CV10: 46022 | CW10: 45930 | CX10: 45838 | CY10: 45747 | CZ10: 45657 | DA10: 45565 | DB10: 45473 | DC10: 45382 | DD10: 45291 | DE10: 45199 | DF10: 45107 | DG10: 45016 | DH10: 44926 | DI10: 44834 | DJ10: 44742 | DK10: 44651 | DL10: 44561 | DM10: 44469 | DN10: 44377 | DO10: 44286 | DP10: 44196 | DR10: =$BT$10 -> 46171 | DS10: 46112 | DT10: 46022 | DU10: 45930 | DV10: 45838 | DW10: 45747 | DX10: 45657 | DY10: 45565 | DZ10: 45473 | EA10: 45382 | EB10: 45291 | EC10: 45199 | ED10: 45107 | EE10: 45016 | EF10: 44926 | EG10: 44834 | EH10: 44742 | EI10: 44651 | EJ10: 44561 | EK10: 44469 | EL10: 44377 | EM10: 44286 | EN10: 44196 | EP10: FYE | EQ10: factor | EV10: =$AN$10 -> 46023 | EW10: =$AO$10 -> 46112 | EX10: =$AP$10 -> 46171 | EZ10: =$AN$10 -> 46023 | FA10: =$AO$10 -> 46112 | FB10: =$AP$10 -> 46171 | FD10: =$AN$10 -> 46023 | FE10: =$AO$10 -> 46112 | FF10: =$AP$10 -> 46171 | FK10: =$AN$10 -> 46023 | FL10: =$AO$10 -> 46112 | FM10: =$AP$10 -> 46171 | FO10: =$AN$10 -> 46023 | FP10: =$AO$10 -> 46112 | FQ10: =$AP$10 -> 46171 | FV10: =$AN$10 -> 46023 | FW10: =$AO$10 -> 46112 | FX10: =$AP$10 -> 46171 | FZ10: =$AN$10 -> 46023 | GA10: =$AO$10 -> 46112 | GB10: =$AP$10 -> 46171 | GD10: =$AN$10 -> 46023 | GE10: =$AO$10 -> 46112 | GF10: =$AP$10 -> 46171 | GK10: =$AN$10 -> 46023 | GL10: =$AO$10 -> 46112 | GM10: =$AP$10 -> 46171 | GO10: =$AN$10 -> 46023 | GP10: =$AO$10 -> 46112 | GQ10: =$AP$10 -> 46171
B11: NVDA US Equity | C11: Nvidia Corp | D11: =IFERROR(IF(MATCH($B11,Compounders!$A:$A,0),"yes"),"") -> yes | G11: yes | J11: =IF(AND(F11="",G11="",H11="",I11=""),"yes","") | K11: 0 | L11: 1 | M11: 0 | N11: 0 | P11: Digital Semis | Q11: 1 | R11: 0 | S11: 0 | T11: 0 | U11: 0 | V11: 0 | W11: 0 | X11: 0 | Y11: 0 | AA11: 4531.95 | AB11: 4237.92 | AC11: {=_xll.BQL(_xll.BQL.LIST($B11:$B510), "cur_mkt_cap(dates=" & _xll.BQL.DATE(AC$10) & ", currency=USD)/1E9", "fill=prev", "showids=f","showheaders=f")} -> 5109.588 | AE11: =$AC11-AA11 -> 577.638 | AF11: =$AC11-AB11 -> 871.668 | AH11: =$AC11/AA11-1 -> 0.12745904 | AI11: =$AC11/AB11-1 -> 0.20568298 | AK11: 29759 | AL11: {=_xll.BQL(_xll.BQL.LIST($B$11:$B$510),$AK$8&"(FPT=A, FPR="&AL$9&")","currency=USD","mode=cached","showids=f","showheaders=f")/10^6} -> 72880 | AN11: 113509.76 | AO11: 120067 | AP11: {=_xll.BQL(_xll.BQL.LIST($B$11:$B$510),$AK$8&"(FPT=A, FPR="&AP$9&")","dates="&_xll.BQL.DATE(AP$10),"currency=USD","mode=cached","showids=f","showheaders=f")/10^6} -> 120067 | AR11: 177521.81 | AS11: 202198.49 | AT11: {=_xll.BQL(_xll.BQL.LIST($B$11:$B$510),$AK$8&"(FPT=A, FPR="&AT$9&")","dates="&_xll.BQL.DATE(AT$10),"currency=USD","mode=cached","showids=f","showheaders=f")/10^6} -> 222791.14 | AV11: 224130.51 | AW11: 268488.89 | AX11: {=_xll.BQL(_xll.BQL.LIST($B$11:$B$510),$AK$8&"(FPT=A, FPR="&AX$9&")","dates="&_xll.BQL.DATE(AX$10),"currency=USD","mode=cached","showids=f","showheaders=f")/10^6} -> 303130.51 | AZ11: 32312 | BA11: {=_xll.BQL(_xll.BQL.LIST($B$11:$B$510),$AZ$8&"(FPT=A, FPR="&BA$9&")","currency=USD","mode=cached","showids=f","showheaders=f")/10^6} -> 74265 | BC11: 114796.15 | BD11: 116997 | BE11: {=_xll.BQL(_xll.BQL.LIST($B$11:$B$510),$AZ$8&"(FPT=A, FPR="&BE$9&")","dates="&_xll.BQL.DATE(BE$10),"currency=USD","mode=cached","showids=f","showheaders=f")/10^6} -> 116997 | BG11: 187965.84 | BH11: 202258.14 | BI11: {=_xll.BQL(_xll.BQL.LIST($B$11:$B$510),$AZ$8&"(FPT=A, FPR="&BI$9&")","dates="&_xll.BQL.DATE(BI$10),"currency=USD","mode=cached","showids=f","showheaders=f")/10^6} -> 216781.38 | BK11: 237197.7 | BL11: 267168.51 | BM11: {=_xll.BQL(_xll.BQL.LIST($B$11:$B$510),$AZ$8&"(FPT=A, FPR="&BM$9&")","dates="&_xll.BQL.DATE(BM$10),"currency=USD","mode=cached","showids=f","showheaders=f")/10^6} -> 306303.89 | BO11: =CHOOSE($AK$6,FH11,GH11) -> 71391.507 | BP11: =CHOOSE($AK$6,FI11,GI11) -> 114070.15 | BR11: =CHOOSE($AK$6,FK11,GK11) -> 182954.22 | BS11: =CHOOSE($AK$6,FL11,GL11) -> 196418.33 | BT11: =CHOOSE($AK$6,FM11,GM11) -> 209946.84 | BV11: =CHOOSE($AK$6,FO11,GO11) -> 233825.65 | BW11: =CHOOSE($AK$6,FP11,GP11) -> 262722.59 | BX11: =CHOOSE($AK$6,FQ11,GQ11) -> 300172.22 | BZ11: =BP11-BO11 -> 42678.644 | CA11: =BT11-BP11 -> 95876.686 | CB11: =BX11-BT11 -> 90225.379 | CD11: =BP11/BO11-1 -> 0.59781122 | CE11: =BT11/BP11-1 -> 0.84050635 | CF11: =BX11/BT11-1 -> 0.42975346 | CH11: =IFERROR(BS11/$BR11-1,"") -> 0.07359282 | CI11: =IFERROR(BT11/$BR11-1,"") -> 0.14753757 | CK11: =IFERROR(BW11/$BV11-1,"") -> 0.12358328 | CL11: =IFERROR(BX11/$BV11-1,"") -> 0.28374373 | CN11: =IFERROR(BS11-$BR11,"") -> 13464.117 | CO11: =IFERROR(BT11-$BR11,"") -> 26992.62 | CQ11: =IFERROR(BW11-$BV11,"") -> 28896.942 | CR11: =IFERROR(BX11-$BV11,"") -> 66346.563 | CT11: {=IFERROR(_xll.BQL(_xll.BQL.LIST($B$11:$B$510),"IS_COMP_NET_INCOME_ADJUST(FPT=LTM, FPO=1, AE=E)","dates="&_xll.BQL.DATE(CT$10),"currency=USD","mode=cached","fill=prev","showids=f","showheaders=f")/10^6,"")} -> 239615.35 | CU11: 202258.14 | CV11: 171315.54 | CW11: 145847.73 | CX11: 119341.18 | CY11: 111470.72 | CZ11: 97583.61 | DA11: 84441.126 | DB11: 72293.671 | DC11: 60934.569 | DD11: 48496.455 | DE11: 36446.689 | DF11: 21862.547 | DG11: 10957.571 | DH11: 9559.757 | DI11: 8610.0602 | DJ11: 13845.21 | DK11: 14464.677 | DL11: 12619.391 | DM11: 10989.674 | DN11: 10233.92 | DO11: 8427.3793 | DP11: 7063.2737 | DR11: =AC11 -> 5109.588 | DS11: 4237.92 | DT11: 4531.95 | DU11: 4533.894 | DV11: 3854.956 | DW11: 2644.472 | DX11: 3288.7621 | DY11: 2978.9232 | DZ11: 3039.084 | EA11: 2258.9 | EB11: 1223.1934 | EC11: 1074.4253 | ED11: 1044.8594 | EE11: 686.0919 | EF11: 359.5044 | EG11: 302.2611 | EH11: 378.975 | EI11: 684.8786 | EJ11: 735.275 | EK11: 517.9 | EL11: 498.4623 | EM11: 331.0366 | EN11: 323.2418 | EP11: 46047 | EQ11: =(DATE(2025,12,31)-EP11)/365 -> -0.068493151 | ES11: =AK11 -> 29759 | ET11: =AL11 -> 72880 | EV11: =AN11 -> 113509.76 | EW11: =AO11 -> 120067 | EX11: =AP11 -> 120067 | EZ11: =AR11 -> 177521.81 | FA11: =AS11 -> 202198.49 | FB11: =AT11 -> 222791.14 | FD11: =AV11 -> 224130.51 | FE11: =AW11 -> 268488.89 | FF11: =AX11 -> 303130.51 | FH11: =IFERROR(IF($EQ11<0,ES11*-$EQ11+ET11*(1+$EQ11),ES11*(1-$EQ11)+ET11*$EQ11),"") -> 69926.507 | FI11: =IFERROR(IF($EQ11<0,ET11*-$EQ11+EX11*(1+$EQ11),ET11*(1-$EQ11)+EX11*$EQ11),"") -> 116835.01 | FK11: =IFERROR(IF($EQ11<0,EV11*-$EQ11+EZ11*(1+$EQ11),EV11*(1-$EQ11)+EZ11*$EQ11),"") -> 173137.43 | FL11: =IFERROR(IF($EQ11<0,EW11*-$EQ11+FA11*(1+$EQ11),EW11*(1-$EQ11)+FA11*$EQ11),"") -> 196573.04 | FM11: =IFERROR(IF($EQ11<0,EX11*-$EQ11+FB11*(1+$EQ11),EX11*(1-$EQ11)+FB11*$EQ11),"") -> 215755.24 | FO11: =IFERROR(IF($EQ11<0,EZ11*-$EQ11+FD11*(1+$EQ11),EZ11*(1-$EQ11)+FD11*$EQ11),"") -> 220938.14 | FP11: =IFERROR(IF($EQ11<0,FA11*-$EQ11+FE11*(1+$EQ11),FA11*(1-$EQ11)+FE11*$EQ11),"") -> 263948.45 | FQ11: =IFERROR(IF($EQ11<0,FB11*-$EQ11+FF11*(1+$EQ11),FB11*(1-$EQ11)+FF11*$EQ11),"") -> 297627.81 | FS11: =AZ11 -> 32312 | FT11: =BA11 -> 74265 | FV11: =BC11 -> 114796.15 | FW11: =BD11 -> 116997 | FX11: =BE11 -> 116997 | FZ11: =BG11 -> 187965.84 | GA11: =BH11 -> 202258.14 | GB11: =BI11 -> 216781.38 | GD11: =BK11 -> 237197.7 | GE11: =BL11 -> 267168.51 | GF11: =BM11 -> 306303.89 | GH11: =IFERROR(IF($EQ11<0,FS11*-$EQ11+FT11*(1+$EQ11),FS11*(1-$EQ11)+FT11*$EQ11),"") -> 71391.507 | GI11: =IFERROR(IF($EQ11<0,FT11*-$EQ11+FX11*(1+$EQ11),FT11*(1-$EQ11)+FX11*$EQ11),"") -> 114070.15 | GK11: =IFERROR(IF($EQ11<0,FV11*-$EQ11+FZ11*(1+$EQ11),FV11*(1-$EQ11)+FZ11*$EQ11),"") -> 182954.22 | GL11: =IFERROR(IF($EQ11<0,FW11*-$EQ11+GA11*(1+$EQ11),FW11*(1-$EQ11)+GA11*$EQ11),"") -> 196418.33 | GM11: =IFERROR(IF($EQ11<0,FX11*-$EQ11+GB11*(1+$EQ11),FX11*(1-$EQ11)+GB11*$EQ11),"") -> 209946.84 | GO11: =IFERROR(IF($EQ11<0,FZ11*-$EQ11+GD11*(1+$EQ11),FZ11*(1-$EQ11)+GD11*$EQ11),"") -> 233825.65 | GP11: =IFERROR(IF($EQ11<0,GA11*-$EQ11+GE11*(1+$EQ11),GA11*(1-$EQ11)+GE11*$EQ11),"") -> 262722.59 | GQ11: =IFERROR(IF($EQ11<0,GB11*-$EQ11+GF11*(1+$EQ11),GB11*(1-$EQ11)+GF11*$EQ11),"") -> 300172.22
B12: AAPL US Equity | C12: Apple Inc | D12: =IFERROR(IF(MATCH($B12,Compounders!$A:$A,0),"yes"),"") -> yes | J12: =IF(AND(F12="",G12="",H12="",I12=""),"yes","") -> yes | K12: =K11+IF(F12="yes",1) -> 0 | L12: =L11+IF(G12="yes",1) -> 1 | M12: =M11+IF(H12="yes",1) -> 0 | N12: =N11+IF(I12="yes",1) -> 0 | Q12: =Q11+IF(Q$10=$P12,1) -> 1 | R12: =R11+IF(R$10=$P12,1) -> 0 | S12: =S11+IF(S$10=$P12,1) -> 0 | T12: =T11+IF(T$10=$P12,1) -> 0 | U12: =U11+IF(U$10=$P12,1) -> 0 | V12: =V11+IF(V$10=$P12,1) -> 0 | W12: =W11+IF(W$10=$P12,1) -> 0 | X12: =X11+IF(X$10=$P12,1) -> 0 | Y12: =Y11+IF(Y$10=$P12,1) -> 0 | AA12: 4017.0993 | AB12: 3725.9265 | AC12: 4583.3363 | AE12: =$AC12-AA12 -> 566.23699 | AF12: =$AC12-AB12 -> 857.40979 | AH12: =$AC12/AA12-1 -> 0.14095668 | AI12: =$AC12/AB12-1 -> 0.23011989 | AK12: 93736 | AL12: 112010 | AN12: 120866.63 | AO12: 124825.95 | AP12: 128442.54 | AR12: 131167.1 | AS12: 134476.1 | AT12: 138910.5 | AV12: 141223.48 | AW12: 143680.41 | AX12: 150837.88 | AZ12: 103982 | BA12: 112010 | BC12: 120866.63 | BD12: 124825.95 | BE12: 128442.54 | BG12: 131167.1 | BH12: 134476.1 | BI12: 138910.5 | BK12: 141223.48 | BL12: 143680.41 | BM12: 150837.88 | BO12: =CHOOSE($AK$6,FH12,GH12) -> 106071.48 | BP12: =CHOOSE($AK$6,FI12,GI12) -> 116286.96 | BR12: =CHOOSE($AK$6,FK12,GK12) -> 123547.58 | BS12: =CHOOSE($AK$6,FL12,GL12) -> 127337.63 | BT12: =CHOOSE($AK$6,FM12,GM12) -> 131167.08 | BV12: =CHOOSE($AK$6,FO12,GO12) -> 133784.51 | BW12: =CHOOSE($AK$6,FP12,GP12) -> 136871.74 | BX12: =CHOOSE($AK$6,FQ12,GQ12) -> 142014.89 | BZ12: =BP12-BO12 -> 10215.483 | CA12: =BT12-BP12 -> 14880.116 | CB12: =BX12-BT12 -> 10847.807 | CD12: =BP12/BO12-1 -> 0.096307542 | CE12: =BT12/BP12-1 -> 0.12796031 | CF12: =BX12/BT12-1 -> 0.082702212 | CH12: =BS12/$BR12-1 -> 0.030676895 | CI12: =BT12/$BR12-1 -> 0.061672609 | CK12: =BW12/$BV12-1 -> 0.023076102 | CL12: =BX12/$BV12-1 -> 0.061519622 | CN12: =IFERROR(BS12-$BR12,"") -> 3790.0561 | CO12: =IFERROR(BT12-$BR12,"") -> 7619.5015 | CQ12: =IFERROR(BW12-$BV12,"") -> 3087.225 | CR12: =IFERROR(BX12-$BV12,"") -> 8230.3727 | CT12: 132848.75 | CU12: 126234.23 | CV12: 120866.63 | CW12: 114929.72 | CX12: 104523.71 | CY12: 111961.42 | CZ12: 110886.21 | DA12: 109999.27 | DB12: 104592.41 | DC12: 102220.56 | DD12: 101365.05 | DE12: 99340.021 | DF12: 96837.006 | DG12: 96340.415 | DH12: 99066.326 | DI12: 99466.621 | DJ12: 99503.352 | DK12: 100700.77 | DL12: 93613.718 | DM12: 91789.6 | DN12: 84592.842 | DO12: 74118.56 | DP12: 66453.844 | DR12: =AC12 -> 4583.3363 | DS12: 3725.9265 | DT12: 4017.0993 | DU12: 3778.8085 | DV12: 3064.3834 | DW12: 3336.8531 | DX12: 3785.3044 | DY12: 3542.5639 | DZ12: 3229.6644 | EA12: 2647.9738 | EB12: 2994.3713 | EC12: 2676.7369 | ED12: 3050.8963 | EE12: 2609.0389 | EF12: 2066.9418 | EG12: 2220.9779 | EH12: 2212.8379 | EI12: 2849.5376 | EJ12: 2913.2839 | EK12: 2339.0185 | EL12: 2285.5379 | EM12: 2050.6659 | EN12: 2255.9691 | EP12: 45927 | EQ12: =(DATE(2025,12,31)-EP12)/365 -> 0.26027397 | ES12: =AK12 -> 93736 | ET12: =AL12 -> 112010 | EV12: =AN12 -> 120866.63 | EW12: =AO12 -> 124825.95 | EX12: =AP12 -> 128442.54 | EZ12: =AR12 -> 131167.1 | FA12: =AS12 -> 134476.1 | FB12: =AT12 -> 138910.5 | FD12: =AV12 -> 141223.48 | FE12: =AW12 -> 143680.41 | FF12: =AX12 -> 150837.88 | FH12: =IFERROR(IF($EQ12<0,ES12*-$EQ12+ET12*(1+$EQ12),ES12*(1-$EQ12)+ET12*$EQ12),"") -> 98492.247 | FI12: =IFERROR(IF($EQ12<0,ET12*-$EQ12+EX12*(1+$EQ12),ET12*(1-$EQ12)+EX12*$EQ12),"") -> 116286.96 | FK12: =IFERROR(IF($EQ12<0,EV12*-$EQ12+EZ12*(1+$EQ12),EV12*(1-$EQ12)+EZ12*$EQ12),"") -> 123547.58 | FL12: =IFERROR(IF($EQ12<0,EW12*-$EQ12+FA12*(1+$EQ12),EW12*(1-$EQ12)+FA12*$EQ12),"") -> 127337.63 | FM12: =IFERROR(IF($EQ12<0,EX12*-$EQ12+FB12*(1+$EQ12),EX12*(1-$EQ12)+FB12*$EQ12),"") -> 131167.08 | FO12: =IFERROR(IF($EQ12<0,EZ12*-$EQ12+FD12*(1+$EQ12),EZ12*(1-$EQ12)+FD12*$EQ12),"") -> 133784.51 | FP12: =IFERROR(IF($EQ12<0,FA12*-$EQ12+FE12*(1+$EQ12),FA12*(1-$EQ12)+FE12*$EQ12),"") -> 136871.74 | FQ12: =IFERROR(IF($EQ12<0,FB12*-$EQ12+FF12*(1+$EQ12),FB12*(1-$EQ12)+FF12*$EQ12),"") -> 142014.89 | FS12: =AZ12 -> 103982 | FT12: =BA12 -> 112010 | FV12: =BC12 -> 120866.63 | FW12: =BD12 -> 124825.95 | FX12: =BE12 -> 128442.54 | FZ12: =BG12 -> 131167.1 | GA12: =BH12 -> 134476.1 | GB12: =BI12 -> 138910.5 | GD12: =BK12 -> 141223.48 | GE12: =BL12 -> 143680.41 | GF12: =BM12 -> 150837.88 | GH12: =IFERROR(IF($EQ12<0,FS12*-$EQ12+FT12*(1+$EQ12),FS12*(1-$EQ12)+FT12*$EQ12),"") -> 106071.48 | GI12: =IFERROR(IF($EQ12<0,FT12*-$EQ12+FX12*(1+$EQ12),FT12*(1-$EQ12)+FX12*$EQ12),"") -> 116286.96 | GK12: =IFERROR(IF($EQ12<0,FV12*-$EQ12+FZ12*(1+$EQ12),FV12*(1-$EQ12)+FZ12*$EQ12),"") -> 123547.58 | GL12: =IFERROR(IF($EQ12<0,FW12*-$EQ12+GA12*(1+$EQ12),FW12*(1-$EQ12)+GA12*$EQ12),"") -> 127337.63 | GM12: =IFERROR(IF($EQ12<0,FX12*-$EQ12+GB12*(1+$EQ12),FX12*(1-$EQ12)+GB12*$EQ12),"") -> 131167.08 | GO12: =IFERROR(IF($EQ12<0,FZ12*-$EQ12+GD12*(1+$EQ12),FZ12*(1-$EQ12)+GD12*$EQ12),"") -> 133784.51 | GP12: =IFERROR(IF($EQ12<0,GA12*-$EQ12+GE12*(1+$EQ12),GA12*(1-$EQ12)+GE12*$EQ12),"") -> 136871.74 | GQ12: =IFERROR(IF($EQ12<0,GB12*-$EQ12+GF12*(1+$EQ12),GB12*(1-$EQ12)+GF12*$EQ12),"") -> 142014.89
B13: MSFT US Equity | C13: Microsoft Corp | D13: =IFERROR(IF(MATCH($B13,Compounders!$A:$A,0),"yes"),"") -> yes | F13: yes | J13: =IF(AND(F13="",G13="",H13="",I13=""),"yes","") | K13: =K12+IF(F13="yes",1) -> 1 | L13: =L12+IF(G13="yes",1) -> 1 | M13: =M12+IF(H13="yes",1) -> 0 | N13: =N12+IF(I13="yes",1) -> 0 | Q13: =Q12+IF(Q$10=$P13,1) -> 1 | R13: =R12+IF(R$10=$P13,1) -> 0 | S13: =S12+IF(S$10=$P13,1) -> 0 | T13: =T12+IF(T$10=$P13,1) -> 0 | U13: =U12+IF(U$10=$P13,1) -> 0 | V13: =V12+IF(V$10=$P13,1) -> 0 | W13: =W12+IF(W$10=$P13,1) -> 0 | X13: =X12+IF(X$10=$P13,1) -> 0 | Y13: =Y12+IF(Y$10=$P13,1) -> 0 | AA13: 3594.4465 | AB13: 2748.7451 | AC13: 3344.5784 | AE13: =$AC13-AA13 -> -249.86804 | AF13: =$AC13-AB13 -> 595.83333 | AH13: =$AC13/AA13-1 -> -0.069515026 | AI13: =$AC13/AB13-1 -> 0.21676558 | AK13: 88136 | AL13: 101832 | AN13: 119088.22 | AO13: 128403.73 | AP13: 128776.85 | AR13: 140470.26 | AS13: 141189.7 | AT13: 144016.85 | AV13: 166629.97 | AW13: 164861.68 | AX13: 170192.62 | AZ13: 88136 | BA13: 101832 | BC13: 119189 | BD13: 125185.24 | BE13: 127200.65 | BG13: 140598 | BH13: 141197.09 | BI13: 144001.13 | BK13: 167060.7 | BL13: 165016.55 | BM13: 170240.37 | BO13: =CHOOSE($AK$6,FH13,GH13) -> 95040.285 | BP13: =CHOOSE($AK$6,FI13,GI13) -> 114620.58 | BR13: =CHOOSE($AK$6,FK13,GK13) -> 129981.48 | BS13: =CHOOSE($AK$6,FL13,GL13) -> 133256.97 | BT13: =CHOOSE($AK$6,FM13,GM13) -> 135669.94 | BV13: =CHOOSE($AK$6,FO13,GO13) -> 153938.1 | BW13: =CHOOSE($AK$6,FP13,GP13) -> 153204.71 | BX13: =CHOOSE($AK$6,FQ13,GQ13) -> 157228.58 | BZ13: =BP13-BO13 -> 19580.296 | CA13: =BT13-BP13 -> 21049.355 | CB13: =BX13-BT13 -> 21558.646 | CD13: =BP13/BO13-1 -> 0.20602102 | CE13: =BT13/BP13-1 -> 0.18364376 | CF13: =BX13/BT13-1 -> 0.15890511 | CH13: =BS13/$BR13-1 -> 0.025199614 | CI13: =BT13/$BR13-1 -> 0.043763573 | CK13: =BW13/$BV13-1 -> -0.0047642149 | CL13: =BX13/$BV13-1 -> 0.021375353 | CN13: =IFERROR(BS13-$BR13,"") -> 3275.4831 | CO13: =IFERROR(BT13-$BR13,"") -> 5688.4541 | CQ13: =IFERROR(BW13-$BV13,"") -> -733.39419 | CR13: =IFERROR(BX13-$BV13,"") -> 3290.4812 | CT13: 138157.57 | CU13: 130587.72 | CV13: 124007.09 | CW13: 116133.15 | CX13: 108872.7 | CY13: 103650.11 | CZ13: 98685.021 | DA13: 98820.946 | DB13: 95586.238 | DC13: 90899.335 | DD13: 84863.259 | DE13: 82460.509 | DF13: 78676.438 | DG13: 73921.291 | DH13: 73450.078 | DI13: 77005.385 | DJ13: 76230.029 | DK13: 73755.079 | DL13: 70304.021 | DM13: 65861.407 | DN13: 61023.492 | DO13: 57040.592 | DP13: 51274.555 | DR13: =AC13 -> 3344.5784 | DS13: 2748.7451 | DT13: 3594.4465 | DU13: 3850.0085 | DV13: 3697.0216 | DW13: 2790.6426 | DX13: 3133.8022 | DY13: 3198.4364 | DZ13: 3321.8691 | EA13: 3126.1331 | EB13: 2794.8279 | EC13: 2345.9479 | ED13: 2532.0809 | EE13: 2146.0486 | EF13: 1787.7317 | EG13: 1736.943 | EH13: 1920.8401 | EI13: 2311.3589 | EJ13: 2525.084 | EK13: 2118.5981 | EL13: 2040.3035 | EM13: 1778.2282 | EN13: 1681.6055 | EP13: 45838 | EQ13: =(DATE(2025,12,31)-EP13)/365 -> 0.50410959 | ES13: =AK13 -> 88136 | ET13: =AL13 -> 101832 | EV13: =AN13 -> 119088.22 | EW13: =AO13 -> 128403.73 | EX13: =AP13 -> 128776.85 | EZ13: =AR13 -> 140470.26 | FA13: =AS13 -> 141189.7 | FB13: =AT13 -> 144016.85 | FD13: =AV13 -> 166629.97 | FE13: =AW13 -> 164861.68 | FF13: =AX13 -> 170192.62 | FH13: =IFERROR(IF($EQ13<0,ES13*-$EQ13+ET13*(1+$EQ13),ES13*(1-$EQ13)+ET13*$EQ13),"") -> 95040.285 | FI13: =IFERROR(IF($EQ13<0,ET13*-$EQ13+EX13*(1+$EQ13),ET13*(1-$EQ13)+EX13*$EQ13),"") -> 115415.16 | FK13: =IFERROR(IF($EQ13<0,EV13*-$EQ13+EZ13*(1+$EQ13),EV13*(1-$EQ13)+EZ13*$EQ13),"") -> 129867.11 | FL13: =IFERROR(IF($EQ13<0,EW13*-$EQ13+FA13*(1+$EQ13),EW13*(1-$EQ13)+FA13*$EQ13),"") -> 134849.26 | FM13: =IFERROR(IF($EQ13<0,EX13*-$EQ13+FB13*(1+$EQ13),EX13*(1-$EQ13)+FB13*$EQ13),"") -> 136459.48 | FO13: =IFERROR(IF($EQ13<0,EZ13*-$EQ13+FD13*(1+$EQ13),EZ13*(1-$EQ13)+FD13*$EQ13),"") -> 153657.62 | FP13: =IFERROR(IF($EQ13<0,FA13*-$EQ13+FE13*(1+$EQ13),FA13*(1-$EQ13)+FE13*$EQ13),"") -> 153122.97 | FQ13: =IFERROR(IF($EQ13<0,FB13*-$EQ13+FF13*(1+$EQ13),FB13*(1-$EQ13)+FF13*$EQ13),"") -> 157212.31 | FS13: =AZ13 -> 88136 | FT13: =BA13 -> 101832 | FV13: =BC13 -> 119189 | FW13: =BD13 -> 125185.24 | FX13: =BE13 -> 127200.65 | FZ13: =BG13 -> 140598 | GA13: =BH13 -> 141197.09 | GB13: =BI13 -> 144001.13 | GD13: =BK13 -> 167060.7 | GE13: =BL13 -> 165016.55 | GF13: =BM13 -> 170240.37 | GH13: =IFERROR(IF($EQ13<0,FS13*-$EQ13+FT13*(1+$EQ13),FS13*(1-$EQ13)+FT13*$EQ13),"") -> 95040.285 | GI13: =IFERROR(IF($EQ13<0,FT13*-$EQ13+FX13*(1+$EQ13),FT13*(1-$EQ13)+FX13*$EQ13),"") -> 114620.58 | GK13: =IFERROR(IF($EQ13<0,FV13*-$EQ13+FZ13*(1+$EQ13),FV13*(1-$EQ13)+FZ13*$EQ13),"") -> 129981.48 | GL13: =IFERROR(IF($EQ13<0,FW13*-$EQ13+GA13*(1+$EQ13),FW13*(1-$EQ13)+GA13*$EQ13),"") -> 133256.97 | GM13: =IFERROR(IF($EQ13<0,FX13*-$EQ13+GB13*(1+$EQ13),FX13*(1-$EQ13)+GB13*$EQ13),"") -> 135669.94 | GO13: =IFERROR(IF($EQ13<0,FZ13*-$EQ13+GD13*(1+$EQ13),FZ13*(1-$EQ13)+GD13*$EQ13),"") -> 153938.1 | GP13: =IFERROR(IF($EQ13<0,GA13*-$EQ13+GE13*(1+$EQ13),GA13*(1-$EQ13)+GE13*$EQ13),"") -> 153204.71 | GQ13: =IFERROR(IF($EQ13<0,GB13*-$EQ13+GF13*(1+$EQ13),GB13*(1-$EQ13)+GF13*$EQ13),"") -> 157228.58
B14: AMZN US Equity | C14: Amazon.Com Inc | D14: =IFERROR(IF(MATCH($B14,Compounders!$A:$A,0),"yes"),"") -> yes | F14: yes | J14: =IF(AND(F14="",G14="",H14="",I14=""),"yes","") | K14: =K13+IF(F14="yes",1) -> 2 | L14: =L13+IF(G14="yes",1) -> 1 | M14: =M13+IF(H14="yes",1) -> 0 | N14: =N13+IF(I14="yes",1) -> 0 | Q14: =Q13+IF(Q$10=$P14,1) -> 1 | R14: =R13+IF(R$10=$P14,1) -> 0 | S14: =S13+IF(S$10=$P14,1) -> 0 | T14: =T13+IF(T$10=$P14,1) -> 0 | U14: =U13+IF(U$10=$P14,1) -> 0 | V14: =V13+IF(V$10=$P14,1) -> 0 | W14: =W13+IF(W$10=$P14,1) -> 0 | X14: =X13+IF(X$10=$P14,1) -> 0 | Y14: =Y13+IF(Y$10=$P14,1) -> 0 | AA14: 2467.5157 | AB14: 2235.762 | AC14: 2911.3041 | AE14: =$AC14-AA14 -> 443.78844 | AF14: =$AC14-AB14 -> 675.54213 | AH14: =$AC14/AA14-1 -> 0.17985233 | AI14: =$AC14/AB14-1 -> 0.30215297 | AK14: 59248 | AL14: 77670 | AN14: 86268.183 | AO14: 84031.143 | AP14: 95575 | AR14: 106375.83 | AS14: 102734.7 | AT14: 109348 | AV14: 127335.65 | AW14: 125690.16 | AX14: 138157.55 | AZ14: 76636.69 | BA14: 93972.3 | BC14: 106189.65 | BD14: 103190.27 | BE14: 113552.29 | BG14: 133870.8 | BH14: 123224.07 | BI14: 127455.79 | BK14: 152436 | BL14: 148298.27 | BM14: 158947.4 | BO14: =CHOOSE($AK$6,FH14,GH14) -> 76636.69 | BP14: =CHOOSE($AK$6,FI14,GI14) -> 93972.3 | BR14: =CHOOSE($AK$6,FK14,GK14) -> 106189.65 | BS14: =CHOOSE($AK$6,FL14,GL14) -> 103190.27 | BT14: =CHOOSE($AK$6,FM14,GM14) -> 113552.29 | BV14: =CHOOSE($AK$6,FO14,GO14) -> 133870.8 | BW14: =CHOOSE($AK$6,FP14,GP14) -> 123224.07 | BX14: =CHOOSE($AK$6,FQ14,GQ14) -> 127455.79 | BZ14: =BP14-BO14 -> 17335.61 | CA14: =BT14-BP14 -> 19579.986 | CB14: =BX14-BT14 -> 13903.5 | CD14: =BP14/BO14-1 -> 0.2262051 | CE14: =BT14/BP14-1 -> 0.20835912 | CF14: =BX14/BT14-1 -> 0.12244139 | CH14: =BS14/$BR14-1 -> -0.028245507 | CI14: =BT14/$BR14-1 -> 0.069334807 | CK14: =BW14/$BV14-1 -> -0.079529915 | CL14: =BX14/$BV14-1 -> -0.047919444 | CN14: =IFERROR(BS14-$BR14,"") -> -2999.3804 | CO14: =IFERROR(BT14-$BR14,"") -> 7362.6387 | CQ14: =IFERROR(BW14-$BV14,"") -> -10646.733 | CR14: =IFERROR(BX14-$BV14,"") -> -6415.0143 | CT14: 107975.04 | CU14: 103190.27 | CV14: 103574.53 | CW14: 94350.325 | CX14: 88807.312 | CY14: 85390.421 | CZ14: 81145.327 | DA14: 74743.467 | DB14: 64273.934 | DC14: 51539.4 | DD14: 51479.619 | DE14: 33734.008 | DF14: 33601.678 | DG14: 30073.944 | DH14: 30636.001 | DI14: 29539.578 | DJ14: 32961.042 | DK14: 33544.067 | DL14: 32685.14 | DM14: 38664.791 | DN14: 37878.375 | DO14: 34492.4 | DP14: 28246.54 | DR14: =AC14 -> 2911.3041 | DS14: 2235.762 | DT14: 2467.5157 | DU14: 2341.6947 | DV14: 2329.1216 | DW14: 2016.324 | DX14: 2306.8883 | DY14: 1955.639 | DZ14: 2011.0807 | EA14: 1873.6758 | EB14: 1570.1526 | EC14: 1311.5925 | ED14: 1337.5397 | EE14: 1058.4395 | EF14: 856.93895 | EG14: 1151.1937 | EH14: 1080.624 | EI14: 1658.8073 | EJ14: 1691.0026 | EK14: 1663.6774 | EL14: 1734.9543 | EM14: 1558.0696 | EN14: 1634.1685 | EP14: 46022 | EQ14: =(DATE(2025,12,31)-EP14)/365 -> 0 | ES14: =AK14 -> 59248 | ET14: =AL14 -> 77670 | EV14: =AN14 -> 86268.183 | EW14: =AO14 -> 84031.143 | EX14: =AP14 -> 95575 | EZ14: =AR14 -> 106375.83 | FA14: =AS14 -> 102734.7 | FB14: =AT14 -> 109348 | FD14: =AV14 -> 127335.65 | FE14: =AW14 -> 125690.16 | FF14: =AX14 -> 138157.55 | FH14: =IFERROR(IF($EQ14<0,ES14*-$EQ14+ET14*(1+$EQ14),ES14*(1-$EQ14)+ET14*$EQ14),"") -> 59248 | FI14: =IFERROR(IF($EQ14<0,ET14*-$EQ14+EX14*(1+$EQ14),ET14*(1-$EQ14)+EX14*$EQ14),"") -> 77670 | FK14: =IFERROR(IF($EQ14<0,EV14*-$EQ14+EZ14*(1+$EQ14),EV14*(1-$EQ14)+EZ14*$EQ14),"") -> 86268.183 | FL14: =IFERROR(IF($EQ14<0,EW14*-$EQ14+FA14*(1+$EQ14),EW14*(1-$EQ14)+FA14*$EQ14),"") -> 84031.143 | FM14: =IFERROR(IF($EQ14<0,EX14*-$EQ14+FB14*(1+$EQ14),EX14*(1-$EQ14)+FB14*$EQ14),"") -> 95575 | FO14: =IFERROR(IF($EQ14<0,EZ14*-$EQ14+FD14*(1+$EQ14),EZ14*(1-$EQ14)+FD14*$EQ14),"") -> 106375.83 | FP14: =IFERROR(IF($EQ14<0,FA14*-$EQ14+FE14*(1+$EQ14),FA14*(1-$EQ14)+FE14*$EQ14),"") -> 102734.7 | FQ14: =IFERROR(IF($EQ14<0,FB14*-$EQ14+FF14*(1+$EQ14),FB14*(1-$EQ14)+FF14*$EQ14),"") -> 109348 | FS14: =AZ14 -> 76636.69 | FT14: =BA14 -> 93972.3 | FV14: =BC14 -> 106189.65 | FW14: =BD14 -> 103190.27 | FX14: =BE14 -> 113552.29 | FZ14: =BG14 -> 133870.8 | GA14: =BH14 -> 123224.07 | GB14: =BI14 -> 127455.79 | GD14: =BK14 -> 152436 | GE14: =BL14 -> 148298.27 | GF14: =BM14 -> 158947.4 | GH14: =IFERROR(IF($EQ14<0,FS14*-$EQ14+FT14*(1+$EQ14),FS14*(1-$EQ14)+FT14*$EQ14),"") -> 76636.69 | GI14: =IFERROR(IF($EQ14<0,FT14*-$EQ14+FX14*(1+$EQ14),FT14*(1-$EQ14)+FX14*$EQ14),"") -> 93972.3 | GK14: =IFERROR(IF($EQ14<0,FV14*-$EQ14+FZ14*(1+$EQ14),FV14*(1-$EQ14)+FZ14*$EQ14),"") -> 106189.65 | GL14: =IFERROR(IF($EQ14<0,FW14*-$EQ14+GA14*(1+$EQ14),FW14*(1-$EQ14)+GA14*$EQ14),"") -> 103190.27 | GM14: =IFERROR(IF($EQ14<0,FX14*-$EQ14+GB14*(1+$EQ14),FX14*(1-$EQ14)+GB14*$EQ14),"") -> 113552.29 | GO14: =IFERROR(IF($EQ14<0,FZ14*-$EQ14+GD14*(1+$EQ14),FZ14*(1-$EQ14)+GD14*$EQ14),"") -> 133870.8 | GP14: =IFERROR(IF($EQ14<0,GA14*-$EQ14+GE14*(1+$EQ14),GA14*(1-$EQ14)+GE14*$EQ14),"") -> 123224.07 | GQ14: =IFERROR(IF($EQ14<0,GB14*-$EQ14+GF14*(1+$EQ14),GB14*(1-$EQ14)+GF14*$EQ14),"") -> 127455.79
B15: GOOGL US Equity | C15: Alphabet Inc | D15: =IFERROR(IF(MATCH($B15,Compounders!$A:$A,0),"yes"),"") -> yes | F15: yes | J15: =IF(AND(F15="",G15="",H15="",I15=""),"yes","") | K15: =K14+IF(F15="yes",1) -> 3 | L15: =L14+IF(G15="yes",1) -> 1 | M15: =M14+IF(H15="yes",1) -> 0 | N15: =N14+IF(I15="yes",1) -> 0 | Q15: =Q14+IF(Q$10=$P15,1) -> 1 | R15: =R14+IF(R$10=$P15,1) -> 0 | S15: =S14+IF(S$10=$P15,1) -> 0 | T15: =T14+IF(T$10=$P15,1) -> 0 | U15: =U14+IF(U$10=$P15,1) -> 0 | V15: =V14+IF(V$10=$P15,1) -> 0 | W15: =W14+IF(W$10=$P15,1) -> 0 | X15: =X14+IF(X$10=$P15,1) -> 0 | Y15: =Y14+IF(Y$10=$P15,1) -> 0 | AA15: 3781.6334 | AB15: 3474.5138 | AC15: 4585.2321 | AE15: =$AC15-AA15 -> 803.5987 | AF15: =$AC15-AB15 -> 1110.7183 | AH15: =$AC15/AA15-1 -> 0.21250042 | AI15: =$AC15/AB15-1 -> 0.3196759 | AK15: 100118 | AL15: 132170 | AN15: 134313.87 | AO15: 140944.13 | AP15: 174690.25 | AR15: 156264.17 | AS15: 163481.46 | AT15: 180500.41 | AV15: 165369.81 | AW15: 188231.75 | AX15: 213237.58 | AZ15: 122903 | BA15: 157123 | BC15: 140407.26 | BD15: 148404.62 | BE15: 176123.76 | BG15: 166577.44 | BH15: 169467.22 | BI15: 182331.38 | BK15: 178076.43 | BL15: 195729 | BM15: 216381.81 | BO15: =CHOOSE($AK$6,FH15,GH15) -> 122903 | BP15: =CHOOSE($AK$6,FI15,GI15) -> 157123 | BR15: =CHOOSE($AK$6,FK15,GK15) -> 140407.26 | BS15: =CHOOSE($AK$6,FL15,GL15) -> 148404.62 | BT15: =CHOOSE($AK$6,FM15,GM15) -> 176123.76 | BV15: =CHOOSE($AK$6,FO15,GO15) -> 166577.44 | BW15: =CHOOSE($AK$6,FP15,GP15) -> 169467.22 | BX15: =CHOOSE($AK$6,FQ15,GQ15) -> 182331.38 | BZ15: =BP15-BO15 -> 34220 | CA15: =BT15-BP15 -> 19000.759 | CB15: =BX15-BT15 -> 6207.626 | CD15: =BP15/BO15-1 -> 0.27843096 | CE15: =BT15/BP15-1 -> 0.1209292 | CF15: =BX15/BT15-1 -> 0.035245818 | CH15: =BS15/$BR15-1 -> 0.056958297 | CI15: =BT15/$BR15-1 -> 0.25437789 | CK15: =BW15/$BV15-1 -> 0.017347933 | CL15: =BX15/$BV15-1 -> 0.09457427 | CN15: =IFERROR(BS15-$BR15,"") -> 7997.3582 | CO15: =IFERROR(BT15-$BR15,"") -> 35716.501 | CQ15: =IFERROR(BW15-$BV15,"") -> 2889.7743 | CR15: =IFERROR(BX15-$BV15,"") -> 15753.94 | CT15: 159738.18 | CU15: 148404.62 | CV15: 134524.28 | CW15: 135612.46 | CX15: 127953.88 | CY15: 113094.22 | CZ15: 112104.11 | DA15: 106537.99 | DB15: 100912.33 | DC15: 88458.514 | DD15: 86185.605 | DE15: 87765.62 | DF15: 77350.356 | DG15: 73546.135 | DH15: 76218.174 | DI15: 76973.7 | DJ15: 85616.052 | DK15: 81188.194 | DL15: 80842.917 | DM15: 82743.714 | DN15: 65481.369 | DO15: 54600.3 | DP15: 46104.5 | DR15: =AC15 -> 4585.2321 | DS15: 3474.5138 | DT15: 3781.6334 | DU15: 2942.6855 | DV15: 2145.38 | DW15: 1894.4855 | DX15: 2324.0225 | DY15: 2049.6776 | DZ15: 2258.6938 | EA15: 1884.633 | EB15: 1756.0003 | EC15: 1656.1899 | ED15: 1527.851 | EE15: 1330.2007 | EF15: 1145.2249 | EG15: 1250.9614 | EH15: 1437.7906 | EI15: 1842.3261 | EJ15: 1921.7766 | EK15: 1779.7672 | EL15: 1658.7588 | EM15: 1392.5618 | EN15: 1185.2636 | EP15: 46022 | EQ15: =(DATE(2025,12,31)-EP15)/365 -> 0 | ES15: =AK15 -> 100118 | ET15: =AL15 -> 132170 | EV15: =AN15 -> 134313.87 | EW15: =AO15 -> 140944.13 | EX15: =AP15 -> 174690.25 | EZ15: =AR15 -> 156264.17 | FA15: =AS15 -> 163481.46 | FB15: =AT15 -> 180500.41 | FD15: =AV15 -> 165369.81 | FE15: =AW15 -> 188231.75 | FF15: =AX15 -> 213237.58 | FH15: =IFERROR(IF($EQ15<0,ES15*-$EQ15+ET15*(1+$EQ15),ES15*(1-$EQ15)+ET15*$EQ15),"") -> 100118 | FI15: =IFERROR(IF($EQ15<0,ET15*-$EQ15+EX15*(1+$EQ15),ET15*(1-$EQ15)+EX15*$EQ15),"") -> 132170 | FK15: =IFERROR(IF($EQ15<0,EV15*-$EQ15+EZ15*(1+$EQ15),EV15*(1-$EQ15)+EZ15*$EQ15),"") -> 134313.87 | FL15: =IFERROR(IF($EQ15<0,EW15*-$EQ15+FA15*(1+$EQ15),EW15*(1-$EQ15)+FA15*$EQ15),"") -> 140944.13 | FM15: =IFERROR(IF($EQ15<0,EX15*-$EQ15+FB15*(1+$EQ15),EX15*(1-$EQ15)+FB15*$EQ15),"") -> 174690.25 | FO15: =IFERROR(IF($EQ15<0,EZ15*-$EQ15+FD15*(1+$EQ15),EZ15*(1-$EQ15)+FD15*$EQ15),"") -> 156264.17 | FP15: =IFERROR(IF($EQ15<0,FA15*-$EQ15+FE15*(1+$EQ15),FA15*(1-$EQ15)+FE15*$EQ15),"") -> 163481.46 | FQ15: =IFERROR(IF($EQ15<0,FB15*-$EQ15+FF15*(1+$EQ15),FB15*(1-$EQ15)+FF15*$EQ15),"") -> 180500.41 | FS15: =AZ15 -> 122903 | FT15: =BA15 -> 157123 | FV15: =BC15 -> 140407.26 | FW15: =BD15 -> 148404.62 | FX15: =BE15 -> 176123.76 | FZ15: =BG15 -> 166577.44 | GA15: =BH15 -> 169467.22 | GB15: =BI15 -> 182331.38 | GD15: =BK15 -> 178076.43 | GE15: =BL15 -> 195729 | GF15: =BM15 -> 216381.81 | GH15: =IFERROR(IF($EQ15<0,FS15*-$EQ15+FT15*(1+$EQ15),FS15*(1-$EQ15)+FT15*$EQ15),"") -> 122903 | GI15: =IFERROR(IF($EQ15<0,FT15*-$EQ15+FX15*(1+$EQ15),FT15*(1-$EQ15)+FX15*$EQ15),"") -> 157123 | GK15: =IFERROR(IF($EQ15<0,FV15*-$EQ15+FZ15*(1+$EQ15),FV15*(1-$EQ15)+FZ15*$EQ15),"") -> 140407.26 | GL15: =IFERROR(IF($EQ15<0,FW15*-$EQ15+GA15*(1+$EQ15),FW15*(1-$EQ15)+GA15*$EQ15),"") -> 148404.62 | GM15: =IFERROR(IF($EQ15<0,FX15*-$EQ15+GB15*(1+$EQ15),FX15*(1-$EQ15)+GB15*$EQ15),"") -> 176123.76 | GO15: =IFERROR(IF($EQ15<0,FZ15*-$EQ15+GD15*(1+$EQ15),FZ15*(1-$EQ15)+GD15*$EQ15),"") -> 166577.44 | GP15: =IFERROR(IF($EQ15<0,GA15*-$EQ15+GE15*(1+$EQ15),GA15*(1-$EQ15)+GE15*$EQ15),"") -> 169467.22 | GQ15: =IFERROR(IF($EQ15<0,GB15*-$EQ15+GF15*(1+$EQ15),GB15*(1-$EQ15)+GF15*$EQ15),"") -> 182331.38
B16: AVGO US Equity | C16: Broadcom Inc | D16: =IFERROR(IF(MATCH($B16,Compounders!$A:$A,0),"yes"),"") -> yes | G16: yes | J16: =IF(AND(F16="",G16="",H16="",I16=""),"yes","") | K16: =K15+IF(F16="yes",1) -> 3 | L16: =L15+IF(G16="yes",1) -> 2 | M16: =M15+IF(H16="yes",1) -> 0 | N16: =N15+IF(I16="yes",1) -> 0 | P16: Digital Semis | Q16: =Q15+IF(Q$10=$P16,1) -> 2 | R16: =R15+IF(R$10=$P16,1) -> 0 | S16: =S15+IF(S$10=$P16,1) -> 0 | T16: =T15+IF(T$10=$P16,1) -> 0 | U16: =U15+IF(U$10=$P16,1) -> 0 | V16: =V15+IF(V$10=$P16,1) -> 0 | W16: =W15+IF(W$10=$P16,1) -> 0 | X16: =X15+IF(X$10=$P16,1) -> 0 | Y16: =Y15+IF(Y$10=$P16,1) -> 0 | AA16: 1640.9549 | AB16: 1465.4271 | AC16: 2115.3077 | AE16: =$AC16-AA16 -> 474.35284 | AF16: =$AC16-AB16 -> 649.88055 | AH16: =$AC16/AA16-1 -> 0.28907123 | AI16: =$AC16/AB16-1 -> 0.44347517 | AK16: 5895 | AL16: 23126 | AN16: 37937.353 | AO16: 42675.886 | AP16: 43342.545 | AR16: 56828.931 | AS16: 72032.361 | AT16: 76026.03 | AV16: 72664.429 | AW16: 89805.167 | AX16: 93675.294 | AZ16: 23733 | BA16: 33728 | BC16: 50148.479 | BD16: 55036.87 | BE16: 55262.696 | BG16: 68076.952 | BH16: 83854.17 | BI16: 88346.042 | BK16: 82167.167 | BL16: 104316.38 | BM16: 111746.96 | BO16: =CHOOSE($AK$6,FH16,GH16) -> 25348.63 | BP16: =CHOOSE($AK$6,FI16,GI16) -> 37208.951 | BR16: =CHOOSE($AK$6,FK16,GK16) -> 53046.506 | BS16: =CHOOSE($AK$6,FL16,GL16) -> 59695.009 | BT16: =CHOOSE($AK$6,FM16,GM16) -> 60610.415 | BV16: =CHOOSE($AK$6,FO16,GO16) -> 70354.549 | BW16: =CHOOSE($AK$6,FP16,GP16) -> 87161.759 | BX16: =CHOOSE($AK$6,FQ16,GQ16) -> 92128.656 | BZ16: =BP16-BO16 -> 11860.321 | CA16: =BT16-BP16 -> 23401.464 | CB16: =BX16-BT16 -> 31518.241 | CD16: =BP16/BO16-1 -> 0.46788803 | CE16: =BT16/BP16-1 -> 0.62892028 | CF16: =BX16/BT16-1 -> 0.52001362 | CH16: =BS16/$BR16-1 -> 0.12533346 | CI16: =BT16/$BR16-1 -> 0.14259013 | CK16: =BW16/$BV16-1 -> 0.23889302 | CL16: =BX16/$BV16-1 -> 0.30949111 | CN16: =IFERROR(BS16-$BR16,"") -> 6648.5022 | CO16: =IFERROR(BT16-$BR16,"") -> 7563.9083 | CQ16: =IFERROR(BW16-$BV16,"") -> 16807.211 | CR16: =IFERROR(BX16-$BV16,"") -> 21774.107 | CT16: 64947.006 | CU16: 64630.735 | CV16: 50148.479 | CW16: 41535.531 | CX16: 36155.309 | CY16: 33767.324 | CZ16: 30887.114 | DA16: 29109.507 | DB16: 26971.011 | DC16: 24623.019 | DD16: 22632.923 | DE16: 19354.542 | DF16: 18678.145 | DG16: 18040.917 | DH16: 17555.778 | DI16: 17424.329 | DJ16: 17060.588 | DK16: 16152.939 | DL16: 14632.538 | DM16: 13626.427 | DN16: 12901.609 | DO16: 12292.605 | DP16: 11781.481 | DR16: =AC16 -> 2115.3077 | DS16: 1465.4271 | DT16: 1640.9549 | DU16: 1557.9554 | DV16: 1296.5118 | DW16: 787.24727 | DX16: 1086.7167 | DY16: 805.67437 | DZ16: 747.35555 | EA16: 614.22314 | EB16: 522.56191 | EC16: 342.80985 | ED16: 357.9757 | EE16: 267.47321 | EF16: 233.65268 | EG16: 179.8247 | EH16: 196.17868 | EI16: 257.08649 | EJ16: 274.73047 | EK16: 199.60509 | EL16: 195.62865 | EM16: 189.31346 | EN16: 178.07934 | EP16: 45963 | EQ16: =(DATE(2025,12,31)-EP16)/365 -> 0.16164384 | ES16: =AK16 -> 5895 | ET16: =AL16 -> 23126 | EV16: =AN16 -> 37937.353 | EW16: =AO16 -> 42675.886 | EX16: =AP16 -> 43342.545 | EZ16: =AR16 -> 56828.931 | FA16: =AS16 -> 72032.361 | FB16: =AT16 -> 76026.03 | FD16: =AV16 -> 72664.429 | FE16: =AW16 -> 89805.167 | FF16: =AX16 -> 93675.294 | FH16: =IFERROR(IF($EQ16<0,ES16*-$EQ16+ET16*(1+$EQ16),ES16*(1-$EQ16)+ET16*$EQ16),"") -> 8680.2849 | FI16: =IFERROR(IF($EQ16<0,ET16*-$EQ16+EX16*(1+$EQ16),ET16*(1-$EQ16)+EX16*$EQ16),"") -> 26393.88 | FK16: =IFERROR(IF($EQ16<0,EV16*-$EQ16+EZ16*(1+$EQ16),EV16*(1-$EQ16)+EZ16*$EQ16),"") -> 40991.06 | FL16: =IFERROR(IF($EQ16<0,EW16*-$EQ16+FA16*(1+$EQ16),EW16*(1-$EQ16)+FA16*$EQ16),"") -> 47421.179 | FM16: =IFERROR(IF($EQ16<0,EX16*-$EQ16+FB16*(1+$EQ16),EX16*(1-$EQ16)+FB16*$EQ16),"") -> 48625.629 | FO16: =IFERROR(IF($EQ16<0,EZ16*-$EQ16+FD16*(1+$EQ16),EZ16*(1-$EQ16)+FD16*$EQ16),"") -> 59388.642 | FP16: =IFERROR(IF($EQ16<0,FA16*-$EQ16+FE16*(1+$EQ16),FA16*(1-$EQ16)+FE16*$EQ16),"") -> 74905.226 | FQ16: =IFERROR(IF($EQ16<0,FB16*-$EQ16+FF16*(1+$EQ16),FB16*(1-$EQ16)+FF16*$EQ16),"") -> 78878.925 | FS16: =AZ16 -> 23733 | FT16: =BA16 -> 33728 | FV16: =BC16 -> 50148.479 | FW16: =BD16 -> 55036.87 | FX16: =BE16 -> 55262.696 | FZ16: =BG16 -> 68076.952 | GA16: =BH16 -> 83854.17 | GB16: =BI16 -> 88346.042 | GD16: =BK16 -> 82167.167 | GE16: =BL16 -> 104316.38 | GF16: =BM16 -> 111746.96 | GH16: =IFERROR(IF($EQ16<0,FS16*-$EQ16+FT16*(1+$EQ16),FS16*(1-$EQ16)+FT16*$EQ16),"") -> 25348.63 | GI16: =IFERROR(IF($EQ16<0,FT16*-$EQ16+FX16*(1+$EQ16),FT16*(1-$EQ16)+FX16*$EQ16),"") -> 37208.951 | GK16: =IFERROR(IF($EQ16<0,FV16*-$EQ16+FZ16*(1+$EQ16),FV16*(1-$EQ16)+FZ16*$EQ16),"") -> 53046.506 | GL16: =IFERROR(IF($EQ16<0,FW16*-$EQ16+GA16*(1+$EQ16),FW16*(1-$EQ16)+GA16*$EQ16),"") -> 59695.009 | GM16: =IFERROR(IF($EQ16<0,FX16*-$EQ16+GB16*(1+$EQ16),FX16*(1-$EQ16)+GB16*$EQ16),"") -> 60610.415 | GO16: =IFERROR(IF($EQ16<0,FZ16*-$EQ16+GD16*(1+$EQ16),FZ16*(1-$EQ16)+GD16*$EQ16),"") -> 70354.549 | GP16: =IFERROR(IF($EQ16<0,GA16*-$EQ16+GE16*(1+$EQ16),GA16*(1-$EQ16)+GE16*$EQ16),"") -> 87161.759 | GQ16: =IFERROR(IF($EQ16<0,GB16*-$EQ16+GF16*(1+$EQ16),GB16*(1-$EQ16)+GF16*$EQ16),"") -> 92128.656
B17: META US Equity | C17: Meta Platforms Inc | D17: =IFERROR(IF(MATCH($B17,Compounders!$A:$A,0),"yes"),"") -> yes | F17: yes | J17: =IF(AND(F17="",G17="",H17="",I17=""),"yes","") | K17: =K16+IF(F17="yes",1) -> 4 | L17: =L16+IF(G17="yes",1) -> 2 | M17: =M16+IF(H17="yes",1) -> 0 | N17: =N16+IF(I17="yes",1) -> 0 | Q17: =Q16+IF(Q$10=$P17,1) -> 2 | R17: =R16+IF(R$10=$P17,1) -> 0 | S17: =S16+IF(S$10=$P17,1) -> 0 | T17: =T16+IF(T$10=$P17,1) -> 0 | U17: =U16+IF(U$10=$P17,1) -> 0 | V17: =V16+IF(V$10=$P17,1) -> 0 | W17: =W16+IF(W$10=$P17,1) -> 0 | X17: =X16+IF(X$10=$P17,1) -> 0 | Y17: =Y16+IF(Y$10=$P17,1) -> 0 | AA17: 1664.132 | AB17: 1447.693 | AC17: 1605.5781 | AE17: =$AC17-AA17 -> -58.553826 | AF17: =$AC17-AB17 -> 157.88512 | AH17: =$AC17/AA17-1 -> -0.035185807 | AI17: =$AC17/AB17-1 -> 0.10905981 | AK17: 62360 | AL17: 60458 | AN17: 76025.673 | AO17: 76328.537 | AP17: 83865.738 | AR17: 85650.977 | AS17: 89154.84 | AT17: 89680.345 | AV17: 99493 | AW17: 104596.97 | AX17: 105220.19 | AZ17: 79050 | BA17: 80885 | BC17: 84822.5 | BD17: 86334.538 | BE17: 95659.929 | BG17: 95313.357 | BH17: 102975.08 | BI17: 105391.31 | BK17: 112790.8 | BL17: 124769 | BM17: 126084.78 | BO17: =CHOOSE($AK$6,FH17,GH17) -> 79050 | BP17: =CHOOSE($AK$6,FI17,GI17) -> 80885 | BR17: =CHOOSE($AK$6,FK17,GK17) -> 84822.5 | BS17: =CHOOSE($AK$6,FL17,GL17) -> 86334.538 | BT17: =CHOOSE($AK$6,FM17,GM17) -> 95659.929 | BV17: =CHOOSE($AK$6,FO17,GO17) -> 95313.357 | BW17: =CHOOSE($AK$6,FP17,GP17) -> 102975.08 | BX17: =CHOOSE($AK$6,FQ17,GQ17) -> 105391.31 | BZ17: =BP17-BO17 -> 1835 | CA17: =BT17-BP17 -> 14774.929 | CB17: =BX17-BT17 -> 9731.3791 | CD17: =BP17/BO17-1 -> 0.023213156 | CE17: =BT17/BP17-1 -> 0.18266587 | CF17: =BX17/BT17-1 -> 0.1017289 | CH17: =BS17/$BR17-1 -> 0.017825912 | CI17: =BT17/$BR17-1 -> 0.12776597 | CK17: =BW17/$BV17-1 -> 0.080384534 | CL17: =BX17/$BV17-1 -> 0.10573492 | CN17: =IFERROR(BS17-$BR17,"") -> 1512.0385 | CO17: =IFERROR(BT17-$BR17,"") -> 10837.429 | CQ17: =IFERROR(BW17-$BV17,"") -> 7661.7198 | CR17: =IFERROR(BX17-$BV17,"") -> 10077.951 | CT17: 92405.9 | CU17: 86334.538 | CV17: 82786.014 | CW17: 86423.917 | CX17: 82310.6 | CY17: 66606.158 | CZ17: 64595.788 | DA17: 59763.442 | DB17: 56288.146 | DC17: 54561.822 | DD17: 45566.67 | DE17: 40590.422 | DF17: 33983.011 | DG17: 27552.944 | DH17: 20620.242 | DI17: 26394.287 | DJ17: 33960.975 | DK17: 36131.476 | DL17: 40959.825 | DM17: 44898.027 | DN17: 44267.964 | DO17: 36349.417 | DP17: 30837.143 | DR17: =AC17 -> 1605.5781 | DS17: 1447.693 | DT17: 1664.132 | DU17: 1844.8665 | DV17: 1855.7998 | DW17: 1460.2999 | DX17: 1478.6429 | DY17: 1448.3425 | DZ17: 1279.1247 | EA17: 1237.9401 | EB17: 909.62861 | EC17: 772.48878 | ED17: 735.45284 | EE17: 549.48403 | EF17: 315.55519 | EG17: 364.64658 | EH17: 436.39465 | EI17: 605.25101 | EJ17: 935.64481 | EK17: 956.89127 | EL17: 985.91948 | EM17: 838.72423 | EN17: 778.03963 | EP17: 46022 | EQ17: =(DATE(2025,12,31)-EP17)/365 -> 0 | ES17: =AK17 -> 62360 | ET17: =AL17 -> 60458 | EV17: =AN17 -> 76025.673 | EW17: =AO17 -> 76328.537 | EX17: =AP17 -> 83865.738 | EZ17: =AR17 -> 85650.977 | FA17: =AS17 -> 89154.84 | FB17: =AT17 -> 89680.345 | FD17: =AV17 -> 99493 | FE17: =AW17 -> 104596.97 | FF17: =AX17 -> 105220.19 | FH17: =IFERROR(IF($EQ17<0,ES17*-$EQ17+ET17*(1+$EQ17),ES17*(1-$EQ17)+ET17*$EQ17),"") -> 62360 | FI17: =IFERROR(IF($EQ17<0,ET17*-$EQ17+EX17*(1+$EQ17),ET17*(1-$EQ17)+EX17*$EQ17),"") -> 60458 | FK17: =IFERROR(IF($EQ17<0,EV17*-$EQ17+EZ17*(1+$EQ17),EV17*(1-$EQ17)+EZ17*$EQ17),"") -> 76025.673 | FL17: =IFERROR(IF($EQ17<0,EW17*-$EQ17+FA17*(1+$EQ17),EW17*(1-$EQ17)+FA17*$EQ17),"") -> 76328.537 | FM17: =IFERROR(IF($EQ17<0,EX17*-$EQ17+FB17*(1+$EQ17),EX17*(1-$EQ17)+FB17*$EQ17),"") -> 83865.738 | FO17: =IFERROR(IF($EQ17<0,EZ17*-$EQ17+FD17*(1+$EQ17),EZ17*(1-$EQ17)+FD17*$EQ17),"") -> 85650.977 | FP17: =IFERROR(IF($EQ17<0,FA17*-$EQ17+FE17*(1+$EQ17),FA17*(1-$EQ17)+FE17*$EQ17),"") -> 89154.84 | FQ17: =IFERROR(IF($EQ17<0,FB17*-$EQ17+FF17*(1+$EQ17),FB17*(1-$EQ17)+FF17*$EQ17),"") -> 89680.345 | FS17: =AZ17 -> 79050 | FT17: =BA17 -> 80885 | FV17: =BC17 -> 84822.5 | FW17: =BD17 -> 86334.538 | FX17: =BE17 -> 95659.929 | FZ17: =BG17 -> 95313.357 | GA17: =BH17 -> 102975.08 | GB17: =BI17 -> 105391.31 | GD17: =BK17 -> 112790.8 | GE17: =BL17 -> 124769 | GF17: =BM17 -> 126084.78 | GH17: =IFERROR(IF($EQ17<0,FS17*-$EQ17+FT17*(1+$EQ17),FS17*(1-$EQ17)+FT17*$EQ17),"") -> 79050 | GI17: =IFERROR(IF($EQ17<0,FT17*-$EQ17+FX17*(1+$EQ17),FT17*(1-$EQ17)+FX17*$EQ17),"") -> 80885 | GK17: =IFERROR(IF($EQ17<0,FV17*-$EQ17+FZ17*(1+$EQ17),FV17*(1-$EQ17)+FZ17*$EQ17),"") -> 84822.5 | GL17: =IFERROR(IF($EQ17<0,FW17*-$EQ17+GA17*(1+$EQ17),FW17*(1-$EQ17)+GA17*$EQ17),"") -> 86334.538 | GM17: =IFERROR(IF($EQ17<0,FX17*-$EQ17+GB17*(1+$EQ17),FX17*(1-$EQ17)+GB17*$EQ17),"") -> 95659.929 | GO17: =IFERROR(IF($EQ17<0,FZ17*-$EQ17+GD17*(1+$EQ17),FZ17*(1-$EQ17)+GD17*$EQ17),"") -> 95313.357 | GP17: =IFERROR(IF($EQ17<0,GA17*-$EQ17+GE17*(1+$EQ17),GA17*(1-$EQ17)+GE17*$EQ17),"") -> 102975.08 | GQ17: =IFERROR(IF($EQ17<0,GB17*-$EQ17+GF17*(1+$EQ17),GB17*(1-$EQ17)+GF17*$EQ17),"") -> 105391.31
B18: TSLA US Equity | C18: Tesla Inc | D18: =IFERROR(IF(MATCH($B18,Compounders!$A:$A,0),"yes"),"") | F18: yes | J18: =IF(AND(F18="",G18="",H18="",I18=""),"yes","") | K18: =K17+IF(F18="yes",1) -> 5 | L18: =L17+IF(G18="yes",1) -> 2 | M18: =M17+IF(H18="yes",1) -> 0 | N18: =N17+IF(I18="yes",1) -> 0 | Q18: =Q17+IF(Q$10=$P18,1) -> 2 | R18: =R17+IF(R$10=$P18,1) -> 0 | S18: =S17+IF(S$10=$P18,1) -> 0 | T18: =T17+IF(T$10=$P18,1) -> 0 | U18: =U17+IF(U$10=$P18,1) -> 0 | V18: =V17+IF(V$10=$P18,1) -> 0 | W18: =W17+IF(W$10=$P18,1) -> 0 | X18: =X17+IF(X$10=$P18,1) -> 0 | Y18: =Y17+IF(Y$10=$P18,1) -> 0 | AA18: 1495.6874 | AB18: 1394.9666 | AC18: 1636.7069 | AE18: =$AC18-AA18 -> 141.01951 | AF18: =$AC18-AB18 -> 241.74032 | AH18: =$AC18/AA18-1 -> 0.09428408 | AI18: =$AC18/AB18-1 -> 0.1732947 | AK18: 7091 | AL18: 3794 | AN18: 6329.1053 | AO18: 5006.9744 | AP18: 4488.8947 | AR18: 9150.8929 | AS18: 7352.4054 | AT18: 6355.8056 | AV18: 13435 | AW18: 11110.24 | AX18: 9246.96 | AZ18: 8419 | BA18: 5858 | BC18: 7489.7895 | BD18: 6622.8696 | BE18: 6602.8605 | BG18: 10429.065 | BH18: 9207.9773 | BI18: 8636.6429 | BK18: 15791.133 | BL18: 12747.448 | BM18: 11892.5 | BO18: =CHOOSE($AK$6,FH18,GH18) -> 8419 | BP18: =CHOOSE($AK$6,FI18,GI18) -> 5858 | BR18: =CHOOSE($AK$6,FK18,GK18) -> 7489.7895 | BS18: =CHOOSE($AK$6,FL18,GL18) -> 6622.8696 | BT18: =CHOOSE($AK$6,FM18,GM18) -> 6602.8605 | BV18: =CHOOSE($AK$6,FO18,GO18) -> 10429.065 | BW18: =CHOOSE($AK$6,FP18,GP18) -> 9207.9773 | BX18: =CHOOSE($AK$6,FQ18,GQ18) -> 8636.6429 | BZ18: =BP18-BO18 -> -2561 | CA18: =BT18-BP18 -> 744.86047 | CB18: =BX18-BT18 -> 2033.7824 | CD18: =BP18/BO18-1 -> -0.3041929 | CE18: =BT18/BP18-1 -> 0.12715269 | CF18: =BX18/BT18-1 -> 0.30801535 | CH18: =BS18/$BR18-1 -> -0.1157469 | CI18: =BT18/$BR18-1 -> -0.11841842 | CK18: =BW18/$BV18-1 -> -0.11708502 | CL18: =BX18/$BV18-1 -> -0.17186792 | CN18: =IFERROR(BS18-$BR18,"") -> -866.91991 | CO18: =IFERROR(BT18-$BR18,"") -> -886.92901 | CQ18: =IFERROR(BW18-$BV18,"") -> -1221.0872 | CR18: =IFERROR(BX18-$BV18,"") -> -1792.4217 | CT18: 7187.1524 | CU18: 6622.8696 | CV18: 7046.0337 | CW18: 7026.4972 | CX18: 7497.767 | CY18: 9490.7755 | CZ18: 11197.672 | DA18: 9566.3201 | DB18: 9453.3492 | DC18: 10159.711 | DD18: 12503.858 | DE18: 13398.492 | DF18: 13084.688 | DG18: 14521.105 | DH18: 17887.471 | DI18: 17738.26 | DJ18: 15025.146 | DK18: 12067.156 | DL18: 9871.2105 | DM18: 7451.139 | DN18: 5601.1429 | DO18: 4692.4762 | DP18: 4358.375 | DR18: =AC18 -> 1636.7069 | DS18: 1394.9666 | DT18: 1495.6874 | DU18: 1478.7611 | DV18: 1023.1689 | DW18: 833.59256 | DX18: 1296.3505 | DY18: 835.81377 | DZ18: 631.07814 | EA18: 559.85431 | EB18: 789.89839 | EC18: 794.1969 | ED18: 829.68114 | EE18: 656.42475 | EF18: 388.97195 | EG18: 831.15293 | EH18: 697.92614 | EI18: 1113.7078 | EJ18: 1061.287 | EK18: 776.85053 | EL18: 654.77571 | EM18: 641.11495 | EN18: 668.90511 | EP18: 46022 | EQ18: =(DATE(2025,12,31)-EP18)/365 -> 0 | ES18: =AK18 -> 7091 | ET18: =AL18 -> 3794 | EV18: =AN18 -> 6329.1053 | EW18: =AO18 -> 5006.9744 | EX18: =AP18 -> 4488.8947 | EZ18: =AR18 -> 9150.8929 | FA18: =AS18 -> 7352.4054 | FB18: =AT18 -> 6355.8056 | FD18: =AV18 -> 13435 | FE18: =AW18 -> 11110.24 | FF18: =AX18 -> 9246.96 | FH18: =IFERROR(IF($EQ18<0,ES18*-$EQ18+ET18*(1+$EQ18),ES18*(1-$EQ18)+ET18*$EQ18),"") -> 7091 | FI18: =IFERROR(IF($EQ18<0,ET18*-$EQ18+EX18*(1+$EQ18),ET18*(1-$EQ18)+EX18*$EQ18),"") -> 3794 | FK18: =IFERROR(IF($EQ18<0,EV18*-$EQ18+EZ18*(1+$EQ18),EV18*(1-$EQ18)+EZ18*$EQ18),"") -> 6329.1053 | FL18: =IFERROR(IF($EQ18<0,EW18*-$EQ18+FA18*(1+$EQ18),EW18*(1-$EQ18)+FA18*$EQ18),"") -> 5006.9744 | FM18: =IFERROR(IF($EQ18<0,EX18*-$EQ18+FB18*(1+$EQ18),EX18*(1-$EQ18)+FB18*$EQ18),"") -> 4488.8947 | FO18: =IFERROR(IF($EQ18<0,EZ18*-$EQ18+FD18*(1+$EQ18),EZ18*(1-$EQ18)+FD18*$EQ18),"") -> 9150.8929 | FP18: =IFERROR(IF($EQ18<0,FA18*-$EQ18+FE18*(1+$EQ18),FA18*(1-$EQ18)+FE18*$EQ18),"") -> 7352.4054 | FQ18: =IFERROR(IF($EQ18<0,FB18*-$EQ18+FF18*(1+$EQ18),FB18*(1-$EQ18)+FF18*$EQ18),"") -> 6355.8056 | FS18: =AZ18 -> 8419 | FT18: =BA18 -> 5858 | FV18: =BC18 -> 7489.7895 | FW18: =BD18 -> 6622.8696 | FX18: =BE18 -> 6602.8605 | FZ18: =BG18 -> 10429.065 | GA18: =BH18 -> 9207.9773 | GB18: =BI18 -> 8636.6429 | GD18: =BK18 -> 15791.133 | GE18: =BL18 -> 12747.448 | GF18: =BM18 -> 11892.5 | GH18: =IFERROR(IF($EQ18<0,FS18*-$EQ18+FT18*(1+$EQ18),FS18*(1-$EQ18)+FT18*$EQ18),"") -> 8419 | GI18: =IFERROR(IF($EQ18<0,FT18*-$EQ18+FX18*(1+$EQ18),FT18*(1-$EQ18)+FX18*$EQ18),"") -> 5858 | GK18: =IFERROR(IF($EQ18<0,FV18*-$EQ18+FZ18*(1+$EQ18),FV18*(1-$EQ18)+FZ18*$EQ18),"") -> 7489.7895 | GL18: =IFERROR(IF($EQ18<0,FW18*-$EQ18+GA18*(1+$EQ18),FW18*(1-$EQ18)+GA18*$EQ18),"") -> 6622.8696 | GM18: =IFERROR(IF($EQ18<0,FX18*-$EQ18+GB18*(1+$EQ18),FX18*(1-$EQ18)+GB18*$EQ18),"") -> 6602.8605 | GO18: =IFERROR(IF($EQ18<0,FZ18*-$EQ18+GD18*(1+$EQ18),FZ18*(1-$EQ18)+GD18*$EQ18),"") -> 10429.065 | GP18: =IFERROR(IF($EQ18<0,GA18*-$EQ18+GE18*(1+$EQ18),GA18*(1-$EQ18)+GE18*$EQ18),"") -> 9207.9773 | GQ18: =IFERROR(IF($EQ18<0,GB18*-$EQ18+GF18*(1+$EQ18),GB18*(1-$EQ18)+GF18*$EQ18),"") -> 8636.6429
B19: MU US Equity | C19: Micron Technology Inc | D19: =IFERROR(IF(MATCH($B19,Compounders!$A:$A,0),"yes"),"") | G19: yes | J19: =IF(AND(F19="",G19="",H19="",I19=""),"yes","") | K19: =K18+IF(F19="yes",1) -> 5 | L19: =L18+IF(G19="yes",1) -> 3 | M19: =M18+IF(H19="yes",1) -> 0 | N19: =N18+IF(I19="yes",1) -> 0 | P19: Memory | Q19: =Q18+IF(Q$10=$P19,1) -> 2 | R19: =R18+IF(R$10=$P19,1) -> 1 | S19: =S18+IF(S$10=$P19,1) -> 0 | T19: =T18+IF(T$10=$P19,1) -> 0 | U19: =U18+IF(U$10=$P19,1) -> 0 | V19: =V18+IF(V$10=$P19,1) -> 0 | W19: =W18+IF(W$10=$P19,1) -> 0 | X19: =X18+IF(X$10=$P19,1) -> 0 | Y19: =Y18+IF(Y$10=$P19,1) -> 0 | AA19: 321.2316 | AB19: 380.99367 | AC19: 1095.0298 | AE19: =$AC19-AA19 -> 773.79817 | AF19: =$AC19-AB19 -> 714.03609 | AH19: =$AC19/AA19-1 -> 2.4088482 | AI19: =$AC19/AB19-1 -> 1.8741416 | AK19: 778 | AL19: 8539 | AN19: 34331.692 | AO19: 62546.485 | AP19: 66943.176 | AR19: 45438.458 | AS19: 104754.9 | AT19: 119493.25 | AV19: 40920.917 | AW19: 89387.056 | AX19: 116308.33 | AZ19: 1472 | BA19: 9470 | BC19: 35433.114 | BD19: 63338.41 | BE19: 68166.553 | BG19: 45249.697 | BH19: 103395.43 | BI19: 121897.62 | BK19: 41320.375 | BL19: 82777.087 | BM19: 115571.86 | BO19: =CHOOSE($AK$6,FH19,GH19) -> 4211.0411 | BP19: =CHOOSE($AK$6,FI19,GI19) -> 29571.559 | BR19: =CHOOSE($AK$6,FK19,GK19) -> 38794.958 | BS19: =CHOOSE($AK$6,FL19,GL19) -> 77056.569 | BT19: =CHOOSE($AK$6,FM19,GM19) -> 86567.604 | BV19: =CHOOSE($AK$6,FO19,GO19) -> 43904.039 | BW19: =CHOOSE($AK$6,FP19,GP19) -> 96334.355 | BX19: =CHOOSE($AK$6,FQ19,GQ19) -> 119731.26 | BZ19: =BP19-BO19 -> 25360.518 | CA19: =BT19-BP19 -> 56996.045 | CB19: =BX19-BT19 -> 33163.66 | CD19: =BP19/BO19-1 -> 6.0223867 | CE19: =BT19/BP19-1 -> 1.927394 | CF19: =BX19/BT19-1 -> 0.38309551 | CH19: =BS19/$BR19-1 -> 0.98625216 | CI19: =BT19/$BR19-1 -> 1.2314138 | CK19: =BW19/$BV19-1 -> 1.1942026 | CL19: =BX19/$BV19-1 -> 1.7271128 | CN19: =IFERROR(BS19-$BR19,"") -> 38261.611 | CO19: =IFERROR(BT19-$BR19,"") -> 47772.646 | CQ19: =IFERROR(BW19-$BV19,"") -> 52430.316 | CR19: =IFERROR(BX19-$BV19,"") -> 75827.225 | CT19: 110653.52 | CU19: 104059.25 | CV19: 40271.475 | CW19: 17651.816 | CX19: 12980.255 | CY19: 10221.453 | CZ19: 9157.2081 | DA19: 10042.839 | DB19: 8539.5695 | DC19: 5131.4486 | DD19: 1867.9303 | DE19: -1644.8485 | DF19: -2757.2481 | DG19: -3290.4008 | DH19: -1434.6076 | DI19: 1768.9133 | DJ19: 9912.6121 | DK19: 13190.749 | DL19: 11098.994 | DM19: 10332.045 | DN19: 12370.204 | DO19: 9452.1016 | DP19: 4187 | DR19: =AC19 -> 1095.0298 | DS19: 380.99367 | DT19: 321.2316 | DU19: 187.25201 | DV19: 137.93217 | DW19: 97.10579 | DX19: 93.76871 | DY19: 114.99793 | DZ19: 145.8459 | EA19: 130.54763 | EB19: 94.207584 | EC19: 74.513368 | ED19: 69.124484 | EE19: 66.035755 | EF19: 54.537004 | EG19: 55.26757 | EH19: 61.729344 | EI19: 86.977181 | EJ19: 104.34381 | EK19: 79.905988 | EL19: 95.297894 | EM19: 98.678012 | EN19: 83.969196 | EP19: 45897 | EQ19: =(DATE(2025,12,31)-EP19)/365 -> 0.34246575 | ES19: =AK19 -> 778 | ET19: =AL19 -> 8539 | EV19: =AN19 -> 34331.692 | EW19: =AO19 -> 62546.485 | EX19: =AP19 -> 66943.176 | EZ19: =AR19 -> 45438.458 | FA19: =AS19 -> 104754.9 | FB19: =AT19 -> 119493.25 | FD19: =AV19 -> 40920.917 | FE19: =AW19 -> 89387.056 | FF19: =AX19 -> 116308.33 | FH19: =IFERROR(IF($EQ19<0,ES19*-$EQ19+ET19*(1+$EQ19),ES19*(1-$EQ19)+ET19*$EQ19),"") -> 3435.8767 | FI19: =IFERROR(IF($EQ19<0,ET19*-$EQ19+EX19*(1+$EQ19),ET19*(1-$EQ19)+EX19*$EQ19),"") -> 28540.43 | FK19: =IFERROR(IF($EQ19<0,EV19*-$EQ19+EZ19*(1+$EQ19),EV19*(1-$EQ19)+EZ19*$EQ19),"") -> 38135.379 | FL19: =IFERROR(IF($EQ19<0,EW19*-$EQ19+FA19*(1+$EQ19),EW19*(1-$EQ19)+FA19*$EQ19),"") -> 77001.423 | FM19: =IFERROR(IF($EQ19<0,EX19*-$EQ19+FB19*(1+$EQ19),EX19*(1-$EQ19)+FB19*$EQ19),"") -> 84939.777 | FO19: =IFERROR(IF($EQ19<0,EZ19*-$EQ19+FD19*(1+$EQ19),EZ19*(1-$EQ19)+FD19*$EQ19),"") -> 43891.355 | FP19: =IFERROR(IF($EQ19<0,FA19*-$EQ19+FE19*(1+$EQ19),FA19*(1-$EQ19)+FE19*$EQ19),"") -> 99491.942 | FQ19: =IFERROR(IF($EQ19<0,FB19*-$EQ19+FF19*(1+$EQ19),FB19*(1-$EQ19)+FF19*$EQ19),"") -> 118402.53 | FS19: =AZ19 -> 1472 | FT19: =BA19 -> 9470 | FV19: =BC19 -> 35433.114 | FW19: =BD19 -> 63338.41 | FX19: =BE19 -> 68166.553 | FZ19: =BG19 -> 45249.697 | GA19: =BH19 -> 103395.43 | GB19: =BI19 -> 121897.62 | GD19: =BK19 -> 41320.375 | GE19: =BL19 -> 82777.087 | GF19: =BM19 -> 115571.86 | GH19: =IFERROR(IF($EQ19<0,FS19*-$EQ19+FT19*(1+$EQ19),FS19*(1-$EQ19)+FT19*$EQ19),"") -> 4211.0411 | GI19: =IFERROR(IF($EQ19<0,FT19*-$EQ19+FX19*(1+$EQ19),FT19*(1-$EQ19)+FX19*$EQ19),"") -> 29571.559 | GK19: =IFERROR(IF($EQ19<0,FV19*-$EQ19+FZ19*(1+$EQ19),FV19*(1-$EQ19)+FZ19*$EQ19),"") -> 38794.958 | GL19: =IFERROR(IF($EQ19<0,FW19*-$EQ19+GA19*(1+$EQ19),FW19*(1-$EQ19)+GA19*$EQ19),"") -> 77056.569 | GM19: =IFERROR(IF($EQ19<0,FX19*-$EQ19+GB19*(1+$EQ19),FX19*(1-$EQ19)+GB19*$EQ19),"") -> 86567.604 | GO19: =IFERROR(IF($EQ19<0,FZ19*-$EQ19+GD19*(1+$EQ19),FZ19*(1-$EQ19)+GD19*$EQ19),"") -> 43904.039 | GP19: =IFERROR(IF($EQ19<0,GA19*-$EQ19+GE19*(1+$EQ19),GA19*(1-$EQ19)+GE19*$EQ19),"") -> 96334.355 | GQ19: =IFERROR(IF($EQ19<0,GB19*-$EQ19+GF19*(1+$EQ19),GB19*(1-$EQ19)+GF19*$EQ19),"") -> 119731.26
B20: BRK/B US Equity | C20: Berkshire Hathaway Inc | D20: =IFERROR(IF(MATCH($B20,Compounders!$A:$A,0),"yes"),"") | J20: =IF(AND(F20="",G20="",H20="",I20=""),"yes","") -> yes | K20: =K19+IF(F20="yes",1) -> 5 | L20: =L19+IF(G20="yes",1) -> 3 | M20: =M19+IF(H20="yes",1) -> 0 | N20: =N19+IF(I20="yes",1) -> 0 | Q20: =Q19+IF(Q$10=$P20,1) -> 2 | R20: =R19+IF(R$10=$P20,1) -> 1 | S20: =S19+IF(S$10=$P20,1) -> 0 | T20: =T19+IF(T$10=$P20,1) -> 0 | U20: =U19+IF(U$10=$P20,1) -> 0 | V20: =V19+IF(V$10=$P20,1) -> 0 | W20: =W19+IF(W$10=$P20,1) -> 0 | X20: =X19+IF(X$10=$P20,1) -> 0 | Y20: =Y19+IF(Y$10=$P20,1) -> 0 | AA20: 1084.816 | AB20: 1033.2357 | AC20: 1022.9695 | AE20: =$AC20-AA20 -> -61.846493 | AF20: =$AC20-AB20 -> -10.266173 | AH20: =$AC20/AA20-1 -> -0.057011044 | AI20: =$AC20/AB20-1 -> -0.0099359451 | AK20: 88995 | AL20: 66968 | AN20: 49656.25 | AO20: 46032 | AP20: 47298.5 | AR20: 48339 | AS20: 50020.25 | AT20: 49076.25 | AV20: 54469 | AW20: 52118 | AX20: 46286 | AZ20: 47437 | BA20: 44486 | BC20: 46396 | BD20: 45160.25 | BE20: 45521.5 | BG20: 48339 | BH20: 46648.25 | BI20: 45720.5 | BK20: 54469 | BL20: 52118 | BM20: 46286 | BO20: =CHOOSE($AK$6,FH20,GH20) -> 47437 | BP20: =CHOOSE($AK$6,FI20,GI20) -> 44486 | BR20: =CHOOSE($AK$6,FK20,GK20) -> 46396 | BS20: =CHOOSE($AK$6,FL20,GL20) -> 45160.25 | BT20: =CHOOSE($AK$6,FM20,GM20) -> 45521.5 | BV20: =CHOOSE($AK$6,FO20,GO20) -> 48339 | BW20: =CHOOSE($AK$6,FP20,GP20) -> 46648.25 | BX20: =CHOOSE($AK$6,FQ20,GQ20) -> 45720.5 | BZ20: =BP20-BO20 -> -2951 | CA20: =BT20-BP20 -> 1035.5 | CB20: =BX20-BT20 -> 199 | CD20: =BP20/BO20-1 -> -0.062208824 | CE20: =BT20/BP20-1 -> 0.023276986 | CF20: =BX20/BT20-1 -> 0.0043715607 | CH20: =BS20/$BR20-1 -> -0.026634839 | CI20: =BT20/$BR20-1 -> -0.018848608 | CK20: =BW20/$BV20-1 -> -0.034976934 | CL20: =BX20/$BV20-1 -> -0.054169511 | CN20: =IFERROR(BS20-$BR20,"") -> -1235.75 | CO20: =IFERROR(BT20-$BR20,"") -> -874.5 | CQ20: =IFERROR(BW20-$BV20,"") -> -1690.75 | CR20: =IFERROR(BX20-$BV20,"") -> -2618.5 | CT20: 43498.5 | CU20: 45160.25 | CV20: 45079 | CW20: 45472.5 | CX20: 45437 | CY20: 44377.667 | CZ20: 41445.167 | DA20: 41289 | DB20: 39005 | DC20: 38688 | DD20: 36360 | DE20: 35669.5 | DF20: 33116.5 | DG20: 28574 | DH20: 33564 | DI20: 30463.667 | DJ20: 28622.5 | DK20: 28591 | DL20: 27266.5 | DM20: 26969 | DN20: 25650 | DO20: 23561 | DP20: 22937 | DR20: =AC20 -> 1022.9695 | DS20: 1033.2357 | DT20: 1084.816 | DU20: 1084.6254 | DV20: 1048.0477 | DW20: 1148.7201 | DX20: 978.01042 | DY20: 992.31738 | DZ20: 877.88081 | EA20: 908.91949 | EB20: 776.89179 | EC20: 763.98636 | ED20: 745.28402 | EE20: 675.65699 | EF20: 681.92096 | EG20: 591.27787 | EH20: 602.01131 | EI20: 779.54232 | EJ20: 669.12203 | EK20: 618.22815 | EL20: 635.74418 | EM20: 587.82314 | EN20: 543.67851 | EP20: 46022 | EQ20: =(DATE(2025,12,31)-EP20)/365 -> 0 | ES20: =AK20 -> 88995 | ET20: =AL20 -> 66968 | EV20: =AN20 -> 49656.25 | EW20: =AO20 -> 46032 | EX20: =AP20 -> 47298.5 | EZ20: =AR20 -> 48339 | FA20: =AS20 -> 50020.25 | FB20: =AT20 -> 49076.25 | FD20: =AV20 -> 54469 | FE20: =AW20 -> 52118 | FF20: =AX20 -> 46286 | FH20: =IFERROR(IF($EQ20<0,ES20*-$EQ20+ET20*(1+$EQ20),ES20*(1-$EQ20)+ET20*$EQ20),"") -> 88995 | FI20: =IFERROR(IF($EQ20<0,ET20*-$EQ20+EX20*(1+$EQ20),ET20*(1-$EQ20)+EX20*$EQ20),"") -> 66968 | FK20: =IFERROR(IF($EQ20<0,EV20*-$EQ20+EZ20*(1+$EQ20),EV20*(1-$EQ20)+EZ20*$EQ20),"") -> 49656.25 | FL20: =IFERROR(IF($EQ20<0,EW20*-$EQ20+FA20*(1+$EQ20),EW20*(1-$EQ20)+FA20*$EQ20),"") -> 46032 | FM20: =IFERROR(IF($EQ20<0,EX20*-$EQ20+FB20*(1+$EQ20),EX20*(1-$EQ20)+FB20*$EQ20),"") -> 47298.5 | FO20: =IFERROR(IF($EQ20<0,EZ20*-$EQ20+FD20*(1+$EQ20),EZ20*(1-$EQ20)+FD20*$EQ20),"") -> 48339 | FP20: =IFERROR(IF($EQ20<0,FA20*-$EQ20+FE20*(1+$EQ20),FA20*(1-$EQ20)+FE20*$EQ20),"") -> 50020.25 | FQ20: =IFERROR(IF($EQ20<0,FB20*-$EQ20+FF20*(1+$EQ20),FB20*(1-$EQ20)+FF20*$EQ20),"") -> 49076.25 | FS20: =AZ20 -> 47437 | FT20: =BA20 -> 44486 | FV20: =BC20 -> 46396 | FW20: =BD20 -> 45160.25 | FX20: =BE20 -> 45521.5 | FZ20: =BG20 -> 48339 | GA20: =BH20 -> 46648.25 | GB20: =BI20 -> 45720.5 | GD20: =BK20 -> 54469 | GE20: =BL20 -> 52118 | GF20: =BM20 -> 46286 | GH20: =IFERROR(IF($EQ20<0,FS20*-$EQ20+FT20*(1+$EQ20),FS20*(1-$EQ20)+FT20*$EQ20),"") -> 47437 | GI20: =IFERROR(IF($EQ20<0,FT20*-$EQ20+FX20*(1+$EQ20),FT20*(1-$EQ20)+FX20*$EQ20),"") -> 44486 | GK20: =IFERROR(IF($EQ20<0,FV20*-$EQ20+FZ20*(1+$EQ20),FV20*(1-$EQ20)+FZ20*$EQ20),"") -> 46396 | GL20: =IFERROR(IF($EQ20<0,FW20*-$EQ20+GA20*(1+$EQ20),FW20*(1-$EQ20)+GA20*$EQ20),"") -> 45160.25 | GM20: =IFERROR(IF($EQ20<0,FX20*-$EQ20+GB20*(1+$EQ20),FX20*(1-$EQ20)+GB20*$EQ20),"") -> 45521.5 | GO20: =IFERROR(IF($EQ20<0,FZ20*-$EQ20+GD20*(1+$EQ20),FZ20*(1-$EQ20)+GD20*$EQ20),"") -> 48339 | GP20: =IFERROR(IF($EQ20<0,GA20*-$EQ20+GE20*(1+$EQ20),GA20*(1-$EQ20)+GE20*$EQ20),"") -> 46648.25 | GQ20: =IFERROR(IF($EQ20<0,GB20*-$EQ20+GF20*(1+$EQ20),GB20*(1-$EQ20)+GF20*$EQ20),"") -> 45720.5
B21: LLY US Equity | C21: Eli Lilly & Co | D21: =IFERROR(IF(MATCH($B21,Compounders!$A:$A,0),"yes"),"") | J21: =IF(AND(F21="",G21="",H21="",I21=""),"yes","") -> yes | K21: =K20+IF(F21="yes",1) -> 5 | L21: =L20+IF(G21="yes",1) -> 3 | M21: =M20+IF(H21="yes",1) -> 0 | N21: =N20+IF(I21="yes",1) -> 0 | Q21: =Q20+IF(Q$10=$P21,1) -> 2 | R21: =R20+IF(R$10=$P21,1) -> 1 | S21: =S20+IF(S$10=$P21,1) -> 0 | T21: =T20+IF(T$10=$P21,1) -> 0 | U21: =U20+IF(U$10=$P21,1) -> 0 | V21: =V20+IF(V$10=$P21,1) -> 0 | W21: =W20+IF(W$10=$P21,1) -> 0 | X21: =X20+IF(X$10=$P21,1) -> 0 | Y21: =Y20+IF(Y$10=$P21,1) -> 0 | AA21: 1015.985 | AB21: 869.01606 | AC21: 1040.6243 | AE21: =$AC21-AA21 -> 24.639238 | AF21: =$AC21-AB21 -> 171.60819 | AH21: =$AC21/AA21-1 -> 0.024251576 | AI21: =$AC21/AB21-1 -> 0.19747413 | AK21: 10590 | AL21: 20640 | AN21: 29041.778 | AO21: 30576 | AP21: 31652.722 | AR21: 35562.938 | AS21: 37155.333 | AT21: 39888 | AV21: 41093.286 | AW21: 43488.25 | AX21: 46179.529 | AZ21: 11746.5 | BA21: 21768 | BC21: 29244.13 | BD21: 31083.5 | BE21: 32167.96 | BG21: 35838.45 | BH21: 37556.036 | BI21: 39850.538 | BK21: 41275.267 | BL21: 43763.4 | BM21: 46190.565 | BO21: =CHOOSE($AK$6,FH21,GH21) -> 11746.5 | BP21: =CHOOSE($AK$6,FI21,GI21) -> 21768 | BR21: =CHOOSE($AK$6,FK21,GK21) -> 29244.13 | BS21: =CHOOSE($AK$6,FL21,GL21) -> 31083.5 | BT21: =CHOOSE($AK$6,FM21,GM21) -> 32167.96 | BV21: =CHOOSE($AK$6,FO21,GO21) -> 35838.45 | BW21: =CHOOSE($AK$6,FP21,GP21) -> 37556.036 | BX21: =CHOOSE($AK$6,FQ21,GQ21) -> 39850.538 | BZ21: =BP21-BO21 -> 10021.5 | CA21: =BT21-BP21 -> 10399.96 | CB21: =BX21-BT21 -> 7682.5785 | CD21: =BP21/BO21-1 -> 0.85314775 | CE21: =BT21/BP21-1 -> 0.47776369 | CF21: =BX21/BT21-1 -> 0.23882703 | CH21: =BS21/$BR21-1 -> 0.062897051 | CI21: =BT21/$BR21-1 -> 0.099980048 | CK21: =BW21/$BV21-1 -> 0.047925781 | CL21: =BX21/$BV21-1 -> 0.11194927 | CN21: =IFERROR(BS21-$BR21,"") -> 1839.3696 | CO21: =IFERROR(BT21-$BR21,"") -> 2923.8296 | CQ21: =IFERROR(BW21-$BV21,"") -> 1717.5857 | CR21: =IFERROR(BX21-$BV21,"") -> 4012.0885 | CT21: 33901.536 | CU21: 31083.5 | CV21: 28114.808 | CW21: 25050.633 | CX21: 22163.333 | CY21: 20988.643 | CZ21: 20066.933 | DA21: 18281.453 | DB21: 13352.567 | DC21: 11318.25 | DD21: 10381.214 | DE21: 10336.167 | DF21: 8586.1422 | DG21: 7690.9286 | DH21: 7007.9846 | DI21: 7212.7083 | DJ21: 7080.7143 | DK21: 7757.4583 | DL21: 7753.8393 | DM21: 7044.5455 | DN21: 7010.4318 | DO21: 7541.2222 | DP21: 7699.8095 | DR21: =AC21 -> 1040.6243 | DS21: 869.01606 | DT21: 1015.985 | DU21: 722.14651 | DV21: 738.78837 | DW21: 782.95372 | DX21: 732.87172 | DY21: 842.02021 | DZ21: 860.47803 | EA21: 739.658 | EB21: 553.37017 | EC21: 509.89492 | ED21: 445.19002 | EE21: 326.3507 | EF21: 347.61308 | EG21: 307.23903 | EH21: 308.07023 | EI21: 272.72365 | EJ21: 264.22995 | EK21: 221.01802 | EL21: 220.11552 | EM21: 179.15892 | EN21: 161.50924 | EP21: 46022 | EQ21: =(DATE(2025,12,31)-EP21)/365 -> 0 | ES21: =AK21 -> 10590 | ET21: =AL21 -> 20640 | EV21: =AN21 -> 29041.778 | EW21: =AO21 -> 30576 | EX21: =AP21 -> 31652.722 | EZ21: =AR21 -> 35562.938 | FA21: =AS21 -> 37155.333 | FB21: =AT21 -> 39888 | FD21: =AV21 -> 41093.286 | FE21: =AW21 -> 43488.25 | FF21: =AX21 -> 46179.529 | FH21: =IFERROR(IF($EQ21<0,ES21*-$EQ21+ET21*(1+$EQ21),ES21*(1-$EQ21)+ET21*$EQ21),"") -> 10590 | FI21: =IFERROR(IF($EQ21<0,ET21*-$EQ21+EX21*(1+$EQ21),ET21*(1-$EQ21)+EX21*$EQ21),"") -> 20640 | FK21: =IFERROR(IF($EQ21<0,EV21*-$EQ21+EZ21*(1+$EQ21),EV21*(1-$EQ21)+EZ21*$EQ21),"") -> 29041.778 | FL21: =IFERROR(IF($EQ21<0,EW21*-$EQ21+FA21*(1+$EQ21),EW21*(1-$EQ21)+FA21*$EQ21),"") -> 30576 | FM21: =IFERROR(IF($EQ21<0,EX21*-$EQ21+FB21*(1+$EQ21),EX21*(1-$EQ21)+FB21*$EQ21),"") -> 31652.722 | FO21: =IFERROR(IF($EQ21<0,EZ21*-$EQ21+FD21*(1+$EQ21),EZ21*(1-$EQ21)+FD21*$EQ21),"") -> 35562.938 | FP21: =IFERROR(IF($EQ21<0,FA21*-$EQ21+FE21*(1+$EQ21),FA21*(1-$EQ21)+FE21*$EQ21),"") -> 37155.333 | FQ21: =IFERROR(IF($EQ21<0,FB21*-$EQ21+FF21*(1+$EQ21),FB21*(1-$EQ21)+FF21*$EQ21),"") -> 39888 | FS21: =AZ21 -> 11746.5 | FT21: =BA21 -> 21768 | FV21: =BC21 -> 29244.13 | FW21: =BD21 -> 31083.5 | FX21: =BE21 -> 32167.96 | FZ21: =BG21 -> 35838.45 | GA21: =BH21 -> 37556.036 | GB21: =BI21 -> 39850.538 | GD21: =BK21 -> 41275.267 | GE21: =BL21 -> 43763.4 | GF21: =BM21 -> 46190.565 | GH21: =IFERROR(IF($EQ21<0,FS21*-$EQ21+FT21*(1+$EQ21),FS21*(1-$EQ21)+FT21*$EQ21),"") -> 11746.5 | GI21: =IFERROR(IF($EQ21<0,FT21*-$EQ21+FX21*(1+$EQ21),FT21*(1-$EQ21)+FX21*$EQ21),"") -> 21768 | GK21: =IFERROR(IF($EQ21<0,FV21*-$EQ21+FZ21*(1+$EQ21),FV21*(1-$EQ21)+FZ21*$EQ21),"") -> 29244.13 | GL21: =IFERROR(IF($EQ21<0,FW21*-$EQ21+GA21*(1+$EQ21),FW21*(1-$EQ21)+GA21*$EQ21),"") -> 31083.5 | GM21: =IFERROR(IF($EQ21<0,FX21*-$EQ21+GB21*(1+$EQ21),FX21*(1-$EQ21)+GB21*$EQ21),"") -> 32167.96 | GO21: =IFERROR(IF($EQ21<0,FZ21*-$EQ21+GD21*(1+$EQ21),FZ21*(1-$EQ21)+GD21*$EQ21),"") -> 35838.45 | GP21: =IFERROR(IF($EQ21<0,GA21*-$EQ21+GE21*(1+$EQ21),GA21*(1-$EQ21)+GE21*$EQ21),"") -> 37556.036 | GQ21: =IFERROR(IF($EQ21<0,GB21*-$EQ21+GF21*(1+$EQ21),GB21*(1-$EQ21)+GF21*$EQ21),"") -> 39850.538
B22: AMD US Equity | C22: Advanced Micro Devices Inc | D22: =IFERROR(IF(MATCH($B22,Compounders!$A:$A,0),"yes"),"") | G22: yes | J22: =IF(AND(F22="",G22="",H22="",I22=""),"yes","") | K22: =K21+IF(F22="yes",1) -> 5 | L22: =L21+IF(G22="yes",1) -> 4 | M22: =M21+IF(H22="yes",1) -> 0 | N22: =N21+IF(I22="yes",1) -> 0 | P22: Digital Semis | Q22: =Q21+IF(Q$10=$P22,1) -> 3 | R22: =R21+IF(R$10=$P22,1) -> 1 | S22: =S21+IF(S$10=$P22,1) -> 0 | T22: =T21+IF(T$10=$P22,1) -> 0 | U22: =U21+IF(U$10=$P22,1) -> 0 | V22: =V21+IF(V$10=$P22,1) -> 0 | W22: =W21+IF(W$10=$P22,1) -> 0 | X22: =X21+IF(X$10=$P22,1) -> 0 | Y22: =Y21+IF(Y$10=$P22,1) -> 0 | AA22: 348.66138 | AB22: 331.65982 | AC22: 841.55299 | AE22: =$AC22-AA22 -> 492.89161 | AF22: =$AC22-AB22 -> 509.89317 | AH22: =$AC22/AA22-1 -> 1.4136685 | AI22: =$AC22/AB22-1 -> 1.5373981 | AK22: 1641 | AL22: 4335 | AN22: 7562.7368 | AO22: 7708.5882 | AP22: 8875.5349 | AR22: 13181.933 | AS22: 14553.697 | AT22: 18107.3 | AV22: 19314 | AW22: 20880.812 | AX22: 26729 | AZ22: 5420 | BA22: 6831 | BC22: 10607.159 | BD22: 11139.756 | BE22: 12078.08 | BG22: 16812.853 | BH22: 18385.591 | BI22: 22026.979 | BK22: 23189.2 | BL22: 24664.056 | BM22: 30601.667 | BO22: =CHOOSE($AK$6,FH22,GH22) -> 5435.463 | BP22: =CHOOSE($AK$6,FI22,GI22) -> 6888.5022 | BR22: =CHOOSE($AK$6,FK22,GK22) -> 10675.167 | BS22: =CHOOSE($AK$6,FL22,GL22) -> 11219.162 | BT22: =CHOOSE($AK$6,FM22,GM22) -> 12187.109 | BV22: =CHOOSE($AK$6,FO22,GO22) -> 16882.731 | BW22: =CHOOSE($AK$6,FP22,GP22) -> 18454.396 | BX22: =CHOOSE($AK$6,FQ22,GQ22) -> 22120.948 | BZ22: =BP22-BO22 -> 1453.0392 | CA22: =BT22-BP22 -> 5298.6068 | CB22: =BX22-BT22 -> 9933.8393 | CD22: =BP22/BO22-1 -> 0.26732575 | CE22: =BT22/BP22-1 -> 0.76919577 | CF22: =BX22/BT22-1 -> 0.8151104 | CH22: =BS22/$BR22-1 -> 0.050958949 | CI22: =BT22/$BR22-1 -> 0.14163173 | CK22: =BW22/$BV22-1 -> 0.093093073 | CL22: =BX22/$BV22-1 -> 0.31027076 | CN22: =IFERROR(BS22-$BR22,"") -> 543.99528 | CO22: =IFERROR(BT22-$BR22,"") -> 1511.9423 | CQ22: =IFERROR(BW22-$BV22,"") -> 1571.6653 | CR22: =IFERROR(BX22-$BV22,"") -> 5238.2176 | CT22: 14338.527 | CU22: 11139.756 | CV22: 9172.4013 | CW22: 8136.4168 | CX22: 6702.5983 | CY22: 7541.8 | CZ22: 7406.0982 | DA22: 7204.3859 | DB22: 6466.4213 | DC22: 5749.6585 | DD22: 5503.375 | DE22: 5407.3794 | DF22: 5070.3943 | DG22: 4904.9688 | DH22: 5073.5161 | DI22: 6911.7619 | DJ22: 6998.044 | DK22: 5220.64 | DL22: 3830.146 | DM22: 3282.3383 | DN22: 2652.3822 | DO22: 2385.7692 | DP22: 2126.1578 | DR22: =AC22 -> 841.55299 | DS22: 331.65982 | DT22: 348.66138 | DU22: 262.55988 | DV22: 230.07726 | DW22: 166.05841 | DX22: 196.0189 | DY22: 265.5605 | DZ22: 262.18227 | EA22: 291.63337 | EB22: 238.14069 | EC22: 166.12333 | ED22: 183.43632 | EE22: 157.93216 | EF22: 104.43231 | EG22: 102.28337 | EH22: 123.92024 | EI22: 177.93609 | EJ22: 173.77514 | EK22: 124.81413 | EL22: 114.12692 | EM22: 95.126569 | EN22: 110.30068 | EP22: 46018 | EQ22: =(DATE(2025,12,31)-EP22)/365 -> 0.010958904 | ES22: =AK22 -> 1641 | ET22: =AL22 -> 4335 | EV22: =AN22 -> 7562.7368 | EW22: =AO22 -> 7708.5882 | EX22: =AP22 -> 8875.5349 | EZ22: =AR22 -> 13181.933 | FA22: =AS22 -> 14553.697 | FB22: =AT22 -> 18107.3 | FD22: =AV22 -> 19314 | FE22: =AW22 -> 20880.812 | FF22: =AX22 -> 26729 | FH22: =IFERROR(IF($EQ22<0,ES22*-$EQ22+ET22*(1+$EQ22),ES22*(1-$EQ22)+ET22*$EQ22),"") -> 1670.5233 | FI22: =IFERROR(IF($EQ22<0,ET22*-$EQ22+EX22*(1+$EQ22),ET22*(1-$EQ22)+EX22*$EQ22),"") -> 4384.7593 | FK22: =IFERROR(IF($EQ22<0,EV22*-$EQ22+EZ22*(1+$EQ22),EV22*(1-$EQ22)+EZ22*$EQ22),"") -> 7624.3171 | FL22: =IFERROR(IF($EQ22<0,EW22*-$EQ22+FA22*(1+$EQ22),EW22*(1-$EQ22)+FA22*$EQ22),"") -> 7783.6031 | FM22: =IFERROR(IF($EQ22<0,EX22*-$EQ22+FB22*(1+$EQ22),EX22*(1-$EQ22)+FB22*$EQ22),"") -> 8976.7049 | FO22: =IFERROR(IF($EQ22<0,EZ22*-$EQ22+FD22*(1+$EQ22),EZ22*(1-$EQ22)+FD22*$EQ22),"") -> 13249.134 | FP22: =IFERROR(IF($EQ22<0,FA22*-$EQ22+FE22*(1+$EQ22),FA22*(1-$EQ22)+FE22*$EQ22),"") -> 14623.035 | FQ22: =IFERROR(IF($EQ22<0,FB22*-$EQ22+FF22*(1+$EQ22),FB22*(1-$EQ22)+FF22*$EQ22),"") -> 18201.784 | FS22: =AZ22 -> 5420 | FT22: =BA22 -> 6831 | FV22: =BC22 -> 10607.159 | FW22: =BD22 -> 11139.756 | FX22: =BE22 -> 12078.08 | FZ22: =BG22 -> 16812.853 | GA22: =BH22 -> 18385.591 | GB22: =BI22 -> 22026.979 | GD22: =BK22 -> 23189.2 | GE22: =BL22 -> 24664.056 | GF22: =BM22 -> 30601.667 | GH22: =IFERROR(IF($EQ22<0,FS22*-$EQ22+FT22*(1+$EQ22),FS22*(1-$EQ22)+FT22*$EQ22),"") -> 5435.463 | GI22: =IFERROR(IF($EQ22<0,FT22*-$EQ22+FX22*(1+$EQ22),FT22*(1-$EQ22)+FX22*$EQ22),"") -> 6888.5022 | GK22: =IFERROR(IF($EQ22<0,FV22*-$EQ22+FZ22*(1+$EQ22),FV22*(1-$EQ22)+FZ22*$EQ22),"") -> 10675.167 | GL22: =IFERROR(IF($EQ22<0,FW22*-$EQ22+GA22*(1+$EQ22),FW22*(1-$EQ22)+GA22*$EQ22),"") -> 11219.162 | GM22: =IFERROR(IF($EQ22<0,FX22*-$EQ22+GB22*(1+$EQ22),FX22*(1-$EQ22)+GB22*$EQ22),"") -> 12187.109 | GO22: =IFERROR(IF($EQ22<0,FZ22*-$EQ22+GD22*(1+$EQ22),FZ22*(1-$EQ22)+GD22*$EQ22),"") -> 16882.731 | GP22: =IFERROR(IF($EQ22<0,GA22*-$EQ22+GE22*(1+$EQ22),GA22*(1-$EQ22)+GE22*$EQ22),"") -> 18454.396 | GQ22: =IFERROR(IF($EQ22<0,GB22*-$EQ22+GF22*(1+$EQ22),GB22*(1-$EQ22)+GF22*$EQ22),"") -> 22120.948
B23: JPM US Equity | C23: Jpmorgan Chase & Co | D23: =IFERROR(IF(MATCH($B23,Compounders!$A:$A,0),"yes"),"") | J23: =IF(AND(F23="",G23="",H23="",I23=""),"yes","") -> yes | K23: =K22+IF(F23="yes",1) -> 5 | L23: =L22+IF(G23="yes",1) -> 4 | M23: =M22+IF(H23="yes",1) -> 0 | N23: =N22+IF(I23="yes",1) -> 0 | Q23: =Q22+IF(Q$10=$P23,1) -> 3 | R23: =R22+IF(R$10=$P23,1) -> 1 | S23: =S22+IF(S$10=$P23,1) -> 0 | T23: =T22+IF(T$10=$P23,1) -> 0 | U23: =U22+IF(U$10=$P23,1) -> 0 | V23: =V22+IF(V$10=$P23,1) -> 0 | W23: =W22+IF(W$10=$P23,1) -> 0 | X23: =X22+IF(X$10=$P23,1) -> 0 | Y23: =Y22+IF(Y$10=$P23,1) -> 0 | AA23: 877.16736 | AB23: 793.35904 | AC23: 802.00456 | AE23: =$AC23-AA23 -> -75.162794 | AF23: =$AC23-AB23 -> 8.6455191 | AH23: =$AC23/AA23-1 -> -0.085688089 | AI23: =$AC23/AB23-1 -> 0.01089736 | AK23: 56868 | AL23: 55681 | AN23: 56416.579 | AO23: 57889.35 | AP23: 60148.421 | AR23: 58910 | AS23: 60100.579 | AT23: 61123.056 | AV23: 59610 | AW23: 64087.875 | AX23: 65034.875 | AZ23: 53313 | BA23: 56032.55 | BC23: 56862.955 | BD23: 57892.577 | BE23: 59989.76 | BG23: 59415.556 | BH23: 62218.2 | BI23: 61516.25 | BK23: 59610 | BL23: 67560.667 | BM23: 64785.333 | BO23: =CHOOSE($AK$6,FH23,GH23) -> 53313 | BP23: =CHOOSE($AK$6,FI23,GI23) -> 56032.55 | BR23: =CHOOSE($AK$6,FK23,GK23) -> 56862.955 | BS23: =CHOOSE($AK$6,FL23,GL23) -> 57892.577 | BT23: =CHOOSE($AK$6,FM23,GM23) -> 59989.76 | BV23: =CHOOSE($AK$6,FO23,GO23) -> 59415.556 | BW23: =CHOOSE($AK$6,FP23,GP23) -> 62218.2 | BX23: =CHOOSE($AK$6,FQ23,GQ23) -> 61516.25 | BZ23: =BP23-BO23 -> 2719.55 | CA23: =BT23-BP23 -> 3957.21 | CB23: =BX23-BT23 -> 1526.49 | CD23: =BP23/BO23-1 -> 0.05101101 | CE23: =BT23/BP23-1 -> 0.070623414 | CF23: =BX23/BT23-1 -> 0.025445843 | CH23: =BS23/$BR23-1 -> 0.018107085 | CI23: =BT23/$BR23-1 -> 0.054988445 | CK23: =BW23/$BV23-1 -> 0.047170214 | CL23: =BX23/$BV23-1 -> 0.035355967 | CN23: =IFERROR(BS23-$BR23,"") -> 1029.6224 | CO23: =IFERROR(BT23-$BR23,"") -> 3126.8055 | CQ23: =IFERROR(BW23-$BV23,"") -> 2802.6444 | CR23: =IFERROR(BX23-$BV23,"") -> 2100.6944 | CT23: 59366.612 | CU23: 57892.577 | CV23: 56473.143 | CW23: 53913.283 | CX23: 50719.122 | CY23: 51520.739 | CZ23: 47429.071 | DA23: 46838.606 | DB23: 46059.833 | DC23: 46418.778 | DD23: 44682.143 | DE23: 43535.286 | DF23: 40234.332 | DG23: 38001.095 | DH23: 38338.337 | DI23: 36673.608 | DJ23: 35127.667 | DK23: 32910.107 | DL23: 34565.695 | DM23: 34505.486 | DN23: 34479.095 | DO23: 32553 | DP23: 28728.582 | DR23: =AC23 -> 802.00456 | DS23: 793.35904 | DT23: 877.16736 | DU23: 867.35486 | DV23: 805.68728 | DW23: 685.88483 | DX23: 674.86525 | DY23: 599.93143 | DZ23: 580.82355 | EA23: 576.93841 | EB23: 491.76052 | EC23: 421.44049 | ED23: 425.01764 | EE23: 383.54865 | EF23: 393.34278 | EG23: 306.45381 | EH23: 330.74125 | EI23: 402.52692 | EJ23: 467.96638 | EK23: 489.13115 | EL23: 470.83951 | EM23: 464.53082 | EN23: 387.33516 | EP23: 46022 | EQ23: =(DATE(2025,12,31)-EP23)/365 -> 0 | ES23: =AK23 -> 56868 | ET23: =AL23 -> 55681 | EV23: =AN23 -> 56416.579 | EW23: =AO23 -> 57889.35 | EX23: =AP23 -> 60148.421 | EZ23: =AR23 -> 58910 | FA23: =AS23 -> 60100.579 | FB23: =AT23 -> 61123.056 | FD23: =AV23 -> 59610 | FE23: =AW23 -> 64087.875 | FF23: =AX23 -> 65034.875 | FH23: =IFERROR(IF($EQ23<0,ES23*-$EQ23+ET23*(1+$EQ23),ES23*(1-$EQ23)+ET23*$EQ23),"") -> 56868 | FI23: =IFERROR(IF($EQ23<0,ET23*-$EQ23+EX23*(1+$EQ23),ET23*(1-$EQ23)+EX23*$EQ23),"") -> 55681 | FK23: =IFERROR(IF($EQ23<0,EV23*-$EQ23+EZ23*(1+$EQ23),EV23*(1-$EQ23)+EZ23*$EQ23),"") -> 56416.579 | FL23: =IFERROR(IF($EQ23<0,EW23*-$EQ23+FA23*(1+$EQ23),EW23*(1-$EQ23)+FA23*$EQ23),"") -> 57889.35 | FM23: =IFERROR(IF($EQ23<0,EX23*-$EQ23+FB23*(1+$EQ23),EX23*(1-$EQ23)+FB23*$EQ23),"") -> 60148.421 | FO23: =IFERROR(IF($EQ23<0,EZ23*-$EQ23+FD23*(1+$EQ23),EZ23*(1-$EQ23)+FD23*$EQ23),"") -> 58910 | FP23: =IFERROR(IF($EQ23<0,FA23*-$EQ23+FE23*(1+$EQ23),FA23*(1-$EQ23)+FE23*$EQ23),"") -> 60100.579 | FQ23: =IFERROR(IF($EQ23<0,FB23*-$EQ23+FF23*(1+$EQ23),FB23*(1-$EQ23)+FF23*$EQ23),"") -> 61123.056 | FS23: =AZ23 -> 53313 | FT23: =BA23 -> 56032.55 | FV23: =BC23 -> 56862.955 | FW23: =BD23 -> 57892.577 | FX23: =BE23 -> 59989.76 | FZ23: =BG23 -> 59415.556 | GA23: =BH23 -> 62218.2 | GB23: =BI23 -> 61516.25 | GD23: =BK23 -> 59610 | GE23: =BL23 -> 67560.667 | GF23: =BM23 -> 64785.333 | GH23: =IFERROR(IF($EQ23<0,FS23*-$EQ23+FT23*(1+$EQ23),FS23*(1-$EQ23)+FT23*$EQ23),"") -> 53313 | GI23: =IFERROR(IF($EQ23<0,FT23*-$EQ23+FX23*(1+$EQ23),FT23*(1-$EQ23)+FX23*$EQ23),"") -> 56032.55 | GK23: =IFERROR(IF($EQ23<0,FV23*-$EQ23+FZ23*(1+$EQ23),FV23*(1-$EQ23)+FZ23*$EQ23),"") -> 56862.955 | GL23: =IFERROR(IF($EQ23<0,FW23*-$EQ23+GA23*(1+$EQ23),FW23*(1-$EQ23)+GA23*$EQ23),"") -> 57892.577 | GM23: =IFERROR(IF($EQ23<0,FX23*-$EQ23+GB23*(1+$EQ23),FX23*(1-$EQ23)+GB23*$EQ23),"") -> 59989.76 | GO23: =IFERROR(IF($EQ23<0,FZ23*-$EQ23+GD23*(1+$EQ23),FZ23*(1-$EQ23)+GD23*$EQ23),"") -> 59415.556 | GP23: =IFERROR(IF($EQ23<0,GA23*-$EQ23+GE23*(1+$EQ23),GA23*(1-$EQ23)+GE23*$EQ23),"") -> 62218.2 | GQ23: =IFERROR(IF($EQ23<0,GB23*-$EQ23+GF23*(1+$EQ23),GB23*(1-$EQ23)+GF23*$EQ23),"") -> 61516.25
B24: XOM US Equity | C24: Exxon Mobil Corp | D24: =IFERROR(IF(MATCH($B24,Compounders!$A:$A,0),"yes"),"") | J24: =IF(AND(F24="",G24="",H24="",I24=""),"yes","") -> yes | K24: =K23+IF(F24="yes",1) -> 5 | L24: =L23+IF(G24="yes",1) -> 4 | M24: =M23+IF(H24="yes",1) -> 0 | N24: =N23+IF(I24="yes",1) -> 0 | Q24: =Q23+IF(Q$10=$P24,1) -> 3 | R24: =R23+IF(R$10=$P24,1) -> 1 | S24: =S23+IF(S$10=$P24,1) -> 0 | T24: =T23+IF(T$10=$P24,1) -> 0 | U24: =U23+IF(U$10=$P24,1) -> 0 | V24: =V23+IF(V$10=$P24,1) -> 0 | W24: =W23+IF(W$10=$P24,1) -> 0 | X24: =X23+IF(X$10=$P24,1) -> 0 | Y24: =Y23+IF(Y$10=$P24,1) -> 0 | AA24: 507.49371 | AB24: 706.93309 | AC24: 602.09502 | AE24: =$AC24-AA24 -> 94.601315 | AF24: =$AC24-AB24 -> -104.83806 | AH24: =$AC24/AA24-1 -> 0.18640884 | AI24: =$AC24/AB24-1 -> -0.14829984 | AK24: 33680 | AL24: 28844 | AN24: 29912.652 | AO24: 36857.583 | AP24: 48141.364 | AR24: 35107.857 | AS24: 37362.542 | AT24: 43581.522 | AV24: 37811.688 | AW24: 39526.667 | AX24: 43574.714 | AZ24: 33464 | BA24: 30109 | BC24: 29704.833 | BD24: 36359.92 | BE24: 47823.217 | BG24: 34779.909 | BH24: 37020.44 | BI24: 43035.792 | BK24: 37811.688 | BL24: 39526.667 | BM24: 43013.091 | BO24: =CHOOSE($AK$6,FH24,GH24) -> 33464 | BP24: =CHOOSE($AK$6,FI24,GI24) -> 30109 | BR24: =CHOOSE($AK$6,FK24,GK24) -> 29704.833 | BS24: =CHOOSE($AK$6,FL24,GL24) -> 36359.92 | BT24: =CHOOSE($AK$6,FM24,GM24) -> 47823.217 | BV24: =CHOOSE($AK$6,FO24,GO24) -> 34779.909 | BW24: =CHOOSE($AK$6,FP24,GP24) -> 37020.44 | BX24: =CHOOSE($AK$6,FQ24,GQ24) -> 43035.792 | BZ24: =BP24-BO24 -> -3355 | CA24: =BT24-BP24 -> 17714.217 | CB24: =BX24-BT24 -> -4787.4257 | CD24: =BP24/BO24-1 -> -0.10025699 | CE24: =BT24/BP24-1 -> 0.58833629 | CF24: =BX24/BT24-1 -> -0.10010673 | CH24: =BS24/$BR24-1 -> 0.22404053 | CI24: =BT24/$BR24-1 -> 0.60994734 | CK24: =BW24/$BV24-1 -> 0.064420264 | CL24: =BX24/$BV24-1 -> 0.23737505 | CN24: =IFERROR(BS24-$BR24,"") -> 6655.0867 | CO24: =IFERROR(BT24-$BR24,"") -> 18118.384 | CQ24: =IFERROR(BW24-$BV24,"") -> 2240.5309 | CR24: =IFERROR(BX24-$BV24,"") -> 8255.8826 | CT24: 51258.823 | CU24: 36359.92 | CV24: 29204.465 | CW24: 28612.211 | CX24: 27885.7 | CY24: 32402.091 | CZ24: 32875.252 | DA24: 34340.763 | DB24: 41586.877 | DC24: 37190.235 | DD24: 37496.345 | DE24: 36490.651 | DF24: 36053.421 | DG24: 40967.286 | DH24: 46149.882 | DI24: 47587.938 | DJ24: 45057.797 | DK24: 34089.292 | DL24: 26700.755 | DM24: 22803.167 | DN24: 17498.516 | DO24: 13060.435 | DP24: 4460.6855 | DR24: =AC24 -> 602.09502 | DS24: 706.93309 | DT24: 507.49371 | DU24: 480.6811 | DV24: 464.57906 | DW24: 516.05431 | DX24: 472.78032 | DY24: 520.78813 | DZ24: 516.42 | EA24: 461.22222 | EB24: 400.5332 | EC24: 470.69541 | ED24: 433.61014 | EE24: 446.42421 | EF24: 454.24776 | EG24: 363.87632 | EH24: 360.7622 | EI24: 349.6524 | EJ24: 259.05195 | EK24: 249.01817 | EL24: 267.05163 | EM24: 236.35758 | EN24: 174.28781 | EP24: 46022 | EQ24: =(DATE(2025,12,31)-EP24)/365 -> 0 | ES24: =AK24 -> 33680 | ET24: =AL24 -> 28844 | EV24: =AN24 -> 29912.652 | EW24: =AO24 -> 36857.583 | EX24: =AP24 -> 48141.364 | EZ24: =AR24 -> 35107.857 | FA24: =AS24 -> 37362.542 | FB24: =AT24 -> 43581.522 | FD24: =AV24 -> 37811.688 | FE24: =AW24 -> 39526.667 | FF24: =AX24 -> 43574.714 | FH24: =IFERROR(IF($EQ24<0,ES24*-$EQ24+ET24*(1+$EQ24),ES24*(1-$EQ24)+ET24*$EQ24),"") -> 33680 | FI24: =IFERROR(IF($EQ24<0,ET24*-$EQ24+EX24*(1+$EQ24),ET24*(1-$EQ24)+EX24*$EQ24),"") -> 28844 | FK24: =IFERROR(IF($EQ24<0,EV24*-$EQ24+EZ24*(1+$EQ24),EV24*(1-$EQ24)+EZ24*$EQ24),"") -> 29912.652 | FL24: =IFERROR(IF($EQ24<0,EW24*-$EQ24+FA24*(1+$EQ24),EW24*(1-$EQ24)+FA24*$EQ24),"") -> 36857.583 | FM24: =IFERROR(IF($EQ24<0,EX24*-$EQ24+FB24*(1+$EQ24),EX24*(1-$EQ24)+FB24*$EQ24),"") -> 48141.364 | FO24: =IFERROR(IF($EQ24<0,EZ24*-$EQ24+FD24*(1+$EQ24),EZ24*(1-$EQ24)+FD24*$EQ24),"") -> 35107.857 | FP24: =IFERROR(IF($EQ24<0,FA24*-$EQ24+FE24*(1+$EQ24),FA24*(1-$EQ24)+FE24*$EQ24),"") -> 37362.542 | FQ24: =IFERROR(IF($EQ24<0,FB24*-$EQ24+FF24*(1+$EQ24),FB24*(1-$EQ24)+FF24*$EQ24),"") -> 43581.522 | FS24: =AZ24 -> 33464 | FT24: =BA24 -> 30109 | FV24: =BC24 -> 29704.833 | FW24: =BD24 -> 36359.92 | FX24: =BE24 -> 47823.217 | FZ24: =BG24 -> 34779.909 | GA24: =BH24 -> 37020.44 | GB24: =BI24 -> 43035.792 | GD24: =BK24 -> 37811.688 | GE24: =BL24 -> 39526.667 | GF24: =BM24 -> 43013.091 | GH24: =IFERROR(IF($EQ24<0,FS24*-$EQ24+FT24*(1+$EQ24),FS24*(1-$EQ24)+FT24*$EQ24),"") -> 33464 | GI24: =IFERROR(IF($EQ24<0,FT24*-$EQ24+FX24*(1+$EQ24),FT24*(1-$EQ24)+FX24*$EQ24),"") -> 30109 | GK24: =IFERROR(IF($EQ24<0,FV24*-$EQ24+FZ24*(1+$EQ24),FV24*(1-$EQ24)+FZ24*$EQ24),"") -> 29704.833 | GL24: =IFERROR(IF($EQ24<0,FW24*-$EQ24+GA24*(1+$EQ24),FW24*(1-$EQ24)+GA24*$EQ24),"") -> 36359.92 | GM24: =IFERROR(IF($EQ24<0,FX24*-$EQ24+GB24*(1+$EQ24),FX24*(1-$EQ24)+GB24*$EQ24),"") -> 47823.217 | GO24: =IFERROR(IF($EQ24<0,FZ24*-$EQ24+GD24*(1+$EQ24),FZ24*(1-$EQ24)+GD24*$EQ24),"") -> 34779.909 | GP24: =IFERROR(IF($EQ24<0,GA24*-$EQ24+GE24*(1+$EQ24),GA24*(1-$EQ24)+GE24*$EQ24),"") -> 37020.44 | GQ24: =IFERROR(IF($EQ24<0,GB24*-$EQ24+GF24*(1+$EQ24),GB24*(1-$EQ24)+GF24*$EQ24),"") -> 43035.792
B25: INTC US Equity | C25: Intel Corp | D25: =IFERROR(IF(MATCH($B25,Compounders!$A:$A,0),"yes"),"") | G25: yes | J25: =IF(AND(F25="",G25="",H25="",I25=""),"yes","") | K25: =K24+IF(F25="yes",1) -> 5 | L25: =L24+IF(G25="yes",1) -> 5 | M25: =M24+IF(H25="yes",1) -> 0 | N25: =N24+IF(I25="yes",1) -> 0 | P25: Digital Semis | Q25: =Q24+IF(Q$10=$P25,1) -> 4 | R25: =R24+IF(R$10=$P25,1) -> 1 | S25: =S24+IF(S$10=$P25,1) -> 0 | T25: =T24+IF(T$10=$P25,1) -> 0 | U25: =U24+IF(U$10=$P25,1) -> 0 | V25: =V24+IF(V$10=$P25,1) -> 0 | W25: =W24+IF(W$10=$P25,1) -> 0 | X25: =X24+IF(X$10=$P25,1) -> 0 | Y25: =Y24+IF(Y$10=$P25,1) -> 0 | AA25: 183.93826 | AB25: 221.57718 | AC25: 576.38168 | AE25: =$AC25-AA25 -> 392.44342 | AF25: =$AC25-AB25 -> 354.8045 | AH25: =$AC25/AA25-1 -> 2.1335606 | AI25: =$AC25/AB25-1 -> 1.6012682 | AK25: -19233 | AL25: -267 | AN25: 83.525926 | AO25: -1406.3333 | AP25: -1660.75 | AR25: 2598.8182 | AS25: 1812.5625 | AT25: 4681.8214 | AV25: 9452 | AW25: 4785.4545 | AX25: 8282.8 | AZ25: -566 | BA25: 1929 | BC25: 3149.35 | BD25: 2724.9143 | BE25: 5586.725 | BG25: 5730.1935 | BH25: 5139.7143 | BI25: 7999.3171 | BK25: 10629.5 | BL25: 6730.5556 | BM25: 12035.125 | BO25: =CHOOSE($AK$6,FH25,GH25) -> -538.65753 | BP25: =CHOOSE($AK$6,FI25,GI25) -> 1969.0847 | BR25: =CHOOSE($AK$6,FK25,GK25) -> 3177.6332 | BS25: =CHOOSE($AK$6,FL25,GL25) -> 2751.3778 | BT25: =CHOOSE($AK$6,FM25,GM25) -> 5613.1644 | BV25: =CHOOSE($AK$6,FO25,GO25) -> 5783.8846 | BW25: =CHOOSE($AK$6,FP25,GP25) -> 5157.1482 | BX25: =CHOOSE($AK$6,FQ25,GQ25) -> 8043.5451 | BZ25: =BP25-BO25 -> 2507.7422 | CA25: =BT25-BP25 -> 3644.0797 | CB25: =BX25-BT25 -> 2430.3807 | CD25: =BP25/BO25-1 -> -4.6555409 | CE25: =BT25/BP25-1 -> 1.8506465 | CF25: =BX25/BT25-1 -> 0.43297872 | CH25: =BS25/$BR25-1 -> -0.13414241 | CI25: =BT25/$BR25-1 -> 0.76646075 | CK25: =BW25/$BV25-1 -> -0.10835908 | CL25: =BX25/$BV25-1 -> 0.39068216 | CN25: =IFERROR(BS25-$BR25,"") -> -426.25537 | CO25: =IFERROR(BT25-$BR25,"") -> 2435.5311 | CQ25: =IFERROR(BW25-$BV25,"") -> -626.73642 | CR25: =IFERROR(BX25-$BV25,"") -> 2259.6605 | CT25: 5602.5937 | CU25: 2724.9143 | CV25: 2201.0653 | CW25: 1257.893 | CX25: 1005.8337 | CY25: 2053.3784 | CZ25: 2976.4592 | DA25: 1541.7172 | DB25: 5220.8538 | DC25: 5750.8929 | DD25: 7329.9506 | DE25: 4932.1583 | DF25: 2822.2772 | DG25: 2032.3143 | DH25: 5853.614 | DI25: 9548.2144 | DJ25: 14278.12 | DK25: 14109.794 | DL25: 14500.445 | DM25: 16785.901 | DN25: 17258.863 | DO25: 18883.933 | DP25: 17816.956 | DR25: =AC25 -> 576.38168 | DS25: 221.57718 | DT25: 183.93826 | DU25: 156.06061 | DV25: 97.7088 | DW25: 99.029036 | DX25: 86.47565 | DY25: 100.31496 | DZ25: 131.83533 | EA25: 186.75076 | EB25: 211.854 | EC25: 148.8834 | ED25: 139.47824 | EE25: 135.15579 | EF25: 109.07661 | EG25: 105.81162 | EH25: 152.96949 | EI25: 202.63577 | EJ25: 209.4505 | EK25: 216.15696 | EL25: 226.69332 | EM25: 260.63012 | EN25: 204.16236 | EP25: 46018 | EQ25: =(DATE(2025,12,31)-EP25)/365 -> 0.010958904 | ES25: =AK25 -> -19233 | ET25: =AL25 -> -267 | EV25: =AN25 -> 83.525926 | EW25: =AO25 -> -1406.3333 | EX25: =AP25 -> -1660.75 | EZ25: =AR25 -> 2598.8182 | FA25: =AS25 -> 1812.5625 | FB25: =AT25 -> 4681.8214 | FD25: =AV25 -> 9452 | FE25: =AW25 -> 4785.4545 | FF25: =AX25 -> 8282.8 | FH25: =IFERROR(IF($EQ25<0,ES25*-$EQ25+ET25*(1+$EQ25),ES25*(1-$EQ25)+ET25*$EQ25),"") -> -19025.153 | FI25: =IFERROR(IF($EQ25<0,ET25*-$EQ25+EX25*(1+$EQ25),ET25*(1-$EQ25)+EX25*$EQ25),"") -> -282.27397 | FK25: =IFERROR(IF($EQ25<0,EV25*-$EQ25+EZ25*(1+$EQ25),EV25*(1-$EQ25)+EZ25*$EQ25),"") -> 111.09077 | FL25: =IFERROR(IF($EQ25<0,EW25*-$EQ25+FA25*(1+$EQ25),EW25*(1-$EQ25)+FA25*$EQ25),"") -> -1371.0578 | FM25: =IFERROR(IF($EQ25<0,EX25*-$EQ25+FB25*(1+$EQ25),EX25*(1-$EQ25)+FB25*$EQ25),"") -> -1591.2424 | FO25: =IFERROR(IF($EQ25<0,EZ25*-$EQ25+FD25*(1+$EQ25),EZ25*(1-$EQ25)+FD25*$EQ25),"") -> 2673.9215 | FP25: =IFERROR(IF($EQ25<0,FA25*-$EQ25+FE25*(1+$EQ25),FA25*(1-$EQ25)+FE25*$EQ25),"") -> 1845.1421 | FQ25: =IFERROR(IF($EQ25<0,FB25*-$EQ25+FF25*(1+$EQ25),FB25*(1-$EQ25)+FF25*$EQ25),"") -> 4721.2842 | FS25: =AZ25 -> -566 | FT25: =BA25 -> 1929 | FV25: =BC25 -> 3149.35 | FW25: =BD25 -> 2724.9143 | FX25: =BE25 -> 5586.725 | FZ25: =BG25 -> 5730.1935 | GA25: =BH25 -> 5139.7143 | GB25: =BI25 -> 7999.3171 | GD25: =BK25 -> 10629.5 | GE25: =BL25 -> 6730.5556 | GF25: =BM25 -> 12035.125 | GH25: =IFERROR(IF($EQ25<0,FS25*-$EQ25+FT25*(1+$EQ25),FS25*(1-$EQ25)+FT25*$EQ25),"") -> -538.65753 | GI25: =IFERROR(IF($EQ25<0,FT25*-$EQ25+FX25*(1+$EQ25),FT25*(1-$EQ25)+FX25*$EQ25),"") -> 1969.0847 | GK25: =IFERROR(IF($EQ25<0,FV25*-$EQ25+FZ25*(1+$EQ25),FV25*(1-$EQ25)+FZ25*$EQ25),"") -> 3177.6332 | GL25: =IFERROR(IF($EQ25<0,FW25*-$EQ25+GA25*(1+$EQ25),FW25*(1-$EQ25)+GA25*$EQ25),"") -> 2751.3778 | GM25: =IFERROR(IF($EQ25<0,FX25*-$EQ25+GB25*(1+$EQ25),FX25*(1-$EQ25)+GB25*$EQ25),"") -> 5613.1644 | GO25: =IFERROR(IF($EQ25<0,FZ25*-$EQ25+GD25*(1+$EQ25),FZ25*(1-$EQ25)+GD25*$EQ25),"") -> 5783.8846 | GP25: =IFERROR(IF($EQ25<0,GA25*-$EQ25+GE25*(1+$EQ25),GA25*(1-$EQ25)+GE25*$EQ25),"") -> 5157.1482 | GQ25: =IFERROR(IF($EQ25<0,GB25*-$EQ25+GF25*(1+$EQ25),GB25*(1-$EQ25)+GF25*$EQ25),"") -> 8043.5451
B26: JNJ US Equity | C26: Johnson & Johnson | D26: =IFERROR(IF(MATCH($B26,Compounders!$A:$A,0),"yes"),"") | J26: =IF(AND(F26="",G26="",H26="",I26=""),"yes","") -> yes | K26: =K25+IF(F26="yes",1) -> 5 | L26: =L25+IF(G26="yes",1) -> 5 | M26: =M25+IF(H26="yes",1) -> 0 | N26: =N25+IF(I26="yes",1) -> 0 | Q26: =Q25+IF(Q$10=$P26,1) -> 4 | R26: =R25+IF(R$10=$P26,1) -> 1 | S26: =S25+IF(S$10=$P26,1) -> 0 | T26: =T25+IF(T$10=$P26,1) -> 0 | U26: =U25+IF(U$10=$P26,1) -> 0 | V26: =V25+IF(V$10=$P26,1) -> 0 | W26: =W25+IF(W$10=$P26,1) -> 0 | X26: =X25+IF(X$10=$P26,1) -> 0 | Y26: =Y25+IF(Y$10=$P26,1) -> 0 | AA26: 498.60362 | AB26: 588.76142 | AC26: 542.4182 | AE26: =$AC26-AA26 -> 43.814579 | AF26: =$AC26-AB26 -> -46.343215 | AH26: =$AC26/AA26-1 -> 0.08787457 | AI26: =$AC26/AB26-1 -> -0.078713064 | AK26: 14066 | AL26: 26804 | AN26: 23600.125 | AO26: 24448.111 | AP26: 23829.467 | AR26: 25042.143 | AS26: 26689.222 | AT26: 26487.333 | AV26: 26958.818 | AW26: 28874 | AX26: 29223.538 | AZ26: 24242 | BA26: 26215 | BC26: 27839.087 | BD26: 28091.5 | BE26: 28243.952 | BG26: 29916.684 | BH26: 30426.043 | BI26: 30917.571 | BK26: 32616.615 | BL26: 33127.5 | BM26: 33956.647 | BO26: =CHOOSE($AK$6,FH26,GH26) -> 24258.216 | BP26: =CHOOSE($AK$6,FI26,GI26) -> 26231.676 | BR26: =CHOOSE($AK$6,FK26,GK26) -> 27856.163 | BS26: =CHOOSE($AK$6,FL26,GL26) -> 28110.688 | BT26: =CHOOSE($AK$6,FM26,GM26) -> 28265.927 | BV26: =CHOOSE($AK$6,FO26,GO26) -> 29938.875 | BW26: =CHOOSE($AK$6,FP26,GP26) -> 30448.247 | BX26: =CHOOSE($AK$6,FQ26,GQ26) -> 30942.55 | BZ26: =BP26-BO26 -> 1973.4599 | CA26: =BT26-BP26 -> 2034.251 | CB26: =BX26-BT26 -> 2676.6228 | CD26: =BP26/BO26-1 -> 0.081352225 | CE26: =BT26/BP26-1 -> 0.07754941 | CF26: =BX26/BT26-1 -> 0.094694321 | CH26: =BS26/$BR26-1 -> 0.0091371137 | CI26: =BT26/$BR26-1 -> 0.014710003 | CK26: =BW26/$BV26-1 -> 0.017013725 | CL26: =BX26/$BV26-1 -> 0.033524128 | CN26: =IFERROR(BS26-$BR26,"") -> 254.52493 | CO26: =IFERROR(BT26-$BR26,"") -> 409.76423 | CQ26: =IFERROR(BW26-$BV26,"") -> 509.3718 | CR26: =IFERROR(BX26-$BV26,"") -> 1003.6747 | CT26: 28739.743 | CU26: 28091.5 | CV26: 26579.923 | CW26: 26385.167 | CX26: 25503.599 | CY26: 25557.3 | CZ26: 24112.567 | DA26: 23466.492 | DB26: 25840.683 | DC26: 25921.55 | DD26: 25240.325 | DE26: 25741.545 | DF26: 27943.949 | DG26: 27815.909 | DH26: 26608.342 | DI26: 26731.77 | DJ26: 27158.857 | DK26: 27933.222 | DL26: 26508.857 | DM26: 26006.74 | DN26: 25427.606 | DO26: 25210.533 | DP26: 22900.519 | DR26: =AC26 -> 542.4182 | DS26: 588.76142 | DT26: 498.60362 | DU26: 446.55419 | DV26: 367.52769 | DW26: 399.64915 | DX26: 348.19043 | DY26: 390.11791 | DZ26: 351.76023 | EA26: 381.20358 | EB26: 377.31685 | EC26: 374.03123 | ED26: 430.14246 | EE26: 402.75043 | EF26: 461.84853 | EG26: 429.50283 | EH26: 467.10013 | EI26: 466.04675 | EJ26: 450.35836 | EK26: 425.14586 | EL26: 433.82566 | EM26: 432.68532 | EN26: 414.30957 | EP26: 46019 | EQ26: =(DATE(2025,12,31)-EP26)/365 -> 0.0082191781 | ES26: =AK26 -> 14066 | ET26: =AL26 -> 26804 | EV26: =AN26 -> 23600.125 | EW26: =AO26 -> 24448.111 | EX26: =AP26 -> 23829.467 | EZ26: =AR26 -> 25042.143 | FA26: =AS26 -> 26689.222 | FB26: =AT26 -> 26487.333 | FD26: =AV26 -> 26958.818 | FE26: =AW26 -> 28874 | FF26: =AX26 -> 29223.538 | FH26: =IFERROR(IF($EQ26<0,ES26*-$EQ26+ET26*(1+$EQ26),ES26*(1-$EQ26)+ET26*$EQ26),"") -> 14170.696 | FI26: =IFERROR(IF($EQ26<0,ET26*-$EQ26+EX26*(1+$EQ26),ET26*(1-$EQ26)+EX26*$EQ26),"") -> 26779.552 | FK26: =IFERROR(IF($EQ26<0,EV26*-$EQ26+EZ26*(1+$EQ26),EV26*(1-$EQ26)+EZ26*$EQ26),"") -> 23611.977 | FL26: =IFERROR(IF($EQ26<0,EW26*-$EQ26+FA26*(1+$EQ26),EW26*(1-$EQ26)+FA26*$EQ26),"") -> 24466.531 | FM26: =IFERROR(IF($EQ26<0,EX26*-$EQ26+FB26*(1+$EQ26),EX26*(1-$EQ26)+FB26*$EQ26),"") -> 23851.312 | FO26: =IFERROR(IF($EQ26<0,EZ26*-$EQ26+FD26*(1+$EQ26),EZ26*(1-$EQ26)+FD26*$EQ26),"") -> 25057.896 | FP26: =IFERROR(IF($EQ26<0,FA26*-$EQ26+FE26*(1+$EQ26),FA26*(1-$EQ26)+FE26*$EQ26),"") -> 26707.179 | FQ26: =IFERROR(IF($EQ26<0,FB26*-$EQ26+FF26*(1+$EQ26),FB26*(1-$EQ26)+FF26*$EQ26),"") -> 26509.823 | FS26: =AZ26 -> 24242 | FT26: =BA26 -> 26215 | FV26: =BC26 -> 27839.087 | FW26: =BD26 -> 28091.5 | FX26: =BE26 -> 28243.952 | FZ26: =BG26 -> 29916.684 | GA26: =BH26 -> 30426.043 | GB26: =BI26 -> 30917.571 | GD26: =BK26 -> 32616.615 | GE26: =BL26 -> 33127.5 | GF26: =BM26 -> 33956.647 | GH26: =IFERROR(IF($EQ26<0,FS26*-$EQ26+FT26*(1+$EQ26),FS26*(1-$EQ26)+FT26*$EQ26),"") -> 24258.216 | GI26: =IFERROR(IF($EQ26<0,FT26*-$EQ26+FX26*(1+$EQ26),FT26*(1-$EQ26)+FX26*$EQ26),"") -> 26231.676 | GK26: =IFERROR(IF($EQ26<0,FV26*-$EQ26+FZ26*(1+$EQ26),FV26*(1-$EQ26)+FZ26*$EQ26),"") -> 27856.163 | GL26: =IFERROR(IF($EQ26<0,FW26*-$EQ26+GA26*(1+$EQ26),FW26*(1-$EQ26)+GA26*$EQ26),"") -> 28110.688 | GM26: =IFERROR(IF($EQ26<0,FX26*-$EQ26+GB26*(1+$EQ26),FX26*(1-$EQ26)+GB26*$EQ26),"") -> 28265.927 | GO26: =IFERROR(IF($EQ26<0,FZ26*-$EQ26+GD26*(1+$EQ26),FZ26*(1-$EQ26)+GD26*$EQ26),"") -> 29938.875 | GP26: =IFERROR(IF($EQ26<0,GA26*-$EQ26+GE26*(1+$EQ26),GA26*(1-$EQ26)+GE26*$EQ26),"") -> 30448.247 | GQ26: =IFERROR(IF($EQ26<0,GB26*-$EQ26+GF26*(1+$EQ26),GB26*(1-$EQ26)+GF26*$EQ26),"") -> 30942.55
B27: V US Equity | C27: Visa Inc | D27: =IFERROR(IF(MATCH($B27,Compounders!$A:$A,0),"yes"),"") -> yes | J27: =IF(AND(F27="",G27="",H27="",I27=""),"yes","") -> yes | K27: =K26+IF(F27="yes",1) -> 5 | L27: =L26+IF(G27="yes",1) -> 5 | M27: =M26+IF(H27="yes",1) -> 0 | N27: =N26+IF(I27="yes",1) -> 0 | Q27: =Q26+IF(Q$10=$P27,1) -> 4 | R27: =R26+IF(R$10=$P27,1) -> 1 | S27: =S26+IF(S$10=$P27,1) -> 0 | T27: =T26+IF(T$10=$P27,1) -> 0 | U27: =U26+IF(U$10=$P27,1) -> 0 | V27: =V26+IF(V$10=$P27,1) -> 0 | W27: =W26+IF(W$10=$P27,1) -> 0 | X27: =X26+IF(X$10=$P27,1) -> 0 | Y27: =Y26+IF(Y$10=$P27,1) -> 0 | AA27: 686.21915 | AB27: 589.96603 | AC27: 629.99528 | AE27: =$AC27-AA27 -> -56.223875 | AF27: =$AC27-AB27 -> 40.029246 | AH27: =$AC27/AA27-1 -> -0.081932827 | AI27: =$AC27/AB27-1 -> 0.067850086 | AK27: 19743 | AL27: 20058 | AN27: 24309.931 | AO27: 24244.241 | AP27: 24402.069 | AR27: 26865.207 | AS27: 27045.448 | AT27: 27472.172 | AV27: 29521.941 | AW27: 29794.727 | AX27: 30345.696 | AZ27: 20389 | BA27: 22542 | BC27: 24493 | BD27: 24600.135 | BE27: 25085.405 | BG27: 27039.735 | BH27: 27184.892 | BI27: 27692.162 | BK27: 29731.15 | BL27: 29946.154 | BM27: 30544.185 | BO27: =CHOOSE($AK$6,FH27,GH27) -> 20931.674 | BP27: =CHOOSE($AK$6,FI27,GI27) -> 23183.078 | BR27: =CHOOSE($AK$6,FK27,GK27) -> 25134.917 | BS27: =CHOOSE($AK$6,FL27,GL27) -> 25251.635 | BT27: =CHOOSE($AK$6,FM27,GM27) -> 25742.451 | BV27: =CHOOSE($AK$6,FO27,GO27) -> 27718.119 | BW27: =CHOOSE($AK$6,FP27,GP27) -> 27880.881 | BX27: =CHOOSE($AK$6,FQ27,GQ27) -> 28411.028 | BZ27: =BP27-BO27 -> 2251.4036 | CA27: =BT27-BP27 -> 2559.3734 | CB27: =BX27-BT27 -> 2668.5773 | CD27: =BP27/BO27-1 -> 0.10755965 | CE27: =BT27/BP27-1 -> 0.11039835 | CF27: =BX27/BT27-1 -> 0.10366446 | CH27: =BS27/$BR27-1 -> 0.0046436846 | CI27: =BT27/$BR27-1 -> 0.024170922 | CK27: =BW27/$BV27-1 -> 0.005872041 | CL27: =BX27/$BV27-1 -> 0.024998412 | CN27: =IFERROR(BS27-$BR27,"") -> 116.71863 | CO27: =IFERROR(BT27-$BR27,"") -> 607.5341 | CQ27: =IFERROR(BW27-$BV27,"") -> 162.76193 | CR27: =IFERROR(BX27-$BV27,"") -> 692.90896 | CT27: 26240.971 | CU27: 25204.184 | CV27: 24493 | CW27: 23900.851 | CX27: 23296.202 | CY27: 22680.234 | CZ27: 22031.417 | DA27: 21333.522 | DB27: 20921.041 | DC27: 20676.09 | DD27: 20084.314 | DE27: 19307.935 | DF27: 18670.034 | DG27: 17911 | DH27: 17257.846 | DI27: 16904.039 | DJ27: 16186.448 | DK27: 15757.009 | DL27: 15094.242 | DM27: 14799.769 | DN27: 13586.325 | DO27: 12542.825 | DP27: 11879.968 | DR27: =AC27 -> 629.99528 | DS27: 589.96603 | DT27: 686.21915 | DU27: 672.37087 | DV27: 703.75371 | DW27: 699.3299 | DX27: 633.01012 | DY27: 557.231 | DZ27: 538.85699 | EA27: 575.18196 | EB27: 536.84899 | EC27: 480.20331 | ED27: 498.30968 | EE27: 475.30711 | EF27: 438.59494 | EG27: 379.45291 | EH27: 422.58342 | EI27: 480.02248 | EJ27: 471.75141 | EK27: 489.13124 | EL27: 515.5188 | EM27: 467.76452 | EN27: 526.99116 | EP27: 45930 | EQ27: =(DATE(2025,12,31)-EP27)/365 -> 0.25205479 | ES27: =AK27 -> 19743 | ET27: =AL27 -> 20058 | EV27: =AN27 -> 24309.931 | EW27: =AO27 -> 24244.241 | EX27: =AP27 -> 24402.069 | EZ27: =AR27 -> 26865.207 | FA27: =AS27 -> 27045.448 | FB27: =AT27 -> 27472.172 | FD27: =AV27 -> 29521.941 | FE27: =AW27 -> 29794.727 | FF27: =AX27 -> 30345.696 | FH27: =IFERROR(IF($EQ27<0,ES27*-$EQ27+ET27*(1+$EQ27),ES27*(1-$EQ27)+ET27*$EQ27),"") -> 19822.397 | FI27: =IFERROR(IF($EQ27<0,ET27*-$EQ27+EX27*(1+$EQ27),ET27*(1-$EQ27)+EX27*$EQ27),"") -> 21152.943 | FK27: =IFERROR(IF($EQ27<0,EV27*-$EQ27+EZ27*(1+$EQ27),EV27*(1-$EQ27)+EZ27*$EQ27),"") -> 24954.001 | FL27: =IFERROR(IF($EQ27<0,EW27*-$EQ27+FA27*(1+$EQ27),EW27*(1-$EQ27)+FA27*$EQ27),"") -> 24950.299 | FM27: =IFERROR(IF($EQ27<0,EX27*-$EQ27+FB27*(1+$EQ27),EX27*(1-$EQ27)+FB27*$EQ27),"") -> 25175.903 | FO27: =IFERROR(IF($EQ27<0,EZ27*-$EQ27+FD27*(1+$EQ27),EZ27*(1-$EQ27)+FD27*$EQ27),"") -> 27534.85 | FP27: =IFERROR(IF($EQ27<0,FA27*-$EQ27+FE27*(1+$EQ27),FA27*(1-$EQ27)+FE27*$EQ27),"") -> 27738.417 | FQ27: =IFERROR(IF($EQ27<0,FB27*-$EQ27+FF27*(1+$EQ27),FB27*(1-$EQ27)+FF27*$EQ27),"") -> 28196.458 | FS27: =AZ27 -> 20389 | FT27: =BA27 -> 22542 | FV27: =BC27 -> 24493 | FW27: =BD27 -> 24600.135 | FX27: =BE27 -> 25085.405 | FZ27: =BG27 -> 27039.735 | GA27: =BH27 -> 27184.892 | GB27: =BI27 -> 27692.162 | GD27: =BK27 -> 29731.15 | GE27: =BL27 -> 29946.154 | GF27: =BM27 -> 30544.185 | GH27: =IFERROR(IF($EQ27<0,FS27*-$EQ27+FT27*(1+$EQ27),FS27*(1-$EQ27)+FT27*$EQ27),"") -> 20931.674 | GI27: =IFERROR(IF($EQ27<0,FT27*-$EQ27+FX27*(1+$EQ27),FT27*(1-$EQ27)+FX27*$EQ27),"") -> 23183.078 | GK27: =IFERROR(IF($EQ27<0,FV27*-$EQ27+FZ27*(1+$EQ27),FV27*(1-$EQ27)+FZ27*$EQ27),"") -> 25134.917 | GL27: =IFERROR(IF($EQ27<0,FW27*-$EQ27+GA27*(1+$EQ27),FW27*(1-$EQ27)+GA27*$EQ27),"") -> 25251.635 | GM27: =IFERROR(IF($EQ27<0,FX27*-$EQ27+GB27*(1+$EQ27),FX27*(1-$EQ27)+GB27*$EQ27),"") -> 25742.451 | GO27: =IFERROR(IF($EQ27<0,FZ27*-$EQ27+GD27*(1+$EQ27),FZ27*(1-$EQ27)+GD27*$EQ27),"") -> 27718.119 | GP27: =IFERROR(IF($EQ27<0,GA27*-$EQ27+GE27*(1+$EQ27),GA27*(1-$EQ27)+GE27*$EQ27),"") -> 27880.881 | GQ27: =IFERROR(IF($EQ27<0,GB27*-$EQ27+GF27*(1+$EQ27),GB27*(1-$EQ27)+GF27*$EQ27),"") -> 28411.028
B28: WMT US Equity | C28: Walmart Inc | D28: =IFERROR(IF(MATCH($B28,Compounders!$A:$A,0),"yes"),"") | J28: =IF(AND(F28="",G28="",H28="",I28=""),"yes","") -> yes | K28: =K27+IF(F28="yes",1) -> 5 | L28: =L27+IF(G28="yes",1) -> 5 | M28: =M27+IF(H28="yes",1) -> 0 | N28: =N27+IF(I28="yes",1) -> 0 | Q28: =Q27+IF(Q$10=$P28,1) -> 4 | R28: =R27+IF(R$10=$P28,1) -> 1 | S28: =S27+IF(S$10=$P28,1) -> 0 | T28: =T27+IF(T$10=$P28,1) -> 0 | U28: =U27+IF(U$10=$P28,1) -> 0 | V28: =V27+IF(V$10=$P28,1) -> 0 | W28: =W27+IF(W$10=$P28,1) -> 0 | X28: =X27+IF(X$10=$P28,1) -> 0 | Y28: =Y27+IF(Y$10=$P28,1) -> 0 | AA28: 887.9563 | AB28: 990.81018 | AC28: 921.14766 | AE28: =$AC28-AA28 -> 33.191361 | AF28: =$AC28-AB28 -> -69.662521 | AH28: =$AC28/AA28-1 -> 0.037379498 | AI28: =$AC28/AB28-1 -> -0.070308644 | AK28: 15511 | AL28: 19436 | AN28: 22804.958 | AO28: 21893 | AP28: 21893 | AR28: 23707.08 | AS28: 23055.19 | AT28: 23071.944 | AV28: 26248.895 | AW28: 25843.895 | AX28: 25670.778 | AZ28: 17974.95 | BA28: 20283.31 | BC28: 21355.812 | BD28: 21178.08 | BE28: 21178.08 | BG28: 23706 | BH28: 23212.312 | BI28: 23330.6 | BK28: 26446.444 | BL28: 25995.645 | BM28: 26043.73 | BO28: =CHOOSE($AK$6,FH28,GH28) -> 20087.258 | BP28: =CHOOSE($AK$6,FI28,GI28) -> 21102.086 | BR28: =CHOOSE($AK$6,FK28,GK28) -> 23506.395 | BS28: =CHOOSE($AK$6,FL28,GL28) -> 23039.542 | BT28: =CHOOSE($AK$6,FM28,GM28) -> 23147.783 | BV28: =CHOOSE($AK$6,FO28,GO28) -> 26213.694 | BW28: =CHOOSE($AK$6,FP28,GP28) -> 25759.253 | BX28: =CHOOSE($AK$6,FQ28,GQ28) -> 25813.3 | BZ28: =BP28-BO28 -> 1014.8283 | CA28: =BT28-BP28 -> 2045.6974 | CB28: =BX28-BT28 -> 2665.5163 | CD28: =BP28/BO28-1 -> 0.050521 | CE28: =BT28/BP28-1 -> 0.0969429 | CF28: =BX28/BT28-1 -> 0.11515212 | CH28: =BS28/$BR28-1 -> -0.019860679 | CI28: =BT28/$BR28-1 -> -0.015255925 | CK28: =BW28/$BV28-1 -> -0.017336047 | CL28: =BX28/$BV28-1 -> -0.015274262 | CN28: =IFERROR(BS28-$BR28,"") -> -466.85297 | CO28: =IFERROR(BT28-$BR28,"") -> -358.6118 | CQ28: =IFERROR(BW28-$BV28,"") -> -454.44184 | CR28: =IFERROR(BX28-$BV28,"") -> -400.39483 | CT28: 23802.644 | CU28: 23212.312 | CV28: 22950.439 | CW28: 22220.974 | CX28: 21467.289 | CY28: 21259.375 | CZ28: 21529.815 | DA28: 20729.024 | DB28: 19899.497 | DC28: 19028.571 | DD28: 18456.729 | DE28: 17992.893 | DF28: 17100.408 | DG28: 16838.595 | DH28: 17230.405 | DI28: 16815.127 | DJ28: 18053.815 | DK28: 18636.3 | DL28: 18317.467 | DM28: 17843.254 | DN28: 16571.326 | DO28: 15231.273 | DP28: 15951.922 | DR28: =AC28 -> 921.14766 | DS28: 990.81018 | DT28: 887.9563 | DU28: 821.68204 | DV28: 780.32529 | DW28: 703.79921 | DX28: 725.81644 | DY28: 649.08878 | DZ28: 544.62832 | EA28: 484.85279 | EB28: 424.43064 | EC28: 430.46181 | ED28: 423.25982 | EE28: 397.47447 | EF28: 382.37928 | EG28: 352.03666 | EH28: 333.26902 | EI28: 409.79502 | EJ28: 401.35247 | EK28: 388.66083 | EL28: 395.15862 | EM28: 382.64285 | EN28: 407.84157 | EP28: 46053 | EQ28: =(DATE(2025,12,31)-EP28)/365 -> -0.084931507 | ES28: =AK28 -> 15511 | ET28: =AL28 -> 19436 | EV28: =AN28 -> 22804.958 | EW28: =AO28 -> 21893 | EX28: =AP28 -> 21893 | EZ28: =AR28 -> 23707.08 | FA28: =AS28 -> 23055.19 | FB28: =AT28 -> 23071.944 | FD28: =AV28 -> 26248.895 | FE28: =AW28 -> 25843.895 | FF28: =AX28 -> 25670.778 | FH28: =IFERROR(IF($EQ28<0,ES28*-$EQ28+ET28*(1+$EQ28),ES28*(1-$EQ28)+ET28*$EQ28),"") -> 19102.644 | FI28: =IFERROR(IF($EQ28<0,ET28*-$EQ28+EX28*(1+$EQ28),ET28*(1-$EQ28)+EX28*$EQ28),"") -> 21684.323 | FK28: =IFERROR(IF($EQ28<0,EV28*-$EQ28+EZ28*(1+$EQ28),EV28*(1-$EQ28)+EZ28*$EQ28),"") -> 23630.461 | FL28: =IFERROR(IF($EQ28<0,EW28*-$EQ28+FA28*(1+$EQ28),EW28*(1-$EQ28)+FA28*$EQ28),"") -> 22956.484 | FM28: =IFERROR(IF($EQ28<0,EX28*-$EQ28+FB28*(1+$EQ28),EX28*(1-$EQ28)+FB28*$EQ28),"") -> 22971.815 | FO28: =IFERROR(IF($EQ28<0,EZ28*-$EQ28+FD28*(1+$EQ28),EZ28*(1-$EQ28)+FD28*$EQ28),"") -> 26033.015 | FP28: =IFERROR(IF($EQ28<0,FA28*-$EQ28+FE28*(1+$EQ28),FA28*(1-$EQ28)+FE28*$EQ28),"") -> 25607.046 | FQ28: =IFERROR(IF($EQ28<0,FB28*-$EQ28+FF28*(1+$EQ28),FB28*(1-$EQ28)+FF28*$EQ28),"") -> 25450.055 | FS28: =AZ28 -> 17974.95 | FT28: =BA28 -> 20283.31 | FV28: =BC28 -> 21355.812 | FW28: =BD28 -> 21178.08 | FX28: =BE28 -> 21178.08 | FZ28: =BG28 -> 23706 | GA28: =BH28 -> 23212.312 | GB28: =BI28 -> 23330.6 | GD28: =BK28 -> 26446.444 | GE28: =BL28 -> 25995.645 | GF28: =BM28 -> 26043.73 | GH28: =IFERROR(IF($EQ28<0,FS28*-$EQ28+FT28*(1+$EQ28),FS28*(1-$EQ28)+FT28*$EQ28),"") -> 20087.258 | GI28: =IFERROR(IF($EQ28<0,FT28*-$EQ28+FX28*(1+$EQ28),FT28*(1-$EQ28)+FX28*$EQ28),"") -> 21102.086 | GK28: =IFERROR(IF($EQ28<0,FV28*-$EQ28+FZ28*(1+$EQ28),FV28*(1-$EQ28)+FZ28*$EQ28),"") -> 23506.395 | GL28: =IFERROR(IF($EQ28<0,FW28*-$EQ28+GA28*(1+$EQ28),FW28*(1-$EQ28)+GA28*$EQ28),"") -> 23039.542 | GM28: =IFERROR(IF($EQ28<0,FX28*-$EQ28+GB28*(1+$EQ28),FX28*(1-$EQ28)+GB28*$EQ28),"") -> 23147.783 | GO28: =IFERROR(IF($EQ28<0,FZ28*-$EQ28+GD28*(1+$EQ28),FZ28*(1-$EQ28)+GD28*$EQ28),"") -> 26213.694 | GP28: =IFERROR(IF($EQ28<0,GA28*-$EQ28+GE28*(1+$EQ28),GA28*(1-$EQ28)+GE28*$EQ28),"") -> 25759.253 | GQ28: =IFERROR(IF($EQ28<0,GB28*-$EQ28+GF28*(1+$EQ28),GB28*(1-$EQ28)+GF28*$EQ28),"") -> 25813.3
B29: CSCO US Equity | C29: Cisco Systems Inc | D29: =IFERROR(IF(MATCH($B29,Compounders!$A:$A,0),"yes"),"") | G29: yes | J29: =IF(AND(F29="",G29="",H29="",I29=""),"yes","") | K29: =K28+IF(F29="yes",1) -> 5 | L29: =L28+IF(G29="yes",1) -> 6 | M29: =M28+IF(H29="yes",1) -> 0 | N29: =N28+IF(I29="yes",1) -> 0 | P29: Hardware/Components | Q29: =Q28+IF(Q$10=$P29,1) -> 4 | R29: =R28+IF(R$10=$P29,1) -> 1 | S29: =S28+IF(S$10=$P29,1) -> 0 | T29: =T28+IF(T$10=$P29,1) -> 0 | U29: =U28+IF(U$10=$P29,1) -> 0 | V29: =V28+IF(V$10=$P29,1) -> 0 | W29: =W28+IF(W$10=$P29,1) -> 1 | X29: =X28+IF(X$10=$P29,1) -> 0 | Y29: =Y28+IF(Y$10=$P29,1) -> 0 | AA29: 304.35281 | AB29: 306.4722 | AC29: 474.62756 | AE29: =$AC29-AA29 -> 170.27475 | AF29: =$AC29-AB29 -> 168.15536 | AH29: =$AC29/AA29-1 -> 0.559465 | AI29: =$AC29/AB29-1 -> 0.54868063 | AK29: 10320 | AL29: 10453 | AN29: 11975.267 | AO29: 12214.533 | AP29: 12853.722 | AR29: 13646.562 | AS29: 13555.143 | AT29: 14763.941 | AV29: 13750.1 | AW29: 14709.1 | AX29: 16879.929 | AZ29: 15150 | BA29: 15213 | BC29: 16395.13 | BD29: 16538.364 | BE29: 17034.174 | BG29: 17568.565 | BH29: 17815.273 | BI29: 18937.13 | BK29: 18610.25 | BL29: 19042.938 | BM29: 20713.05 | BO29: =CHOOSE($AK$6,FH29,GH29) -> 15177.271 | BP29: =CHOOSE($AK$6,FI29,GI29) -> 16001.344 | BR29: =CHOOSE($AK$6,FK29,GK29) -> 16903.083 | BS29: =CHOOSE($AK$6,FL29,GL29) -> 17091.108 | BT29: =CHOOSE($AK$6,FM29,GM29) -> 17857.919 | BV29: =CHOOSE($AK$6,FO29,GO29) -> 18019.486 | BW29: =CHOOSE($AK$6,FP29,GP29) -> 18346.7 | BX29: =CHOOSE($AK$6,FQ29,GQ29) -> 19705.885 | BZ29: =BP29-BO29 -> 824.07254 | CA29: =BT29-BP29 -> 1856.5757 | CB29: =BX29-BT29 -> 1847.9652 | CD29: =BP29/BO29-1 -> 0.054296489 | CE29: =BT29/BP29-1 -> 0.11602624 | CF29: =BX29/BT29-1 -> 0.10348155 | CH29: =BS29/$BR29-1 -> 0.0111237 | CI29: =BT29/$BR29-1 -> 0.056488893 | CK29: =BW29/$BV29-1 -> 0.018158893 | CL29: =BX29/$BV29-1 -> 0.093587482 | CN29: =IFERROR(BS29-$BR29,"") -> 188.02482 | CO29: =IFERROR(BT29-$BR29,"") -> 954.83645 | CQ29: =IFERROR(BW29-$BV29,"") -> 327.21392 | CR29: =IFERROR(BX29-$BV29,"") -> 1686.3984 | CT29: 18636.708 | CU29: 17002.307 | CV29: 16640.267 | CW29: 15993.136 | CX29: 15702.412 | CY29: 15245.717 | CZ29: 14683.571 | DA29: 14389.19 | DB29: 13860.993 | DC29: 14603.021 | DD29: 15355.908 | DE29: 16337.333 | DF29: 16444.789 | DG29: 16179.595 | DH29: 14791.972 | DI29: 14645.815 | DJ29: 14272.546 | DK29: 14948.321 | DL29: 14787.103 | DM29: 14473.36 | DN29: 13975.874 | DO29: 13989.71 | DP29: 13573.643 | DR29: =AC29 -> 474.62756 | DS29: 306.4722 | DT29: 304.35281 | DU29: 270.47774 | DV29: 274.74467 | DW29: 245.50043 | DX29: 235.77929 | DY29: 212.38691 | DZ29: 192.37688 | EA29: 202.09493 | EB29: 205.28679 | EC29: 217.98915 | ED29: 210.84351 | EE29: 214.10916 | EF29: 195.71003 | EG29: 164.35377 | EH29: 176.57071 | EI29: 231.63641 | EJ29: 267.26973 | EK29: 229.57137 | EL29: 223.35285 | EM29: 218.30853 | EN29: 189.09177 | EP29: 45864 | EQ29: =(DATE(2025,12,31)-EP29)/365 -> 0.43287671 | ES29: =AK29 -> 10320 | ET29: =AL29 -> 10453 | EV29: =AN29 -> 11975.267 | EW29: =AO29 -> 12214.533 | EX29: =AP29 -> 12853.722 | EZ29: =AR29 -> 13646.562 | FA29: =AS29 -> 13555.143 | FB29: =AT29 -> 14763.941 | FD29: =AV29 -> 13750.1 | FE29: =AW29 -> 14709.1 | FF29: =AX29 -> 16879.929 | FH29: =IFERROR(IF($EQ29<0,ES29*-$EQ29+ET29*(1+$EQ29),ES29*(1-$EQ29)+ET29*$EQ29),"") -> 10377.573 | FI29: =IFERROR(IF($EQ29<0,ET29*-$EQ29+EX29*(1+$EQ29),ET29*(1-$EQ29)+EX29*$EQ29),"") -> 11492.217 | FK29: =IFERROR(IF($EQ29<0,EV29*-$EQ29+EZ29*(1+$EQ29),EV29*(1-$EQ29)+EZ29*$EQ29),"") -> 12698.732 | FL29: =IFERROR(IF($EQ29<0,EW29*-$EQ29+FA29*(1+$EQ29),EW29*(1-$EQ29)+FA29*$EQ29),"") -> 12794.852 | FM29: =IFERROR(IF($EQ29<0,EX29*-$EQ29+FB29*(1+$EQ29),EX29*(1-$EQ29)+FB29*$EQ29),"") -> 13680.612 | FO29: =IFERROR(IF($EQ29<0,EZ29*-$EQ29+FD29*(1+$EQ29),EZ29*(1-$EQ29)+FD29*$EQ29),"") -> 13691.381 | FP29: =IFERROR(IF($EQ29<0,FA29*-$EQ29+FE29*(1+$EQ29),FA29*(1-$EQ29)+FE29*$EQ29),"") -> 14054.664 | FQ29: =IFERROR(IF($EQ29<0,FB29*-$EQ29+FF29*(1+$EQ29),FB29*(1-$EQ29)+FF29*$EQ29),"") -> 15679.903 | FS29: =AZ29 -> 15150 | FT29: =BA29 -> 15213 | FV29: =BC29 -> 16395.13 | FW29: =BD29 -> 16538.364 | FX29: =BE29 -> 17034.174 | FZ29: =BG29 -> 17568.565 | GA29: =BH29 -> 17815.273 | GB29: =BI29 -> 18937.13 | GD29: =BK29 -> 18610.25 | GE29: =BL29 -> 19042.938 | GF29: =BM29 -> 20713.05 | GH29: =IFERROR(IF($EQ29<0,FS29*-$EQ29+FT29*(1+$EQ29),FS29*(1-$EQ29)+FT29*$EQ29),"") -> 15177.271 | GI29: =IFERROR(IF($EQ29<0,FT29*-$EQ29+FX29*(1+$EQ29),FT29*(1-$EQ29)+FX29*$EQ29),"") -> 16001.344 | GK29: =IFERROR(IF($EQ29<0,FV29*-$EQ29+FZ29*(1+$EQ29),FV29*(1-$EQ29)+FZ29*$EQ29),"") -> 16903.083 | GL29: =IFERROR(IF($EQ29<0,FW29*-$EQ29+GA29*(1+$EQ29),FW29*(1-$EQ29)+GA29*$EQ29),"") -> 17091.108 | GM29: =IFERROR(IF($EQ29<0,FX29*-$EQ29+GB29*(1+$EQ29),FX29*(1-$EQ29)+GB29*$EQ29),"") -> 17857.919 | GO29: =IFERROR(IF($EQ29<0,FZ29*-$EQ29+GD29*(1+$EQ29),FZ29*(1-$EQ29)+GD29*$EQ29),"") -> 18019.486 | GP29: =IFERROR(IF($EQ29<0,GA29*-$EQ29+GE29*(1+$EQ29),GA29*(1-$EQ29)+GE29*$EQ29),"") -> 18346.7 | GQ29: =IFERROR(IF($EQ29<0,GB29*-$EQ29+GF29*(1+$EQ29),GB29*(1-$EQ29)+GF29*$EQ29),"") -> 19705.885
B30: COST US Equity | C30: Costco Wholesale Corp | D30: =IFERROR(IF(MATCH($B30,Compounders!$A:$A,0),"yes"),"") | J30: =IF(AND(F30="",G30="",H30="",I30=""),"yes","") -> yes | K30: =K29+IF(F30="yes",1) -> 5 | L30: =L29+IF(G30="yes",1) -> 6 | M30: =M29+IF(H30="yes",1) -> 0 | N30: =N29+IF(I30="yes",1) -> 0 | Q30: =Q29+IF(Q$10=$P30,1) -> 4 | R30: =R29+IF(R$10=$P30,1) -> 1 | S30: =S29+IF(S$10=$P30,1) -> 0 | T30: =T29+IF(T$10=$P30,1) -> 0 | U30: =U29+IF(U$10=$P30,1) -> 0 | V30: =V29+IF(V$10=$P30,1) -> 0 | W30: =W29+IF(W$10=$P30,1) -> 1 | X30: =X29+IF(X$10=$P30,1) -> 0 | Y30: =Y29+IF(Y$10=$P30,1) -> 0 | AA30: 382.76635 | AB30: 442.0687 | AC30: 424.14131 | AE30: =$AC30-AA30 -> 41.374961 | AF30: =$AC30-AB30 -> -17.927392 | AH30: =$AC30/AA30-1 -> 0.10809456 | AI30: =$AC30/AB30-1 -> -0.040553407 | AK30: 7367 | AL30: 8099 | AN30: 9041.9286 | AO30: 9103.7812 | AP30: 9116.0278 | AR30: 9869.5 | AS30: 10106.061 | AT30: 10047.361 | AV30: 10872.688 | AW30: 11209 | AX30: 11058.36 | AZ30: 7367 | BA30: 8099 | BC30: 9041.3793 | BD30: 9103.6667 | BE30: 9116.0278 | BG30: 9872.5862 | BH30: 10106.118 | BI30: 10047.361 | BK30: 10888.294 | BL30: 11213.273 | BM30: 11058.36 | BO30: =CHOOSE($AK$6,FH30,GH30) -> 7611.6685 | BP30: =CHOOSE($AK$6,FI30,GI30) -> 8438.9381 | BR30: =CHOOSE($AK$6,FK30,GK30) -> 9319.2074 | BS30: =CHOOSE($AK$6,FL30,GL30) -> 9438.7325 | BT30: =CHOOSE($AK$6,FM30,GM30) -> 9427.3228 | BV30: =CHOOSE($AK$6,FO30,GO30) -> 10212.083 | BW30: =CHOOSE($AK$6,FP30,GP30) -> 10476.18 | BX30: =CHOOSE($AK$6,FQ30,GQ30) -> 10385.284 | BZ30: =BP30-BO30 -> 827.26956 | CA30: =BT30-BP30 -> 988.3847 | CB30: =BX30-BT30 -> 957.96127 | CD30: =BP30/BO30-1 -> 0.10868439 | CE30: =BT30/BP30-1 -> 0.11712193 | CF30: =BX30/BT30-1 -> 0.10161541 | CH30: =BS30/$BR30-1 -> 0.012825673 | CI30: =BT30/$BR30-1 -> 0.01160135 | CK30: =BW30/$BV30-1 -> 0.025861261 | CL30: =BX30/$BV30-1 -> 0.016960392 | CN30: =IFERROR(BS30-$BR30,"") -> 119.5251 | CO30: =IFERROR(BT30-$BR30,"") -> 108.11539 | CQ30: =IFERROR(BW30-$BV30,"") -> 264.09734 | CR30: =IFERROR(BX30-$BV30,"") -> 173.20093 | CT30: 9744.5622 | CU30: 9459.4586 | CV30: 9140.059 | CW30: 8905.7353 | CX30: 8629.0433 | CY30: 8443.3013 | CZ30: 8242.6984 | DA30: 7931.6562 | DB30: 7625.7745 | DC30: 7352.1154 | DD30: 7038.5952 | DE30: 6924.4865 | DF30: 6759.7949 | DG30: 6636.0312 | DH30: 6517.3451 | DI30: 6460.7742 | DJ30: 6157.575 | DK30: 5973.35 | DL30: 5637.5751 | DM30: 5312.4167 | DN30: 4941.0476 | DO30: 4595.1761 | DP30: 4539.1866 | DR30: =AC30 -> 424.14131 | DS30: 442.0687 | DT30: 382.76635 | DU30: 410.4957 | DV30: 439.01571 | DW30: 419.62685 | DX30: 406.73122 | DY30: 393.02537 | DZ30: 376.83034 | EA30: 324.92436 | EB30: 292.89625 | EC30: 250.16033 | ED30: 238.58228 | EE30: 220.3535 | EF30: 202.5623 | EG30: 209.05693 | EH30: 212.30328 | EI30: 255.23071 | EJ30: 251.73662 | EK30: 198.53406 | EL30: 174.91348 | EM30: 155.98431 | EN30: 166.89667 | EP30: 45900 | EQ30: =(DATE(2025,12,31)-EP30)/365 -> 0.33424658 | ES30: =AK30 -> 7367 | ET30: =AL30 -> 8099 | EV30: =AN30 -> 9041.9286 | EW30: =AO30 -> 9103.7812 | EX30: =AP30 -> 9116.0278 | EZ30: =AR30 -> 9869.5 | FA30: =AS30 -> 10106.061 | FB30: =AT30 -> 10047.361 | FD30: =AV30 -> 10872.688 | FE30: =AW30 -> 11209 | FF30: =AX30 -> 11058.36 | FH30: =IFERROR(IF($EQ30<0,ES30*-$EQ30+ET30*(1+$EQ30),ES30*(1-$EQ30)+ET30*$EQ30),"") -> 7611.6685 | FI30: =IFERROR(IF($EQ30<0,ET30*-$EQ30+EX30*(1+$EQ30),ET30*(1-$EQ30)+EX30*$EQ30),"") -> 8438.9381 | FK30: =IFERROR(IF($EQ30<0,EV30*-$EQ30+EZ30*(1+$EQ30),EV30*(1-$EQ30)+EZ30*$EQ30),"") -> 9318.5415 | FL30: =IFERROR(IF($EQ30<0,EW30*-$EQ30+FA30*(1+$EQ30),EW30*(1-$EQ30)+FA30*$EQ30),"") -> 9438.7897 | FM30: =IFERROR(IF($EQ30<0,EX30*-$EQ30+FB30*(1+$EQ30),EX30*(1-$EQ30)+FB30*$EQ30),"") -> 9427.3228 | FO30: =IFERROR(IF($EQ30<0,EZ30*-$EQ30+FD30*(1+$EQ30),EZ30*(1-$EQ30)+FD30*$EQ30),"") -> 10204.812 | FP30: =IFERROR(IF($EQ30<0,FA30*-$EQ30+FE30*(1+$EQ30),FA30*(1-$EQ30)+FE30*$EQ30),"") -> 10474.714 | FQ30: =IFERROR(IF($EQ30<0,FB30*-$EQ30+FF30*(1+$EQ30),FB30*(1-$EQ30)+FF30*$EQ30),"") -> 10385.284 | FS30: =AZ30 -> 7367 | FT30: =BA30 -> 8099 | FV30: =BC30 -> 9041.3793 | FW30: =BD30 -> 9103.6667 | FX30: =BE30 -> 9116.0278 | FZ30: =BG30 -> 9872.5862 | GA30: =BH30 -> 10106.118 | GB30: =BI30 -> 10047.361 | GD30: =BK30 -> 10888.294 | GE30: =BL30 -> 11213.273 | GF30: =BM30 -> 11058.36 | GH30: =IFERROR(IF($EQ30<0,FS30*-$EQ30+FT30*(1+$EQ30),FS30*(1-$EQ30)+FT30*$EQ30),"") -> 7611.6685 | GI30: =IFERROR(IF($EQ30<0,FT30*-$EQ30+FX30*(1+$EQ30),FT30*(1-$EQ30)+FX30*$EQ30),"") -> 8438.9381 | GK30: =IFERROR(IF($EQ30<0,FV30*-$EQ30+FZ30*(1+$EQ30),FV30*(1-$EQ30)+FZ30*$EQ30),"") -> 9319.2074 | GL30: =IFERROR(IF($EQ30<0,FW30*-$EQ30+GA30*(1+$EQ30),FW30*(1-$EQ30)+GA30*$EQ30),"") -> 9438.7325 | GM30: =IFERROR(IF($EQ30<0,FX30*-$EQ30+GB30*(1+$EQ30),FX30*(1-$EQ30)+GB30*$EQ30),"") -> 9427.3228 | GO30: =IFERROR(IF($EQ30<0,FZ30*-$EQ30+GD30*(1+$EQ30),FZ30*(1-$EQ30)+GD30*$EQ30),"") -> 10212.083 | GP30: =IFERROR(IF($EQ30<0,GA30*-$EQ30+GE30*(1+$EQ30),GA30*(1-$EQ30)+GE30*$EQ30),"") -> 10476.18 | GQ30: =IFERROR(IF($EQ30<0,GB30*-$EQ30+GF30*(1+$EQ30),GB30*(1-$EQ30)+GF30*$EQ30),"") -> 10385.284
B31: CAT US Equity | C31: Caterpillar Inc | D31: =IFERROR(IF(MATCH($B31,Compounders!$A:$A,0),"yes"),"") -> yes | G31: yes | J31: =IF(AND(F31="",G31="",H31="",I31=""),"yes","") | K31: =K30+IF(F31="yes",1) -> 5 | L31: =L30+IF(G31="yes",1) -> 7 | M31: =M30+IF(H31="yes",1) -> 0 | N31: =N30+IF(I31="yes",1) -> 0 | P31: Power | Q31: =Q30+IF(Q$10=$P31,1) -> 4 | R31: =R30+IF(R$10=$P31,1) -> 1 | S31: =S30+IF(S$10=$P31,1) -> 0 | T31: =T30+IF(T$10=$P31,1) -> 0 | U31: =U30+IF(U$10=$P31,1) -> 1 | V31: =V30+IF(V$10=$P31,1) -> 0 | W31: =W30+IF(W$10=$P31,1) -> 1 | X31: =X30+IF(X$10=$P31,1) -> 0 | Y31: =Y30+IF(Y$10=$P31,1) -> 0 | AA31: 268.09147 | AB31: 329.63746 | AC31: 403.4187 | AE31: =$AC31-AA31 -> 135.32723 | AF31: =$AC31-AB31 -> 73.781237 | AH31: =$AC31/AA31-1 -> 0.50478006 | AI31: =$AC31/AB31-1 -> 0.2238254 | AK31: 10792 | AL31: 8884 | AN31: 10543.133 | AO31: 10695.444 | AP31: 11239.688 | AR31: 12595.231 | AS31: 12770.333 | AT31: 13718.375 | AV31: 14003.857 | AW31: 15078.8 | AX31: 16307.8 | AZ31: 10716 | BA31: 9004 | BC31: 10425.19 | BD31: 10599.435 | BE31: 11312.875 | BG31: 12201.812 | BH31: 12575.043 | BI31: 13604.304 | BK31: 14040.571 | BL31: 14562.615 | BM31: 16076.214 | BO31: =CHOOSE($AK$6,FH31,GH31) -> 10716 | BP31: =CHOOSE($AK$6,FI31,GI31) -> 9004 | BR31: =CHOOSE($AK$6,FK31,GK31) -> 10425.19 | BS31: =CHOOSE($AK$6,FL31,GL31) -> 10599.435 | BT31: =CHOOSE($AK$6,FM31,GM31) -> 11312.875 | BV31: =CHOOSE($AK$6,FO31,GO31) -> 12201.812 | BW31: =CHOOSE($AK$6,FP31,GP31) -> 12575.043 | BX31: =CHOOSE($AK$6,FQ31,GQ31) -> 13604.304 | BZ31: =BP31-BO31 -> -1712 | CA31: =BT31-BP31 -> 2308.875 | CB31: =BX31-BT31 -> 2291.4293 | CD31: =BP31/BO31-1 -> -0.1597611 | CE31: =BT31/BP31-1 -> 0.2564277 | CF31: =BX31/BT31-1 -> 0.20255058 | CH31: =BS31/$BR31-1 -> 0.016713777 | CI31: =BT31/$BR31-1 -> 0.085148039 | CK31: =BW31/$BV31-1 -> 0.030588159 | CL31: =BX31/$BV31-1 -> 0.11494127 | CN31: =IFERROR(BS31-$BR31,"") -> 174.24431 | CO31: =IFERROR(BT31-$BR31,"") -> 887.68452 | CQ31: =IFERROR(BW31-$BV31,"") -> 373.23098 | CR31: =IFERROR(BX31-$BV31,"") -> 1402.4918 | CT31: 11757.071 | CU31: 10599.435 | CV31: 9698.7822 | CW31: 8846.7042 | CX31: 8908.6667 | CY31: 9609.7143 | CZ31: 9885.8056 | DA31: 10154.597 | DB31: 10621.282 | DC31: 10516.733 | DD31: 10204.701 | DE31: 10148.237 | DF31: 9051.1839 | DG31: 8086.92 | DH31: 7801.2667 | DI31: 6883.6786 | DJ31: 6839 | DK31: 6419.087 | DL31: 6097.5934 | DM31: 5624.1987 | DN31: 5373.4359 | DO31: 4377.6316 | DP31: 3541.8667 | DR31: =AC31 -> 403.4187 | DS31: 329.63746 | DT31: 268.09147 | DU31: 223.53472 | DV31: 182.58098 | DW31: 157.62198 | DX31: 175.14143 | DY31: 189.65335 | DZ31: 162.9035 | EA31: 182.98681 | EB31: 150.52109 | EC31: 139.26907 | ED31: 126.80326 | EE31: 118.1605 | EF31: 124.66927 | EG31: 86.619332 | EH31: 95.34601 | EI31: 119.40658 | EJ31: 111.83427 | EK31: 105.0981 | EL31: 119.21492 | EM31: 126.4396 | EN31: 98.883873 | EP31: 46022 | EQ31: =(DATE(2025,12,31)-EP31)/365 -> 0 | ES31: =AK31 -> 10792 | ET31: =AL31 -> 8884 | EV31: =AN31 -> 10543.133 | EW31: =AO31 -> 10695.444 | EX31: =AP31 -> 11239.688 | EZ31: =AR31 -> 12595.231 | FA31: =AS31 -> 12770.333 | FB31: =AT31 -> 13718.375 | FD31: =AV31 -> 14003.857 | FE31: =AW31 -> 15078.8 | FF31: =AX31 -> 16307.8 | FH31: =IFERROR(IF($EQ31<0,ES31*-$EQ31+ET31*(1+$EQ31),ES31*(1-$EQ31)+ET31*$EQ31),"") -> 10792 | FI31: =IFERROR(IF($EQ31<0,ET31*-$EQ31+EX31*(1+$EQ31),ET31*(1-$EQ31)+EX31*$EQ31),"") -> 8884 | FK31: =IFERROR(IF($EQ31<0,EV31*-$EQ31+EZ31*(1+$EQ31),EV31*(1-$EQ31)+EZ31*$EQ31),"") -> 10543.133 | FL31: =IFERROR(IF($EQ31<0,EW31*-$EQ31+FA31*(1+$EQ31),EW31*(1-$EQ31)+FA31*$EQ31),"") -> 10695.444 | FM31: =IFERROR(IF($EQ31<0,EX31*-$EQ31+FB31*(1+$EQ31),EX31*(1-$EQ31)+FB31*$EQ31),"") -> 11239.688 | FO31: =IFERROR(IF($EQ31<0,EZ31*-$EQ31+FD31*(1+$EQ31),EZ31*(1-$EQ31)+FD31*$EQ31),"") -> 12595.231 | FP31: =IFERROR(IF($EQ31<0,FA31*-$EQ31+FE31*(1+$EQ31),FA31*(1-$EQ31)+FE31*$EQ31),"") -> 12770.333 | FQ31: =IFERROR(IF($EQ31<0,FB31*-$EQ31+FF31*(1+$EQ31),FB31*(1-$EQ31)+FF31*$EQ31),"") -> 13718.375 | FS31: =AZ31 -> 10716 | FT31: =BA31 -> 9004 | FV31: =BC31 -> 10425.19 | FW31: =BD31 -> 10599.435 | FX31: =BE31 -> 11312.875 | FZ31: =BG31 -> 12201.812 | GA31: =BH31 -> 12575.043 | GB31: =BI31 -> 13604.304 | GD31: =BK31 -> 14040.571 | GE31: =BL31 -> 14562.615 | GF31: =BM31 -> 16076.214 | GH31: =IFERROR(IF($EQ31<0,FS31*-$EQ31+FT31*(1+$EQ31),FS31*(1-$EQ31)+FT31*$EQ31),"") -> 10716 | GI31: =IFERROR(IF($EQ31<0,FT31*-$EQ31+FX31*(1+$EQ31),FT31*(1-$EQ31)+FX31*$EQ31),"") -> 9004 | GK31: =IFERROR(IF($EQ31<0,FV31*-$EQ31+FZ31*(1+$EQ31),FV31*(1-$EQ31)+FZ31*$EQ31),"") -> 10425.19 | GL31: =IFERROR(IF($EQ31<0,FW31*-$EQ31+GA31*(1+$EQ31),FW31*(1-$EQ31)+GA31*$EQ31),"") -> 10599.435 | GM31: =IFERROR(IF($EQ31<0,FX31*-$EQ31+GB31*(1+$EQ31),FX31*(1-$EQ31)+GB31*$EQ31),"") -> 11312.875 | GO31: =IFERROR(IF($EQ31<0,FZ31*-$EQ31+GD31*(1+$EQ31),FZ31*(1-$EQ31)+GD31*$EQ31),"") -> 12201.812 | GP31: =IFERROR(IF($EQ31<0,GA31*-$EQ31+GE31*(1+$EQ31),GA31*(1-$EQ31)+GE31*$EQ31),"") -> 12575.043 | GQ31: =IFERROR(IF($EQ31<0,GB31*-$EQ31+GF31*(1+$EQ31),GB31*(1-$EQ31)+GF31*$EQ31),"") -> 13604.304
B32: MA US Equity | C32: Mastercard Inc | D32: =IFERROR(IF(MATCH($B32,Compounders!$A:$A,0),"yes"),"") -> yes | J32: =IF(AND(F32="",G32="",H32="",I32=""),"yes","") -> yes | K32: =K31+IF(F32="yes",1) -> 5 | L32: =L31+IF(G32="yes",1) -> 7 | M32: =M31+IF(H32="yes",1) -> 0 | N32: =N31+IF(I32="yes",1) -> 0 | Q32: =Q31+IF(Q$10=$P32,1) -> 4 | R32: =R31+IF(R$10=$P32,1) -> 1 | S32: =S31+IF(S$10=$P32,1) -> 0 | T32: =T31+IF(T$10=$P32,1) -> 0 | U32: =U31+IF(U$10=$P32,1) -> 1 | V32: =V31+IF(V$10=$P32,1) -> 0 | W32: =W31+IF(W$10=$P32,1) -> 1 | X32: =X31+IF(X$10=$P32,1) -> 0 | Y32: =Y31+IF(Y$10=$P32,1) -> 0 | AA32: 512.64787 | AB32: 445.67376 | AC32: 436.56663 | AE32: =$AC32-AA32 -> -76.081241 | AF32: =$AC32-AB32 -> -9.1071325 | AH32: =$AC32/AA32-1 -> -0.14840838 | AI32: =$AC32/AB32-1 -> -0.020434527 | AK32: 12874 | AL32: 14968 | AN32: 16956.71 | AO32: 17194.355 | AP32: 17141.467 | AR32: 19276.64 | AS32: 19515.452 | AT32: 19522.387 | AV32: 21455.6 | AW32: 22064.588 | AX32: 21962.667 | AZ32: 13541 | BA32: 15415 | BC32: 16979.351 | BD32: 17344.556 | BE32: 17387.75 | BG32: 19314.7 | BH32: 19580.568 | BI32: 19631.622 | BK32: 21562.8 | BL32: 22196.81 | BM32: 22166.304 | BO32: =CHOOSE($AK$6,FH32,GH32) -> 13541 | BP32: =CHOOSE($AK$6,FI32,GI32) -> 15415 | BR32: =CHOOSE($AK$6,FK32,GK32) -> 16979.351 | BS32: =CHOOSE($AK$6,FL32,GL32) -> 17344.556 | BT32: =CHOOSE($AK$6,FM32,GM32) -> 17387.75 | BV32: =CHOOSE($AK$6,FO32,GO32) -> 19314.7 | BW32: =CHOOSE($AK$6,FP32,GP32) -> 19580.568 | BX32: =CHOOSE($AK$6,FQ32,GQ32) -> 19631.622 | BZ32: =BP32-BO32 -> 1874 | CA32: =BT32-BP32 -> 1972.75 | CB32: =BX32-BT32 -> 2243.8716 | CD32: =BP32/BO32-1 -> 0.13839451 | CE32: =BT32/BP32-1 -> 0.127976 | CF32: =BX32/BT32-1 -> 0.12904899 | CH32: =BS32/$BR32-1 -> 0.021508725 | CI32: =BT32/$BR32-1 -> 0.024052665 | CK32: =BW32/$BV32-1 -> 0.013765037 | CL32: =BX32/$BV32-1 -> 0.016408312 | CN32: =IFERROR(BS32-$BR32,"") -> 365.2042 | CO32: =IFERROR(BT32-$BR32,"") -> 408.39865 | CQ32: =IFERROR(BW32-$BV32,"") -> 265.86757 | CR32: =IFERROR(BX32-$BV32,"") -> 316.92162 | CT32: 17765.519 | CU32: 17344.556 | CV32: 16414.183 | CW32: 15805.562 | CX32: 14857.929 | CY32: 14406.171 | CZ32: 14318.41 | DA32: 14022.316 | DB32: 13638.051 | DC32: 13413.455 | DD32: 12778.517 | DE32: 12508.222 | DF32: 11957.471 | DG32: 11578.333 | DH32: 10960.236 | DI32: 10736.62 | DJ32: 10315.454 | DK32: 10068.029 | DL32: 9601.5735 | DM32: 9129.2857 | DN32: 8276.0285 | DO32: 7972.3158 | DP32: 7422.978 | DR32: =AC32 -> 436.56663 | DS32: 445.67376 | DT32: 512.64787 | DU32: 514.21097 | DV32: 510.26828 | DW32: 499.72567 | DX32: 483.3575 | DY32: 456.21143 | DZ32: 410.11928 | EA32: 449.25256 | EB32: 399.97087 | EC32: 373.03129 | ED32: 372.70243 | EE32: 346.41787 | EF32: 334.32841 | EG32: 274.77937 | EH32: 306.84996 | EI32: 349.33053 | EJ32: 353.05252 | EK32: 343.08195 | EL32: 361.82153 | EM32: 353.68666 | EN32: 355.84253 | EP32: 46022 | EQ32: =(DATE(2025,12,31)-EP32)/365 -> 0 | ES32: =AK32 -> 12874 | ET32: =AL32 -> 14968 | EV32: =AN32 -> 16956.71 | EW32: =AO32 -> 17194.355 | EX32: =AP32 -> 17141.467 | EZ32: =AR32 -> 19276.64 | FA32: =AS32 -> 19515.452 | FB32: =AT32 -> 19522.387 | FD32: =AV32 -> 21455.6 | FE32: =AW32 -> 22064.588 | FF32: =AX32 -> 21962.667 | FH32: =IFERROR(IF($EQ32<0,ES32*-$EQ32+ET32*(1+$EQ32),ES32*(1-$EQ32)+ET32*$EQ32),"") -> 12874 | FI32: =IFERROR(IF($EQ32<0,ET32*-$EQ32+EX32*(1+$EQ32),ET32*(1-$EQ32)+EX32*$EQ32),"") -> 14968 | FK32: =IFERROR(IF($EQ32<0,EV32*-$EQ32+EZ32*(1+$EQ32),EV32*(1-$EQ32)+EZ32*$EQ32),"") -> 16956.71 | FL32: =IFERROR(IF($EQ32<0,EW32*-$EQ32+FA32*(1+$EQ32),EW32*(1-$EQ32)+FA32*$EQ32),"") -> 17194.355 | FM32: =IFERROR(IF($EQ32<0,EX32*-$EQ32+FB32*(1+$EQ32),EX32*(1-$EQ32)+FB32*$EQ32),"") -> 17141.467 | FO32: =IFERROR(IF($EQ32<0,EZ32*-$EQ32+FD32*(1+$EQ32),EZ32*(1-$EQ32)+FD32*$EQ32),"") -> 19276.64 | FP32: =IFERROR(IF($EQ32<0,FA32*-$EQ32+FE32*(1+$EQ32),FA32*(1-$EQ32)+FE32*$EQ32),"") -> 19515.452 | FQ32: =IFERROR(IF($EQ32<0,FB32*-$EQ32+FF32*(1+$EQ32),FB32*(1-$EQ32)+FF32*$EQ32),"") -> 19522.387 | FS32: =AZ32 -> 13541 | FT32: =BA32 -> 15415 | FV32: =BC32 -> 16979.351 | FW32: =BD32 -> 17344.556 | FX32: =BE32 -> 17387.75 | FZ32: =BG32 -> 19314.7 | GA32: =BH32 -> 19580.568 | GB32: =BI32 -> 19631.622 | GD32: =BK32 -> 21562.8 | GE32: =BL32 -> 22196.81 | GF32: =BM32 -> 22166.304 | GH32: =IFERROR(IF($EQ32<0,FS32*-$EQ32+FT32*(1+$EQ32),FS32*(1-$EQ32)+FT32*$EQ32),"") -> 13541 | GI32: =IFERROR(IF($EQ32<0,FT32*-$EQ32+FX32*(1+$EQ32),FT32*(1-$EQ32)+FX32*$EQ32),"") -> 15415 | GK32: =IFERROR(IF($EQ32<0,FV32*-$EQ32+FZ32*(1+$EQ32),FV32*(1-$EQ32)+FZ32*$EQ32),"") -> 16979.351 | GL32: =IFERROR(IF($EQ32<0,FW32*-$EQ32+GA32*(1+$EQ32),FW32*(1-$EQ32)+GA32*$EQ32),"") -> 17344.556 | GM32: =IFERROR(IF($EQ32<0,FX32*-$EQ32+GB32*(1+$EQ32),FX32*(1-$EQ32)+GB32*$EQ32),"") -> 17387.75 | GO32: =IFERROR(IF($EQ32<0,FZ32*-$EQ32+GD32*(1+$EQ32),FZ32*(1-$EQ32)+GD32*$EQ32),"") -> 19314.7 | GP32: =IFERROR(IF($EQ32<0,GA32*-$EQ32+GE32*(1+$EQ32),GA32*(1-$EQ32)+GE32*$EQ32),"") -> 19580.568 | GQ32: =IFERROR(IF($EQ32<0,GB32*-$EQ32+GF32*(1+$EQ32),GB32*(1-$EQ32)+GF32*$EQ32),"") -> 19631.622
B33: LRCX US Equity | C33: Lam Research Corp | D33: =IFERROR(IF(MATCH($B33,Compounders!$A:$A,0),"yes"),"") | G33: yes | J33: =IF(AND(F33="",G33="",H33="",I33=""),"yes","") | K33: =K32+IF(F33="yes",1) -> 5 | L33: =L32+IF(G33="yes",1) -> 8 | M33: =M32+IF(H33="yes",1) -> 0 | N33: =N32+IF(I33="yes",1) -> 0 | P33: Semicap | Q33: =Q32+IF(Q$10=$P33,1) -> 4 | R33: =R32+IF(R$10=$P33,1) -> 1 | S33: =S32+IF(S$10=$P33,1) -> 1 | T33: =T32+IF(T$10=$P33,1) -> 0 | U33: =U32+IF(U$10=$P33,1) -> 1 | V33: =V32+IF(V$10=$P33,1) -> 0 | W33: =W32+IF(W$10=$P33,1) -> 1 | X33: =X32+IF(X$10=$P33,1) -> 0 | Y33: =Y32+IF(Y$10=$P33,1) -> 0 | AA33: 215.00722 | AB33: 266.81241 | AC33: 397.90668 | AE33: =$AC33-AA33 -> 182.89947 | AF33: =$AC33-AB33 -> 131.09427 | AH33: =$AC33/AA33-1 -> 0.85066664 | AI33: =$AC33/AB33-1 -> 0.49133497 | AK33: 3827.772 | AL33: 5358.217 | AN33: 6038.5238 | AO33: 6679.6 | AP33: 7099.7826 | AR33: 6906.3333 | AS33: 8747.2917 | AT33: 9841.3043 | AV33: 7531.9091 | AW33: 9866.9231 | AX33: 11952.286 | AZ33: 3997.82 | BA33: 5330.229 | BC33: 6106.9259 | BD33: 6716.0323 | BE33: 7143.375 | BG33: 7098.913 | BH33: 8776.5667 | BI33: 9905.3438 | BK33: 7736.1333 | BL33: 9811 | BM33: 11627.381 | BO33: =CHOOSE($AK$6,FH33,GH33) -> 4673.1506 | BP33: =CHOOSE($AK$6,FI33,GI33) -> 6249.2208 | BR33: =CHOOSE($AK$6,FK33,GK33) -> 6609.7139 | BS33: =CHOOSE($AK$6,FL33,GL33) -> 7760.4127 | BT33: =CHOOSE($AK$6,FM33,GM33) -> 8543.277 | BV33: =CHOOSE($AK$6,FO33,GO33) -> 7421.8877 | BW33: =CHOOSE($AK$6,FP33,GP33) -> 9300.8685 | BX33: =CHOOSE($AK$6,FQ33,GQ33) -> 10778.157 | BZ33: =BP33-BO33 -> 1576.0702 | CA33: =BT33-BP33 -> 2294.0562 | CB33: =BX33-BT33 -> 2234.8802 | CD33: =BP33/BO33-1 -> 0.33726074 | CE33: =BT33/BP33-1 -> 0.36709475 | CF33: =BX33/BT33-1 -> 0.26159519 | CH33: =BS33/$BR33-1 -> 0.17409207 | CI33: =BT33/$BR33-1 -> 0.29253355 | CK33: =BW33/$BV33-1 -> 0.2531675 | CL33: =BX33/$BV33-1 -> 0.45221237 | CN33: =IFERROR(BS33-$BR33,"") -> 1150.6988 | CO33: =IFERROR(BT33-$BR33,"") -> 1933.5631 | CQ33: =IFERROR(BW33-$BV33,"") -> 1878.9808 | CR33: =IFERROR(BX33-$BV33,"") -> 3356.2694 | CT33: 9266.4167 | CU33: 7720.67 | CV33: 6193.0304 | CW33: 5651.7241 | CX33: 5280.6467 | CY33: 4955.4654 | CZ33: 4712.5435 | DA33: 4636.963 | DB33: 4399.1981 | DC33: 4104.817 | DD33: 3727.6219 | DE33: 3515.1818 | DF33: 3149.5082 | DG33: 3268.0526 | DH33: 4077.0396 | DI33: 5044.0435 | DJ33: 4868.5882 | DK33: 4997.6875 | DL33: 4931.7667 | DM33: 4774.75 | DN33: 4472.1569 | DO33: 3697.693 | DP33: 3289.4044 | DR33: =AC33 -> 397.90668 | DS33: 266.81241 | DT33: 215.00722 | DU33: 168.85222 | DV33: 124.50935 | DW33: 93.322227 | DX33: 92.937258 | DY33: 105.77333 | DZ33: 139.21423 | EA33: 127.37574 | EB33: 103.2274 | EC33: 83.054359 | ED33: 86.362117 | EE33: 71.532383 | EF33: 57.320235 | EG33: 50.081437 | EH33: 59.113409 | EI33: 74.996672 | EJ33: 101.25538 | EK33: 80.137872 | EL33: 92.802408 | EM33: 85.064745 | EN33: 68.011234 | EP33: 45837 | EQ33: =(DATE(2025,12,31)-EP33)/365 -> 0.50684932 | ES33: =AK33 -> 3827.772 | ET33: =AL33 -> 5358.217 | EV33: =AN33 -> 6038.5238 | EW33: =AO33 -> 6679.6 | EX33: =AP33 -> 7099.7826 | EZ33: =AR33 -> 6906.3333 | FA33: =AS33 -> 8747.2917 | FB33: =AT33 -> 9841.3043 | FD33: =AV33 -> 7531.9091 | FE33: =AW33 -> 9866.9231 | FF33: =AX33 -> 11952.286 | FH33: =IFERROR(IF($EQ33<0,ES33*-$EQ33+ET33*(1+$EQ33),ES33*(1-$EQ33)+ET33*$EQ33),"") -> 4603.477 | FI33: =IFERROR(IF($EQ33<0,ET33*-$EQ33+EX33*(1+$EQ33),ET33*(1-$EQ33)+EX33*$EQ33),"") -> 6240.9283 | FK33: =IFERROR(IF($EQ33<0,EV33*-$EQ33+EZ33*(1+$EQ33),EV33*(1-$EQ33)+EZ33*$EQ33),"") -> 6478.3725 | FL33: =IFERROR(IF($EQ33<0,EW33*-$EQ33+FA33*(1+$EQ33),EW33*(1-$EQ33)+FA33*$EQ33),"") -> 7727.6081 | FM33: =IFERROR(IF($EQ33<0,EX33*-$EQ33+FB33*(1+$EQ33),EX33*(1-$EQ33)+FB33*$EQ33),"") -> 8489.321 | FO33: =IFERROR(IF($EQ33<0,EZ33*-$EQ33+FD33*(1+$EQ33),EZ33*(1-$EQ33)+FD33*$EQ33),"") -> 7223.406 | FP33: =IFERROR(IF($EQ33<0,FA33*-$EQ33+FE33*(1+$EQ33),FA33*(1-$EQ33)+FE33*$EQ33),"") -> 9314.7761 | FQ33: =IFERROR(IF($EQ33<0,FB33*-$EQ33+FF33*(1+$EQ33),FB33*(1-$EQ33)+FF33*$EQ33),"") -> 10911.254 | FS33: =AZ33 -> 3997.82 | FT33: =BA33 -> 5330.229 | FV33: =BC33 -> 6106.9259 | FW33: =BD33 -> 6716.0323 | FX33: =BE33 -> 7143.375 | FZ33: =BG33 -> 7098.913 | GA33: =BH33 -> 8776.5667 | GB33: =BI33 -> 9905.3438 | GD33: =BK33 -> 7736.1333 | GE33: =BL33 -> 9811 | GF33: =BM33 -> 11627.381 | GH33: =IFERROR(IF($EQ33<0,FS33*-$EQ33+FT33*(1+$EQ33),FS33*(1-$EQ33)+FT33*$EQ33),"") -> 4673.1506 | GI33: =IFERROR(IF($EQ33<0,FT33*-$EQ33+FX33*(1+$EQ33),FT33*(1-$EQ33)+FX33*$EQ33),"") -> 6249.2208 | GK33: =IFERROR(IF($EQ33<0,FV33*-$EQ33+FZ33*(1+$EQ33),FV33*(1-$EQ33)+FZ33*$EQ33),"") -> 6609.7139 | GL33: =IFERROR(IF($EQ33<0,FW33*-$EQ33+GA33*(1+$EQ33),FW33*(1-$EQ33)+GA33*$EQ33),"") -> 7760.4127 | GM33: =IFERROR(IF($EQ33<0,FX33*-$EQ33+GB33*(1+$EQ33),FX33*(1-$EQ33)+GB33*$EQ33),"") -> 8543.277 | GO33: =IFERROR(IF($EQ33<0,FZ33*-$EQ33+GD33*(1+$EQ33),FZ33*(1-$EQ33)+GD33*$EQ33),"") -> 7421.8877 | GP33: =IFERROR(IF($EQ33<0,GA33*-$EQ33+GE33*(1+$EQ33),GA33*(1-$EQ33)+GE33*$EQ33),"") -> 9300.8685 | GQ33: =IFERROR(IF($EQ33<0,GB33*-$EQ33+GF33*(1+$EQ33),GB33*(1-$EQ33)+GF33*$EQ33),"") -> 10778.157
B34: ABBV US Equity | C34: Abbvie Inc | D34: =IFERROR(IF(MATCH($B34,Compounders!$A:$A,0),"yes"),"") | J34: =IF(AND(F34="",G34="",H34="",I34=""),"yes","") -> yes | K34: =K33+IF(F34="yes",1) -> 5 | L34: =L33+IF(G34="yes",1) -> 8 | M34: =M33+IF(H34="yes",1) -> 0 | N34: =N33+IF(I34="yes",1) -> 0 | Q34: =Q33+IF(Q$10=$P34,1) -> 4 | R34: =R33+IF(R$10=$P34,1) -> 1 | S34: =S33+IF(S$10=$P34,1) -> 1 | T34: =T33+IF(T$10=$P34,1) -> 0 | U34: =U33+IF(U$10=$P34,1) -> 1 | V34: =V33+IF(V$10=$P34,1) -> 0 | W34: =W33+IF(W$10=$P34,1) -> 1 | X34: =X33+IF(X$10=$P34,1) -> 0 | Y34: =Y33+IF(Y$10=$P34,1) -> 0 | AA34: 403.82971 | AB34: 384.68813 | AC34: 384.66613 | AE34: =$AC34-AA34 -> -19.163582 | AF34: =$AC34-AB34 -> -0.021996386 | AH34: =$AC34/AA34-1 -> -0.04745461 | AI34: =$AC34/AB34-1 -> -5.7179788e-05 | AK34: 4278 | AL34: 4226 | AN34: 18462.85 | AO34: 18547 | AP34: 17128.524 | AR34: 21414.647 | AS34: 23626.278 | AT34: 22283.3 | AV34: 23820.071 | AW34: 26593.588 | AX34: 25101.263 | AZ34: 18001 | BA34: 17784 | BC34: 25023.909 | BD34: 25875.3 | BE34: 25230.095 | BG34: 28125.905 | BH34: 27928.5 | BI34: 28061.174 | BK34: 31495.125 | BL34: 31312.286 | BM34: 30918 | BO34: =CHOOSE($AK$6,FH34,GH34) -> 18001 | BP34: =CHOOSE($AK$6,FI34,GI34) -> 17784 | BR34: =CHOOSE($AK$6,FK34,GK34) -> 25023.909 | BS34: =CHOOSE($AK$6,FL34,GL34) -> 25875.3 | BT34: =CHOOSE($AK$6,FM34,GM34) -> 25230.095 | BV34: =CHOOSE($AK$6,FO34,GO34) -> 28125.905 | BW34: =CHOOSE($AK$6,FP34,GP34) -> 27928.5 | BX34: =CHOOSE($AK$6,FQ34,GQ34) -> 28061.174 | BZ34: =BP34-BO34 -> -217 | CA34: =BT34-BP34 -> 7446.0952 | CB34: =BX34-BT34 -> 2831.0787 | CD34: =BP34/BO34-1 -> -0.012054886 | CE34: =BT34/BP34-1 -> 0.41869631 | CF34: =BX34/BT34-1 -> 0.11221038 | CH34: =BS34/$BR34-1 -> 0.034023098 | CI34: =BT34/$BR34-1 -> 0.0082395659 | CK34: =BW34/$BV34-1 -> -0.0070186102 | CL34: =BX34/$BV34-1 -> -0.0023014673 | CN34: =IFERROR(BS34-$BR34,"") -> 851.39091 | CO34: =IFERROR(BT34-$BR34,"") -> 206.18615 | CQ34: =IFERROR(BW34-$BV34,"") -> -197.40476 | CR34: =IFERROR(BX34-$BV34,"") -> -64.730849 | CT34: 26366.033 | CU34: 25875.3 | CV34: 23740.937 | CW34: 23441.519 | CX34: 22652.113 | CY34: 21875 | CZ34: 20974.143 | DA34: 20792.878 | DB34: 20680.25 | DC34: 19845.133 | DD34: 19690.018 | DE34: 19336.28 | DF34: 19532.662 | DG34: 19605.385 | DH34: 22414.85 | DI34: 23544.708 | DJ34: 24794.25 | DK34: 25302.81 | DL34: 23969.661 | DM34: 23286.079 | DN34: 23046.064 | DO34: 22154.533 | DP34: 21097.6 | DR34: =AC34 -> 384.66613 | DS34: 384.68813 | DT34: 403.82971 | DU34: 409.0289 | DV34: 327.87973 | DW34: 370.63633 | DX34: 314.02084 | DY34: 348.81756 | DZ34: 302.88164 | EA34: 322.43482 | EB34: 273.60533 | EC34: 263.09786 | ED34: 237.70275 | EE34: 281.98927 | EF34: 285.80413 | EG34: 237.29623 | EH34: 270.65058 | EI34: 286.33245 | EJ34: 239.37101 | EK34: 190.62522 | EL34: 198.94728 | EM34: 191.10372 | EN34: 189.17053 | EP34: 46022 | EQ34: =(DATE(2025,12,31)-EP34)/365 -> 0 | ES34: =AK34 -> 4278 | ET34: =AL34 -> 4226 | EV34: =AN34 -> 18462.85 | EW34: =AO34 -> 18547 | EX34: =AP34 -> 17128.524 | EZ34: =AR34 -> 21414.647 | FA34: =AS34 -> 23626.278 | FB34: =AT34 -> 22283.3 | FD34: =AV34 -> 23820.071 | FE34: =AW34 -> 26593.588 | FF34: =AX34 -> 25101.263 | FH34: =IFERROR(IF($EQ34<0,ES34*-$EQ34+ET34*(1+$EQ34),ES34*(1-$EQ34)+ET34*$EQ34),"") -> 4278 | FI34: =IFERROR(IF($EQ34<0,ET34*-$EQ34+EX34*(1+$EQ34),ET34*(1-$EQ34)+EX34*$EQ34),"") -> 4226 | FK34: =IFERROR(IF($EQ34<0,EV34*-$EQ34+EZ34*(1+$EQ34),EV34*(1-$EQ34)+EZ34*$EQ34),"") -> 18462.85 | FL34: =IFERROR(IF($EQ34<0,EW34*-$EQ34+FA34*(1+$EQ34),EW34*(1-$EQ34)+FA34*$EQ34),"") -> 18547 | FM34: =IFERROR(IF($EQ34<0,EX34*-$EQ34+FB34*(1+$EQ34),EX34*(1-$EQ34)+FB34*$EQ34),"") -> 17128.524 | FO34: =IFERROR(IF($EQ34<0,EZ34*-$EQ34+FD34*(1+$EQ34),EZ34*(1-$EQ34)+FD34*$EQ34),"") -> 21414.647 | FP34: =IFERROR(IF($EQ34<0,FA34*-$EQ34+FE34*(1+$EQ34),FA34*(1-$EQ34)+FE34*$EQ34),"") -> 23626.278 | FQ34: =IFERROR(IF($EQ34<0,FB34*-$EQ34+FF34*(1+$EQ34),FB34*(1-$EQ34)+FF34*$EQ34),"") -> 22283.3 | FS34: =AZ34 -> 18001 | FT34: =BA34 -> 17784 | FV34: =BC34 -> 25023.909 | FW34: =BD34 -> 25875.3 | FX34: =BE34 -> 25230.095 | FZ34: =BG34 -> 28125.905 | GA34: =BH34 -> 27928.5 | GB34: =BI34 -> 28061.174 | GD34: =BK34 -> 31495.125 | GE34: =BL34 -> 31312.286 | GF34: =BM34 -> 30918 | GH34: =IFERROR(IF($EQ34<0,FS34*-$EQ34+FT34*(1+$EQ34),FS34*(1-$EQ34)+FT34*$EQ34),"") -> 18001 | GI34: =IFERROR(IF($EQ34<0,FT34*-$EQ34+FX34*(1+$EQ34),FT34*(1-$EQ34)+FX34*$EQ34),"") -> 17784 | GK34: =IFERROR(IF($EQ34<0,FV34*-$EQ34+FZ34*(1+$EQ34),FV34*(1-$EQ34)+FZ34*$EQ34),"") -> 25023.909 | GL34: =IFERROR(IF($EQ34<0,FW34*-$EQ34+GA34*(1+$EQ34),FW34*(1-$EQ34)+GA34*$EQ34),"") -> 25875.3 | GM34: =IFERROR(IF($EQ34<0,FX34*-$EQ34+GB34*(1+$EQ34),FX34*(1-$EQ34)+GB34*$EQ34),"") -> 25230.095 | GO34: =IFERROR(IF($EQ34<0,FZ34*-$EQ34+GD34*(1+$EQ34),FZ34*(1-$EQ34)+GD34*$EQ34),"") -> 28125.905 | GP34: =IFERROR(IF($EQ34<0,GA34*-$EQ34+GE34*(1+$EQ34),GA34*(1-$EQ34)+GE34*$EQ34),"") -> 27928.5 | GQ34: =IFERROR(IF($EQ34<0,GB34*-$EQ34+GF34*(1+$EQ34),GB34*(1-$EQ34)+GF34*$EQ34),"") -> 28061.174
B35: NFLX US Equity | C35: Netflix Inc | D35: =IFERROR(IF(MATCH($B35,Compounders!$A:$A,0),"yes"),"") | J35: =IF(AND(F35="",G35="",H35="",I35=""),"yes","") -> yes | K35: =K34+IF(F35="yes",1) -> 5 | L35: =L34+IF(G35="yes",1) -> 8 | M35: =M34+IF(H35="yes",1) -> 0 | N35: =N34+IF(I35="yes",1) -> 0 | Q35: =Q34+IF(Q$10=$P35,1) -> 4 | R35: =R34+IF(R$10=$P35,1) -> 1 | S35: =S34+IF(S$10=$P35,1) -> 1 | T35: =T34+IF(T$10=$P35,1) -> 0 | U35: =U34+IF(U$10=$P35,1) -> 1 | V35: =V34+IF(V$10=$P35,1) -> 0 | W35: =W34+IF(W$10=$P35,1) -> 1 | X35: =X34+IF(X$10=$P35,1) -> 0 | Y35: =Y34+IF(Y$10=$P35,1) -> 0 | AA35: 428.43585 | AB35: 405.96089 | AC35: 362.21289 | AE35: =$AC35-AA35 -> -66.222966 | AF35: =$AC35-AB35 -> -43.748001 | AH35: =$AC35/AA35-1 -> -0.15456915 | AI35: =$AC35/AB35-1 -> -0.10776408 | AK35: 8711.631 | AL35: 10981.201 | AN35: 13829.37 | AO35: 13631.444 | AP35: 15347.58 | AR35: 16533.868 | AS35: 16275.8 | AT35: 16183.959 | AV35: 19247.182 | AW35: 19176.622 | AX35: 19078.5 | AZ35: 8984.219 | BA35: 11349.65 | BC35: 13786.714 | BD35: 13536.875 | BE35: 15384.167 | BG35: 16300.4 | BH35: 16609.125 | BI35: 16162.667 | BK35: 18509.5 | BL35: 19854.273 | BM35: 19105 | BO35: =CHOOSE($AK$6,FH35,GH35) -> 8984.219 | BP35: =CHOOSE($AK$6,FI35,GI35) -> 11349.65 | BR35: =CHOOSE($AK$6,FK35,GK35) -> 13786.714 | BS35: =CHOOSE($AK$6,FL35,GL35) -> 13536.875 | BT35: =CHOOSE($AK$6,FM35,GM35) -> 15384.167 | BV35: =CHOOSE($AK$6,FO35,GO35) -> 16300.4 | BW35: =CHOOSE($AK$6,FP35,GP35) -> 16609.125 | BX35: =CHOOSE($AK$6,FQ35,GQ35) -> 16162.667 | BZ35: =BP35-BO35 -> 2365.431 | CA35: =BT35-BP35 -> 4034.5167 | CB35: =BX35-BT35 -> 778.5 | CD35: =BP35/BO35-1 -> 0.26328733 | CE35: =BT35/BP35-1 -> 0.35547499 | CF35: =BX35/BT35-1 -> 0.050603976 | CH35: =BS35/$BR35-1 -> -0.018121742 | CI35: =BT35/$BR35-1 -> 0.11586897 | CK35: =BW35/$BV35-1 -> 0.018939719 | CL35: =BX35/$BV35-1 -> -0.0084496904 | CN35: =IFERROR(BS35-$BR35,"") -> -249.83929 | CO35: =IFERROR(BT35-$BR35,"") -> 1597.4524 | CQ35: =IFERROR(BW35-$BV35,"") -> 308.725 | CR35: =IFERROR(BX35-$BV35,"") -> -137.73333 | CT35: 14179.06 | CU35: 13536.875 | CV35: 13409.028 | CW35: 12571.083 | CX35: 11786.722 | CY35: 10695.348 | CZ35: 10025.164 | DA35: 9108.373 | DB35: 8409.1842 | DC35: 7543.7917 | DD35: 6776.0111 | DE35: 6055.7516 | DF35: 5784.8235 | DG35: 5206.6667 | DH35: 4750.5824 | DI35: 4626.6538 | DJ35: 5155.1746 | DK35: 5396 | DL35: 5358.6667 | DM35: 4853.6 | DN35: 4956.8 | DO35: 4874.25 | DP35: 4514.8333 | DR35: =AC35 -> 362.21289 | DS35: 405.96089 | DT35: 428.43585 | DU35: 509.45269 | DV35: 569.89525 | DW35: 398.89633 | DX35: 381.00197 | DY35: 304.39359 | DZ35: 290.80658 | EA35: 262.82788 | EB35: 213.09748 | EC35: 167.33221 | ED35: 195.81592 | EE35: 153.8584 | EF35: 131.22764 | EG35: 104.70148 | EH35: 77.690168 | EI35: 166.30414 | EJ35: 266.85212 | EK35: 270.13397 | EL35: 234.20976 | EM35: 231.04074 | EN35: 238.89181 | EP35: 46022 | EQ35: =(DATE(2025,12,31)-EP35)/365 -> 0 | ES35: =AK35 -> 8711.631 | ET35: =AL35 -> 10981.201 | EV35: =AN35 -> 13829.37 | EW35: =AO35 -> 13631.444 | EX35: =AP35 -> 15347.58 | EZ35: =AR35 -> 16533.868 | FA35: =AS35 -> 16275.8 | FB35: =AT35 -> 16183.959 | FD35: =AV35 -> 19247.182 | FE35: =AW35 -> 19176.622 | FF35: =AX35 -> 19078.5 | FH35: =IFERROR(IF($EQ35<0,ES35*-$EQ35+ET35*(1+$EQ35),ES35*(1-$EQ35)+ET35*$EQ35),"") -> 8711.631 | FI35: =IFERROR(IF($EQ35<0,ET35*-$EQ35+EX35*(1+$EQ35),ET35*(1-$EQ35)+EX35*$EQ35),"") -> 10981.201 | FK35: =IFERROR(IF($EQ35<0,EV35*-$EQ35+EZ35*(1+$EQ35),EV35*(1-$EQ35)+EZ35*$EQ35),"") -> 13829.37 | FL35: =IFERROR(IF($EQ35<0,EW35*-$EQ35+FA35*(1+$EQ35),EW35*(1-$EQ35)+FA35*$EQ35),"") -> 13631.444 | FM35: =IFERROR(IF($EQ35<0,EX35*-$EQ35+FB35*(1+$EQ35),EX35*(1-$EQ35)+FB35*$EQ35),"") -> 15347.58 | FO35: =IFERROR(IF($EQ35<0,EZ35*-$EQ35+FD35*(1+$EQ35),EZ35*(1-$EQ35)+FD35*$EQ35),"") -> 16533.868 | FP35: =IFERROR(IF($EQ35<0,FA35*-$EQ35+FE35*(1+$EQ35),FA35*(1-$EQ35)+FE35*$EQ35),"") -> 16275.8 | FQ35: =IFERROR(IF($EQ35<0,FB35*-$EQ35+FF35*(1+$EQ35),FB35*(1-$EQ35)+FF35*$EQ35),"") -> 16183.959 | FS35: =AZ35 -> 8984.219 | FT35: =BA35 -> 11349.65 | FV35: =BC35 -> 13786.714 | FW35: =BD35 -> 13536.875 | FX35: =BE35 -> 15384.167 | FZ35: =BG35 -> 16300.4 | GA35: =BH35 -> 16609.125 | GB35: =BI35 -> 16162.667 | GD35: =BK35 -> 18509.5 | GE35: =BL35 -> 19854.273 | GF35: =BM35 -> 19105 | GH35: =IFERROR(IF($EQ35<0,FS35*-$EQ35+FT35*(1+$EQ35),FS35*(1-$EQ35)+FT35*$EQ35),"") -> 8984.219 | GI35: =IFERROR(IF($EQ35<0,FT35*-$EQ35+FX35*(1+$EQ35),FT35*(1-$EQ35)+FX35*$EQ35),"") -> 11349.65 | GK35: =IFERROR(IF($EQ35<0,FV35*-$EQ35+FZ35*(1+$EQ35),FV35*(1-$EQ35)+FZ35*$EQ35),"") -> 13786.714 | GL35: =IFERROR(IF($EQ35<0,FW35*-$EQ35+GA35*(1+$EQ35),FW35*(1-$EQ35)+GA35*$EQ35),"") -> 13536.875 | GM35: =IFERROR(IF($EQ35<0,FX35*-$EQ35+GB35*(1+$EQ35),FX35*(1-$EQ35)+GB35*$EQ35),"") -> 15384.167 | GO35: =IFERROR(IF($EQ35<0,FZ35*-$EQ35+GD35*(1+$EQ35),FZ35*(1-$EQ35)+GD35*$EQ35),"") -> 16300.4 | GP35: =IFERROR(IF($EQ35<0,GA35*-$EQ35+GE35*(1+$EQ35),GA35*(1-$EQ35)+GE35*$EQ35),"") -> 16609.125 | GQ35: =IFERROR(IF($EQ35<0,GB35*-$EQ35+GF35*(1+$EQ35),GB35*(1-$EQ35)+GF35*$EQ35),"") -> 16162.667
B36: AMAT US Equity | C36: Applied Materials Inc | D36: =IFERROR(IF(MATCH($B36,Compounders!$A:$A,0),"yes"),"") | G36: yes | J36: =IF(AND(F36="",G36="",H36="",I36=""),"yes","") | K36: =K35+IF(F36="yes",1) -> 5 | L36: =L35+IF(G36="yes",1) -> 9 | M36: =M35+IF(H36="yes",1) -> 0 | N36: =N35+IF(I36="yes",1) -> 0 | P36: Semicap | Q36: =Q35+IF(Q$10=$P36,1) -> 4 | R36: =R35+IF(R$10=$P36,1) -> 1 | S36: =S35+IF(S$10=$P36,1) -> 2 | T36: =T35+IF(T$10=$P36,1) -> 0 | U36: =U35+IF(U$10=$P36,1) -> 1 | V36: =V35+IF(V$10=$P36,1) -> 0 | W36: =W35+IF(W$10=$P36,1) -> 1 | X36: =X35+IF(X$10=$P36,1) -> 0 | Y36: =Y35+IF(Y$10=$P36,1) -> 0 | AA36: 203.77852 | AB36: 271.24792 | AC36: 357.32938 | AE36: =$AC36-AA36 -> 153.55087 | AF36: =$AC36-AB36 -> 86.081465 | AH36: =$AC36/AA36-1 -> 0.75351842 | AI36: =$AC36/AB36-1 -> 0.31735346 | AK36: 7177 | AL36: 6998 | AN36: 7444.6087 | AO36: 8821.7222 | AP36: 10351.087 | AR36: 8880.5238 | AS36: 11118.167 | AT36: 13141.545 | AV36: 9008 | AW36: 12035.9 | AX36: 15750.462 | AZ36: 7210 | BA36: 7607 | BC36: 7467.1154 | BD36: 8787.9583 | BE36: 9752.2759 | BG36: 8923.6364 | BH36: 11073.4 | BI36: 13012.594 | BK36: 9187.1538 | BL36: 12101.667 | BM36: 15577.059 | BO36: =CHOOSE($AK$6,FH36,GH36) -> 7281.7863 | BP36: =CHOOSE($AK$6,FI36,GI36) -> 7994.9129 | BR36: =CHOOSE($AK$6,FK36,GK36) -> 7730.4863 | BS36: =CHOOSE($AK$6,FL36,GL36) -> 9201.2163 | BT36: =CHOOSE($AK$6,FM36,GM36) -> 10341.813 | BV36: =CHOOSE($AK$6,FO36,GO36) -> 8971.2861 | BW36: =CHOOSE($AK$6,FP36,GP36) -> 11259.333 | BX36: =CHOOSE($AK$6,FQ36,GQ36) -> 13476.305 | BZ36: =BP36-BO36 -> 713.12659 | CA36: =BT36-BP36 -> 2346.8999 | CB36: =BX36-BT36 -> 3134.4924 | CD36: =BP36/BO36-1 -> 0.09793292 | CE36: =BT36/BP36-1 -> 0.29354915 | CF36: =BX36/BT36-1 -> 0.30308927 | CH36: =BS36/$BR36-1 -> 0.19025064 | CI36: =BT36/$BR36-1 -> 0.33779589 | CK36: =BW36/$BV36-1 -> 0.25504114 | CL36: =BX36/$BV36-1 -> 0.50215979 | CN36: =IFERROR(BS36-$BR36,"") -> 1470.73 | CO36: =IFERROR(BT36-$BR36,"") -> 2611.3265 | CQ36: =IFERROR(BW36-$BV36,"") -> 2288.0471 | CR36: =IFERROR(BX36-$BV36,"") -> 4505.0191 | CT36: 11670.125 | CU36: 9482.4235 | CV36: 7467.1154 | CW36: 7182.8333 | CX36: 7719.1286 | CY36: 7609.6216 | CZ36: 7661.25 | DA36: 7723.785 | DB36: 7306.5696 | DC36: 6967.4651 | DD36: 6443.7826 | DE36: 6397.2984 | DF36: 5548.4861 | DG36: 5444.55 | DH36: 5738.3793 | DI36: 6907.9708 | DJ36: 7042.5965 | DK36: 7690.2461 | DL36: 7330.55 | DM36: 7258.142 | DN36: 6575.4706 | DO36: 5691.4059 | DP36: 4594.9 | DR36: =AC36 -> 357.32938 | DS36: 271.24792 | DT36: 203.77852 | DU36: 163.10457 | DV36: 146.91335 | DW36: 117.90142 | DX36: 132.32953 | DY36: 166.57085 | DZ36: 195.39378 | EA36: 171.35596 | EB36: 134.69105 | EC36: 115.81811 | ED36: 121.37709 | EE36: 103.8059 | EF36: 82.202326 | EG36: 70.485147 | EH36: 79.147803 | EI36: 116.43141 | EJ36: 139.81644 | EK36: 116.23399 | EL36: 130.15086 | EM36: 122.59949 | EN36: 78.907904 | EP36: 45956 | EQ36: =(DATE(2025,12,31)-EP36)/365 -> 0.18082192 | ES36: =AK36 -> 7177 | ET36: =AL36 -> 6998 | EV36: =AN36 -> 7444.6087 | EW36: =AO36 -> 8821.7222 | EX36: =AP36 -> 10351.087 | EZ36: =AR36 -> 8880.5238 | FA36: =AS36 -> 11118.167 | FB36: =AT36 -> 13141.545 | FD36: =AV36 -> 9008 | FE36: =AW36 -> 12035.9 | FF36: =AX36 -> 15750.462 | FH36: =IFERROR(IF($EQ36<0,ES36*-$EQ36+ET36*(1+$EQ36),ES36*(1-$EQ36)+ET36*$EQ36),"") -> 7144.6329 | FI36: =IFERROR(IF($EQ36<0,ET36*-$EQ36+EX36*(1+$EQ36),ET36*(1-$EQ36)+EX36*$EQ36),"") -> 7604.3116 | FK36: =IFERROR(IF($EQ36<0,EV36*-$EQ36+EZ36*(1+$EQ36),EV36*(1-$EQ36)+EZ36*$EQ36),"") -> 7704.2536 | FL36: =IFERROR(IF($EQ36<0,EW36*-$EQ36+FA36*(1+$EQ36),EW36*(1-$EQ36)+FA36*$EQ36),"") -> 9236.9697 | FM36: =IFERROR(IF($EQ36<0,EX36*-$EQ36+FB36*(1+$EQ36),EX36*(1-$EQ36)+FB36*$EQ36),"") -> 10855.663 | FO36: =IFERROR(IF($EQ36<0,EZ36*-$EQ36+FD36*(1+$EQ36),EZ36*(1-$EQ36)+FD36*$EQ36),"") -> 8903.5743 | FP36: =IFERROR(IF($EQ36<0,FA36*-$EQ36+FE36*(1+$EQ36),FA36*(1-$EQ36)+FE36*$EQ36),"") -> 11284.113 | FQ36: =IFERROR(IF($EQ36<0,FB36*-$EQ36+FF36*(1+$EQ36),FB36*(1-$EQ36)+FF36*$EQ36),"") -> 13613.295 | FS36: =AZ36 -> 7210 | FT36: =BA36 -> 7607 | FV36: =BC36 -> 7467.1154 | FW36: =BD36 -> 8787.9583 | FX36: =BE36 -> 9752.2759 | FZ36: =BG36 -> 8923.6364 | GA36: =BH36 -> 11073.4 | GB36: =BI36 -> 13012.594 | GD36: =BK36 -> 9187.1538 | GE36: =BL36 -> 12101.667 | GF36: =BM36 -> 15577.059 | GH36: =IFERROR(IF($EQ36<0,FS36*-$EQ36+FT36*(1+$EQ36),FS36*(1-$EQ36)+FT36*$EQ36),"") -> 7281.7863 | GI36: =IFERROR(IF($EQ36<0,FT36*-$EQ36+FX36*(1+$EQ36),FT36*(1-$EQ36)+FX36*$EQ36),"") -> 7994.9129 | GK36: =IFERROR(IF($EQ36<0,FV36*-$EQ36+FZ36*(1+$EQ36),FV36*(1-$EQ36)+FZ36*$EQ36),"") -> 7730.4863 | GL36: =IFERROR(IF($EQ36<0,FW36*-$EQ36+GA36*(1+$EQ36),FW36*(1-$EQ36)+GA36*$EQ36),"") -> 9201.2163 | GM36: =IFERROR(IF($EQ36<0,FX36*-$EQ36+GB36*(1+$EQ36),FX36*(1-$EQ36)+GB36*$EQ36),"") -> 10341.813 | GO36: =IFERROR(IF($EQ36<0,FZ36*-$EQ36+GD36*(1+$EQ36),FZ36*(1-$EQ36)+GD36*$EQ36),"") -> 8971.2861 | GP36: =IFERROR(IF($EQ36<0,GA36*-$EQ36+GE36*(1+$EQ36),GA36*(1-$EQ36)+GE36*$EQ36),"") -> 11259.333 | GQ36: =IFERROR(IF($EQ36<0,GB36*-$EQ36+GF36*(1+$EQ36),GB36*(1-$EQ36)+GF36*$EQ36),"") -> 13476.305
B37: UNH US Equity | C37: Unitedhealth Group Inc | D37: =IFERROR(IF(MATCH($B37,Compounders!$A:$A,0),"yes"),"") -> yes | J37: =IF(AND(F37="",G37="",H37="",I37=""),"yes","") -> yes | K37: =K36+IF(F37="yes",1) -> 5 | L37: =L36+IF(G37="yes",1) -> 9 | M37: =M36+IF(H37="yes",1) -> 0 | N37: =N36+IF(I37="yes",1) -> 0 | Q37: =Q36+IF(Q$10=$P37,1) -> 4 | R37: =R36+IF(R$10=$P37,1) -> 1 | S37: =S36+IF(S$10=$P37,1) -> 2 | T37: =T36+IF(T$10=$P37,1) -> 0 | U37: =U36+IF(U$10=$P37,1) -> 1 | V37: =V36+IF(V$10=$P37,1) -> 0 | W37: =W36+IF(W$10=$P37,1) -> 1 | X37: =X36+IF(X$10=$P37,1) -> 0 | Y37: =Y36+IF(Y$10=$P37,1) -> 0 | AA37: 299.02639 | AB37: 245.60801 | AC37: 345.3764 | AE37: =$AC37-AA37 -> 46.350011 | AF37: =$AC37-AB37 -> 99.768393 | AH37: =$AC37/AA37-1 -> 0.15500308 | AI37: =$AC37/AB37-1 -> 0.40620986 | AK37: 14405 | AL37: 12056 | AN37: 14866.7 | AO37: 15346.81 | AP37: 15574.8 | AR37: 16602.632 | AS37: 17102.9 | AT37: 17166.15 | AV37: 20835.75 | AW37: 19854.429 | AX37: 20642.786 | AZ37: 25699 | BA37: 14897 | BC37: 16011.652 | BD37: 16291.143 | BE37: 16605.458 | BG37: 18702.455 | BH37: 17989.455 | BI37: 18843.792 | BK37: 22256.2 | BL37: 21178 | BM37: 21985.167 | BO37: =CHOOSE($AK$6,FH37,GH37) -> 25699 | BP37: =CHOOSE($AK$6,FI37,GI37) -> 14897 | BR37: =CHOOSE($AK$6,FK37,GK37) -> 16011.652 | BS37: =CHOOSE($AK$6,FL37,GL37) -> 16291.143 | BT37: =CHOOSE($AK$6,FM37,GM37) -> 16605.458 | BV37: =CHOOSE($AK$6,FO37,GO37) -> 18702.455 | BW37: =CHOOSE($AK$6,FP37,GP37) -> 17989.455 | BX37: =CHOOSE($AK$6,FQ37,GQ37) -> 18843.792 | BZ37: =BP37-BO37 -> -10802 | CA37: =BT37-BP37 -> 1708.4583 | CB37: =BX37-BT37 -> 2238.3333 | CD37: =BP37/BO37-1 -> -0.42032764 | CE37: =BT37/BP37-1 -> 0.11468472 | CF37: =BX37/BT37-1 -> 0.13479503 | CH37: =BS37/$BR37-1 -> 0.017455456 | CI37: =BT37/$BR37-1 -> 0.037085877 | CK37: =BW37/$BV37-1 -> -0.038123338 | CL37: =BX37/$BV37-1 -> 0.0075571429 | CN37: =IFERROR(BS37-$BR37,"") -> 279.49068 | CO37: =IFERROR(BT37-$BR37,"") -> 593.80616 | CQ37: =IFERROR(BW37-$BV37,"") -> -713 | CR37: =IFERROR(BX37-$BV37,"") -> 141.33712 | CT37: 17123.092 | CU37: 16291.143 | CV37: 15249.429 | CW37: 14299.752 | CX37: 20620.577 | CY37: 27188.864 | CZ37: 26610.128 | DA37: 26667.491 | DB37: 25647.318 | DC37: 25424.68 | DD37: 24915.765 | DE37: 24346.012 | DF37: 23500.463 | DG37: 23045.704 | DH37: 22361.934 | DI37: 21732.872 | DJ37: 21133.232 | DK37: 20301.346 | DL37: 19610.214 | DM37: 18319.428 | DN37: 17522.89 | DO37: 17324.833 | DP37: 15149.49 | DR37: =AC37 -> 345.3764 | DS37: 245.60801 | DT37: 299.02639 | DU37: 312.7291 | DV37: 283.0006 | DW37: 479.08058 | DX37: 465.53503 | DY37: 539.90412 | DZ37: 468.7153 | EA37: 456.0808 | EB37: 486.94542 | EC37: 467.03379 | ED37: 447.49123 | EE37: 440.85398 | EF37: 495.37319 | EG37: 472.40568 | EH37: 481.87308 | EI37: 479.83034 | EJ37: 472.94119 | EK37: 368.43553 | EL37: 377.89608 | EM37: 351.72499 | EN37: 332.73245 | EP37: 46022 | EQ37: =(DATE(2025,12,31)-EP37)/365 -> 0 | ES37: =AK37 -> 14405 | ET37: =AL37 -> 12056 | EV37: =AN37 -> 14866.7 | EW37: =AO37 -> 15346.81 | EX37: =AP37 -> 15574.8 | EZ37: =AR37 -> 16602.632 | FA37: =AS37 -> 17102.9 | FB37: =AT37 -> 17166.15 | FD37: =AV37 -> 20835.75 | FE37: =AW37 -> 19854.429 | FF37: =AX37 -> 20642.786 | FH37: =IFERROR(IF($EQ37<0,ES37*-$EQ37+ET37*(1+$EQ37),ES37*(1-$EQ37)+ET37*$EQ37),"") -> 14405 | FI37: =IFERROR(IF($EQ37<0,ET37*-$EQ37+EX37*(1+$EQ37),ET37*(1-$EQ37)+EX37*$EQ37),"") -> 12056 | FK37: =IFERROR(IF($EQ37<0,EV37*-$EQ37+EZ37*(1+$EQ37),EV37*(1-$EQ37)+EZ37*$EQ37),"") -> 14866.7 | FL37: =IFERROR(IF($EQ37<0,EW37*-$EQ37+FA37*(1+$EQ37),EW37*(1-$EQ37)+FA37*$EQ37),"") -> 15346.81 | FM37: =IFERROR(IF($EQ37<0,EX37*-$EQ37+FB37*(1+$EQ37),EX37*(1-$EQ37)+FB37*$EQ37),"") -> 15574.8 | FO37: =IFERROR(IF($EQ37<0,EZ37*-$EQ37+FD37*(1+$EQ37),EZ37*(1-$EQ37)+FD37*$EQ37),"") -> 16602.632 | FP37: =IFERROR(IF($EQ37<0,FA37*-$EQ37+FE37*(1+$EQ37),FA37*(1-$EQ37)+FE37*$EQ37),"") -> 17102.9 | FQ37: =IFERROR(IF($EQ37<0,FB37*-$EQ37+FF37*(1+$EQ37),FB37*(1-$EQ37)+FF37*$EQ37),"") -> 17166.15 | FS37: =AZ37 -> 25699 | FT37: =BA37 -> 14897 | FV37: =BC37 -> 16011.652 | FW37: =BD37 -> 16291.143 | FX37: =BE37 -> 16605.458 | FZ37: =BG37 -> 18702.455 | GA37: =BH37 -> 17989.455 | GB37: =BI37 -> 18843.792 | GD37: =BK37 -> 22256.2 | GE37: =BL37 -> 21178 | GF37: =BM37 -> 21985.167 | GH37: =IFERROR(IF($EQ37<0,FS37*-$EQ37+FT37*(1+$EQ37),FS37*(1-$EQ37)+FT37*$EQ37),"") -> 25699 | GI37: =IFERROR(IF($EQ37<0,FT37*-$EQ37+FX37*(1+$EQ37),FT37*(1-$EQ37)+FX37*$EQ37),"") -> 14897 | GK37: =IFERROR(IF($EQ37<0,FV37*-$EQ37+FZ37*(1+$EQ37),FV37*(1-$EQ37)+FZ37*$EQ37),"") -> 16011.652 | GL37: =IFERROR(IF($EQ37<0,FW37*-$EQ37+GA37*(1+$EQ37),FW37*(1-$EQ37)+GA37*$EQ37),"") -> 16291.143 | GM37: =IFERROR(IF($EQ37<0,FX37*-$EQ37+GB37*(1+$EQ37),FX37*(1-$EQ37)+GB37*$EQ37),"") -> 16605.458 | GO37: =IFERROR(IF($EQ37<0,FZ37*-$EQ37+GD37*(1+$EQ37),FZ37*(1-$EQ37)+GD37*$EQ37),"") -> 18702.455 | GP37: =IFERROR(IF($EQ37<0,GA37*-$EQ37+GE37*(1+$EQ37),GA37*(1-$EQ37)+GE37*$EQ37),"") -> 17989.455 | GQ37: =IFERROR(IF($EQ37<0,GB37*-$EQ37+GF37*(1+$EQ37),GB37*(1-$EQ37)+GF37*$EQ37),"") -> 18843.792
B38: PG US Equity | C38: Procter & Gamble Co/The | D38: =IFERROR(IF(MATCH($B38,Compounders!$A:$A,0),"yes"),"") | J38: =IF(AND(F38="",G38="",H38="",I38=""),"yes","") -> yes | K38: =K37+IF(F38="yes",1) -> 5 | L38: =L37+IF(G38="yes",1) -> 9 | M38: =M37+IF(H38="yes",1) -> 0 | N38: =N37+IF(I38="yes",1) -> 0 | Q38: =Q37+IF(Q$10=$P38,1) -> 4 | R38: =R37+IF(R$10=$P38,1) -> 1 | S38: =S37+IF(S$10=$P38,1) -> 2 | T38: =T37+IF(T$10=$P38,1) -> 0 | U38: =U37+IF(U$10=$P38,1) -> 1 | V38: =V37+IF(V$10=$P38,1) -> 0 | W38: =W37+IF(W$10=$P38,1) -> 1 | X38: =X37+IF(X$10=$P38,1) -> 0 | Y38: =Y37+IF(Y$10=$P38,1) -> 0 | AA38: 334.87728 | AB38: 335.67866 | AC38: 334.29367 | AE38: =$AC38-AA38 -> -0.58361563 | AF38: =$AC38-AB38 -> -1.3849897 | AH38: =$AC38/AA38-1 -> -0.0017427746 | AI38: =$AC38/AB38-1 -> -0.004125939 | AK38: 14879 | AL38: 15974 | AN38: 16822.9 | AO38: 16677.417 | AP38: 16508.846 | AR38: 17484.6 | AS38: 17401.417 | AT38: 16971.643 | AV38: 18361.875 | AW38: 18290 | AX38: 17918.583 | AZ38: 16281 | BA38: 16775 | BC38: 17030 | BD38: 16873.857 | BE38: 16690.105 | BG38: 17737 | BH38: 17602.524 | BI38: 17035.05 | BK38: 18563.562 | BL38: 18487.765 | BM38: 17958.188 | BO38: =CHOOSE($AK$6,FH38,GH38) -> 16530.03 | BP38: =CHOOSE($AK$6,FI38,GI38) -> 16732.204 | BR38: =CHOOSE($AK$6,FK38,GK38) -> 17386.405 | BS38: =CHOOSE($AK$6,FL38,GL38) -> 17241.185 | BT38: =CHOOSE($AK$6,FM38,GM38) -> 16863.995 | BV38: =CHOOSE($AK$6,FO38,GO38) -> 18153.678 | BW38: =CHOOSE($AK$6,FP38,GP38) -> 18048.782 | BX38: =CHOOSE($AK$6,FQ38,GQ38) -> 17500.412 | BZ38: =BP38-BO38 -> 202.17361 | CA38: =BT38-BP38 -> 131.79146 | CB38: =BX38-BT38 -> 636.41725 | CD38: =BP38/BO38-1 -> 0.012230686 | CE38: =BT38/BP38-1 -> 0.0078765156 | CF38: =BX38/BT38-1 -> 0.037738225 | CH38: =BS38/$BR38-1 -> -0.0083525305 | CI38: =BT38/$BR38-1 -> -0.030047054 | CK38: =BW38/$BV38-1 -> -0.0057782146 | CL38: =BX38/$BV38-1 -> -0.035985304 | CN38: =IFERROR(BS38-$BR38,"") -> -145.22048 | CO38: =IFERROR(BT38-$BR38,"") -> -522.41027 | CQ38: =IFERROR(BW38-$BV38,"") -> -104.89585 | CR38: =IFERROR(BX38-$BV38,"") -> -653.26562 | CT38: 16754.802 | CU38: 17214.373 | CV38: 17176.137 | CW38: 16952.227 | CX38: 16818.797 | CY38: 17242.451 | CZ38: 17246.644 | DA38: 17014.32 | DB38: 16718.118 | DC38: 16350.638 | DD38: 15995.783 | DE38: 15698.625 | DF38: 15282.192 | DG38: 14950.076 | DH38: 14683.678 | DI38: 14816.905 | DJ38: 15058.832 | DK38: 15486.875 | DL38: 15359.85 | DM38: 15078.857 | DN38: 14735.091 | DO38: 15100.063 | DP38: 14598.762 | DR38: =AC38 -> 334.29367 | DS38: 335.67866 | DT38: 334.87728 | DU38: 359.61556 | DV38: 373.53244 | DW38: 399.60965 | DX38: 394.82275 | DY38: 406.96938 | DZ38: 389.23351 | EA38: 381.77767 | EB38: 345.37811 | EC38: 343.77652 | ED38: 357.64652 | EE38: 350.78114 | EF38: 359.15126 | EG38: 301.68118 | EH38: 344.99489 | EI38: 366.27164 | EJ38: 395.85506 | EK38: 339.47853 | EL38: 330.34005 | EM38: 333.49313 | EN38: 345.01236 | EP38: 45838 | EQ38: =(DATE(2025,12,31)-EP38)/365 -> 0.50410959 | ES38: =AK38 -> 14879 | ET38: =AL38 -> 15974 | EV38: =AN38 -> 16822.9 | EW38: =AO38 -> 16677.417 | EX38: =AP38 -> 16508.846 | EZ38: =AR38 -> 17484.6 | FA38: =AS38 -> 17401.417 | FB38: =AT38 -> 16971.643 | FD38: =AV38 -> 18361.875 | FE38: =AW38 -> 18290 | FF38: =AX38 -> 17918.583 | FH38: =IFERROR(IF($EQ38<0,ES38*-$EQ38+ET38*(1+$EQ38),ES38*(1-$EQ38)+ET38*$EQ38),"") -> 15431 | FI38: =IFERROR(IF($EQ38<0,ET38*-$EQ38+EX38*(1+$EQ38),ET38*(1-$EQ38)+EX38*$EQ38),"") -> 16243.621 | FK38: =IFERROR(IF($EQ38<0,EV38*-$EQ38+EZ38*(1+$EQ38),EV38*(1-$EQ38)+EZ38*$EQ38),"") -> 17156.469 | FL38: =IFERROR(IF($EQ38<0,EW38*-$EQ38+FA38*(1+$EQ38),EW38*(1-$EQ38)+FA38*$EQ38),"") -> 17042.392 | FM38: =IFERROR(IF($EQ38<0,EX38*-$EQ38+FB38*(1+$EQ38),EX38*(1-$EQ38)+FB38*$EQ38),"") -> 16742.146 | FO38: =IFERROR(IF($EQ38<0,EZ38*-$EQ38+FD38*(1+$EQ38),EZ38*(1-$EQ38)+FD38*$EQ38),"") -> 17926.843 | FP38: =IFERROR(IF($EQ38<0,FA38*-$EQ38+FE38*(1+$EQ38),FA38*(1-$EQ38)+FE38*$EQ38),"") -> 17849.36 | FQ38: =IFERROR(IF($EQ38<0,FB38*-$EQ38+FF38*(1+$EQ38),FB38*(1-$EQ38)+FF38*$EQ38),"") -> 17449.005 | FS38: =AZ38 -> 16281 | FT38: =BA38 -> 16775 | FV38: =BC38 -> 17030 | FW38: =BD38 -> 16873.857 | FX38: =BE38 -> 16690.105 | FZ38: =BG38 -> 17737 | GA38: =BH38 -> 17602.524 | GB38: =BI38 -> 17035.05 | GD38: =BK38 -> 18563.562 | GE38: =BL38 -> 18487.765 | GF38: =BM38 -> 17958.188 | GH38: =IFERROR(IF($EQ38<0,FS38*-$EQ38+FT38*(1+$EQ38),FS38*(1-$EQ38)+FT38*$EQ38),"") -> 16530.03 | GI38: =IFERROR(IF($EQ38<0,FT38*-$EQ38+FX38*(1+$EQ38),FT38*(1-$EQ38)+FX38*$EQ38),"") -> 16732.204 | GK38: =IFERROR(IF($EQ38<0,FV38*-$EQ38+FZ38*(1+$EQ38),FV38*(1-$EQ38)+FZ38*$EQ38),"") -> 17386.405 | GL38: =IFERROR(IF($EQ38<0,FW38*-$EQ38+GA38*(1+$EQ38),FW38*(1-$EQ38)+GA38*$EQ38),"") -> 17241.185 | GM38: =IFERROR(IF($EQ38<0,FX38*-$EQ38+GB38*(1+$EQ38),FX38*(1-$EQ38)+GB38*$EQ38),"") -> 16863.995 | GO38: =IFERROR(IF($EQ38<0,FZ38*-$EQ38+GD38*(1+$EQ38),FZ38*(1-$EQ38)+GD38*$EQ38),"") -> 18153.678 | GP38: =IFERROR(IF($EQ38<0,GA38*-$EQ38+GE38*(1+$EQ38),GA38*(1-$EQ38)+GE38*$EQ38),"") -> 18048.782 | GQ38: =IFERROR(IF($EQ38<0,GB38*-$EQ38+GF38*(1+$EQ38),GB38*(1-$EQ38)+GF38*$EQ38),"") -> 17500.412
B39: CVX US Equity | C39: Chevron Corp | D39: =IFERROR(IF(MATCH($B39,Compounders!$A:$A,0),"yes"),"") | J39: =IF(AND(F39="",G39="",H39="",I39=""),"yes","") -> yes | K39: =K38+IF(F39="yes",1) -> 5 | L39: =L38+IF(G39="yes",1) -> 9 | M39: =M38+IF(H39="yes",1) -> 0 | N39: =N38+IF(I39="yes",1) -> 0 | Q39: =Q38+IF(Q$10=$P39,1) -> 4 | R39: =R38+IF(R$10=$P39,1) -> 1 | S39: =S38+IF(S$10=$P39,1) -> 2 | T39: =T38+IF(T$10=$P39,1) -> 0 | U39: =U38+IF(U$10=$P39,1) -> 1 | V39: =V38+IF(V$10=$P39,1) -> 0 | W39: =W38+IF(W$10=$P39,1) -> 1 | X39: =X38+IF(X$10=$P39,1) -> 0 | Y39: =Y38+IF(Y$10=$P39,1) -> 0 | AA39: 306.88083 | AB39: 412.84527 | AC39: 363.38692 | AE39: =$AC39-AA39 -> 56.506096 | AF39: =$AC39-AB39 -> -49.458346 | AH39: =$AC39/AA39-1 -> 0.18413042 | AI39: =$AC39/AB39-1 -> -0.11979875 | AK39: 17661 | AL39: 12299 | AN39: 14247.833 | AO39: 17838 | AP39: 29405.591 | AR39: 18381.429 | AS39: 19026.68 | AT39: 24303.136 | AV39: 19765.833 | AW39: 20506.526 | AX39: 24301.471 | AZ39: 18256 | BA39: 13521 | BC39: 14299.2 | BD39: 17716.63 | BE39: 29120.913 | BG39: 18374.273 | BH39: 19023.731 | BI39: 24069.652 | BK39: 19765.833 | BL39: 20454.45 | BM39: 24042.222 | BO39: =CHOOSE($AK$6,FH39,GH39) -> 18256 | BP39: =CHOOSE($AK$6,FI39,GI39) -> 13521 | BR39: =CHOOSE($AK$6,FK39,GK39) -> 14299.2 | BS39: =CHOOSE($AK$6,FL39,GL39) -> 17716.63 | BT39: =CHOOSE($AK$6,FM39,GM39) -> 29120.913 | BV39: =CHOOSE($AK$6,FO39,GO39) -> 18374.273 | BW39: =CHOOSE($AK$6,FP39,GP39) -> 19023.731 | BX39: =CHOOSE($AK$6,FQ39,GQ39) -> 24069.652 | BZ39: =BP39-BO39 -> -4735 | CA39: =BT39-BP39 -> 15599.913 | CB39: =BX39-BT39 -> -5051.2609 | CD39: =BP39/BO39-1 -> -0.25936678 | CE39: =BT39/BP39-1 -> 1.1537544 | CF39: =BX39/BT39-1 -> -0.17345819 | CH39: =BS39/$BR39-1 -> 0.23899446 | CI39: =BT39/$BR39-1 -> 1.0365414 | CK39: =BW39/$BV39-1 -> 0.035346054 | CL39: =BX39/$BV39-1 -> 0.30996489 | CN39: =IFERROR(BS39-$BR39,"") -> 3417.4296 | CO39: =IFERROR(BT39-$BR39,"") -> 14821.713 | CQ39: =IFERROR(BW39-$BV39,"") -> 649.45804 | CR39: =IFERROR(BX39-$BV39,"") -> 5695.3794 | CT39: 33279.188 | CU39: 17716.63 | CV39: 13391.987 | CW39: 15818.054 | CX39: 14833.162 | CY39: 18461.333 | CZ39: 18565.679 | DA39: 19915.86 | DB39: 26177.267 | DC39: 24345.238 | DD39: 27718.519 | DE39: 25986.073 | DF39: 24568.639 | DG39: 28192.958 | DH39: 31310.477 | DI39: 33785.468 | DJ39: 33432.417 | DK39: 25399.889 | DL39: 19203.727 | DM39: 15608.838 | DN39: 12298.864 | DO39: 9895.7059 | DP39: 4071.9149 | DR39: =AC39 -> 363.38692 | DS39: 412.84527 | DT39: 306.88083 | DU39: 317.9398 | DV39: 250.06614 | DW39: 292.70995 | DX39: 260.29071 | DY39: 269.34462 | DZ39: 288.95779 | EA39: 292.96564 | EB39: 281.57659 | EC39: 314.85489 | ED39: 298.12215 | EE39: 311.09294 | EF39: 347.06878 | EG39: 281.22466 | EH39: 284.46569 | EI39: 317.12011 | EJ39: 226.21394 | EK39: 196.19537 | EL39: 202.4372 | EM39: 201.86502 | EN39: 162.56768 | EP39: 46022 | EQ39: =(DATE(2025,12,31)-EP39)/365 -> 0 | ES39: =AK39 -> 17661 | ET39: =AL39 -> 12299 | EV39: =AN39 -> 14247.833 | EW39: =AO39 -> 17838 | EX39: =AP39 -> 29405.591 | EZ39: =AR39 -> 18381.429 | FA39: =AS39 -> 19026.68 | FB39: =AT39 -> 24303.136 | FD39: =AV39 -> 19765.833 | FE39: =AW39 -> 20506.526 | FF39: =AX39 -> 24301.471 | FH39: =IFERROR(IF($EQ39<0,ES39*-$EQ39+ET39*(1+$EQ39),ES39*(1-$EQ39)+ET39*$EQ39),"") -> 17661 | FI39: =IFERROR(IF($EQ39<0,ET39*-$EQ39+EX39*(1+$EQ39),ET39*(1-$EQ39)+EX39*$EQ39),"") -> 12299 | FK39: =IFERROR(IF($EQ39<0,EV39*-$EQ39+EZ39*(1+$EQ39),EV39*(1-$EQ39)+EZ39*$EQ39),"") -> 14247.833 | FL39: =IFERROR(IF($EQ39<0,EW39*-$EQ39+FA39*(1+$EQ39),EW39*(1-$EQ39)+FA39*$EQ39),"") -> 17838 | FM39: =IFERROR(IF($EQ39<0,EX39*-$EQ39+FB39*(1+$EQ39),EX39*(1-$EQ39)+FB39*$EQ39),"") -> 29405.591 | FO39: =IFERROR(IF($EQ39<0,EZ39*-$EQ39+FD39*(1+$EQ39),EZ39*(1-$EQ39)+FD39*$EQ39),"") -> 18381.429 | FP39: =IFERROR(IF($EQ39<0,FA39*-$EQ39+FE39*(1+$EQ39),FA39*(1-$EQ39)+FE39*$EQ39),"") -> 19026.68 | FQ39: =IFERROR(IF($EQ39<0,FB39*-$EQ39+FF39*(1+$EQ39),FB39*(1-$EQ39)+FF39*$EQ39),"") -> 24303.136 | FS39: =AZ39 -> 18256 | FT39: =BA39 -> 13521 | FV39: =BC39 -> 14299.2 | FW39: =BD39 -> 17716.63 | FX39: =BE39 -> 29120.913 | FZ39: =BG39 -> 18374.273 | GA39: =BH39 -> 19023.731 | GB39: =BI39 -> 24069.652 | GD39: =BK39 -> 19765.833 | GE39: =BL39 -> 20454.45 | GF39: =BM39 -> 24042.222 | GH39: =IFERROR(IF($EQ39<0,FS39*-$EQ39+FT39*(1+$EQ39),FS39*(1-$EQ39)+FT39*$EQ39),"") -> 18256 | GI39: =IFERROR(IF($EQ39<0,FT39*-$EQ39+FX39*(1+$EQ39),FT39*(1-$EQ39)+FX39*$EQ39),"") -> 13521 | GK39: =IFERROR(IF($EQ39<0,FV39*-$EQ39+FZ39*(1+$EQ39),FV39*(1-$EQ39)+FZ39*$EQ39),"") -> 14299.2 | GL39: =IFERROR(IF($EQ39<0,FW39*-$EQ39+GA39*(1+$EQ39),FW39*(1-$EQ39)+GA39*$EQ39),"") -> 17716.63 | GM39: =IFERROR(IF($EQ39<0,FX39*-$EQ39+GB39*(1+$EQ39),FX39*(1-$EQ39)+GB39*$EQ39),"") -> 29120.913 | GO39: =IFERROR(IF($EQ39<0,FZ39*-$EQ39+GD39*(1+$EQ39),FZ39*(1-$EQ39)+GD39*$EQ39),"") -> 18374.273 | GP39: =IFERROR(IF($EQ39<0,GA39*-$EQ39+GE39*(1+$EQ39),GA39*(1-$EQ39)+GE39*$EQ39),"") -> 19023.731 | GQ39: =IFERROR(IF($EQ39<0,GB39*-$EQ39+GF39*(1+$EQ39),GB39*(1-$EQ39)+GF39*$EQ39),"") -> 24069.652
B40: BAC US Equity | C40: Bank Of America Corp | D40: =IFERROR(IF(MATCH($B40,Compounders!$A:$A,0),"yes"),"") | J40: =IF(AND(F40="",G40="",H40="",I40=""),"yes","") -> yes | K40: =K39+IF(F40="yes",1) -> 5 | L40: =L39+IF(G40="yes",1) -> 9 | M40: =M39+IF(H40="yes",1) -> 0 | N40: =N39+IF(I40="yes",1) -> 0 | Q40: =Q39+IF(Q$10=$P40,1) -> 4 | R40: =R39+IF(R$10=$P40,1) -> 1 | S40: =S39+IF(S$10=$P40,1) -> 2 | T40: =T39+IF(T$10=$P40,1) -> 0 | U40: =U39+IF(U$10=$P40,1) -> 1 | V40: =V39+IF(V$10=$P40,1) -> 0 | W40: =W39+IF(W$10=$P40,1) -> 1 | X40: =X39+IF(X$10=$P40,1) -> 0 | Y40: =Y39+IF(Y$10=$P40,1) -> 0 | AA40: 401.63726 | AB40: 348.35332 | AC40: 366.18408 | AE40: =$AC40-AA40 -> -35.453178 | AF40: =$AC40-AB40 -> 17.830755 | AH40: =$AC40/AA40-1 -> -0.088271636 | AI40: =$AC40/AB40-1 -> 0.051185833 | AK40: 25503 | AL40: 29055 | AN40: 31657.062 | AO40: 31666.067 | AP40: 32557.125 | AR40: 34428.667 | AS40: 34210.667 | AT40: 34709.25 | AV40: 36410 | AW40: 36901.8 | AX40: 37039.167 | AZ40: 25819 | BA40: 29055 | BC40: 32103.579 | BD40: 32160.941 | BE40: 32771.471 | BG40: 35043.389 | BH40: 34971.647 | BI40: 35055.059 | BK40: 37130 | BL40: 37510.111 | BM40: 37530.3 | BO40: =CHOOSE($AK$6,FH40,GH40) -> 25819 | BP40: =CHOOSE($AK$6,FI40,GI40) -> 29055 | BR40: =CHOOSE($AK$6,FK40,GK40) -> 32103.579 | BS40: =CHOOSE($AK$6,FL40,GL40) -> 32160.941 | BT40: =CHOOSE($AK$6,FM40,GM40) -> 32771.471 | BV40: =CHOOSE($AK$6,FO40,GO40) -> 35043.389 | BW40: =CHOOSE($AK$6,FP40,GP40) -> 34971.647 | BX40: =CHOOSE($AK$6,FQ40,GQ40) -> 35055.059 | BZ40: =BP40-BO40 -> 3236 | CA40: =BT40-BP40 -> 3716.4706 | CB40: =BX40-BT40 -> 2283.5882 | CD40: =BP40/BO40-1 -> 0.12533406 | CE40: =BT40/BP40-1 -> 0.12791157 | CF40: =BX40/BT40-1 -> 0.069682202 | CH40: =BS40/$BR40-1 -> 0.0017867861 | CI40: =BT40/$BR40-1 -> 0.020804274 | CK40: =BW40/$BV40-1 -> -0.0020472287 | CL40: =BX40/$BV40-1 -> 0.00033301387 | CN40: =IFERROR(BS40-$BR40,"") -> 57.362229 | CO40: =IFERROR(BT40-$BR40,"") -> 667.89164 | CQ40: =IFERROR(BW40-$BV40,"") -> -71.74183 | CR40: =IFERROR(BX40-$BV40,"") -> 11.669935 | CT40: 32965.622 | CU40: 32160.941 | CV40: 31306.815 | CW40: 29307.403 | CX40: 28033.4 | CY40: 28086.333 | CZ40: 27002.791 | DA40: 26104.857 | DB40: 26038.83 | DC40: 24789.526 | DD40: 25002.2 | DE40: 25394.241 | DF40: 26130.033 | DG40: 27246.762 | DH40: 28513.529 | DI40: 27928.176 | DJ40: 27426.613 | DK40: 26378.864 | DL40: 25659.056 | DM40: 24292.867 | DN40: 25052.045 | DO40: 21476.278 | DP40: 17925.871 | DR40: =AC40 -> 366.18408 | DS40: 348.35332 | DT40: 401.63726 | DU40: 382.12441 | DV40: 356.40838 | DW40: 317.26477 | DX40: 337.22306 | DY40: 307.90003 | DZ40: 311.01613 | EA40: 299.21303 | EB40: 266.45536 | EC40: 217.57166 | ED40: 228.63499 | EE40: 228.9098 | EF40: 265.70296 | EG40: 242.66422 | EH40: 250.81072 | EI40: 332.43332 | EJ40: 364.1099 | EK40: 357.21267 | EL40: 353.31296 | EM40: 333.7884 | EN40: 262.20544 | EP40: 46022 | EQ40: =(DATE(2025,12,31)-EP40)/365 -> 0 | ES40: =AK40 -> 25503 | ET40: =AL40 -> 29055 | EV40: =AN40 -> 31657.062 | EW40: =AO40 -> 31666.067 | EX40: =AP40 -> 32557.125 | EZ40: =AR40 -> 34428.667 | FA40: =AS40 -> 34210.667 | FB40: =AT40 -> 34709.25 | FD40: =AV40 -> 36410 | FE40: =AW40 -> 36901.8 | FF40: =AX40 -> 37039.167 | FH40: =IFERROR(IF($EQ40<0,ES40*-$EQ40+ET40*(1+$EQ40),ES40*(1-$EQ40)+ET40*$EQ40),"") -> 25503 | FI40: =IFERROR(IF($EQ40<0,ET40*-$EQ40+EX40*(1+$EQ40),ET40*(1-$EQ40)+EX40*$EQ40),"") -> 29055 | FK40: =IFERROR(IF($EQ40<0,EV40*-$EQ40+EZ40*(1+$EQ40),EV40*(1-$EQ40)+EZ40*$EQ40),"") -> 31657.062 | FL40: =IFERROR(IF($EQ40<0,EW40*-$EQ40+FA40*(1+$EQ40),EW40*(1-$EQ40)+FA40*$EQ40),"") -> 31666.067 | FM40: =IFERROR(IF($EQ40<0,EX40*-$EQ40+FB40*(1+$EQ40),EX40*(1-$EQ40)+FB40*$EQ40),"") -> 32557.125 | FO40: =IFERROR(IF($EQ40<0,EZ40*-$EQ40+FD40*(1+$EQ40),EZ40*(1-$EQ40)+FD40*$EQ40),"") -> 34428.667 | FP40: =IFERROR(IF($EQ40<0,FA40*-$EQ40+FE40*(1+$EQ40),FA40*(1-$EQ40)+FE40*$EQ40),"") -> 34210.667 | FQ40: =IFERROR(IF($EQ40<0,FB40*-$EQ40+FF40*(1+$EQ40),FB40*(1-$EQ40)+FF40*$EQ40),"") -> 34709.25 | FS40: =AZ40 -> 25819 | FT40: =BA40 -> 29055 | FV40: =BC40 -> 32103.579 | FW40: =BD40 -> 32160.941 | FX40: =BE40 -> 32771.471 | FZ40: =BG40 -> 35043.389 | GA40: =BH40 -> 34971.647 | GB40: =BI40 -> 35055.059 | GD40: =BK40 -> 37130 | GE40: =BL40 -> 37510.111 | GF40: =BM40 -> 37530.3 | GH40: =IFERROR(IF($EQ40<0,FS40*-$EQ40+FT40*(1+$EQ40),FS40*(1-$EQ40)+FT40*$EQ40),"") -> 25819 | GI40: =IFERROR(IF($EQ40<0,FT40*-$EQ40+FX40*(1+$EQ40),FT40*(1-$EQ40)+FX40*$EQ40),"") -> 29055 | GK40: =IFERROR(IF($EQ40<0,FV40*-$EQ40+FZ40*(1+$EQ40),FV40*(1-$EQ40)+FZ40*$EQ40),"") -> 32103.579 | GL40: =IFERROR(IF($EQ40<0,FW40*-$EQ40+GA40*(1+$EQ40),FW40*(1-$EQ40)+GA40*$EQ40),"") -> 32160.941 | GM40: =IFERROR(IF($EQ40<0,FX40*-$EQ40+GB40*(1+$EQ40),FX40*(1-$EQ40)+GB40*$EQ40),"") -> 32771.471 | GO40: =IFERROR(IF($EQ40<0,FZ40*-$EQ40+GD40*(1+$EQ40),FZ40*(1-$EQ40)+GD40*$EQ40),"") -> 35043.389 | GP40: =IFERROR(IF($EQ40<0,GA40*-$EQ40+GE40*(1+$EQ40),GA40*(1-$EQ40)+GE40*$EQ40),"") -> 34971.647 | GQ40: =IFERROR(IF($EQ40<0,GB40*-$EQ40+GF40*(1+$EQ40),GB40*(1-$EQ40)+GF40*$EQ40),"") -> 35055.059
B41: GE US Equity | C41: General Electric Co | D41: =IFERROR(IF(MATCH($B41,Compounders!$A:$A,0),"yes"),"") -> yes | J41: =IF(AND(F41="",G41="",H41="",I41=""),"yes","") -> yes | K41: =K40+IF(F41="yes",1) -> 5 | L41: =L40+IF(G41="yes",1) -> 9 | M41: =M40+IF(H41="yes",1) -> 0 | N41: =N40+IF(I41="yes",1) -> 0 | Q41: =Q40+IF(Q$10=$P41,1) -> 4 | R41: =R40+IF(R$10=$P41,1) -> 1 | S41: =S40+IF(S$10=$P41,1) -> 2 | T41: =T40+IF(T$10=$P41,1) -> 0 | U41: =U40+IF(U$10=$P41,1) -> 1 | V41: =V40+IF(V$10=$P41,1) -> 0 | W41: =W40+IF(W$10=$P41,1) -> 1 | X41: =X40+IF(X$10=$P41,1) -> 0 | Y41: =Y40+IF(Y$10=$P41,1) -> 0 | AA41: 324.91433 | AB41: 296.4913 | AC41: 337.79086 | AE41: =$AC41-AA41 -> 12.876534 | AF41: =$AC41-AB41 -> 41.299567 | AH41: =$AC41/AA41-1 -> 0.039630552 | AI41: =$AC41/AB41-1 -> 0.13929437 | AK41: 6670 | AL41: 8598 | AN41: 8348.125 | AO41: 8924.75 | AP41: 8683.7 | AR41: 9492 | AS41: 9899.125 | AT41: 9891.6 | AV41: 10707.833 | AW41: 10897.625 | AX41: 10883.8 | AZ41: 5035 | BA41: 6812 | BC41: 7530.875 | BD41: 7812.6667 | BE41: 7932.8095 | BG41: 8709.3846 | BH41: 8904.2 | BI41: 8990.9 | BK41: 9363.875 | BL41: 10024.143 | BM41: 10023.389 | BO41: =CHOOSE($AK$6,FH41,GH41) -> 5035 | BP41: =CHOOSE($AK$6,FI41,GI41) -> 6812 | BR41: =CHOOSE($AK$6,FK41,GK41) -> 7530.875 | BS41: =CHOOSE($AK$6,FL41,GL41) -> 7812.6667 | BT41: =CHOOSE($AK$6,FM41,GM41) -> 7932.8095 | BV41: =CHOOSE($AK$6,FO41,GO41) -> 8709.3846 | BW41: =CHOOSE($AK$6,FP41,GP41) -> 8904.2 | BX41: =CHOOSE($AK$6,FQ41,GQ41) -> 8990.9 | BZ41: =BP41-BO41 -> 1777 | CA41: =BT41-BP41 -> 1120.8095 | CB41: =BX41-BT41 -> 1058.0905 | CD41: =BP41/BO41-1 -> 0.35292949 | CE41: =BT41/BP41-1 -> 0.16453457 | CF41: =BX41/BT41-1 -> 0.13338156 | CH41: =BS41/$BR41-1 -> 0.037418184 | CI41: =BT41/$BR41-1 -> 0.053371557 | CK41: =BW41/$BV41-1 -> 0.022368444 | CL41: =BX41/$BV41-1 -> 0.032323223 | CN41: =IFERROR(BS41-$BR41,"") -> 281.79167 | CO41: =IFERROR(BT41-$BR41,"") -> 401.93452 | CQ41: =IFERROR(BW41-$BV41,"") -> 194.81538 | CR41: =IFERROR(BX41-$BV41,"") -> 281.51538 | CT41: 8109.8819 | CU41: 7812.6667 | CV41: 7123.026 | CW41: 6330 | CX41: 5916.7143 | CY41: 5825 | CZ41: 5238.5385 | DA41: 4894.6525 | DB41: 4651.6721 | DC41: 5025.5714 | DD41: 4251.0308 | DE41: 3551.4545 | DF41: 2659.4848 | DG41: 2210 | DH41: 4225.0778 | DI41: 3908.5818 | DJ41: 3825.5455 | DK41: 3705.2353 | DL41: 3696.9848 | DM41: 3475.5556 | DN41: 2994.5833 | DO41: 2154.3636 | DP41: 2377.8111 | DR41: =AC41 -> 337.79086 | DS41: 296.4913 | DT41: 324.91433 | DU41: 319.00138 | DV41: 274.47726 | DW41: 213.47574 | DX41: 180.51582 | DY41: 204.47937 | DZ41: 174.00962 | EA41: 191.90118 | EB41: 138.91071 | EC41: 120.32021 | ED41: 119.62226 | EE41: 104.23105 | EF41: 91.554663 | EG41: 67.887603 | EH41: 70.079339 | EI41: 100.81025 | EJ41: 103.74101 | EK41: 113.09221 | EL41: 118.16051 | EM41: 115.34247 | EN41: 94.606628 | EP41: 46022 | EQ41: =(DATE(2025,12,31)-EP41)/365 -> 0 | ES41: =AK41 -> 6670 | ET41: =AL41 -> 8598 | EV41: =AN41 -> 8348.125 | EW41: =AO41 -> 8924.75 | EX41: =AP41 -> 8683.7 | EZ41: =AR41 -> 9492 | FA41: =AS41 -> 9899.125 | FB41: =AT41 -> 9891.6 | FD41: =AV41 -> 10707.833 | FE41: =AW41 -> 10897.625 | FF41: =AX41 -> 10883.8 | FH41: =IFERROR(IF($EQ41<0,ES41*-$EQ41+ET41*(1+$EQ41),ES41*(1-$EQ41)+ET41*$EQ41),"") -> 6670 | FI41: =IFERROR(IF($EQ41<0,ET41*-$EQ41+EX41*(1+$EQ41),ET41*(1-$EQ41)+EX41*$EQ41),"") -> 8598 | FK41: =IFERROR(IF($EQ41<0,EV41*-$EQ41+EZ41*(1+$EQ41),EV41*(1-$EQ41)+EZ41*$EQ41),"") -> 8348.125 | FL41: =IFERROR(IF($EQ41<0,EW41*-$EQ41+FA41*(1+$EQ41),EW41*(1-$EQ41)+FA41*$EQ41),"") -> 8924.75 | FM41: =IFERROR(IF($EQ41<0,EX41*-$EQ41+FB41*(1+$EQ41),EX41*(1-$EQ41)+FB41*$EQ41),"") -> 8683.7 | FO41: =IFERROR(IF($EQ41<0,EZ41*-$EQ41+FD41*(1+$EQ41),EZ41*(1-$EQ41)+FD41*$EQ41),"") -> 9492 | FP41: =IFERROR(IF($EQ41<0,FA41*-$EQ41+FE41*(1+$EQ41),FA41*(1-$EQ41)+FE41*$EQ41),"") -> 9899.125 | FQ41: =IFERROR(IF($EQ41<0,FB41*-$EQ41+FF41*(1+$EQ41),FB41*(1-$EQ41)+FF41*$EQ41),"") -> 9891.6 | FS41: =AZ41 -> 5035 | FT41: =BA41 -> 6812 | FV41: =BC41 -> 7530.875 | FW41: =BD41 -> 7812.6667 | FX41: =BE41 -> 7932.8095 | FZ41: =BG41 -> 8709.3846 | GA41: =BH41 -> 8904.2 | GB41: =BI41 -> 8990.9 | GD41: =BK41 -> 9363.875 | GE41: =BL41 -> 10024.143 | GF41: =BM41 -> 10023.389 | GH41: =IFERROR(IF($EQ41<0,FS41*-$EQ41+FT41*(1+$EQ41),FS41*(1-$EQ41)+FT41*$EQ41),"") -> 5035 | GI41: =IFERROR(IF($EQ41<0,FT41*-$EQ41+FX41*(1+$EQ41),FT41*(1-$EQ41)+FX41*$EQ41),"") -> 6812 | GK41: =IFERROR(IF($EQ41<0,FV41*-$EQ41+FZ41*(1+$EQ41),FV41*(1-$EQ41)+FZ41*$EQ41),"") -> 7530.875 | GL41: =IFERROR(IF($EQ41<0,FW41*-$EQ41+GA41*(1+$EQ41),FW41*(1-$EQ41)+GA41*$EQ41),"") -> 7812.6667 | GM41: =IFERROR(IF($EQ41<0,FX41*-$EQ41+GB41*(1+$EQ41),FX41*(1-$EQ41)+GB41*$EQ41),"") -> 7932.8095 | GO41: =IFERROR(IF($EQ41<0,FZ41*-$EQ41+GD41*(1+$EQ41),FZ41*(1-$EQ41)+GD41*$EQ41),"") -> 8709.3846 | GP41: =IFERROR(IF($EQ41<0,GA41*-$EQ41+GE41*(1+$EQ41),GA41*(1-$EQ41)+GE41*$EQ41),"") -> 8904.2 | GQ41: =IFERROR(IF($EQ41<0,GB41*-$EQ41+GF41*(1+$EQ41),GB41*(1-$EQ41)+GF41*$EQ41),"") -> 8990.9
B42: ORCL US Equity | C42: Oracle Corp | D42: =IFERROR(IF(MATCH($B42,Compounders!$A:$A,0),"yes"),"") -> yes | F42: yes | J42: =IF(AND(F42="",G42="",H42="",I42=""),"yes","") | K42: =K41+IF(F42="yes",1) -> 6 | L42: =L41+IF(G42="yes",1) -> 9 | M42: =M41+IF(H42="yes",1) -> 0 | N42: =N41+IF(I42="yes",1) -> 0 | Q42: =Q41+IF(Q$10=$P42,1) -> 4 | R42: =R41+IF(R$10=$P42,1) -> 1 | S42: =S41+IF(S$10=$P42,1) -> 2 | T42: =T41+IF(T$10=$P42,1) -> 0 | U42: =U41+IF(U$10=$P42,1) -> 1 | V42: =V41+IF(V$10=$P42,1) -> 0 | W42: =W41+IF(W$10=$P42,1) -> 1 | X42: =X41+IF(X$10=$P42,1) -> 0 | Y42: =Y41+IF(Y$10=$P42,1) -> 0 | AA42: 560.00177 | AB42: 423.09513 | AC42: 649.35367 | AE42: =$AC42-AA42 -> 89.351898 | AF42: =$AC42-AB42 -> 226.25854 | AH42: =$AC42/AA42-1 -> 0.15955646 | AI42: =$AC42/AB42-1 -> 0.5347699 | AK42: 10467 | AL42: 12443 | AN42: 17189.091 | AO42: 17206.8 | AP42: 17201.059 | AR42: 18869.515 | AS42: 19036.733 | AT42: 18923.588 | AV42: 26769.654 | AW42: 26867.192 | AX42: 26746.345 | AZ42: 15709 | BA42: 17284 | BC42: 21435.231 | BD42: 21853.222 | BE42: 21852.825 | BG42: 23390.524 | BH42: 23881.5 | BI42: 23821.125 | BK42: 31730.788 | BL42: 32937.833 | BM42: 32613.206 | BO42: =CHOOSE($AK$6,FH42,GH42) -> 16632.425 | BP42: =CHOOSE($AK$6,FI42,GI42) -> 19962.708 | BR42: =CHOOSE($AK$6,FK42,GK42) -> 22581.622 | BS42: =CHOOSE($AK$6,FL42,GL42) -> 23042.404 | BT42: =CHOOSE($AK$6,FM42,GM42) -> 23006.842 | BV42: =CHOOSE($AK$6,FO42,GO42) -> 28280.432 | BW42: =CHOOSE($AK$6,FP42,GP42) -> 29191.241 | BX42: =CHOOSE($AK$6,FQ42,GQ42) -> 28975.934 | BZ42: =BP42-BO42 -> 3330.2837 | CA42: =BT42-BP42 -> 3044.1336 | CB42: =BX42-BT42 -> 5969.0921 | CD42: =BP42/BO42-1 -> 0.2002284 | CE42: =BT42/BP42-1 -> 0.15249101 | CF42: =BX42/BT42-1 -> 0.25944856 | CH42: =BS42/$BR42-1 -> 0.0204052 | CI42: =BT42/$BR42-1 -> 0.018830367 | CK42: =BW42/$BV42-1 -> 0.032206318 | CL42: =BX42/$BV42-1 -> 0.024593047 | CN42: =IFERROR(BS42-$BR42,"") -> 460.7825 | CO42: =IFERROR(BT42-$BR42,"") -> 425.22023 | CQ42: =IFERROR(BW42-$BV42,"") -> 910.80858 | CR42: =IFERROR(BX42-$BV42,"") -> 695.50201 | CT42: 22580.382 | CU42: 22625.062 | CV42: 21482.631 | CW42: 20717.733 | CX42: 19563.939 | CY42: 18571.424 | CZ42: 18719.666 | DA42: 18516.118 | DB42: 17748.333 | DC42: 17066 | DD42: 16519.627 | DE42: 16116.005 | DF42: 15324.821 | DG42: 15056.991 | DH42: 14203.518 | DI42: 14007.609 | DJ42: 14246.846 | DK42: 13850.668 | DL42: 13469.623 | DM42: 13220.472 | DN42: 13108.905 | DO42: 13683.558 | DP42: 13352.114 | DR42: =AC42 -> 649.35367 | DS42: 423.09513 | DT42: 560.00177 | DU42: 801.75691 | DV42: 614.09516 | DW42: 392.05996 | DX42: 466.08475 | DY42: 472.18915 | DZ42: 389.12743 | EA42: 345.24084 | EB42: 289.81885 | EC42: 290.15471 | ED42: 323.2411 | EE42: 250.8656 | EF42: 220.39172 | EG42: 164.65488 | EH42: 186.19838 | EI42: 220.73663 | EJ42: 232.88968 | EK42: 238.18606 | EL42: 217.32928 | EM42: 202.33765 | EN42: 190.44956 | EP42: 45808 | EQ42: =(DATE(2025,12,31)-EP42)/365 -> 0.58630137 | ES42: =AK42 -> 10467 | ET42: =AL42 -> 12443 | EV42: =AN42 -> 17189.091 | EW42: =AO42 -> 17206.8 | EX42: =AP42 -> 17201.059 | EZ42: =AR42 -> 18869.515 | FA42: =AS42 -> 19036.733 | FB42: =AT42 -> 18923.588 | FD42: =AV42 -> 26769.654 | FE42: =AW42 -> 26867.192 | FF42: =AX42 -> 26746.345 | FH42: =IFERROR(IF($EQ42<0,ES42*-$EQ42+ET42*(1+$EQ42),ES42*(1-$EQ42)+ET42*$EQ42),"") -> 11625.532 | FI42: =IFERROR(IF($EQ42<0,ET42*-$EQ42+EX42*(1+$EQ42),ET42*(1-$EQ42)+EX42*$EQ42),"") -> 15232.656 | FK42: =IFERROR(IF($EQ42<0,EV42*-$EQ42+EZ42*(1+$EQ42),EV42*(1-$EQ42)+EZ42*$EQ42),"") -> 18174.326 | FL42: =IFERROR(IF($EQ42<0,EW42*-$EQ42+FA42*(1+$EQ42),EW42*(1-$EQ42)+FA42*$EQ42),"") -> 18279.692 | FM42: =IFERROR(IF($EQ42<0,EX42*-$EQ42+FB42*(1+$EQ42),EX42*(1-$EQ42)+FB42*$EQ42),"") -> 18210.98 | FO42: =IFERROR(IF($EQ42<0,EZ42*-$EQ42+FD42*(1+$EQ42),EZ42*(1-$EQ42)+FD42*$EQ42),"") -> 23501.377 | FP42: =IFERROR(IF($EQ42<0,FA42*-$EQ42+FE42*(1+$EQ42),FA42*(1-$EQ42)+FE42*$EQ42),"") -> 23627.742 | FQ42: =IFERROR(IF($EQ42<0,FB42*-$EQ42+FF42*(1+$EQ42),FB42*(1-$EQ42)+FF42*$EQ42),"") -> 23510.081 | FS42: =AZ42 -> 15709 | FT42: =BA42 -> 17284 | FV42: =BC42 -> 21435.231 | FW42: =BD42 -> 21853.222 | FX42: =BE42 -> 21852.825 | FZ42: =BG42 -> 23390.524 | GA42: =BH42 -> 23881.5 | GB42: =BI42 -> 23821.125 | GD42: =BK42 -> 31730.788 | GE42: =BL42 -> 32937.833 | GF42: =BM42 -> 32613.206 | GH42: =IFERROR(IF($EQ42<0,FS42*-$EQ42+FT42*(1+$EQ42),FS42*(1-$EQ42)+FT42*$EQ42),"") -> 16632.425 | GI42: =IFERROR(IF($EQ42<0,FT42*-$EQ42+FX42*(1+$EQ42),FT42*(1-$EQ42)+FX42*$EQ42),"") -> 19962.708 | GK42: =IFERROR(IF($EQ42<0,FV42*-$EQ42+FZ42*(1+$EQ42),FV42*(1-$EQ42)+FZ42*$EQ42),"") -> 22581.622 | GL42: =IFERROR(IF($EQ42<0,FW42*-$EQ42+GA42*(1+$EQ42),FW42*(1-$EQ42)+GA42*$EQ42),"") -> 23042.404 | GM42: =IFERROR(IF($EQ42<0,FX42*-$EQ42+GB42*(1+$EQ42),FX42*(1-$EQ42)+GB42*$EQ42),"") -> 23006.842 | GO42: =IFERROR(IF($EQ42<0,FZ42*-$EQ42+GD42*(1+$EQ42),FZ42*(1-$EQ42)+GD42*$EQ42),"") -> 28280.432 | GP42: =IFERROR(IF($EQ42<0,GA42*-$EQ42+GE42*(1+$EQ42),GA42*(1-$EQ42)+GE42*$EQ42),"") -> 29191.241 | GQ42: =IFERROR(IF($EQ42<0,GB42*-$EQ42+GF42*(1+$EQ42),GB42*(1-$EQ42)+GF42*$EQ42),"") -> 28975.934
B43: HD US Equity | C43: Home Depot Inc/The | D43: =IFERROR(IF(MATCH($B43,Compounders!$A:$A,0),"yes"),"") | J43: =IF(AND(F43="",G43="",H43="",I43=""),"yes","") -> yes | K43: =K42+IF(F43="yes",1) -> 6 | L43: =L42+IF(G43="yes",1) -> 9 | M43: =M42+IF(H43="yes",1) -> 0 | N43: =N42+IF(I43="yes",1) -> 0 | Q43: =Q42+IF(Q$10=$P43,1) -> 4 | R43: =R42+IF(R$10=$P43,1) -> 1 | S43: =S42+IF(S$10=$P43,1) -> 2 | T43: =T42+IF(T$10=$P43,1) -> 0 | U43: =U42+IF(U$10=$P43,1) -> 1 | V43: =V42+IF(V$10=$P43,1) -> 0 | W43: =W42+IF(W$10=$P43,1) -> 1 | X43: =X42+IF(X$10=$P43,1) -> 0 | Y43: =Y42+IF(Y$10=$P43,1) -> 0 | AA43: 342.5555 | AB43: 327.57821 | AC43: 316.22558 | AE43: =$AC43-AA43 -> -26.329917 | AF43: =$AC43-AB43 -> -11.352627 | AH43: =$AC43/AA43-1 -> -0.076863216 | AI43: =$AC43/AB43-1 -> -0.034656232 | AK43: #N/A | AL43: 14806 | AN43: 14088 | AO43: 14156 | AP43: 14156 | AR43: 14768.826 | AS43: 14794.208 | AT43: 14632.625 | AV43: 16032.789 | AW43: 15945.609 | AX43: 15747.375 | AZ43: 14806 | BA43: 15133.32 | BC43: 14421.15 | BD43: 14616.55 | BE43: 14616.55 | BG43: 14901.964 | BH43: 14911.967 | BI43: 14905.107 | BK43: 15986.87 | BL43: 16017.069 | BM43: 15935.192 | BO43: =CHOOSE($AK$6,FH43,GH43) -> 15104.623 | BP43: =CHOOSE($AK$6,FI43,GI43) -> 14661.856 | BR43: =CHOOSE($AK$6,FK43,GK43) -> 14859.811 | BS43: =CHOOSE($AK$6,FL43,GL43) -> 14886.067 | BT43: =CHOOSE($AK$6,FM43,GM43) -> 14879.809 | BV43: =CHOOSE($AK$6,FO43,GO43) -> 15891.755 | BW43: =CHOOSE($AK$6,FP43,GP43) -> 15920.183 | BX43: =CHOOSE($AK$6,FQ43,GQ43) -> 15844.883 | BZ43: =BP43-BO43 -> -442.76759 | CA43: =BT43-BP43 -> 217.95312 | CB43: =BX43-BT43 -> 965.07449 | CD43: =BP43/BO43-1 -> -0.029313381 | CE43: =BT43/BP43-1 -> 0.014865316 | CF43: =BX43/BT43-1 -> 0.064857989 | CH43: =BS43/$BR43-1 -> 0.0017669417 | CI43: =BT43/$BR43-1 -> 0.0013457963 | CK43: =BW43/$BV43-1 -> 0.0017888964 | CL43: =BX43/$BV43-1 -> -0.0029493981 | CN43: =IFERROR(BS43-$BR43,"") -> 26.256419 | CO43: =IFERROR(BT43-$BR43,"") -> 19.998278 | CQ43: =IFERROR(BW43-$BV43,"") -> 28.428703 | CR43: =IFERROR(BX43-$BV43,"") -> -46.87111 | CT43: 15248.636 | CU43: 14911.967 | CV43: 15283.943 | CW43: 15577.704 | CX43: 15198.078 | CY43: 14959.032 | CZ43: 15494.224 | DA43: 15065.69 | DB43: 15323.247 | DC43: 15165.077 | DD43: 14941.594 | DE43: 15468.704 | DF43: 15041.63 | DG43: 15977.371 | DH43: 16909.155 | DI43: 17161.286 | DJ43: 17060.957 | DK43: 16556.333 | DL43: 16565.583 | DM43: 15035.485 | DN43: 14770.059 | DO43: 13541.077 | DP43: 13011.136 | DR43: =AC43 -> 316.22558 | DS43: 327.57821 | DT43: 342.5555 | DU43: 403.32072 | DV43: 364.7804 | DW43: 364.30285 | DX43: 386.40812 | DY43: 402.48248 | DZ43: 341.35327 | EA43: 380.15365 | EB43: 344.90799 | EC43: 302.17994 | ED43: 312.31004 | EE43: 299.53367 | EF43: 321.9201 | EG43: 282.48707 | EH43: 281.88235 | EI43: 309.31264 | EJ43: 433.3697 | EK43: 346.43205 | EL43: 339.06248 | EM43: 328.77543 | EN43: 285.9667 | EP43: 46054 | EQ43: =(DATE(2025,12,31)-EP43)/365 -> -0.087671233 | ES43: =AK43 -> #N/A | ET43: =AL43 -> 14806 | EV43: =AN43 -> 14088 | EW43: =AO43 -> 14156 | EX43: =AP43 -> 14156 | EZ43: =AR43 -> 14768.826 | FA43: =AS43 -> 14794.208 | FB43: =AT43 -> 14632.625 | FD43: =AV43 -> 16032.789 | FE43: =AW43 -> 15945.609 | FF43: =AX43 -> 15747.375 | FH43: =IFERROR(IF($EQ43<0,ES43*-$EQ43+ET43*(1+$EQ43),ES43*(1-$EQ43)+ET43*$EQ43),"") | FI43: =IFERROR(IF($EQ43<0,ET43*-$EQ43+EX43*(1+$EQ43),ET43*(1-$EQ43)+EX43*$EQ43),"") -> 14212.986 | FK43: =IFERROR(IF($EQ43<0,EV43*-$EQ43+EZ43*(1+$EQ43),EV43*(1-$EQ43)+EZ43*$EQ43),"") -> 14709.137 | FL43: =IFERROR(IF($EQ43<0,EW43*-$EQ43+FA43*(1+$EQ43),EW43*(1-$EQ43)+FA43*$EQ43),"") -> 14738.256 | FM43: =IFERROR(IF($EQ43<0,EX43*-$EQ43+FB43*(1+$EQ43),EX43*(1-$EQ43)+FB43*$EQ43),"") -> 14590.839 | FO43: =IFERROR(IF($EQ43<0,EZ43*-$EQ43+FD43*(1+$EQ43),EZ43*(1-$EQ43)+FD43*$EQ43),"") -> 15921.976 | FP43: =IFERROR(IF($EQ43<0,FA43*-$EQ43+FE43*(1+$EQ43),FA43*(1-$EQ43)+FE43*$EQ43),"") -> 15844.664 | FQ43: =IFERROR(IF($EQ43<0,FB43*-$EQ43+FF43*(1+$EQ43),FB43*(1-$EQ43)+FF43*$EQ43),"") -> 15649.643 | FS43: =AZ43 -> 14806 | FT43: =BA43 -> 15133.32 | FV43: =BC43 -> 14421.15 | FW43: =BD43 -> 14616.55 | FX43: =BE43 -> 14616.55 | FZ43: =BG43 -> 14901.964 | GA43: =BH43 -> 14911.967 | GB43: =BI43 -> 14905.107 | GD43: =BK43 -> 15986.87 | GE43: =BL43 -> 16017.069 | GF43: =BM43 -> 15935.192 | GH43: =IFERROR(IF($EQ43<0,FS43*-$EQ43+FT43*(1+$EQ43),FS43*(1-$EQ43)+FT43*$EQ43),"") -> 15104.623 | GI43: =IFERROR(IF($EQ43<0,FT43*-$EQ43+FX43*(1+$EQ43),FT43*(1-$EQ43)+FX43*$EQ43),"") -> 14661.856 | GK43: =IFERROR(IF($EQ43<0,FV43*-$EQ43+FZ43*(1+$EQ43),FV43*(1-$EQ43)+FZ43*$EQ43),"") -> 14859.811 | GL43: =IFERROR(IF($EQ43<0,FW43*-$EQ43+GA43*(1+$EQ43),FW43*(1-$EQ43)+GA43*$EQ43),"") -> 14886.067 | GM43: =IFERROR(IF($EQ43<0,FX43*-$EQ43+GB43*(1+$EQ43),FX43*(1-$EQ43)+GB43*$EQ43),"") -> 14879.809 | GO43: =IFERROR(IF($EQ43<0,FZ43*-$EQ43+GD43*(1+$EQ43),FZ43*(1-$EQ43)+GD43*$EQ43),"") -> 15891.755 | GP43: =IFERROR(IF($EQ43<0,GA43*-$EQ43+GE43*(1+$EQ43),GA43*(1-$EQ43)+GE43*$EQ43),"") -> 15920.183 | GQ43: =IFERROR(IF($EQ43<0,GB43*-$EQ43+GF43*(1+$EQ43),GB43*(1-$EQ43)+GF43*$EQ43),"") -> 15844.883
B44: KO US Equity | C44: Coca-Cola Co/The | D44: =IFERROR(IF(MATCH($B44,Compounders!$A:$A,0),"yes"),"") | J44: =IF(AND(F44="",G44="",H44="",I44=""),"yes","") -> yes | K44: =K43+IF(F44="yes",1) -> 6 | L44: =L43+IF(G44="yes",1) -> 9 | M44: =M43+IF(H44="yes",1) -> 0 | N44: =N43+IF(I44="yes",1) -> 0 | Q44: =Q43+IF(Q$10=$P44,1) -> 4 | R44: =R43+IF(R$10=$P44,1) -> 1 | S44: =S43+IF(S$10=$P44,1) -> 2 | T44: =T43+IF(T$10=$P44,1) -> 0 | U44: =U43+IF(U$10=$P44,1) -> 1 | V44: =V43+IF(V$10=$P44,1) -> 0 | W44: =W43+IF(W$10=$P44,1) -> 1 | X44: =X43+IF(X$10=$P44,1) -> 0 | Y44: =Y43+IF(Y$10=$P44,1) -> 0 | AA44: 300.72547 | AB44: 327.33083 | AC44: 339.93914 | AE44: =$AC44-AA44 -> 39.213661 | AF44: =$AC44-AB44 -> 12.608309 | AH44: =$AC44/AA44-1 -> 0.13039687 | AI44: =$AC44/AB44-1 -> 0.038518552 | AK44: 10631 | AL44: 13107 | AN44: 13864.636 | AO44: 13907.667 | AP44: 14106 | AR44: 14779.176 | AS44: 14861.333 | AT44: 14963.9 | AV44: 15772.667 | AW44: 15786.143 | AX44: 15860.429 | AZ44: 12463 | BA44: 12958 | BC44: 13860.87 | BD44: 13905.955 | BE44: 14104.381 | BG44: 14760.444 | BH44: 14860.273 | BI44: 14962.857 | BK44: 15772.667 | BL44: 15793.467 | BM44: 15869.6 | BO44: =CHOOSE($AK$6,FH44,GH44) -> 12463 | BP44: =CHOOSE($AK$6,FI44,GI44) -> 12958 | BR44: =CHOOSE($AK$6,FK44,GK44) -> 13860.87 | BS44: =CHOOSE($AK$6,FL44,GL44) -> 13905.955 | BT44: =CHOOSE($AK$6,FM44,GM44) -> 14104.381 | BV44: =CHOOSE($AK$6,FO44,GO44) -> 14760.444 | BW44: =CHOOSE($AK$6,FP44,GP44) -> 14860.273 | BX44: =CHOOSE($AK$6,FQ44,GQ44) -> 14962.857 | BZ44: =BP44-BO44 -> 495 | CA44: =BT44-BP44 -> 1146.381 | CB44: =BX44-BT44 -> 858.47619 | CD44: =BP44/BO44-1 -> 0.039717564 | CE44: =BT44/BP44-1 -> 0.088468973 | CF44: =BX44/BT44-1 -> 0.060865925 | CH44: =BS44/$BR44-1 -> 0.0032526805 | CI44: =BT44/$BR44-1 -> 0.017568262 | CK44: =BW44/$BV44-1 -> 0.0067632301 | CL44: =BX44/$BV44-1 -> 0.013713185 | CN44: =IFERROR(BS44-$BR44,"") -> 45.08498 | CO44: =IFERROR(BT44-$BR44,"") -> 243.51139 | CQ44: =IFERROR(BW44-$BV44,"") -> 99.828283 | CR44: =IFERROR(BX44-$BV44,"") -> 202.4127 | CT44: 14248.173 | CU44: 13905.955 | CV44: 13780.701 | CW44: 13340.122 | CX44: 13007.051 | CY44: 12722.19 | CZ44: 12554.272 | DA44: 12594.176 | DB44: 12301.966 | DC44: 12167.19 | DD44: 11964.058 | DE44: 11764.852 | DF44: 11467.805 | DG44: 11282.652 | DH44: 10727 | DI44: 10830.325 | DJ44: 10850.421 | DK44: 10674.565 | DL44: 10335.857 | DM44: 10053.183 | DN44: 9619.8542 | DO44: 9277.2105 | DP44: 8908.2168 | DR44: =AC44 -> 339.93914 | DS44: 327.33083 | DT44: 300.72547 | DU44: 285.41921 | DV44: 304.52687 | DW44: 308.22146 | DX44: 268.20345 | DY44: 309.70713 | DZ44: 274.20136 | EA44: 263.75864 | EB44: 254.77878 | EC44: 242.07682 | ED44: 260.4261 | EE44: 268.36073 | EF44: 275.08229 | EG44: 242.26573 | EH44: 272.71666 | EI44: 268.76969 | EJ44: 255.75287 | EK44: 226.49298 | EL44: 233.30504 | EM44: 227.14382 | EN44: 235.67131 | EP44: 46022 | EQ44: =(DATE(2025,12,31)-EP44)/365 -> 0 | ES44: =AK44 -> 10631 | ET44: =AL44 -> 13107 | EV44: =AN44 -> 13864.636 | EW44: =AO44 -> 13907.667 | EX44: =AP44 -> 14106 | EZ44: =AR44 -> 14779.176 | FA44: =AS44 -> 14861.333 | FB44: =AT44 -> 14963.9 | FD44: =AV44 -> 15772.667 | FE44: =AW44 -> 15786.143 | FF44: =AX44 -> 15860.429 | FH44: =IFERROR(IF($EQ44<0,ES44*-$EQ44+ET44*(1+$EQ44),ES44*(1-$EQ44)+ET44*$EQ44),"") -> 10631 | FI44: =IFERROR(IF($EQ44<0,ET44*-$EQ44+EX44*(1+$EQ44),ET44*(1-$EQ44)+EX44*$EQ44),"") -> 13107 | FK44: =IFERROR(IF($EQ44<0,EV44*-$EQ44+EZ44*(1+$EQ44),EV44*(1-$EQ44)+EZ44*$EQ44),"") -> 13864.636 | FL44: =IFERROR(IF($EQ44<0,EW44*-$EQ44+FA44*(1+$EQ44),EW44*(1-$EQ44)+FA44*$EQ44),"") -> 13907.667 | FM44: =IFERROR(IF($EQ44<0,EX44*-$EQ44+FB44*(1+$EQ44),EX44*(1-$EQ44)+FB44*$EQ44),"") -> 14106 | FO44: =IFERROR(IF($EQ44<0,EZ44*-$EQ44+FD44*(1+$EQ44),EZ44*(1-$EQ44)+FD44*$EQ44),"") -> 14779.176 | FP44: =IFERROR(IF($EQ44<0,FA44*-$EQ44+FE44*(1+$EQ44),FA44*(1-$EQ44)+FE44*$EQ44),"") -> 14861.333 | FQ44: =IFERROR(IF($EQ44<0,FB44*-$EQ44+FF44*(1+$EQ44),FB44*(1-$EQ44)+FF44*$EQ44),"") -> 14963.9 | FS44: =AZ44 -> 12463 | FT44: =BA44 -> 12958 | FV44: =BC44 -> 13860.87 | FW44: =BD44 -> 13905.955 | FX44: =BE44 -> 14104.381 | FZ44: =BG44 -> 14760.444 | GA44: =BH44 -> 14860.273 | GB44: =BI44 -> 14962.857 | GD44: =BK44 -> 15772.667 | GE44: =BL44 -> 15793.467 | GF44: =BM44 -> 15869.6 | GH44: =IFERROR(IF($EQ44<0,FS44*-$EQ44+FT44*(1+$EQ44),FS44*(1-$EQ44)+FT44*$EQ44),"") -> 12463 | GI44: =IFERROR(IF($EQ44<0,FT44*-$EQ44+FX44*(1+$EQ44),FT44*(1-$EQ44)+FX44*$EQ44),"") -> 12958 | GK44: =IFERROR(IF($EQ44<0,FV44*-$EQ44+FZ44*(1+$EQ44),FV44*(1-$EQ44)+FZ44*$EQ44),"") -> 13860.87 | GL44: =IFERROR(IF($EQ44<0,FW44*-$EQ44+GA44*(1+$EQ44),FW44*(1-$EQ44)+GA44*$EQ44),"") -> 13905.955 | GM44: =IFERROR(IF($EQ44<0,FX44*-$EQ44+GB44*(1+$EQ44),FX44*(1-$EQ44)+GB44*$EQ44),"") -> 14104.381 | GO44: =IFERROR(IF($EQ44<0,FZ44*-$EQ44+GD44*(1+$EQ44),FZ44*(1-$EQ44)+GD44*$EQ44),"") -> 14760.444 | GP44: =IFERROR(IF($EQ44<0,GA44*-$EQ44+GE44*(1+$EQ44),GA44*(1-$EQ44)+GE44*$EQ44),"") -> 14860.273 | GQ44: =IFERROR(IF($EQ44<0,GB44*-$EQ44+GF44*(1+$EQ44),GB44*(1-$EQ44)+GF44*$EQ44),"") -> 14962.857
B45: PLTR US Equity | C45: Palantir Technologies Inc | D45: =IFERROR(IF(MATCH($B45,Compounders!$A:$A,0),"yes"),"") | J45: =IF(AND(F45="",G45="",H45="",I45=""),"yes","") -> yes | K45: =K44+IF(F45="yes",1) -> 6 | L45: =L44+IF(G45="yes",1) -> 9 | M45: =M44+IF(H45="yes",1) -> 0 | N45: =N44+IF(I45="yes",1) -> 0 | Q45: =Q44+IF(Q$10=$P45,1) -> 4 | R45: =R44+IF(R$10=$P45,1) -> 1 | S45: =S44+IF(S$10=$P45,1) -> 2 | T45: =T44+IF(T$10=$P45,1) -> 0 | U45: =U44+IF(U$10=$P45,1) -> 1 | V45: =V44+IF(V$10=$P45,1) -> 0 | W45: =W44+IF(W$10=$P45,1) -> 1 | X45: =X44+IF(X$10=$P45,1) -> 0 | Y45: =Y44+IF(Y$10=$P45,1) -> 0 | AA45: 423.47424 | AB45: 349.85432 | AC45: 375.27533 | AE45: =$AC45-AA45 -> -48.198913 | AF45: =$AC45-AB45 -> 25.421003 | AH45: =$AC45/AA45-1 -> -0.11381782 | AI45: =$AC45/AB45-1 -> 0.072661682 | AK45: 462.19 | AL45: 1625.033 | AN45: 1993.375 | AO45: 2961.5 | AP45: 3424.2 | AR45: 2884.6 | AS45: 4307.6 | AT45: 4699.4 | AV45: 4595.6 | AW45: 6212.4 | AX45: 6852.1111 | AZ45: 1001.849 | BA45: 1915.638 | BC45: 2641.25 | BD45: 3439.2963 | BE45: 3775.3571 | BG45: 3724.0667 | BH45: 4952.8889 | BI45: 5432.7143 | BK45: 5123 | BL45: 7134.75 | BM45: 8018.8571 | BO45: =CHOOSE($AK$6,FH45,GH45) -> 1001.849 | BP45: =CHOOSE($AK$6,FI45,GI45) -> 1915.638 | BR45: =CHOOSE($AK$6,FK45,GK45) -> 2641.25 | BS45: =CHOOSE($AK$6,FL45,GL45) -> 3439.2963 | BT45: =CHOOSE($AK$6,FM45,GM45) -> 3775.3571 | BV45: =CHOOSE($AK$6,FO45,GO45) -> 3724.0667 | BW45: =CHOOSE($AK$6,FP45,GP45) -> 4952.8889 | BX45: =CHOOSE($AK$6,FQ45,GQ45) -> 5432.7143 | BZ45: =BP45-BO45 -> 913.789 | CA45: =BT45-BP45 -> 1859.7191 | CB45: =BX45-BT45 -> 1657.3571 | CD45: =BP45/BO45-1 -> 0.91210252 | CE45: =BT45/BP45-1 -> 0.97080928 | CF45: =BX45/BT45-1 -> 0.43899347 | CH45: =BS45/$BR45-1 -> 0.3021472 | CI45: =BT45/$BR45-1 -> 0.42938273 | CK45: =BW45/$BV45-1 -> 0.32996784 | CL45: =BX45/$BV45-1 -> 0.45881231 | CN45: =IFERROR(BS45-$BR45,"") -> 798.0463 | CO45: =IFERROR(BT45-$BR45,"") -> 1134.1071 | CQ45: =IFERROR(BW45-$BV45,"") -> 1228.8222 | CR45: =IFERROR(BX45-$BV45,"") -> 1708.6476 | CT45: 4155.1029 | CU45: 3439.2963 | CV45: 2478.8056 | CW45: 1954.2014 | CX45: 1612.5125 | CY45: 1422.7059 | CZ45: 1153.3333 | DA45: 969.05 | DB45: 830.97222 | DC45: 774.3125 | DD45: 645.74333 | DE45: 551.80333 | DF45: 487.57444 | DG45: 463.5625 | DH45: 358.575 | DI45: 321.58056 | DJ45: 447.48889 | DK45: 470.8 | DL45: 460.24667 | DM45: 418.16667 | DN45: 358.53333 | DO45: 308.5 | DP45: 206.35 | DR45: =AC45 -> 375.27533 | DS45: 349.85432 | DT45: 423.47424 | DU45: 432.7627 | DV45: 321.70326 | DW45: 197.94809 | DX45: 172.22565 | DY45: 83.286426 | DZ45: 56.407287 | EA45: 50.914986 | EB45: 37.361737 | EC45: 34.429206 | ED45: 32.47576 | EE45: 17.756722 | EF45: 13.354852 | EG45: 16.781639 | EH45: 18.562612 | EI45: 27.873525 | EJ45: 36.507789 | EK45: 46.953067 | EL45: 49.471033 | EM45: 42.440611 | EN45: 41.025175 | EP45: 46022 | EQ45: =(DATE(2025,12,31)-EP45)/365 -> 0 | ES45: =AK45 -> 462.19 | ET45: =AL45 -> 1625.033 | EV45: =AN45 -> 1993.375 | EW45: =AO45 -> 2961.5 | EX45: =AP45 -> 3424.2 | EZ45: =AR45 -> 2884.6 | FA45: =AS45 -> 4307.6 | FB45: =AT45 -> 4699.4 | FD45: =AV45 -> 4595.6 | FE45: =AW45 -> 6212.4 | FF45: =AX45 -> 6852.1111 | FH45: =IFERROR(IF($EQ45<0,ES45*-$EQ45+ET45*(1+$EQ45),ES45*(1-$EQ45)+ET45*$EQ45),"") -> 462.19 | FI45: =IFERROR(IF($EQ45<0,ET45*-$EQ45+EX45*(1+$EQ45),ET45*(1-$EQ45)+EX45*$EQ45),"") -> 1625.033 | FK45: =IFERROR(IF($EQ45<0,EV45*-$EQ45+EZ45*(1+$EQ45),EV45*(1-$EQ45)+EZ45*$EQ45),"") -> 1993.375 | FL45: =IFERROR(IF($EQ45<0,EW45*-$EQ45+FA45*(1+$EQ45),EW45*(1-$EQ45)+FA45*$EQ45),"") -> 2961.5 | FM45: =IFERROR(IF($EQ45<0,EX45*-$EQ45+FB45*(1+$EQ45),EX45*(1-$EQ45)+FB45*$EQ45),"") -> 3424.2 | FO45: =IFERROR(IF($EQ45<0,EZ45*-$EQ45+FD45*(1+$EQ45),EZ45*(1-$EQ45)+FD45*$EQ45),"") -> 2884.6 | FP45: =IFERROR(IF($EQ45<0,FA45*-$EQ45+FE45*(1+$EQ45),FA45*(1-$EQ45)+FE45*$EQ45),"") -> 4307.6 | FQ45: =IFERROR(IF($EQ45<0,FB45*-$EQ45+FF45*(1+$EQ45),FB45*(1-$EQ45)+FF45*$EQ45),"") -> 4699.4 | FS45: =AZ45 -> 1001.849 | FT45: =BA45 -> 1915.638 | FV45: =BC45 -> 2641.25 | FW45: =BD45 -> 3439.2963 | FX45: =BE45 -> 3775.3571 | FZ45: =BG45 -> 3724.0667 | GA45: =BH45 -> 4952.8889 | GB45: =BI45 -> 5432.7143 | GD45: =BK45 -> 5123 | GE45: =BL45 -> 7134.75 | GF45: =BM45 -> 8018.8571 | GH45: =IFERROR(IF($EQ45<0,FS45*-$EQ45+FT45*(1+$EQ45),FS45*(1-$EQ45)+FT45*$EQ45),"") -> 1001.849 | GI45: =IFERROR(IF($EQ45<0,FT45*-$EQ45+FX45*(1+$EQ45),FT45*(1-$EQ45)+FX45*$EQ45),"") -> 1915.638 | GK45: =IFERROR(IF($EQ45<0,FV45*-$EQ45+FZ45*(1+$EQ45),FV45*(1-$EQ45)+FZ45*$EQ45),"") -> 2641.25 | GL45: =IFERROR(IF($EQ45<0,FW45*-$EQ45+GA45*(1+$EQ45),FW45*(1-$EQ45)+GA45*$EQ45),"") -> 3439.2963 | GM45: =IFERROR(IF($EQ45<0,FX45*-$EQ45+GB45*(1+$EQ45),FX45*(1-$EQ45)+GB45*$EQ45),"") -> 3775.3571 | GO45: =IFERROR(IF($EQ45<0,FZ45*-$EQ45+GD45*(1+$EQ45),FZ45*(1-$EQ45)+GD45*$EQ45),"") -> 3724.0667 | GP45: =IFERROR(IF($EQ45<0,GA45*-$EQ45+GE45*(1+$EQ45),GA45*(1-$EQ45)+GE45*$EQ45),"") -> 4952.8889 | GQ45: =IFERROR(IF($EQ45<0,GB45*-$EQ45+GF45*(1+$EQ45),GB45*(1-$EQ45)+GF45*$EQ45),"") -> 5432.7143
B46: GS US Equity | C46: Goldman Sachs Group Inc/The | D46: =IFERROR(IF(MATCH($B46,Compounders!$A:$A,0),"yes"),"") -> yes | J46: =IF(AND(F46="",G46="",H46="",I46=""),"yes","") -> yes | K46: =K45+IF(F46="yes",1) -> 6 | L46: =L45+IF(G46="yes",1) -> 9 | M46: =M45+IF(H46="yes",1) -> 0 | N46: =N45+IF(I46="yes",1) -> 0 | Q46: =Q45+IF(Q$10=$P46,1) -> 4 | R46: =R45+IF(R$10=$P46,1) -> 1 | S46: =S45+IF(S$10=$P46,1) -> 2 | T46: =T45+IF(T$10=$P46,1) -> 0 | U46: =U45+IF(U$10=$P46,1) -> 1 | V46: =V45+IF(V$10=$P46,1) -> 0 | W46: =W45+IF(W$10=$P46,1) -> 1 | X46: =X45+IF(X$10=$P46,1) -> 0 | Y46: =Y45+IF(Y$10=$P46,1) -> 0 | AA46: 273.7913 | AB46: 259.33473 | AC46: 314.39499 | AE46: =$AC46-AA46 -> 40.603698 | AF46: =$AC46-AB46 -> 55.060263 | AH46: =$AC46/AA46-1 -> 0.14830164 | AI46: =$AC46/AB46-1 -> 0.2123135 | AK46: 13525 | AL46: 16300 | AN46: 16960.864 | AO46: 17962.048 | AP46: 18029.125 | AR46: 18156.722 | AS46: 19334.955 | AT46: 19251 | AV46: 19525 | AW46: 20233.308 | AX46: 20108.571 | AZ46: 13525 | BA46: 16300 | BC46: 17012.609 | BD46: 17987.045 | BE46: 18022.64 | BG46: 18178.105 | BH46: 19320.826 | BI46: 19220.32 | BK46: 19525 | BL46: 20192.286 | BM46: 20038.733 | BO46: =CHOOSE($AK$6,FH46,GH46) -> 13525 | BP46: =CHOOSE($AK$6,FI46,GI46) -> 16300 | BR46: =CHOOSE($AK$6,FK46,GK46) -> 17012.609 | BS46: =CHOOSE($AK$6,FL46,GL46) -> 17987.045 | BT46: =CHOOSE($AK$6,FM46,GM46) -> 18022.64 | BV46: =CHOOSE($AK$6,FO46,GO46) -> 18178.105 | BW46: =CHOOSE($AK$6,FP46,GP46) -> 19320.826 | BX46: =CHOOSE($AK$6,FQ46,GQ46) -> 19220.32 | BZ46: =BP46-BO46 -> 2775 | CA46: =BT46-BP46 -> 1722.64 | CB46: =BX46-BT46 -> 1197.68 | CD46: =BP46/BO46-1 -> 0.2051756 | CE46: =BT46/BP46-1 -> 0.10568344 | CF46: =BX46/BT46-1 -> 0.066454193 | CH46: =BS46/$BR46-1 -> 0.057277327 | CI46: =BT46/$BR46-1 -> 0.059369572 | CK46: =BW46/$BV46-1 -> 0.062862482 | CL46: =BX46/$BV46-1 -> 0.057333519 | CN46: =IFERROR(BS46-$BR46,"") -> 974.43676 | CO46: =IFERROR(BT46-$BR46,"") -> 1010.0313 | CQ46: =IFERROR(BW46-$BV46,"") -> 1142.7208 | CR46: =IFERROR(BX46-$BV46,"") -> 1042.2147 | CT46: 17915.565 | CU46: 17987.045 | CV46: 16791.986 | CW46: 15481.649 | CX46: 14150.758 | CY46: 14835.864 | CZ46: 13442.748 | DA46: 12456.833 | DB46: 12363.848 | DC46: 11421.429 | DD46: 10925.358 | DE46: 10877.39 | DF46: 10804.409 | DG46: 12070.962 | DH46: 12384.983 | DI46: 12759.428 | DJ46: 13360.887 | DK46: 13952.034 | DL46: 14653.562 | DM46: 13483.083 | DN46: 12420.411 | DO46: 10857.444 | DP46: 9117.25 | DR46: =AC46 -> 314.39499 | DS46: 259.33473 | DT46: 273.7913 | DU46: 250.27131 | DV46: 225.34268 | DW46: 176.09238 | DX46: 186.3659 | DY46: 162.07499 | DZ46: 151.08185 | EA46: 140.37685 | EB46: 130.26079 | EC46: 110.40953 | ED46: 110.95376 | EE46: 114.2175 | EF46: 120.97277 | EG46: 104.03275 | EH46: 105.85793 | EI46: 116.47123 | EJ46: 132.93613 | EK46: 132.2727 | EL46: 133.86023 | EM46: 116.38117 | EN46: 93.88076 | EP46: 46022 | EQ46: =(DATE(2025,12,31)-EP46)/365 -> 0 | ES46: =AK46 -> 13525 | ET46: =AL46 -> 16300 | EV46: =AN46 -> 16960.864 | EW46: =AO46 -> 17962.048 | EX46: =AP46 -> 18029.125 | EZ46: =AR46 -> 18156.722 | FA46: =AS46 -> 19334.955 | FB46: =AT46 -> 19251 | FD46: =AV46 -> 19525 | FE46: =AW46 -> 20233.308 | FF46: =AX46 -> 20108.571 | FH46: =IFERROR(IF($EQ46<0,ES46*-$EQ46+ET46*(1+$EQ46),ES46*(1-$EQ46)+ET46*$EQ46),"") -> 13525 | FI46: =IFERROR(IF($EQ46<0,ET46*-$EQ46+EX46*(1+$EQ46),ET46*(1-$EQ46)+EX46*$EQ46),"") -> 16300 | FK46: =IFERROR(IF($EQ46<0,EV46*-$EQ46+EZ46*(1+$EQ46),EV46*(1-$EQ46)+EZ46*$EQ46),"") -> 16960.864 | FL46: =IFERROR(IF($EQ46<0,EW46*-$EQ46+FA46*(1+$EQ46),EW46*(1-$EQ46)+FA46*$EQ46),"") -> 17962.048 | FM46: =IFERROR(IF($EQ46<0,EX46*-$EQ46+FB46*(1+$EQ46),EX46*(1-$EQ46)+FB46*$EQ46),"") -> 18029.125 | FO46: =IFERROR(IF($EQ46<0,EZ46*-$EQ46+FD46*(1+$EQ46),EZ46*(1-$EQ46)+FD46*$EQ46),"") -> 18156.722 | FP46: =IFERROR(IF($EQ46<0,FA46*-$EQ46+FE46*(1+$EQ46),FA46*(1-$EQ46)+FE46*$EQ46),"") -> 19334.955 | FQ46: =IFERROR(IF($EQ46<0,FB46*-$EQ46+FF46*(1+$EQ46),FB46*(1-$EQ46)+FF46*$EQ46),"") -> 19251 | FS46: =AZ46 -> 13525 | FT46: =BA46 -> 16300 | FV46: =BC46 -> 17012.609 | FW46: =BD46 -> 17987.045 | FX46: =BE46 -> 18022.64 | FZ46: =BG46 -> 18178.105 | GA46: =BH46 -> 19320.826 | GB46: =BI46 -> 19220.32 | GD46: =BK46 -> 19525 | GE46: =BL46 -> 20192.286 | GF46: =BM46 -> 20038.733 | GH46: =IFERROR(IF($EQ46<0,FS46*-$EQ46+FT46*(1+$EQ46),FS46*(1-$EQ46)+FT46*$EQ46),"") -> 13525 | GI46: =IFERROR(IF($EQ46<0,FT46*-$EQ46+FX46*(1+$EQ46),FT46*(1-$EQ46)+FX46*$EQ46),"") -> 16300 | GK46: =IFERROR(IF($EQ46<0,FV46*-$EQ46+FZ46*(1+$EQ46),FV46*(1-$EQ46)+FZ46*$EQ46),"") -> 17012.609 | GL46: =IFERROR(IF($EQ46<0,FW46*-$EQ46+GA46*(1+$EQ46),FW46*(1-$EQ46)+GA46*$EQ46),"") -> 17987.045 | GM46: =IFERROR(IF($EQ46<0,FX46*-$EQ46+GB46*(1+$EQ46),FX46*(1-$EQ46)+GB46*$EQ46),"") -> 18022.64 | GO46: =IFERROR(IF($EQ46<0,FZ46*-$EQ46+GD46*(1+$EQ46),FZ46*(1-$EQ46)+GD46*$EQ46),"") -> 18178.105 | GP46: =IFERROR(IF($EQ46<0,GA46*-$EQ46+GE46*(1+$EQ46),GA46*(1-$EQ46)+GE46*$EQ46),"") -> 19320.826 | GQ46: =IFERROR(IF($EQ46<0,GB46*-$EQ46+GF46*(1+$EQ46),GB46*(1-$EQ46)+GF46*$EQ46),"") -> 19220.32
B47: MRK US Equity | C47: Merck & Co Inc | D47: =IFERROR(IF(MATCH($B47,Compounders!$A:$A,0),"yes"),"") | J47: =IF(AND(F47="",G47="",H47="",I47=""),"yes","") -> yes | K47: =K46+IF(F47="yes",1) -> 6 | L47: =L46+IF(G47="yes",1) -> 9 | M47: =M46+IF(H47="yes",1) -> 0 | N47: =N46+IF(I47="yes",1) -> 0 | Q47: =Q46+IF(Q$10=$P47,1) -> 4 | R47: =R46+IF(R$10=$P47,1) -> 1 | S47: =S46+IF(S$10=$P47,1) -> 2 | T47: =T46+IF(T$10=$P47,1) -> 0 | U47: =U46+IF(U$10=$P47,1) -> 1 | V47: =V46+IF(V$10=$P47,1) -> 0 | W47: =W46+IF(W$10=$P47,1) -> 1 | X47: =X46+IF(X$10=$P47,1) -> 0 | Y47: =Y46+IF(Y$10=$P47,1) -> 0 | AA47: 261.25769 | AB47: 297.40403 | AC47: 293.21755 | AE47: =$AC47-AA47 -> 31.959862 | AF47: =$AC47-AB47 -> -4.1864795 | AH47: =$AC47/AA47-1 -> 0.1223308 | AI47: =$AC47/AB47-1 -> -0.014076741 | AK47: 17117 | AL47: 18254 | AN47: 19194 | AO47: 10805.867 | AP47: 8622.1333 | AR47: 22963.333 | AS47: 21582.857 | AT47: 20799.071 | AV47: 24235.1 | AW47: 23739 | AX47: 23118.857 | AZ47: 19444 | BA47: 22513 | BC47: 19604.533 | BD47: 12619.55 | BE47: 12735.875 | BG47: 25016.053 | BH47: 23695.632 | BI47: 23617.947 | BK47: 26397.6 | BL47: 25840.167 | BM47: 25863.444 | BO47: =CHOOSE($AK$6,FH47,GH47) -> 19444 | BP47: =CHOOSE($AK$6,FI47,GI47) -> 22513 | BR47: =CHOOSE($AK$6,FK47,GK47) -> 19604.533 | BS47: =CHOOSE($AK$6,FL47,GL47) -> 12619.55 | BT47: =CHOOSE($AK$6,FM47,GM47) -> 12735.875 | BV47: =CHOOSE($AK$6,FO47,GO47) -> 25016.053 | BW47: =CHOOSE($AK$6,FP47,GP47) -> 23695.632 | BX47: =CHOOSE($AK$6,FQ47,GQ47) -> 23617.947 | BZ47: =BP47-BO47 -> 3069 | CA47: =BT47-BP47 -> -9777.125 | CB47: =BX47-BT47 -> 10882.072 | CD47: =BP47/BO47-1 -> 0.15783789 | CE47: =BT47/BP47-1 -> -0.43428797 | CF47: =BX47/BT47-1 -> 0.85444246 | CH47: =BS47/$BR47-1 -> -0.35629429 | CI47: =BT47/$BR47-1 -> -0.35036072 | CK47: =BW47/$BV47-1 -> -0.05278295 | CL47: =BX47/$BV47-1 -> -0.055888324 | CN47: =IFERROR(BS47-$BR47,"") -> -6984.9833 | CO47: =IFERROR(BT47-$BR47,"") -> -6868.6583 | CQ47: =IFERROR(BW47-$BV47,"") -> -1320.4211 | CR47: =IFERROR(BX47-$BV47,"") -> -1398.1053 | CT47: 20869.824 | CU47: 12619.55 | CV47: 18837.375 | CW47: 23016.373 | CX47: 22555.176 | CY47: 22724.15 | CZ47: 24414.571 | DA47: 21508.528 | DB47: 22773.287 | DC47: 21739.857 | DD47: 15849.55 | DE47: 19524.052 | DF47: 18948.847 | DG47: 17582.682 | DH47: 17633.783 | DI47: 17068.74 | DJ47: 17428.196 | DK47: 18460.4 | DL47: 17862.25 | DM47: 15765.414 | DN47: 15311.429 | DO47: 16444.824 | DP47: 15487.757 | DR47: =AC47 -> 293.21755 | DS47: 297.40403 | DT47: 261.25769 | DU47: 209.63894 | DV47: 198.77323 | DW47: 226.73701 | DX47: 251.64815 | DY47: 287.85295 | DZ47: 313.56142 | EA47: 334.18236 | EB47: 276.2592 | EC47: 261.2378 | ED47: 292.79473 | EE47: 270.08085 | EF47: 281.30218 | EG47: 218.16606 | EH47: 230.55115 | EI47: 207.40054 | EJ47: 193.58834 | EK47: 190.13155 | EL47: 196.91818 | EM47: 195.06203 | EN47: 206.95682 | EP47: 46022 | EQ47: =(DATE(2025,12,31)-EP47)/365 -> 0 | ES47: =AK47 -> 17117 | ET47: =AL47 -> 18254 | EV47: =AN47 -> 19194 | EW47: =AO47 -> 10805.867 | EX47: =AP47 -> 8622.1333 | EZ47: =AR47 -> 22963.333 | FA47: =AS47 -> 21582.857 | FB47: =AT47 -> 20799.071 | FD47: =AV47 -> 24235.1 | FE47: =AW47 -> 23739 | FF47: =AX47 -> 23118.857 | FH47: =IFERROR(IF($EQ47<0,ES47*-$EQ47+ET47*(1+$EQ47),ES47*(1-$EQ47)+ET47*$EQ47),"") -> 17117 | FI47: =IFERROR(IF($EQ47<0,ET47*-$EQ47+EX47*(1+$EQ47),ET47*(1-$EQ47)+EX47*$EQ47),"") -> 18254 | FK47: =IFERROR(IF($EQ47<0,EV47*-$EQ47+EZ47*(1+$EQ47),EV47*(1-$EQ47)+EZ47*$EQ47),"") -> 19194 | FL47: =IFERROR(IF($EQ47<0,EW47*-$EQ47+FA47*(1+$EQ47),EW47*(1-$EQ47)+FA47*$EQ47),"") -> 10805.867 | FM47: =IFERROR(IF($EQ47<0,EX47*-$EQ47+FB47*(1+$EQ47),EX47*(1-$EQ47)+FB47*$EQ47),"") -> 8622.1333 | FO47: =IFERROR(IF($EQ47<0,EZ47*-$EQ47+FD47*(1+$EQ47),EZ47*(1-$EQ47)+FD47*$EQ47),"") -> 22963.333 | FP47: =IFERROR(IF($EQ47<0,FA47*-$EQ47+FE47*(1+$EQ47),FA47*(1-$EQ47)+FE47*$EQ47),"") -> 21582.857 | FQ47: =IFERROR(IF($EQ47<0,FB47*-$EQ47+FF47*(1+$EQ47),FB47*(1-$EQ47)+FF47*$EQ47),"") -> 20799.071 | FS47: =AZ47 -> 19444 | FT47: =BA47 -> 22513 | FV47: =BC47 -> 19604.533 | FW47: =BD47 -> 12619.55 | FX47: =BE47 -> 12735.875 | FZ47: =BG47 -> 25016.053 | GA47: =BH47 -> 23695.632 | GB47: =BI47 -> 23617.947 | GD47: =BK47 -> 26397.6 | GE47: =BL47 -> 25840.167 | GF47: =BM47 -> 25863.444 | GH47: =IFERROR(IF($EQ47<0,FS47*-$EQ47+FT47*(1+$EQ47),FS47*(1-$EQ47)+FT47*$EQ47),"") -> 19444 | GI47: =IFERROR(IF($EQ47<0,FT47*-$EQ47+FX47*(1+$EQ47),FT47*(1-$EQ47)+FX47*$EQ47),"") -> 22513 | GK47: =IFERROR(IF($EQ47<0,FV47*-$EQ47+FZ47*(1+$EQ47),FV47*(1-$EQ47)+FZ47*$EQ47),"") -> 19604.533 | GL47: =IFERROR(IF($EQ47<0,FW47*-$EQ47+GA47*(1+$EQ47),FW47*(1-$EQ47)+GA47*$EQ47),"") -> 12619.55 | GM47: =IFERROR(IF($EQ47<0,FX47*-$EQ47+GB47*(1+$EQ47),FX47*(1-$EQ47)+GB47*$EQ47),"") -> 12735.875 | GO47: =IFERROR(IF($EQ47<0,FZ47*-$EQ47+GD47*(1+$EQ47),FZ47*(1-$EQ47)+GD47*$EQ47),"") -> 25016.053 | GP47: =IFERROR(IF($EQ47<0,GA47*-$EQ47+GE47*(1+$EQ47),GA47*(1-$EQ47)+GE47*$EQ47),"") -> 23695.632 | GQ47: =IFERROR(IF($EQ47<0,GB47*-$EQ47+GF47*(1+$EQ47),GB47*(1-$EQ47)+GF47*$EQ47),"") -> 23617.947
B48: TXN US Equity | C48: Texas Instruments Inc | D48: =IFERROR(IF(MATCH($B48,Compounders!$A:$A,0),"yes"),"") -> yes | G48: yes | J48: =IF(AND(F48="",G48="",H48="",I48=""),"yes","") | K48: =K47+IF(F48="yes",1) -> 6 | L48: =L47+IF(G48="yes",1) -> 10 | M48: =M47+IF(H48="yes",1) -> 0 | N48: =N47+IF(I48="yes",1) -> 0 | P48: Analog/MCU | Q48: =Q47+IF(Q$10=$P48,1) -> 4 | R48: =R47+IF(R$10=$P48,1) -> 1 | S48: =S47+IF(S$10=$P48,1) -> 2 | T48: =T47+IF(T$10=$P48,1) -> 1 | U48: =U47+IF(U$10=$P48,1) -> 1 | V48: =V47+IF(V$10=$P48,1) -> 0 | W48: =W47+IF(W$10=$P48,1) -> 1 | X48: =X47+IF(X$10=$P48,1) -> 0 | Y48: =Y47+IF(Y$10=$P48,1) -> 0 | AA48: 157.63701 | AB48: 176.75736 | AC48: 278.19716 | AE48: =$AC48-AA48 -> 120.56016 | AF48: =$AC48-AB48 -> 101.4398 | AH48: =$AC48/AA48-1 -> 0.76479602 | AI48: =$AC48/AB48-1 -> 0.57389296 | AK48: 4799 | AL48: 5001 | AN48: 5559.2581 | AO48: 5857.8667 | AP48: 7068.5517 | AR48: 6835.625 | AS48: 7076.9655 | AT48: 8220.0357 | AV48: 8917.6 | AW48: 8775.0769 | AX48: 9529 | AZ48: 4799 | BA48: 5420 | BC48: 5565.4615 | BD48: 5805.1071 | BE48: 7080.2222 | BG48: 6788.9048 | BH48: 6981.3793 | BI48: 8235.6897 | BK48: 8572.5714 | BL48: 8586.8182 | BM48: 9458.875 | BO48: =CHOOSE($AK$6,FH48,GH48) -> 4799 | BP48: =CHOOSE($AK$6,FI48,GI48) -> 5420 | BR48: =CHOOSE($AK$6,FK48,GK48) -> 5565.4615 | BS48: =CHOOSE($AK$6,FL48,GL48) -> 5805.1071 | BT48: =CHOOSE($AK$6,FM48,GM48) -> 7080.2222 | BV48: =CHOOSE($AK$6,FO48,GO48) -> 6788.9048 | BW48: =CHOOSE($AK$6,FP48,GP48) -> 6981.3793 | BX48: =CHOOSE($AK$6,FQ48,GQ48) -> 8235.6897 | BZ48: =BP48-BO48 -> 621 | CA48: =BT48-BP48 -> 1660.2222 | CB48: =BX48-BT48 -> 1155.4674 | CD48: =BP48/BO48-1 -> 0.12940196 | CE48: =BT48/BP48-1 -> 0.30631406 | CF48: =BX48/BT48-1 -> 0.16319649 | CH48: =BS48/$BR48-1 -> 0.043059431 | CI48: =BT48/$BR48-1 -> 0.27217162 | CK48: =BW48/$BV48-1 -> 0.02835134 | CL48: =BX48/$BV48-1 -> 0.21311021 | CN48: =IFERROR(BS48-$BR48,"") -> 239.6456 | CO48: =IFERROR(BT48-$BR48,"") -> 1514.7607 | CQ48: =IFERROR(BW48-$BV48,"") -> 192.47455 | CR48: =IFERROR(BX48-$BV48,"") -> 1446.7849 | CT48: 7422.2611 | CU48: 5805.1071 | CV48: 5299.1932 | CW48: 5471.3236 | CX48: 5198.1481 | CY48: 5063.4815 | CZ48: 5754.2036 | DA48: 5238.9117 | DB48: 4934.4035 | DC48: 4743.3333 | DD48: 5832.8723 | DE48: 6763.1625 | DF48: 6895.1801 | DG48: 7150.36 | DH48: 7349.4763 | DI48: 8442.234 | DJ48: 8107.5697 | DK48: 8598.6471 | DL48: 7724.2222 | DM48: 7303.7917 | DN48: 7015.7679 | DO48: 6467.1429 | DP48: 5369.9091 | DR48: =AC48 -> 278.19716 | DS48: 176.75736 | DT48: 157.63701 | DU48: 167.03577 | DV48: 188.61697 | DW48: 163.51223 | DX48: 171.04974 | DY48: 188.6079 | DZ48: 177.11609 | EA48: 158.40701 | EB48: 154.81247 | EC48: 144.37573 | ED48: 163.39585 | EE48: 168.77468 | EF48: 149.949 | EG48: 141.42363 | EH48: 141.68587 | EI48: 169.45241 | EJ48: 174.05695 | EK48: 177.45019 | EL48: 177.59357 | EM48: 174.43934 | EN48: 150.66184 | EP48: 46022 | EQ48: =(DATE(2025,12,31)-EP48)/365 -> 0 | ES48: =AK48 -> 4799 | ET48: =AL48 -> 5001 | EV48: =AN48 -> 5559.2581 | EW48: =AO48 -> 5857.8667 | EX48: =AP48 -> 7068.5517 | EZ48: =AR48 -> 6835.625 | FA48: =AS48 -> 7076.9655 | FB48: =AT48 -> 8220.0357 | FD48: =AV48 -> 8917.6 | FE48: =AW48 -> 8775.0769 | FF48: =AX48 -> 9529 | FH48: =IFERROR(IF($EQ48<0,ES48*-$EQ48+ET48*(1+$EQ48),ES48*(1-$EQ48)+ET48*$EQ48),"") -> 4799 | FI48: =IFERROR(IF($EQ48<0,ET48*-$EQ48+EX48*(1+$EQ48),ET48*(1-$EQ48)+EX48*$EQ48),"") -> 5001 | FK48: =IFERROR(IF($EQ48<0,EV48*-$EQ48+EZ48*(1+$EQ48),EV48*(1-$EQ48)+EZ48*$EQ48),"") -> 5559.2581 | FL48: =IFERROR(IF($EQ48<0,EW48*-$EQ48+FA48*(1+$EQ48),EW48*(1-$EQ48)+FA48*$EQ48),"") -> 5857.8667 | FM48: =IFERROR(IF($EQ48<0,EX48*-$EQ48+FB48*(1+$EQ48),EX48*(1-$EQ48)+FB48*$EQ48),"") -> 7068.5517 | FO48: =IFERROR(IF($EQ48<0,EZ48*-$EQ48+FD48*(1+$EQ48),EZ48*(1-$EQ48)+FD48*$EQ48),"") -> 6835.625 | FP48: =IFERROR(IF($EQ48<0,FA48*-$EQ48+FE48*(1+$EQ48),FA48*(1-$EQ48)+FE48*$EQ48),"") -> 7076.9655 | FQ48: =IFERROR(IF($EQ48<0,FB48*-$EQ48+FF48*(1+$EQ48),FB48*(1-$EQ48)+FF48*$EQ48),"") -> 8220.0357 | FS48: =AZ48 -> 4799 | FT48: =BA48 -> 5420 | FV48: =BC48 -> 5565.4615 | FW48: =BD48 -> 5805.1071 | FX48: =BE48 -> 7080.2222 | FZ48: =BG48 -> 6788.9048 | GA48: =BH48 -> 6981.3793 | GB48: =BI48 -> 8235.6897 | GD48: =BK48 -> 8572.5714 | GE48: =BL48 -> 8586.8182 | GF48: =BM48 -> 9458.875 | GH48: =IFERROR(IF($EQ48<0,FS48*-$EQ48+FT48*(1+$EQ48),FS48*(1-$EQ48)+FT48*$EQ48),"") -> 4799 | GI48: =IFERROR(IF($EQ48<0,FT48*-$EQ48+FX48*(1+$EQ48),FT48*(1-$EQ48)+FX48*$EQ48),"") -> 5420 | GK48: =IFERROR(IF($EQ48<0,FV48*-$EQ48+FZ48*(1+$EQ48),FV48*(1-$EQ48)+FZ48*$EQ48),"") -> 5565.4615 | GL48: =IFERROR(IF($EQ48<0,FW48*-$EQ48+GA48*(1+$EQ48),FW48*(1-$EQ48)+GA48*$EQ48),"") -> 5805.1071 | GM48: =IFERROR(IF($EQ48<0,FX48*-$EQ48+GB48*(1+$EQ48),FX48*(1-$EQ48)+GB48*$EQ48),"") -> 7080.2222 | GO48: =IFERROR(IF($EQ48<0,FZ48*-$EQ48+GD48*(1+$EQ48),FZ48*(1-$EQ48)+GD48*$EQ48),"") -> 6788.9048 | GP48: =IFERROR(IF($EQ48<0,GA48*-$EQ48+GE48*(1+$EQ48),GA48*(1-$EQ48)+GE48*$EQ48),"") -> 6981.3793 | GQ48: =IFERROR(IF($EQ48<0,GB48*-$EQ48+GF48*(1+$EQ48),GB48*(1-$EQ48)+GF48*$EQ48),"") -> 8235.6897
