Workbook

Sheet Summary
D1: IRR yrs: | CM1: =TODAY() -> 46183 | DT1: 46387 | DU1: =DT1+365 -> 46752 | DV1: =DU1+365 -> 47117 | DW1: =DV1+365 -> 47482
B2: =IFERROR($D$4:$ED$55,"--> select table 1") -> --> select table 1 | D2: =TODAY() -> 46183 | DT2: =(DT1-$D$2)/365 -> 0.55890411 | DU2: =(DU1-$D$2)/365 -> 1.5589041 | DV2: =(DV1-$D$2)/365 -> 2.5589041 | DW2: =(DW1-$D$2)/365 -> 3.5589041 | FF2: WORK IN PROGRESS
B3: =IFERROR($D$4:$EM$44,"--> select table 2") -> --> select table 2
D4: =$D$2 -> 46183 | O4: Revs | X4: GM | AG4: Adj GP | AP4: Adj EPS | AY4: Mendo EPS | BH4: EV / Revs | BO4: EV / GP | BT4: P/E (Adj, Ex SBC) | BY4: Mendo P/E | CD4: x | CE4: Target Mult (GP or P/E) | CI4: Target Px (old, hardcoded) | CN4: Derived Target Px for IRR calc | CS4: Net Cash per Share | CX4: EV | DC4: WADSO | DH4: Net Debt | DO4: DPS | DT4: IRR | DU4: IRR | DX4: MoM | EB4: Recent Performance | EE4: NTM - YE28 IRR Decomp | EL4: '26-'29 CAGR | EN4: Key details | EX4: Consensus key metric | FB4: Mendo vs Consensus | FF4: Earnings | FI4: Valuation | FL4: 3yr Net | FN4: Up/Down | FT4: Val up/down
D5: Company | E5: Port | F5: Update | G5: Update by | H5: Px | I5: Shares | J5: Cash | K5: Debt | L5: Min Int | M5: Net Debt | N5: EV | O5: 2022 | P5: =O5+1 -> 2023 | Q5: =P5+1 -> 2024 | R5: =Q5+1 -> 2025 | S5: =R5+1 -> 2026 | T5: 2027 | U5: 2028 | V5: 2029 | W5: 2030 | X5: 2022 | Y5: =X5+1 -> 2023 | Z5: =Y5+1 -> 2024 | AA5: =Z5+1 -> 2025 | AB5: =AA5+1 -> 2026 | AC5: 2027 | AD5: 2028 | AE5: 2029 | AF5: 2030 | AG5: 2022 | AH5: =AG5+1 -> 2023 | AI5: =AH5+1 -> 2024 | AJ5: =AI5+1 -> 2025 | AK5: =AJ5+1 -> 2026 | AL5: 2027 | AM5: 2028 | AN5: 2029 | AO5: 2030 | AP5: 2022 | AQ5: =AP5+1 -> 2023 | AR5: =AQ5+1 -> 2024 | AS5: =AR5+1 -> 2025 | AT5: =AS5+1 -> 2026 | AU5: 2027 | AV5: 2028 | AW5: 2029 | AX5: 2030 | AY5: 2022 | AZ5: =AY5+1 -> 2023 | BA5: =AZ5+1 -> 2024 | BB5: =BA5+1 -> 2025 | BC5: =BB5+1 -> 2026 | BD5: 2027 | BE5: 2028 | BF5: 2029 | BG5: 2030 | BH5: 2024 | BI5: 2025 | BJ5: 2026 | BK5: 2027 | BL5: 2028 | BM5: =BL5+1 -> 2029 | BN5: =BM5+1 -> 2030 | BO5: 2026 | BP5: 2027 | BQ5: 2028 | BR5: 2029 | BS5: 2030 | BT5: 2026 | BU5: 2027 | BV5: 2028 | BW5: 2029 | BX5: 2030 | BY5: 2026 | BZ5: 2027 | CA5: 2028 | CB5: 2029 | CC5: 2030 | CD5: 2026 | CE5: 2027 | CF5: 2028 | CG5: 2029 | CH5: 2030 | CI5: 2026 | CJ5: 2027 | CK5: 2028 | CL5: 2029 | CM5: 2030 | CN5: 2026 | CO5: 2027 | CP5: 2028 | CQ5: 2029 | CR5: 2030 | CS5: 2026 | CT5: 2027 | CU5: 2028 | CV5: 2029 | CW5: 2030 | CX5: 2026 | CY5: 2027 | CZ5: 2028 | DA5: 2029 | DB5: 2030 | DC5: 2026 | DD5: 2027 | DE5: 2028 | DF5: 2029 | DG5: 2030 | DH5: 2026 | DI5: 2027 | DJ5: 2028 | DK5: 2029 | DL5: 2030 | DO5: 2026 | DP5: 2027 | DQ5: 2028 | DR5: 2029 | DS5: 2030 | DT5: 2026 | DU5: 2027 | DV5: 2028 | DW5: 2029 | DX5: 2026 | DY5: 2027 | DZ5: 2028 | EA5: 2029 | EB5: 1M | EC5: 3M | ED5: 6M | EE5: Revs | EF5: Margin | EG5: Mendo NI | EH5: Yield | EI5: EPS + Divs | EJ5: Multiple | EK5: Return | EL5: GP | EM5: mEPS | EN5: 3Mo ADV ($m) | EQ5: Div yield | ER5: Mendo EPS CAGR | ES5: Total Yield | EU5: Multiple CAGR | EX5: 2026 | EY5: =EX5+1 -> 2027 | EZ5: =EY5+1 -> 2028 | FA5: =EZ5+1 -> 2029 | FB5: 2026 | FC5: =FB5+1 -> 2027 | FD5: =FC5+1 -> 2028 | FE5: =FD5+1 -> 2029 | FF5: Convex | FG5: Risk | FH5: Range | FI5: Convex | FJ5: Risk | FK5: Range | FL5: Earnings | FM5: Val | FN5: Up | FO5: Down | FP5: Net | FQ5: Base | FR5: Skew | FS5: Range | FT5: up | FU5: down | FV5: Notes
D6: Big Tech
B7: WDAY US EQUITY | D7: WDAY | E7: 1 | F7: 45991 | H7: {=_xll.BQL($B7, "px_last", "dates=" & _xll.BQL.DATE($D$2))} -> #N/A Connection | I7: {=_xll.BQL(""&B7&"", "CB_IS_ADJ_DILUTED_AVG_SHS/1M", "FPT=Q", "FPO=0Q", "ACT_EST_MAPPING=PRECISE", "FS=MRC", "CURRENCY=USD", "XLFILL=b")} -> 254.313 | J7: -8017 | K7: 2984 | M7: =K7+J7 -> -5033 | N7: =I7*H7+M7+L7 -> #VALUE! | O7: 6215.818 | P7: 7258.753 | Q7: 8446 | R7: 9552 | S7: 10723.337 | T7: 11959.266 | U7: 13226.36 | V7: 14542.97 | W7: 15876.671 | X7: =AG7/O7 -> 0.76955632 | Y7: =AH7/P7 -> 0.79683535 | Z7: =AI7/Q7 -> 0.78886878 | AA7: =AJ7/R7 -> 0.79169571 | AB7: =AK7/S7 -> 0.80060817 | AC7: =AL7/T7 -> 0.80656338 | AD7: =AM7/U7 -> 0.81225976 | AE7: =AN7/V7 -> 0.81644821 | AF7: =AO7/W7 -> 0.82046166 | AG7: 4783.422 | AH7: 5784.031 | AI7: 6662.7857 | AJ7: 7562.2774 | AK7: 8585.1913 | AL7: 9645.9061 | AM7: 10743.24 | AN7: 11873.582 | AO7: 13026.2 | AQ7: 5.6577043 | AR7: 7.13432 | AS7: 9.0770109 | AT7: 10.410325 | AU7: 13.111934 | AV7: 15.687176 | AW7: 18.590369 | AX7: 21.987373 | AZ7: 1.3596545 | BA7: 2.6061784 | BB7: 4.2675468 | BC7: 5.5610566 | BD7: 7.7961783 | BE7: 9.9297272 | BF7: 12.341413 | BG7: 15.25191 | BH7: =$N7/Q7 -> #VALUE! | BI7: =$N7/R7 -> #VALUE! | BJ7: =$N7/S7 -> #VALUE! | BK7: =$N7/T7 -> #VALUE! | BL7: =$N7/U7 -> #VALUE! | BM7: =$N7/V7 -> #VALUE! | BN7: =$N7/W7 -> #VALUE! | BO7: =$N7/AK7 -> #VALUE! | BP7: =$N7/AL7 -> #VALUE! | BQ7: =$N7/AM7 -> #VALUE! | BR7: =$N7/AN7 -> #VALUE! | BS7: =$N7/AO7 -> #VALUE! | BT7: =$H7/AT7 -> #VALUE! | BU7: =$H7/AU7 -> #VALUE! | BV7: =$H7/AV7 -> #VALUE! | BW7: =$H7/AW7 -> #VALUE! | BX7: =$H7/AX7 -> #VALUE! | BY7: =$H7/BC7 -> #VALUE! | BZ7: =$H7/BD7 -> #VALUE! | CA7: =$H7/BE7 -> #VALUE! | CB7: =$H7/BF7 -> #VALUE! | CC7: =$H7/BG7 -> #VALUE! | CD7: 22 | CE7: 22 | CF7: 22 | CG7: 22 | CH7: 20 | CN7: =CD7*BD7+CS7 -> 180.93166 | CO7: =CE7*BE7+CT7 -> 228.34968 | CP7: =CF7*BF7+CU7 -> 281.87397 | CQ7: =CG7*BG7+CV7 -> 346.43357 | CS7: 9.4157415 | CT7: 9.8956805 | CU7: 10.362889 | CV7: 10.891539 | CW7: 11.486062 | CX7: =CN7*DC7+DH7 -> 46054.855 | CY7: =CO7*DD7+DI7 -> 57106.681 | CZ7: =CP7*DE7+DJ7 -> 67502.046 | DA7: =CQ7*DF7+DK7 -> 79648.601 | DC7: 268.117 | DD7: 260.83979 | DE7: 248.1891 | DF7: 236.99955 | DG7: 225.49614 | DH7: -2456 | DI7: -2456 | DJ7: -2456 | DK7: -2456 | DL7: -2456 | DT7: =_xlfn.RRI(DT$2,$H7,CN7+$DO7*$DT$2) -> #VALUE! | DU7: =_xlfn.RRI(DU$2,$H7,CO7+$DO7*$DT$2+SUM($DP7:DP7)) -> #VALUE! | DV7: =_xlfn.RRI(DV$2,$H7,CP7+$DO7*$DT$2+SUM($DP7:DQ7)) -> #VALUE! | DW7: =_xlfn.RRI(DW$2,$H7,CQ7+$DO7*$DT$2+SUM($DP7:DR7)) -> #VALUE! | DX7: =SUM(CN7,$DO7:DO7)/$H7 -> #VALUE! | DY7: =SUM(CO7,$DO7:DP7)/$H7 -> #VALUE! | DZ7: =SUM(CP7,$DO7:DQ7)/$H7 -> #VALUE! | EA7: =SUM(CQ7,$DO7:DR7)/$H7 -> #VALUE! | EB7: {=_xll.BDP(""&$B7&"","CHG_PCT_1M")/100} -> 0.1284518 | EC7: {=_xll.BDP(""&$B7&"","CHG_PCT_3M")/100} -> -0.04495494 | ED7: {=_xll.BDP(""&$B7&"","CHG_PCT_6M")/100} -> -0.3472851 | EE7: =_xlfn.RRI(2+$DT$2,$DT$2*S7+(1-$DT$2)*T7,V7) -> 0.10482808 | EF7: =EG7-EE7 -> 0.12287853 | EG7: =_xlfn.RRI(2+$DT$2,$DT$2*(BC7*DC7)+(1-$DT$2)*(BD7*DD7),(BF7*DF7)) -> 0.2277066 | EH7: =EI7-EG7 -> #VALUE! | EI7: =ER7+EQ7 -> #VALUE! | EJ7: =EK7-EI7 -> #VALUE! | EK7: =DV7 -> #VALUE! | EL7: =_xlfn.RRI(3,AK7,AN7) -> 0.11415067 | EM7: =_xlfn.RRI(3,BC7,BF7) -> 0.30437516 | EN7: {=_xll.BDP(B7,"AVG_DAILY_VALUE_TRADED_3M")/10^6} -> 667.04992 | EQ7: =CU7/H7/$DV$2 -> #VALUE! | ER7: =_xlfn.RRI(2+$DT$2,$DT$2*(BC7)+(1-$DT$2)*(BD7),(BF7)) -> 0.28113523 | ES7: =ER7-EG7+EQ7 -> #VALUE! | EU7: =_xlfn.RRI(2+$DT$2,($DT$2*BY7+(1-$DT$2)*BZ7),CF7) -> #VALUE! | EV7: =EJ7-EU7 -> #VALUE! | FF7: 0.2 | FG7: -0.2 | FH7: =FF7-FG7 -> 0.4 | FI7: =FT7/CF7-1 -> 0.090909091 | FJ7: =FU7/CF7-1 -> -0.36363636 | FK7: =FI7-FJ7 -> 0.45454545 | FL7: =FF7+FG7 -> 0 | FM7: =FJ7+FI7 -> -0.27272727 | FN7: =EK7+FF7/3+FI7/3 -> #VALUE! | FO7: =EK7+FG7/3+FJ7/3 -> #VALUE! | FP7: =EK7+FL7/3+FM7/3 -> #VALUE! | FQ7: =EK7 -> #VALUE! | FR7: =FP7-FQ7 -> #VALUE! | FS7: =FN7-FO7 -> #VALUE! | FT7: 24 | FU7: 14
B8: MSFT US EQUITY | D8: MSFT | E8: 1 | F8: 46119 | H8: {=_xll.BQL($B8, "px_last", "dates=" & _xll.BQL.DATE($D$2))} -> #N/A Connection | I8: 7460 | J8: -89462 | K8: =40262+22865 -> 63127 | M8: =K8+J8 -> -26335 | N8: =I8*H8+M8+L8 -> #VALUE! | O8: 204094 | P8: 227582 | Q8: 261803 | R8: 305440 | S8: 356800.78 | T8: 418430.46 | U8: 491728.15 | V8: 575920.69 | W8: 670017.49 | X8: 0.6815977 | Y8: 0.69748486 | Z8: 0.69409059 | AA8: 0.68589248 | AB8: =AA8-0.25% -> 0.68339248 | AC8: =AB8-0.25% -> 0.68089248 | AD8: =AC8-0.25% -> 0.67839248 | AE8: =AD8-0.25% -> 0.67589248 | AF8: =AE8-0.25% -> 0.67339248 | AG8: =X8*O8 -> 139110 | AH8: =Y8*P8 -> 158735 | AI8: =Z8*Q8 -> 181715 | AJ8: =AA8*R8 -> 209499 | AK8: =AB8*S8 -> 243834.97 | AL8: =AC8*T8 -> 284906.16 | AM8: =AD8*U8 -> 333584.68 | AN8: =AE8*V8 -> 389260.47 | AO8: =AF8*W8 -> 451184.74 | AP8: 9.1199413 | AQ8: 11.056696 | AR8: 12.415501 | AS8: 15.949195 | AT8: 18.277836 | AU8: 21.13818 | AV8: 24.860954 | AW8: 30.196774 | AX8: 36.555023 | AY8: =AP8 -> 9.1199413 | AZ8: =AQ8 -> 11.056696 | BA8: =AR8 -> 12.415501 | BB8: =AS8 -> 15.949195 | BC8: =AT8 -> 18.277836 | BD8: =AU8 -> 21.13818 | BE8: =AV8 -> 24.860954 | BF8: =AW8 -> 30.196774 | BG8: =AX8 -> 36.555023 | BH8: =$N8/Q8 -> #VALUE! | BI8: =$N8/R8 -> #VALUE! | BJ8: =$N8/S8 -> #VALUE! | BK8: =$N8/T8 -> #VALUE! | BL8: =$N8/U8 -> #VALUE! | BM8: =$N8/V8 -> #VALUE! | BN8: =$N8/W8 -> #VALUE! | BO8: =$N8/AK8 -> #VALUE! | BP8: =$N8/AL8 -> #VALUE! | BQ8: =$N8/AM8 -> #VALUE! | BR8: =$N8/AN8 -> #VALUE! | BS8: =$N8/AO8 -> #VALUE! | BT8: =$H8/AT8 -> #VALUE! | BU8: =$H8/AU8 -> #VALUE! | BV8: =$H8/AV8 -> #VALUE! | BW8: =$H8/AW8 -> #VALUE! | BX8: =$H8/AX8 -> #VALUE! | BY8: =$H8/BC8 -> #VALUE! | BZ8: =$H8/BD8 -> #VALUE! | CA8: =$H8/BE8 -> #VALUE! | CB8: =$H8/BF8 -> #VALUE! | CC8: =$H8/BG8 -> #VALUE! | CD8: 24 | CE8: =CD8 -> 24 | CF8: =CE8 -> 24 | CG8: =CF8 -> 24 | CH8: =CG8 -> 24 | CN8: =CD8*BD8+CS8 -> 543.48941 | CO8: =CE8*BE8+CT8 -> 632.905 | CP8: =CF8*BF8+CU8 -> 761.24215 | CQ8: =CG8*BG8+CV8 -> 914.51529 | CS8: 36.173085 | CT8: 36.24212 | CU8: 36.51958 | CV8: 37.194743 | CW8: 38.054831 | DC8: 7464.1132 | DD8: 7449.8954 | DE8: 7393.2942 | DF8: 7259.0903 | DG8: 7095.0257 | DH8: -26335 | DI8: -26335 | DJ8: -26335 | DK8: -26335 | DL8: -26335 | DO8: 3.828 | DP8: 4.2108 | DQ8: 4.63188 | DR8: 5.095068 | DS8: 5.6045748 | DT8: =_xlfn.RRI(DT$2,$H8,CN8+$DO8*$DT$2) -> #VALUE! | DU8: =_xlfn.RRI(DU$2,$H8,CO8+$DO8*$DT$2+SUM($DP8:DP8)) -> #VALUE! | DV8: =_xlfn.RRI(DV$2,$H8,CP8+$DO8*$DT$2+SUM($DP8:DQ8)) -> #VALUE! | DW8: =_xlfn.RRI(DW$2,$H8,CQ8+$DO8*$DT$2+SUM($DP8:DR8)) -> #VALUE! | DX8: =SUM(CN8,$DO8:DO8)/$H8 -> #VALUE! | DY8: =SUM(CO8,$DO8:DP8)/$H8 -> #VALUE! | DZ8: =SUM(CP8,$DO8:DQ8)/$H8 -> #VALUE! | EA8: =SUM(CQ8,$DO8:DR8)/$H8 -> #VALUE! | EB8: {=_xll.BDP(""&$B8&"","CHG_PCT_1M")/100} -> -0.004974454 | EC8: {=_xll.BDP(""&$B8&"","CHG_PCT_3M")/100} -> 0.01001323 | ED8: {=_xll.BDP(""&$B8&"","CHG_PCT_6M")/100} -> -0.1587817 | EE8: =_xlfn.RRI(2+$DT$2,$DT$2*S8+(1-$DT$2)*T8,V8) -> 0.17165081 | EF8: =EG8-EE8 -> 0.0013687749 | EG8: =_xlfn.RRI(2+$DT$2,$DT$2*(BC8*DC8)+(1-$DT$2)*(BD8*DD8),(BF8*DF8)) -> 0.17301959 | EH8: =EI8-EG8 -> #VALUE! | EI8: =EK8-EJ8 -> #VALUE! | EJ8: =EU8 -> #VALUE! | EK8: =DV8 -> #VALUE! | EL8: =_xlfn.RRI(3,AK8,AN8) -> 0.16873155 | EM8: =_xlfn.RRI(3,BC8,BF8) -> 0.18216635 | EN8: {=_xll.BDP(B8,"AVG_DAILY_VALUE_TRADED_3M")/10^6} -> 14042.203 | EQ8: =IFERROR(AVERAGE(DP8:DQ8)/H8,0) -> 0 | ER8: =_xlfn.RRI(2+$DT$2,$DT$2*(BC8)+(1-$DT$2)*(BD8),(BF8)) -> 0.18543558 | ES8: =ER8-EG8+EQ8 -> 0.012415992 | EU8: =_xlfn.RRI(2+$DT$2,($DT$2*BY8+(1-$DT$2)*BZ8),CF8) -> #VALUE! | EV8: =EJ8-EU8 -> #VALUE! | FF8: 0.3 | FG8: -0.2 | FH8: =FF8-FG8 -> 0.5 | FI8: =FT8/CF8-1 -> 0.25 | FJ8: =FU8/CF8-1 -> -0.25 | FK8: =FI8-FJ8 -> 0.5 | FL8: =FF8+FG8 -> 0.1 | FM8: =FJ8+FI8 -> 0 | FN8: =EK8+FF8/3+FI8/3 -> #VALUE! | FO8: =EK8+FG8/3+FJ8/3 -> #VALUE! | FP8: =EK8+FL8/3+FM8/3 -> #VALUE! | FQ8: =EK8 -> #VALUE! | FR8: =FP8-FQ8 -> #VALUE! | FS8: =FN8-FO8 -> #VALUE! | FT8: 30 | FU8: 18
B9: SAP GY EQUITY | D9: SAP | E9: 1 | F9: 45688 | H9: {=_xll.BQL($B9, "px_last", "dates=" & _xll.BQL.DATE($D$2))} -> #N/A Connection | I9: 1169 | J9: -9609 | K9: =7169+4277 -> 11446 | M9: =K9+J9 -> 1837 | N9: =I9*H9+M9+L9 -> #VALUE! | O9: 29520 | P9: 31207 | Q9: 34176 | R9: 36800 | S9: 40273.14 | T9: 45307.135 | U9: 50851.13 | V9: 56381.116 | W9: 62355.58 | X9: =AG9/O9 -> 0.74261518 | Y9: =AH9/P9 -> 0.72429263 | Z9: =AI9/Q9 -> 0.73182935 | AA9: =AJ9/R9 -> 0.73764946 | AB9: =AK9/S9 -> 0.7380271 | AC9: =AL9/T9 -> 0.73982573 | AD9: =AM9/U9 -> 0.74211568 | AE9: =AN9/V9 -> 0.74533219 | AF9: =AO9/W9 -> 0.74935858 | AG9: 21922 | AH9: 22603 | AI9: 25011 | AJ9: 27145.5 | AK9: 29722.669 | AL9: 33519.384 | AM9: 37737.421 | AN9: 42022.661 | AO9: 46726.689 | AP9: 4.0161702 | AQ9: 3.6754237 | AR9: 4.479661 | AS9: 6.0991489 | AT9: 7.1545717 | AU9: 8.5750357 | AV9: 10.465866 | AW9: 12.432473 | AX9: 14.872587 | AY9: =AP9 -> 4.0161702 | AZ9: =AQ9 -> 3.6754237 | BA9: =AR9 -> 4.479661 | BB9: =AS9 -> 6.0991489 | BC9: =AT9 -> 7.1545717 | BD9: =AU9 -> 8.5750357 | BE9: =AV9 -> 10.465866 | BF9: =AW9 -> 12.432473 | BG9: =AX9 -> 14.872587 | BH9: =$N9/Q9 -> #VALUE! | BI9: =$N9/R9 -> #VALUE! | BJ9: =$N9/S9 -> #VALUE! | BK9: =$N9/T9 -> #VALUE! | BL9: =$N9/U9 -> #VALUE! | BM9: =$N9/V9 -> #VALUE! | BN9: =$N9/W9 -> #VALUE! | BO9: =$N9/AK9 -> #VALUE! | BP9: =$N9/AL9 -> #VALUE! | BQ9: =$N9/AM9 -> #VALUE! | BR9: =$N9/AN9 -> #VALUE! | BS9: =$N9/AO9 -> #VALUE! | BT9: =$H9/AT9 -> #VALUE! | BU9: =$H9/AU9 -> #VALUE! | BV9: =$H9/AV9 -> #VALUE! | BW9: =$H9/AW9 -> #VALUE! | BX9: =$H9/AX9 -> #VALUE! | BY9: =$H9/BC9 -> #VALUE! | BZ9: =$H9/BD9 -> #VALUE! | CA9: =$H9/BE9 -> #VALUE! | CB9: =$H9/BF9 -> #VALUE! | CC9: =$H9/BG9 -> #VALUE! | CD9: 22 | CE9: 22 | CF9: 22 | CG9: 22 | CH9: 24 | CN9: =CD9*BD9 -> 188.65079 | CO9: =CE9*BE9 -> 230.24906 | CP9: =CF9*BF9 -> 273.5144 | CQ9: =CG9*BG9 -> 327.19691 | CX9: =CN9*DC9+DH9 -> 220789.28 | CY9: =CO9*DD9+DI9 -> 263601.12 | CZ9: =CP9*DE9+DJ9 -> 305681.97 | DA9: =CQ9*DF9+DK9 -> 356154.29 | DC9: 1160.6221 | DD9: 1136.8738 | DE9: 1110.892 | DF9: 1082.887 | DG9: 1053.2432 | DH9: =$M$9 -> 1837 | DI9: =$M$9 -> 1837 | DJ9: =$M$9 -> 1837 | DK9: =$M$9 -> 1837 | DL9: =$M$9 -> 1837 | DO9: 2.8618287 | DP9: 3.4300143 | DQ9: 4.1863466 | DR9: 4.9729891 | DS9: 5.9490347 | DT9: =_xlfn.RRI(DT$2,$H9,CN9+$DO9*$DT$2) -> #VALUE! | DU9: =_xlfn.RRI(DU$2,$H9,CO9+$DO9*$DT$2+SUM($DP9:DP9)) -> #VALUE! | DV9: =_xlfn.RRI(DV$2,$H9,CP9+$DO9*$DT$2+SUM($DP9:DQ9)) -> #VALUE! | DW9: =_xlfn.RRI(DW$2,$H9,CQ9+$DO9*$DT$2+SUM($DP9:DR9)) -> #VALUE! | DX9: =SUM(CN9,$DO9:DO9)/$H9 -> #VALUE! | DY9: =SUM(CO9,$DO9:DP9)/$H9 -> #VALUE! | DZ9: =SUM(CP9,$DO9:DQ9)/$H9 -> #VALUE! | EA9: =SUM(CQ9,$DO9:DR9)/$H9 -> #VALUE! | EB9: {=_xll.BDP(""&$B9&"","CHG_PCT_1M")/100} -> 0.08454175 | EC9: {=_xll.BDP(""&$B9&"","CHG_PCT_3M")/100} -> -0.08208872 | ED9: {=_xll.BDP(""&$B9&"","CHG_PCT_6M")/100} -> -0.2453118 | EE9: =_xlfn.RRI(2+$DT$2,$DT$2*S9+(1-$DT$2)*T9,V9) -> 0.11684576 | EF9: =EG9-EE9 -> 0.056599069 | EG9: =_xlfn.RRI(2+$DT$2,$DT$2*(BC9*DC9)+(1-$DT$2)*(BD9*DD9),(BF9*DF9)) -> 0.17344483 | EH9: =EI9-EG9 -> 0.027524659 | EI9: =ER9+EQ9 -> 0.20096949 | EJ9: =EK9-EI9 -> #VALUE! | EK9: =DV9 -> #VALUE! | EL9: =_xlfn.RRI(3,AK9,AN9) -> 0.12235932 | EM9: =_xlfn.RRI(3,BC9,BF9) -> 0.20224032 | EN9: {=_xll.BDP(B9,"AVG_DAILY_VALUE_TRADED_3M")/10^6} -> 476.4628 | EQ9: =IFERROR(AVERAGE(DP9:DQ9)/H9,0) -> 0 | ER9: =_xlfn.RRI(2+$DT$2,$DT$2*(BC9)+(1-$DT$2)*(BD9),(BF9)) -> 0.20096949 | ES9: =ER9-EG9+EQ9 -> 0.027524659 | EU9: =_xlfn.RRI(2+$DT$2,($DT$2*BY9+(1-$DT$2)*BZ9),CF9) -> #VALUE! | EV9: =EJ9-EU9 -> #VALUE! | FF9: 0.1 | FG9: -0.1 | FH9: =FF9-FG9 -> 0.2 | FI9: =FT9/CF9-1 -> 0.27272727 | FJ9: =FU9/CF9-1 -> -0.27272727 | FK9: =FI9-FJ9 -> 0.54545455 | FL9: =FF9+FG9 -> 0 | FM9: =FJ9+FI9 -> 0 | FN9: =EK9+FF9/3+FI9/3 -> #VALUE! | FO9: =EK9+FG9/3+FJ9/3 -> #VALUE! | FP9: =EK9+FL9/3+FM9/3 -> #VALUE! | FQ9: =EK9 -> #VALUE! | FR9: =FP9-FQ9 -> #VALUE! | FS9: =FN9-FO9 -> #VALUE! | FT9: 28 | FU9: 16 | FV9: Set Mendo EPS = adj EPS (SBC ~5% revs)
B10: META US EQUITY | D10: META | E10: 1 | F10: 46163 | H10: {=_xll.BQL($B10, "px_last", "dates=" & _xll.BQL.DATE($D$2))} -> #N/A Connection | I10: 2573.7761 | J10: -84819 | K10: 85081 | M10: =K10+J10 -> 262 | N10: =I10*H10+M10+L10 -> #VALUE! | O10: 116608 | P10: 134902 | Q10: 164500 | R10: 200965 | S10: 245901.56 | T10: 290756.51 | U10: 334809.81 | V10: 378121.6 | W10: 419230.59 | AG10: =X10*O10 -> 0 | AH10: =Y10*P10 -> 0 | AI10: =Z10*Q10 -> 0 | AJ10: =AA10*R10 -> 0 | AK10: =AB10*S10 -> 0 | AL10: =AC10*T10 -> 0 | AM10: =AD10*U10 -> 0 | AN10: =AE10*V10 -> 0 | AO10: =AF10*W10 -> 0 | AP10: 10.440785 | AQ10: 16.379135 | AR10: 24.207034 | AS10: 29.015803 | AT10: 28.213866 | AU10: 33.053023 | AV10: 42.085773 | AW10: 52.931226 | AX10: 63.198373 | AY10: 10.440785 | AZ10: 16.379135 | BA10: 24.207034 | BB10: 29.015803 | BC10: 28.213866 | BD10: 33.053023 | BE10: 42.085773 | BF10: 52.931226 | BG10: 63.198373 | BH10: =$N10/Q10 -> #VALUE! | BI10: =$N10/R10 -> #VALUE! | BJ10: =$N10/S10 -> #VALUE! | BK10: =$N10/T10 -> #VALUE! | BL10: =$N10/U10 -> #VALUE! | BM10: =$N10/V10 -> #VALUE! | BN10: =$N10/W10 -> #VALUE! | BO10: =IFERROR($N10/AK10,"n/a") -> n/a | BP10: =IFERROR($N10/AL10,"n/a") -> n/a | BQ10: =IFERROR($N10/AM10,"n/a") -> n/a | BR10: =IFERROR($N10/AN10,"n/a") -> n/a | BS10: =IFERROR($N10/AO10,"n/a") -> n/a | BT10: =$H10/AT10 -> #VALUE! | BU10: =$H10/AU10 -> #VALUE! | BV10: =$H10/AV10 -> #VALUE! | BW10: =$H10/AW10 -> #VALUE! | BX10: =$H10/AX10 -> #VALUE! | BY10: =$H10/BC10 -> #VALUE! | BZ10: =$H10/BD10 -> #VALUE! | CA10: =$H10/BE10 -> #VALUE! | CB10: =$H10/BF10 -> #VALUE! | CC10: =$H10/BG10 -> #VALUE! | CD10: 19 | CE10: 19 | CF10: 19 | CG10: 19 | CH10: 20 | CN10: =CD10*BD10 -> 628.00744 | CO10: =CE10*BE10 -> 799.62969 | CP10: =CF10*BF10 -> 1005.6933 | CQ10: =CG10*BG10 -> 1200.7691 | DC10: 2573.7761 | DD10: 2573.7761 | DE10: 2508.1621 | DF10: 2422.9536 | DG10: 2332.756 | DO10: 2.205 | DP10: 2.31525 | DQ10: 2.4310125 | DR10: 2.5525631 | DS10: 2.6801913 | DT10: =_xlfn.RRI(DT$2,$H10,CN10+$DO10*$DT$2) -> #VALUE! | DU10: =_xlfn.RRI(DU$2,$H10,CO10+$DO10*$DT$2+SUM($DP10:DP10)) -> #VALUE! | DV10: =_xlfn.RRI(DV$2,$H10,CP10+$DO10*$DT$2+SUM($DP10:DQ10)) -> #VALUE! | DW10: =_xlfn.RRI(DW$2,$H10,CQ10+$DO10*$DT$2+SUM($DP10:DR10)) -> #VALUE! | DX10: =SUM(CN10,$DO10:DO10)/$H10 -> #VALUE! | DY10: =SUM(CO10,$DO10:DP10)/$H10 -> #VALUE! | DZ10: =SUM(CP10,$DO10:DQ10)/$H10 -> #VALUE! | EA10: =SUM(CQ10,$DO10:DR10)/$H10 -> #VALUE! | EB10: {=_xll.BDP(""&$B10&"","CHG_PCT_1M")/100} -> -0.03228188 | EC10: {=_xll.BDP(""&$B10&"","CHG_PCT_3M")/100} -> -0.08515024 | ED10: {=_xll.BDP(""&$B10&"","CHG_PCT_6M")/100} -> -0.1152519 | EE10: =_xlfn.RRI(2+$DT$2,$DT$2*S10+(1-$DT$2)*T10,V10) -> 0.14787172 | EF10: =EG10-EE10 -> 0.065956756 | EG10: =_xlfn.RRI(2+$DT$2,$DT$2*(BC10*DC10)+(1-$DT$2)*(BD10*DD10),(BF10*DF10)) -> 0.21382847 | EH10: =EI10-EG10 -> 0.028985448 | EI10: =ER10+EQ10 -> 0.24281392 | EJ10: =EK10-EI10 -> #VALUE! | EK10: =DV10 -> #VALUE! | EL10: =_xlfn.RRI(3,AK10,AN10) -> 0 | EM10: =_xlfn.RRI(3,BC10,BF10) -> 0.23334085 | EN10: {=_xll.BDP(B10,"AVG_DAILY_VALUE_TRADED_3M")/10^6} -> 10224.256 | EQ10: =IFERROR(AVERAGE(DP10:DQ10)/H10,0) -> 0 | ER10: =_xlfn.RRI(2+$DT$2,$DT$2*(BC10)+(1-$DT$2)*(BD10),(BF10)) -> 0.24281392 | ES10: =ER10-EG10+EQ10 -> 0.028985448 | EU10: =_xlfn.RRI(2+$DT$2,($DT$2*BY10+(1-$DT$2)*BZ10),CF10) -> #VALUE! | EV10: =EJ10-EU10 -> #VALUE! | FF10: 0.25 | FG10: -0.25 | FN10: x | FO10: x | FP10: x | FQ10: x | FR10: x | FS10: x | FV10: Core EPS Only
B11: AMZN US EQUITY | D11: AMZN | E11: 1 | F11: 46120 | H11: {=_xll.BQL($B11, "px_last", "dates=" & _xll.BQL.DATE($D$2))} -> #N/A Connection | I11: 10827 | J11: -123329 | K11: 178547 | M11: =K11+J11 -> 55218 | N11: =I11*H11+M11+L11 -> #VALUE! | O11: 513983 | P11: 574785 | Q11: 637959 | R11: 716924 | S11: 817469.18 | T11: 928320.74 | U11: 1044416 | V11: 1153879.7 | W11: 1265801 | X11: =AG11/O11 -> 0.4380534 | Y11: =AH11/P11 -> 0.46982089 | Z11: =AI11/Q11 -> 0.48854393 | AA11: =AJ11/R11 -> 0.50285665 | AB11: =AK11/S11 -> 0.52586233 | AC11: =AL11/T11 -> 0.54940611 | AD11: =AM11/U11 -> 0.56879977 | AE11: =AN11/V11 -> 0.58047854 | AF11: =AO11/W11 -> 0.58999333 | AG11: 225152 | AH11: 270046 | AI11: 311671 | AJ11: 360510 | AK11: 429876.24 | AL11: 510025.09 | AM11: 594063.59 | AN11: 669802.4 | AO11: 746814.14 | AP11: -0.26715085 | AQ11: 2.8998284 | AR11: 5.5263502 | AS11: 7.1737323 | AT11: 7.3680359 | AU11: 9.512152 | AV11: 12.252122 | AW11: 15.255782 | AX11: 19.175997 | AY11: 1.3825694 | AZ11: 2.8115707 | BA11: 5.7456394 | BB11: 5.8183246 | BC11: 7.3680359 | BD11: 9.512152 | BE11: 12.252122 | BF11: 15.255782 | BG11: 19.175997 | BH11: =$N11/Q11 -> #VALUE! | BI11: =$N11/R11 -> #VALUE! | BJ11: =$N11/S11 -> #VALUE! | BK11: =$N11/T11 -> #VALUE! | BL11: =$N11/U11 -> #VALUE! | BM11: =$N11/V11 -> #VALUE! | BN11: =$N11/W11 -> #VALUE! | BO11: =$N11/AK11 -> #VALUE! | BP11: =$N11/AL11 -> #VALUE! | BQ11: =$N11/AM11 -> #VALUE! | BR11: =$N11/AN11 -> #VALUE! | BS11: =$N11/AO11 -> #VALUE! | BT11: =$H11/AT11 -> #VALUE! | BU11: =$H11/AU11 -> #VALUE! | BV11: =$H11/AV11 -> #VALUE! | BW11: =$H11/AW11 -> #VALUE! | BX11: =$H11/AX11 -> #VALUE! | BY11: =$H11/BC11 -> #VALUE! | BZ11: =$H11/BD11 -> #VALUE! | CA11: =$H11/BE11 -> #VALUE! | CB11: =$H11/BF11 -> #VALUE! | CC11: =$H11/BG11 -> #VALUE! | CD11: 26 | CE11: 26 | CF11: 26 | CG11: 26 | CH11: 24 | CN11: =CD11*BD11 -> 247.31595 | CO11: =CE11*BE11 -> 318.55518 | CP11: =CF11*BF11 -> 396.65032 | CQ11: =CG11*BG11 -> 498.57591 | DC11: 10827 | DD11: 10788.313 | DE11: 10587.029 | DF11: 10192.759 | DG11: 9738.2353 | DT11: =_xlfn.RRI(DT$2,$H11,CN11+$DO11*$DT$2) -> #VALUE! | DU11: =_xlfn.RRI(DU$2,$H11,CO11+$DO11*$DT$2+SUM($DP11:DP11)) -> #VALUE! | DV11: =_xlfn.RRI(DV$2,$H11,CP11+$DO11*$DT$2+SUM($DP11:DQ11)) -> #VALUE! | DW11: =_xlfn.RRI(DW$2,$H11,CQ11+$DO11*$DT$2+SUM($DP11:DR11)) -> #VALUE! | DX11: =SUM(CN11,$DO11:DO11)/$H11 -> #VALUE! | DY11: =SUM(CO11,$DO11:DP11)/$H11 -> #VALUE! | DZ11: =SUM(CP11,$DO11:DQ11)/$H11 -> #VALUE! | EA11: =SUM(CQ11,$DO11:DR11)/$H11 -> #VALUE! | EB11: {=_xll.BDP(""&$B11&"","CHG_PCT_1M")/100} -> -0.0941763 | EC11: {=_xll.BDP(""&$B11&"","CHG_PCT_3M")/100} -> 0.1584822 | ED11: {=_xll.BDP(""&$B11&"","CHG_PCT_6M")/100} -> 0.08863326 | EE11: =_xlfn.RRI(2+$DT$2,$DT$2*S11+(1-$DT$2)*T11,V11) -> 0.11850465 | EF11: =EG11-EE11 -> 0.12054217 | EG11: =_xlfn.RRI(2+$DT$2,$DT$2*(BC11*DC11)+(1-$DT$2)*(BD11*DD11),(BF11*DF11)) -> 0.23904682 | EH11: =EI11-EG11 -> 0.028682545 | EI11: =ER11+EQ11 -> 0.26772937 | EJ11: =EK11-EI11 -> #VALUE! | EK11: =DV11 -> #VALUE! | EL11: =_xlfn.RRI(3,AK11,AN11) -> 0.15931401 | EM11: =_xlfn.RRI(3,BC11,BF11) -> 0.27456184 | EN11: {=_xll.BDP(B11,"AVG_DAILY_VALUE_TRADED_3M")/10^6} -> 10871.718 | EQ11: =IFERROR(AVERAGE(DP11:DQ11)/H11,0) -> 0 | ER11: =_xlfn.RRI(2+$DT$2,$DT$2*(BC11)+(1-$DT$2)*(BD11),(BF11)) -> 0.26772937 | ES11: =ER11-EG11+EQ11 -> 0.028682545 | EU11: =_xlfn.RRI(2+$DT$2,($DT$2*BY11+(1-$DT$2)*BZ11),CF11) -> #VALUE! | EV11: =EJ11-EU11 -> #VALUE! | EX11: 7.3668545 | EY11: 9.541088 | EZ11: 11.93265 | FA11: 14.251233 | FB11: =BC11/EX11-1 -> 0.00016036555 | FC11: =BD11/EY11-1 -> -0.0030327757 | FD11: =BE11/EZ11-1 -> 0.026772975 | FE11: =BF11/FA11-1 -> 0.070488537 | FF11: 0.2 | FG11: -0.1 | FH11: =FF11-FG11 -> 0.3 | FI11: =FT11/CF11-1 -> 0.26923077 | FJ11: =FU11/CF11-1 -> -0.23076923 | FK11: =FI11-FJ11 -> 0.5 | FL11: =FF11+FG11 -> 0.1 | FM11: =FJ11+FI11 -> 0.038461538 | FN11: =EK11+FF11/3+FI11/3 -> #VALUE! | FO11: =EK11+FG11/3+FJ11/3 -> #VALUE! | FP11: =EK11+FL11/3+FM11/3 -> #VALUE! | FQ11: =EK11 -> #VALUE! | FR11: =FP11-FQ11 -> #VALUE! | FS11: =FN11-FO11 -> #VALUE! | FT11: 33 | FU11: 20
B12: 2330 TT EQUITY | D12: TSMC | F12: 46140 | H12: {=_xll.BQL($B12, "px_last", "dates=" & _xll.BQL.DATE($D$2))} -> #N/A Connection | I12: 25930 | J12: -3192142.3 | K12: 1036072.4 | M12: =K12+J12 -> -2156069.9 | N12: =I12*H12+M12+L12 -> #VALUE! | O12: 2263891.3 | P12: 2161735.8 | Q12: 2894307.7 | R12: 3809054.3 | S12: 5039894.5 | T12: 6594728.5 | U12: 8633128.7 | V12: 10355421 | W12: 12283063 | X12: =AG12/O12 -> 0.59559167 | Y12: =AH12/P12 -> 0.54359585 | Z12: =AI12/Q12 -> 0.56122352 | AA12: =AJ12/R12 -> 0.59891349 | AB12: =AK12/S12 -> 0.66920044 | AC12: =AL12/T12 -> 0.66322768 | AD12: =AM12/U12 -> 0.65343679 | AE12: =AN12/V12 -> 0.62939631 | AF12: =AO12/W12 -> 0.61454739 | AG12: 1348354.8 | AH12: 1175110.6 | AI12: 1624353.6 | AJ12: 2281294 | AK12: 3372699.6 | AL12: 4373806.4 | AM12: 5641203.9 | AN12: 6517663.5 | AO12: 7548524.5 | AP12: 39.204375 | AQ12: 32.338218 | AR12: 45.247501 | AS12: 66.248221 | AT12: 94.04858 | AU12: 122.02141 | AV12: 157.5557 | AW12: 182.32036 | AX12: 211.90932 | AY12: =AP12 -> 39.204375 | AZ12: =AQ12 -> 32.338218 | BA12: =AR12 -> 45.247501 | BB12: =AS12 -> 66.248221 | BC12: =AT12 -> 94.04858 | BD12: =AU12 -> 122.02141 | BE12: =AV12 -> 157.5557 | BF12: =AW12 -> 182.32036 | BG12: =AX12 -> 211.90932 | BH12: =$N12/Q12 -> #VALUE! | BI12: =$N12/R12 -> #VALUE! | BJ12: =$N12/S12 -> #VALUE! | BK12: =$N12/T12 -> #VALUE! | BL12: =$N12/U12 -> #VALUE! | BM12: =$N12/V12 -> #VALUE! | BN12: =$N12/W12 -> #VALUE! | BO12: =$N12/AK12 -> #VALUE! | BP12: =$N12/AL12 -> #VALUE! | BQ12: =$N12/AM12 -> #VALUE! | BR12: =$N12/AN12 -> #VALUE! | BS12: =$N12/AO12 -> #VALUE! | BT12: =$H12/AT12 -> #VALUE! | BU12: =$H12/AU12 -> #VALUE! | BV12: =$H12/AV12 -> #VALUE! | BW12: =$H12/AW12 -> #VALUE! | BX12: =$H12/AX12 -> #VALUE! | BY12: =$H12/BC12 -> #VALUE! | BZ12: =$H12/BD12 -> #VALUE! | CA12: =$H12/BE12 -> #VALUE! | CB12: =$H12/BF12 -> #VALUE! | CC12: =$H12/BG12 -> #VALUE! | CD12: 20 | CE12: 20 | CF12: 20 | CG12: 20 | CH12: 18 | CN12: =CD12*BD12+CS12 -> 2558.166 | CO12: =CE12*BE12+CT12 -> 3322.4769 | CP12: =CF12*BF12+CU12 -> 3888.5981 | CQ12: =CG12*BG12+CV12 -> 4566.6877 | CS12: 117.73782 | CT12: 171.36295 | CU12: 242.19095 | CV12: 328.50126 | CW12: 431.59469 | DC12: 25931 | DD12: 25931 | DE12: 25931 | DF12: 25931 | DG12: 25931 | DO12: 22.501022 | DP12: 28.126277 | DQ12: 35.157847 | DR12: 43.947308 | DS12: 54.934135 | DT12: =_xlfn.RRI(DT$2,$H12,CN12+$DO12*$DT$2) -> #VALUE! | DU12: =_xlfn.RRI(DU$2,$H12,CO12+$DO12*$DT$2+SUM($DP12:DP12)) -> #VALUE! | DV12: =_xlfn.RRI(DV$2,$H12,CP12+$DO12*$DT$2+SUM($DP12:DQ12)) -> #VALUE! | DW12: =_xlfn.RRI(DW$2,$H12,CQ12+$DO12*$DT$2+SUM($DP12:DR12)) -> #VALUE! | DX12: =SUM(CN12,$DO12:DO12)/$H12 -> #VALUE! | DY12: =SUM(CO12,$DO12:DP12)/$H12 -> #VALUE! | DZ12: =SUM(CP12,$DO12:DQ12)/$H12 -> #VALUE! | EA12: =SUM(CQ12,$DO12:DR12)/$H12 -> #VALUE! | EB12: {=_xll.BDP(""&$B12&"","CHG_PCT_1M")/100} -> 0.002183406 | EC12: {=_xll.BDP(""&$B12&"","CHG_PCT_3M")/100} -> 0.2142857 | ED12: {=_xll.BDP(""&$B12&"","CHG_PCT_6M")/100} -> 0.5351171 | EE12: =_xlfn.RRI(2+$DT$2,$DT$2*S12+(1-$DT$2)*T12,V12) -> 0.26056547 | EF12: =EG12-EE12 -> -0.02625594 | EG12: =_xlfn.RRI(2+$DT$2,$DT$2*(BC12*DC12)+(1-$DT$2)*(BD12*DD12),(BF12*DF12)) -> 0.23430953 | EH12: =EI12-EG12 -> #VALUE! | EI12: =ER12+EQ12 -> #VALUE! | EJ12: =EK12-EI12 -> #VALUE! | EK12: =DV12 -> #VALUE! | EL12: =_xlfn.RRI(3,AK12,AN12) -> 0.24557942 | EM12: =_xlfn.RRI(3,BC12,BF12) -> 0.24688856 | EN12: {=_xll.BDP(B12,"AVG_DAILY_VALUE_TRADED_3M")/10^6} -> 88790.61 | EQ12: =CU12/H12/$DV$2 -> #VALUE! | ER12: =_xlfn.RRI(2+$DT$2,$DT$2*(BC12)+(1-$DT$2)*(BD12),(BF12)) -> 0.23430953 | ES12: =ER12-EG12+EQ12 -> #VALUE! | EU12: =_xlfn.RRI(2+$DT$2,($DT$2*BY12+(1-$DT$2)*BZ12),CF12) -> #VALUE! | EV12: =EJ12-EU12 -> #VALUE! | FN12: x | FO12: x | FP12: x | FQ12: x | FR12: x | FS12: x
B13: GOOG US EQUITY | D13: GOOG | E13: 2 | F13: 46120 | H13: {=_xll.BQL($B13, "px_last", "dates=" & _xll.BQL.DATE($D$2))} -> #N/A Connection | I13: 12230 | J13: -126843 | K13: 66967 | M13: =K13+J13 -> -59876 | N13: =I13*H13+M13+L13 -> #VALUE! | O13: 282836 | P13: 307394 | Q13: 350018 | R13: 402836 | S13: 474201.19 | T13: 547000.07 | U13: 627861.63 | V13: 715818.21 | W13: 803490.68 | X13: =AG13/O13 -> 0.55379443 | Y13: =AH13/P13 -> 0.56625048 | Z13: =AI13/Q13 -> 0.58200435 | AA13: =AJ13/R13 -> 0.59652315 | AB13: =AK13/S13 -> 0.60130017 | AC13: =AL13/T13 -> 0.60309319 | AD13: =AM13/U13 -> 0.60681934 | AE13: =AN13/V13 -> 0.61614806 | AF13: =AO13/W13 -> 0.62285471 | AG13: 156633 | AH13: 174062 | AI13: 203712 | AJ13: 240301 | AK13: 285137.25 | AL13: 329892.01 | AM13: 380998.59 | AN13: 441050 | AO13: 500457.95 | AP13: 4.5574892 | AQ13: 5.8005817 | AR13: 8.0435446 | AS13: 10.807032 | AT13: 10.430843 | AU13: 12.047233 | AV13: 14.174341 | AW13: 17.360857 | AX13: 20.696308 | AY13: 4.9626111 | AZ13: 5.968244 | BA13: 7.7855708 | BB13: 8.6659035 | BC13: 10.430843 | BD13: 12.047233 | BE13: 14.174341 | BF13: 17.360857 | BG13: 20.696308 | BH13: =$N13/Q13 -> #VALUE! | BI13: =$N13/R13 -> #VALUE! | BJ13: =$N13/S13 -> #VALUE! | BK13: =$N13/T13 -> #VALUE! | BL13: =$N13/U13 -> #VALUE! | BM13: =$N13/V13 -> #VALUE! | BN13: =$N13/W13 -> #VALUE! | BO13: =$N13/AK13 -> #VALUE! | BP13: =$N13/AL13 -> #VALUE! | BQ13: =$N13/AM13 -> #VALUE! | BR13: =$N13/AN13 -> #VALUE! | BS13: =$N13/AO13 -> #VALUE! | BT13: =$H13/AT13 -> #VALUE! | BU13: =$H13/AU13 -> #VALUE! | BV13: =$H13/AV13 -> #VALUE! | BW13: =$H13/AW13 -> #VALUE! | BX13: =$H13/AX13 -> #VALUE! | BY13: =$H13/BC13 -> #VALUE! | BZ13: =$H13/BD13 -> #VALUE! | CA13: =$H13/BE13 -> #VALUE! | CB13: =$H13/BF13 -> #VALUE! | CC13: =$H13/BG13 -> #VALUE! | CD13: 24 | CE13: 24 | CF13: 24 | CG13: 24 | CH13: 24 | CN13: =CD13*BD13 -> 289.13359 | CO13: =CE13*BE13 -> 340.18418 | CP13: =CF13*BF13 -> 416.66057 | CQ13: =CG13*BG13 -> 496.71138 | DC13: 12230 | DD13: 12230 | DE13: 12155.112 | DF13: 11921.29 | DG13: 11635.202 | DO13: 0.83 | DP13: 0.83 | DQ13: 0.83 | DR13: 0.83 | DS13: 0.83 | DT13: =_xlfn.RRI(DT$2,$H13,CN13+$DO13*$DT$2) -> #VALUE! | DU13: =_xlfn.RRI(DU$2,$H13,CO13+$DO13*$DT$2+SUM($DP13:DP13)) -> #VALUE! | DV13: =_xlfn.RRI(DV$2,$H13,CP13+$DO13*$DT$2+SUM($DP13:DQ13)) -> #VALUE! | DW13: =_xlfn.RRI(DW$2,$H13,CQ13+$DO13*$DT$2+SUM($DP13:DR13)) -> #VALUE! | DX13: =SUM(CN13,$DO13:DO13)/$H13 -> #VALUE! | DY13: =SUM(CO13,$DO13:DP13)/$H13 -> #VALUE! | DZ13: =SUM(CP13,$DO13:DQ13)/$H13 -> #VALUE! | EA13: =SUM(CQ13,$DO13:DR13)/$H13 -> #VALUE! | EB13: {=_xll.BDP(""&$B13&"","CHG_PCT_1M")/100} -> -0.0941191 | EC13: {=_xll.BDP(""&$B13&"","CHG_PCT_3M")/100} -> 0.2057661 | ED13: {=_xll.BDP(""&$B13&"","CHG_PCT_6M")/100} -> 0.1438384 | EE13: =_xlfn.RRI(2+$DT$2,$DT$2*S13+(1-$DT$2)*T13,V13) -> 0.14490369 | EF13: =EG13-EE13 -> 0.032438938 | EG13: =_xlfn.RRI(2+$DT$2,$DT$2*(BC13*DC13)+(1-$DT$2)*(BD13*DD13),(BF13*DF13)) -> 0.17734262 | EH13: =EI13-EG13 -> 0.011821827 | EI13: =ER13+EQ13 -> 0.18916445 | EJ13: =EK13-EI13 -> #VALUE! | EK13: =DV13 -> #VALUE! | EL13: =_xlfn.RRI(3,AK13,AN13) -> 0.1564973 | EM13: =_xlfn.RRI(3,BC13,BF13) -> 0.18508797 | EN13: {=_xll.BDP(B13,"AVG_DAILY_VALUE_TRADED_3M")/10^6} -> 6855.36 | EQ13: =IFERROR(AVERAGE(DP13:DQ13)/H13,0) -> 0 | ER13: =_xlfn.RRI(2+$DT$2,$DT$2*(BC13)+(1-$DT$2)*(BD13),(BF13)) -> 0.18916445 | ES13: =ER13-EG13+EQ13 -> 0.011821827 | EU13: =_xlfn.RRI(2+$DT$2,($DT$2*BY13+(1-$DT$2)*BZ13),CF13) -> #VALUE! | EV13: =EJ13-EU13 -> #VALUE! | EX13: 11.031304 | EY13: 14.359029 | EZ13: 16.630616 | FA13: 18.821076 | FB13: =BC13/EX13-1 -> -0.054432497 | FC13: =BD13/EY13-1 -> -0.16099945 | FD13: =BE13/EZ13-1 -> -0.14769599 | FE13: =BF13/FA13-1 -> -0.077584258 | FF13: 0.2 | FG13: -0.25 | FH13: =FF13-FG13 -> 0.45 | FI13: =FT13/CF13-1 -> 0.25 | FJ13: =FU13/CF13-1 -> -0.25 | FK13: =FI13-FJ13 -> 0.5 | FL13: =FF13+FG13 -> -0.05 | FM13: =FJ13+FI13 -> 0 | FN13: =EK13+FF13/3+FI13/3 -> #VALUE! | FO13: =EK13+FG13/3+FJ13/3 -> #VALUE! | FP13: =EK13+FL13/3+FM13/3 -> #VALUE! | FQ13: =EK13 -> #VALUE! | FR13: =FP13-FQ13 -> #VALUE! | FS13: =FN13-FO13 -> #VALUE! | FT13: 30 | FU13: 18
B14: ORCL US EQUITY | D14: ORCL | E14: 2 | F14: 46176 | H14: {=_xll.BQL($B14, "px_last", "dates=" & _xll.BQL.DATE($D$2))} -> #N/A Connection | I14: 2922 | J14: -39132 | K14: 153117 | L14: 506 | M14: =K14+J14 -> 113985 | N14: =I14*H14+M14+L14 -> #VALUE! | O14: 45821.3 | P14: 51307.15 | Q14: 54958.1 | R14: 61719.45 | S14: 75204.625 | T14: 104489.41 | U14: 142360.79 | V14: 175595.92 | W14: 205597.03 | X14: =AG14/O14 -> 0 | Y14: =AH14/P14 -> 0 | Z14: =AI14/Q14 -> 0 | AA14: =AJ14/R14 -> 0 | AB14: =AK14/S14 -> 0 | AC14: =AL14/T14 -> 0 | AD14: =AM14/U14 -> 0 | AE14: =AN14/V14 -> 0 | AF14: =AO14/W14 -> 0 | AP14: 5.0031859 | AQ14: 5.3230505 | AR14: 5.7745681 | AS14: 6.454935 | AT14: 7.2746091 | AU14: 8.8268237 | AV14: 11.433058 | AW14: 14.568182 | AX14: 18.169251 | AY14: 4.0882316 | AZ14: 4.2208092 | BA14: 4.5594142 | BB14: 5.0951717 | BC14: 5.7413934 | BD14: 6.8261649 | BE14: 8.8185383 | BF14: 11.461698 | BG14: 14.573029 | BH14: =$N14/Q14 -> #VALUE! | BI14: =$N14/R14 -> #VALUE! | BJ14: =$N14/S14 -> #VALUE! | BK14: =$N14/T14 -> #VALUE! | BL14: =$N14/U14 -> #VALUE! | BM14: =$N14/V14 -> #VALUE! | BN14: =$N14/W14 -> #VALUE! | BO14: =IFERROR($N14/AK14,"n/a") -> n/a | BP14: =IFERROR($N14/AL14,"n/a") -> n/a | BQ14: =IFERROR($N14/AM14,"n/a") -> n/a | BR14: =IFERROR($N14/AN14,"n/a") -> n/a | BS14: =IFERROR($N14/AO14,"n/a") -> n/a | BT14: =$H14/AT14 -> #VALUE! | BU14: =$H14/AU14 -> #VALUE! | BV14: =$H14/AV14 -> #VALUE! | BW14: =$H14/AW14 -> #VALUE! | BX14: =$H14/AX14 -> #VALUE! | BY14: =$H14/BC14 -> #VALUE! | BZ14: =$H14/BD14 -> #VALUE! | CA14: =$H14/BE14 -> #VALUE! | CB14: =$H14/BF14 -> #VALUE! | CC14: =$H14/BG14 -> #VALUE! | CD14: 22 | CE14: 22 | CF14: 22 | CG14: 22 | CH14: 27 | CN14: =CD14*BD14 -> 150.17563 | CO14: =CE14*BE14 -> 194.00784 | CP14: =CF14*BF14 -> 252.15737 | CQ14: =CG14*BG14 -> 320.60664 | DC14: 2896.1304 | DD14: 2996.4985 | DE14: 3130.2032 | DF14: 3251.6731 | DG14: 3293.9439 | DO14: 2.1218486 | DP14: 2.2227497 | DQ14: 2.6178339 | DR14: 2.9650544 | DS14: 3.2721282 | DT14: =_xlfn.RRI(DT$2,$H14,CN14+$DO14*$DT$2) -> #VALUE! | DU14: =_xlfn.RRI(DU$2,$H14,CO14+$DO14*$DT$2+SUM($DP14:DP14)) -> #VALUE! | DV14: =_xlfn.RRI(DV$2,$H14,CP14+$DO14*$DT$2+SUM($DP14:DQ14)) -> #VALUE! | DW14: =_xlfn.RRI(DW$2,$H14,CQ14+$DO14*$DT$2+SUM($DP14:DR14)) -> #VALUE! | DX14: =SUM(CN14,$DO14:DO14)/$H14 -> #VALUE! | DY14: =SUM(CO14,$DO14:DP14)/$H14 -> #VALUE! | DZ14: =SUM(CP14,$DO14:DQ14)/$H14 -> #VALUE! | EA14: =SUM(CQ14,$DO14:DR14)/$H14 -> #VALUE! | EB14: {=_xll.BDP(""&$B14&"","CHG_PCT_1M")/100} -> 0.09282982 | EC14: {=_xll.BDP(""&$B14&"","CHG_PCT_3M")/100} -> 0.3999738 | ED14: {=_xll.BDP(""&$B14&"","CHG_PCT_6M")/100} -> -0.02901965 | EE14: =_xlfn.RRI(2+$DT$2,$DT$2*S14+(1-$DT$2)*T14,V14) -> 0.30922689 | EF14: =EG14-EE14 -> 0.010764702 | EG14: =_xlfn.RRI(2+$DT$2,$DT$2*(BC14*DC14)+(1-$DT$2)*(BD14*DD14),(BF14*DF14)) -> 0.3199916 | EH14: =EI14-EG14 -> -0.050170899 | EI14: =ER14+EQ14 -> 0.2698207 | EJ14: =EK14-EI14 -> #VALUE! | EK14: =DV14 -> #VALUE! | EL14: =_xlfn.RRI(3,AK14,AN14) -> 0 | EM14: =_xlfn.RRI(3,BC14,BF14) -> 0.25914929 | EN14: {=_xll.BDP(B14,"AVG_DAILY_VALUE_TRADED_3M")/10^6} -> 4774.8613 | EQ14: =IFERROR(AVERAGE(DP14:DQ14)/H14,0) -> 0 | ER14: =_xlfn.RRI(2+$DT$2,$DT$2*(BC14)+(1-$DT$2)*(BD14),(BF14)) -> 0.2698207 | ES14: =ER14-EG14+EQ14 -> -0.050170899 | EU14: =_xlfn.RRI(2+$DT$2,($DT$2*BY14+(1-$DT$2)*BZ14),CF14) -> #VALUE! | EV14: =EJ14-EU14 -> #VALUE! | FF14: 0.25 | FG14: -0.25 | FH14: =FF14-FG14 -> 0.5 | FI14: =FT14/CF14-1 -> 0.36363636 | FJ14: =FU14/CF14-1 -> -0.18181818 | FK14: =FI14-FJ14 -> 0.54545455 | FL14: =FF14+FG14 -> 0 | FM14: =FJ14+FI14 -> 0.18181818 | FN14: =EK14+FF14/3+FI14/3 -> #VALUE! | FO14: =EK14+FG14/3+FJ14/3 -> #VALUE! | FP14: =EK14+FL14/3+FM14/3 -> #VALUE! | FQ14: =EK14 -> #VALUE! | FR14: =FP14-FQ14 -> #VALUE! | FS14: =FN14-FO14 -> #VALUE! | FT14: 30 | FU14: 18
B15: NVDA US Equity | D15: NVDA | F15: 46119 | H15: {=_xll.BQL($B15, "px_last", "dates=" & _xll.BQL.DATE($D$2))} -> #N/A Connection | I15: 23949.959 | J15: -43210 | K15: 10270 | M15: =K15+J15 -> -32940 | N15: =I15*H15+M15+L15 -> #VALUE! | O15: 26974 | P15: 60922 | Q15: 130497 | R15: 215938 | S15: 354704.9 | T15: 400449.92 | U15: 409606.62 | V15: 430668.61 | W15: 452513.22 | AG15: =X15*O15 -> 0 | AH15: =Y15*P15 -> 0 | AI15: =Z15*Q15 -> 0 | AJ15: =AA15*R15 -> 0 | AK15: =AB15*S15 -> 0 | AL15: =AC15*T15 -> 0 | AM15: =AD15*U15 -> 0 | AN15: =AE15*V15 -> 0 | AO15: =AF15*W15 -> 0 | AP15: 0.33370562 | AQ15: 1.2955894 | AR15: 2.9940735 | AS15: 4.81 | AT15: 8.4278766 | AU15: 9.782115 | AV15: 10.22572 | AW15: 10.981352 | AX15: 11.757462 | AY15: =AP15 -> 0.33370562 | AZ15: =AQ15 -> 1.2955894 | BA15: =AR15 -> 2.9940735 | BB15: =AS15 -> 4.81 | BC15: =AT15 -> 8.4278766 | BD15: =AU15 -> 9.782115 | BE15: =AV15 -> 10.22572 | BF15: =AW15 -> 10.981352 | BG15: =AX15 -> 11.757462 | BH15: =$N15/Q15 -> #VALUE! | BI15: =$N15/R15 -> #VALUE! | BJ15: =$N15/S15 -> #VALUE! | BK15: =$N15/T15 -> #VALUE! | BL15: =$N15/U15 -> #VALUE! | BM15: =$N15/V15 -> #VALUE! | BN15: =$N15/W15 -> #VALUE! | BO15: n/a | BP15: n/a | BQ15: =$N15/AM15 -> #VALUE! | BR15: =$N15/AN15 -> #VALUE! | BS15: =$N15/AO15 -> #VALUE! | BT15: =$H15/AT15 -> #VALUE! | BU15: =$H15/AU15 -> #VALUE! | BV15: =$H15/AV15 -> #VALUE! | BW15: =$H15/AW15 -> #VALUE! | BX15: =$H15/AX15 -> #VALUE! | BY15: =$H15/BC15 -> #VALUE! | BZ15: =$H15/BD15 -> #VALUE! | CA15: =$H15/BE15 -> #VALUE! | CB15: =$H15/BF15 -> #VALUE! | CC15: =$H15/BG15 -> #VALUE! | CD15: 24 | CE15: 24 | CF15: 24 | CG15: 24 | CH15: 24 | CN15: =CD15*BD15+CS15 -> 234.77076 | CO15: =CE15*BE15+CT15 -> 245.41728 | CP15: =CF15*BF15+CU15 -> 263.55246 | CQ15: =CG15*BG15+CV15 -> 282.17909 | DC15: 22739.184 | DD15: 21525.915 | DE15: 20428.256 | DF15: 19409.325 | DG15: 18466.078 | DH15: -32940 | DI15: -32940 | DJ15: -32940 | DK15: -32940 | DL15: -32940 | DO15: 0.044 | DP15: 0.0484 | DQ15: 0.05324 | DR15: 0.058564 | DS15: 0.0644204 | DT15: =_xlfn.RRI(DT$2,$H15,CN15+$DO15*$DT$2) -> #VALUE! | DU15: =_xlfn.RRI(DU$2,$H15,CO15+$DO15*$DT$2+SUM($DP15:DP15)) -> #VALUE! | DV15: =_xlfn.RRI(DV$2,$H15,CP15+$DO15*$DT$2+SUM($DP15:DQ15)) -> #VALUE! | DW15: =_xlfn.RRI(DW$2,$H15,CQ15+$DO15*$DT$2+SUM($DP15:DR15)) -> #VALUE! | DX15: =SUM(CN15,$DO15:DO15)/$H15 -> #VALUE! | DY15: =SUM(CO15,$DO15:DP15)/$H15 -> #VALUE! | DZ15: =SUM(CP15,$DO15:DQ15)/$H15 -> #VALUE! | EA15: =SUM(CQ15,$DO15:DR15)/$H15 -> #VALUE! | EB15: {=_xll.BDP(""&$B15&"","CHG_PCT_1M")/100} -> -0.03094794 | EC15: {=_xll.BDP(""&$B15&"","CHG_PCT_3M")/100} -> 0.1727589 | ED15: {=_xll.BDP(""&$B15&"","CHG_PCT_6M")/100} -> 0.1239019 | EE15: =_xlfn.RRI(2+$DT$2,$DT$2*S15+(1-$DT$2)*T15,V15) -> 0.055709232 | EF15: =EG15-EE15 -> -0.030511792 | EG15: =_xlfn.RRI(2+$DT$2,$DT$2*(BC15*DC15)+(1-$DT$2)*(BD15*DD15),(BF15*DF15)) -> 0.02519744 | EH15: =EI15-EG15 -> 0.054481494 | EI15: =ER15+EQ15 -> 0.079678934 | EJ15: =EK15-EI15 -> #VALUE! | EK15: =DV15 -> #VALUE! | EL15: =_xlfn.RRI(3,AK15,AN15) -> 0 | EM15: =_xlfn.RRI(3,BC15,BF15) -> 0.092226106 | EN15: {=_xll.BDP(B15,"AVG_DAILY_VALUE_TRADED_3M")/10^6} -> 33095.848 | EQ15: =IFERROR(AVERAGE(DP15:DQ15)/H15,0) -> 0 | ER15: =_xlfn.RRI(2+$DT$2,$DT$2*(BC15)+(1-$DT$2)*(BD15),(BF15)) -> 0.079678934 | ES15: =ER15-EG15+EQ15 -> 0.054481494 | EU15: =_xlfn.RRI(2+$DT$2,($DT$2*BY15+(1-$DT$2)*BZ15),CF15) -> #VALUE! | EV15: =EJ15-EU15 -> #VALUE! | FF15: 0.25 | FG15: -0.25 | FH15: =FF15-FG15 -> 0.5 | FI15: =FT15/CF15-1 -> 0.25 | FJ15: =FU15/CF15-1 -> -0.25 | FK15: =FI15-FJ15 -> 0.5 | FL15: =FF15+FG15 -> 0 | FM15: =FJ15+FI15 -> 0 | FN15: =EK15+FF15/3+FI15/3 -> #VALUE! | FO15: =EK15+FG15/3+FJ15/3 -> #VALUE! | FP15: =EK15+FL15/3+FM15/3 -> #VALUE! | FQ15: =EK15 -> #VALUE! | FR15: =FP15-FQ15 -> #VALUE! | FS15: =FN15-FO15 -> #VALUE! | FT15: 30 | FU15: 18
D17: Info Svcs
B18: CSGP US EQUITY | D18: CSGP | E18: 1 | F18: 45689 | H18: {=_xll.BQL($B18, "px_last", "dates=" & _xll.BQL.DATE($D$2))} -> #N/A Connection | I18: 419.6 | J18: -1633 | K18: =992.5+800 -> 1792.5 | M18: =K18+J18 -> 159.5 | N18: =I18*H18+M18+L18 -> #VALUE! | O18: 2182.399 | P18: 2455 | Q18: 2736.2 | R18: 3247 | S18: 3843.75 | T18: 4442.3 | U18: 4976.173 | V18: 5551.398 | W18: 6162.0518 | X18: 0.8 | Y18: 0.8 | Z18: 0.8 | AA18: 0.8 | AB18: 0.8 | AC18: 0.8 | AD18: 0.8 | AE18: 0.8 | AF18: 0.8 | AG18: =X18*O18 -> 1745.9192 | AH18: =Y18*P18 -> 1964 | AI18: =Z18*Q18 -> 2188.96 | AJ18: =AA18*R18 -> 2597.6 | AK18: =AB18*S18 -> 3075 | AL18: =AC18*T18 -> 3553.84 | AM18: =AD18*U18 -> 3980.9384 | AN18: =AE18*V18 -> 4441.1184 | AO18: =AF18*W18 -> 4929.6415 | AP18: 1.132733 | AQ18: 1.0695484 | AR18: 0.56728908 | AS18: 0.69200325 | AT18: 1.1941425 | AU18: 1.8720325 | AV18: 2.6769596 | AW18: 3.6100842 | AX18: 4.6848994 | AY18: =AP18 -> 1.132733 | AZ18: =AQ18 -> 1.0695484 | BA18: =AR18 -> 0.56728908 | BB18: =AS18 -> 0.69200325 | BC18: =AT18 -> 1.1941425 | BD18: =AU18 -> 1.8720325 | BE18: =AV18 -> 2.6769596 | BF18: =AW18 -> 3.6100842 | BG18: =AX18 -> 4.6848994 | BH18: =$N18/Q18 -> #VALUE! | BI18: =$N18/R18 -> #VALUE! | BJ18: =$N18/S18 -> #VALUE! | BK18: =$N18/T18 -> #VALUE! | BL18: =$N18/U18 -> #VALUE! | BM18: =$N18/V18 -> #VALUE! | BN18: =$N18/W18 -> #VALUE! | BO18: =$N18/AK18 -> #VALUE! | BP18: =$N18/AL18 -> #VALUE! | BQ18: =$N18/AM18 -> #VALUE! | BR18: =$N18/AN18 -> #VALUE! | BS18: =$N18/AO18 -> #VALUE! | BT18: =$H18/AT18 -> #VALUE! | BU18: =$H18/AU18 -> #VALUE! | BV18: =$H18/AV18 -> #VALUE! | BW18: =$H18/AW18 -> #VALUE! | BX18: =$H18/AX18 -> #VALUE! | BY18: =$H18/BC18 -> #VALUE! | BZ18: =$H18/BD18 -> #VALUE! | CA18: =$H18/BE18 -> #VALUE! | CB18: =$H18/BF18 -> #VALUE! | CC18: =$H18/BG18 -> #VALUE! | CD18: 22 | CE18: 22 | CF18: 22 | CG18: 22 | CH18: 22 | CN18: =CD18*BD18 -> 41.184715 | CO18: =CE18*BE18 -> 58.893111 | CP18: =CF18*BF18 -> 79.421852 | CQ18: =CG18*BG18 -> 103.06779 | DC18: 414.18387 | DD18: 401.21459 | DE18: 388.58912 | DF18: 377.61046 | DG18: 368.06379 | DO18: 0 | DP18: 0 | DQ18: 0 | DR18: 0 | DS18: 0 | DT18: =_xlfn.RRI(DT$2,$H18,CN18+$DO18*$DT$2) -> #VALUE! | DU18: =_xlfn.RRI(DU$2,$H18,CO18+$DO18*$DT$2+SUM($DP18:DP18)) -> #VALUE! | DV18: =_xlfn.RRI(DV$2,$H18,CP18+$DO18*$DT$2+SUM($DP18:DQ18)) -> #VALUE! | DW18: =_xlfn.RRI(DW$2,$H18,CQ18+$DO18*$DT$2+SUM($DP18:DR18)) -> #VALUE! | DX18: =SUM(CN18,$DO18:DO18)/$H18 -> #VALUE! | DY18: =SUM(CO18,$DO18:DP18)/$H18 -> #VALUE! | DZ18: =SUM(CP18,$DO18:DQ18)/$H18 -> #VALUE! | EA18: =SUM(CQ18,$DO18:DR18)/$H18 -> #VALUE! | EB18: {=_xll.BDP(""&$B18&"","CHG_PCT_1M")/100} -> 0.03021054 | EC18: {=_xll.BDP(""&$B18&"","CHG_PCT_3M")/100} -> -0.302191 | ED18: {=_xll.BDP(""&$B18&"","CHG_PCT_6M")/100} -> -0.4910297 | EE18: =_xlfn.RRI(2+$DT$2,$DT$2*S18+(1-$DT$2)*T18,V18) -> 0.12490086 | EF18: =EG18-EE18 -> 0.24632538 | EG18: =_xlfn.RRI(2+$DT$2,$DT$2*(BC18*DC18)+(1-$DT$2)*(BD18*DD18),(BF18*DF18)) -> 0.37122624 | EH18: =EI18-EG18 -> 0.040772778 | EI18: =ER18+EQ18 -> 0.41199902 | EJ18: =EK18-EI18 -> #VALUE! | EK18: =DV18 -> #VALUE! | EL18: =_xlfn.RRI(3,AK18,AN18) -> 0.1303573 | EM18: =_xlfn.RRI(3,BC18,BF18) -> 0.44595148 | EN18: {=_xll.BDP(B18,"AVG_DAILY_VALUE_TRADED_3M")/10^6} -> 262.39074 | EQ18: =IFERROR(AVERAGE(DP18:DQ18)/H18,0) -> 0 | ER18: =_xlfn.RRI(2+$DT$2,$DT$2*(BC18)+(1-$DT$2)*(BD18),(BF18)) -> 0.41199902 | ES18: =ER18-EG18+EQ18 -> 0.040772778 | EU18: =_xlfn.RRI(2+$DT$2,($DT$2*BY18+(1-$DT$2)*BZ18),CF18) -> #VALUE! | EV18: =EJ18-EU18 -> #VALUE! | FF18: 0.05 | FG18: -0.25 | FH18: =FF18-FG18 -> 0.3 | FI18: =FT18/CF18-1 -> 0.36363636 | FJ18: =FU18/CF18-1 -> -0.18181818 | FK18: =FI18-FJ18 -> 0.54545455 | FL18: =FF18+FG18 -> -0.2 | FM18: =FJ18+FI18 -> 0.18181818 | FN18: =EK18+FF18/3+FI18/3 -> #VALUE! | FO18: =EK18+FG18/3+FJ18/3 -> #VALUE! | FP18: =EK18+FL18/3+FM18/3 -> #VALUE! | FQ18: =EK18 -> #VALUE! | FR18: =FP18-FQ18 -> #VALUE! | FS18: =FN18-FO18 -> #VALUE! | FT18: 30 | FU18: 18
B19: TRU US EQUITY | D19: TRU | E19: 1 | F19: 45810 | H19: {=_xll.BQL($B19, "px_last", "dates=" & _xll.BQL.DATE($D$2))} -> #N/A Connection | I19: 197.2 | J19: -853.6 | K19: 5103.8 | L19: 106.7 | M19: =K19+J19 -> 4250.2 | N19: =I19*H19+M19+L19 -> #VALUE! | O19: 3710 | P19: 3831.4 | Q19: 4183.8 | R19: 4576.2 | S19: 5129.4412 | T19: 5454.1426 | U19: 5789.8404 | V19: 6148.0729 | W19: 6528.9595 | X19: 0.6 | Y19: 0.6 | Z19: 0.6 | AA19: 0.6 | AB19: 0.6 | AC19: 0.6 | AD19: 0.6 | AE19: 0.6 | AF19: 0.6 | AG19: =X19*O19 -> 2226 | AH19: =Y19*P19 -> 2298.84 | AI19: =Z19*Q19 -> 2510.28 | AJ19: =AA19*R19 -> 2745.72 | AK19: =AB19*S19 -> 3077.6647 | AL19: =AC19*T19 -> 3272.4856 | AM19: =AD19*U19 -> 3473.9042 | AN19: =AE19*V19 -> 3688.8438 | AO19: =AF19*W19 -> 3917.3757 | AP19: 3.2912726 | AQ19: 2.9783798 | AR19: 3.4392731 | AS19: 3.7571823 | AT19: 4.2698664 | AU19: 4.9567662 | AV19: 5.7838143 | AW19: 6.7404567 | AX19: 7.8511706 | AY19: =AP19 -> 3.2912726 | AZ19: =AQ19 -> 2.9783798 | BA19: =AR19 -> 3.4392731 | BB19: =AS19 -> 3.7571823 | BC19: =AT19 -> 4.2698664 | BD19: =AU19 -> 4.9567662 | BE19: =AV19 -> 5.7838143 | BF19: =AW19 -> 6.7404567 | BG19: =AX19 -> 7.8511706 | BH19: =$N19/Q19 -> #VALUE! | BI19: =$N19/R19 -> #VALUE! | BJ19: =$N19/S19 -> #VALUE! | BK19: =$N19/T19 -> #VALUE! | BL19: =$N19/U19 -> #VALUE! | BM19: =$N19/V19 -> #VALUE! | BN19: =$N19/W19 -> #VALUE! | BO19: =$N19/AK19 -> #VALUE! | BP19: =$N19/AL19 -> #VALUE! | BQ19: =$N19/AM19 -> #VALUE! | BR19: =$N19/AN19 -> #VALUE! | BS19: =$N19/AO19 -> #VALUE! | BT19: =$H19/AT19 -> #VALUE! | BU19: =$H19/AU19 -> #VALUE! | BV19: =$H19/AV19 -> #VALUE! | BW19: =$H19/AW19 -> #VALUE! | BX19: =$H19/AX19 -> #VALUE! | BY19: =$H19/BC19 -> #VALUE! | BZ19: =$H19/BD19 -> #VALUE! | CA19: =$H19/BE19 -> #VALUE! | CB19: =$H19/BF19 -> #VALUE! | CC19: =$H19/BG19 -> #VALUE! | CD19: 20 | CE19: 20 | CF19: 20 | CG19: 20 | CH19: 20 | CI19: 103.9279 | CJ19: 130.01874 | CK19: 162.57321 | CL19: 192.09422 | CN19: =CD19*BD19 -> 99.135323 | CO19: =CE19*BE19 -> 115.67629 | CP19: =CF19*BF19 -> 134.80913 | CQ19: =CG19*BG19 -> 157.02341 | DC19: 190.1472 | DD19: 181.44159 | DE19: 172.73599 | DF19: 164.03039 | DG19: 155.32478 | DO19: 0.52590835 | DP19: 0.56767579 | DQ19: 0.61417426 | DR19: 0.66617351 | DS19: 0.72461637 | DT19: =_xlfn.RRI(DT$2,$H19,CN19+$DO19*$DT$2) -> #VALUE! | DU19: =_xlfn.RRI(DU$2,$H19,CO19+$DO19*$DT$2+SUM($DP19:DP19)) -> #VALUE! | DV19: =_xlfn.RRI(DV$2,$H19,CP19+$DO19*$DT$2+SUM($DP19:DQ19)) -> #VALUE! | DW19: =_xlfn.RRI(DW$2,$H19,CQ19+$DO19*$DT$2+SUM($DP19:DR19)) -> #VALUE! | DX19: =SUM(CN19,$DO19:DO19)/$H19 -> #VALUE! | DY19: =SUM(CO19,$DO19:DP19)/$H19 -> #VALUE! | DZ19: =SUM(CP19,$DO19:DQ19)/$H19 -> #VALUE! | EA19: =SUM(CQ19,$DO19:DR19)/$H19 -> #VALUE! | EB19: {=_xll.BDP(""&$B19&"","CHG_PCT_1M")/100} -> -0.02361111 | EC19: {=_xll.BDP(""&$B19&"","CHG_PCT_3M")/100} -> -0.09149648 | ED19: {=_xll.BDP(""&$B19&"","CHG_PCT_6M")/100} -> -0.1427875 | EE19: =_xlfn.RRI(2+$DT$2,$DT$2*S19+(1-$DT$2)*T19,V19) -> 0.061864924 | EF19: =EG19-EE19 -> 0.046110901 | EG19: =_xlfn.RRI(2+$DT$2,$DT$2*(BC19*DC19)+(1-$DT$2)*(BD19*DD19),(BF19*DF19)) -> 0.10797582 | EH19: =EI19-EG19 -> 0.055746156 | EI19: =ER19+EQ19 -> 0.16372198 | EJ19: =EK19-EI19 -> #VALUE! | EK19: =DV19 -> #VALUE! | EL19: =_xlfn.RRI(3,AK19,AN19) -> 0.062240815 | EM19: =_xlfn.RRI(3,BC19,BF19) -> 0.1643718 | EN19: {=_xll.BDP(B19,"AVG_DAILY_VALUE_TRADED_3M")/10^6} -> 160.06408 | EQ19: =IFERROR(AVERAGE(DP19:DQ19)/H19,0) -> 0 | ER19: =_xlfn.RRI(2+$DT$2,$DT$2*(BC19)+(1-$DT$2)*(BD19),(BF19)) -> 0.16372198 | ES19: =ER19-EG19+EQ19 -> 0.055746156 | EU19: =_xlfn.RRI(2+$DT$2,($DT$2*BY19+(1-$DT$2)*BZ19),CF19) -> #VALUE! | EV19: =EJ19-EU19 -> #VALUE! | FF19: 0.2 | FG19: -0.2 | FH19: =FF19-FG19 -> 0.4 | FI19: =FT19/CF19-1 -> 0.3 | FJ19: =FU19/CF19-1 -> -0.3 | FK19: =FI19-FJ19 -> 0.6 | FL19: =FF19+FG19 -> 0 | FM19: =FJ19+FI19 -> 0 | FN19: =EK19+FF19/3+FI19/3 -> #VALUE! | FO19: =EK19+FG19/3+FJ19/3 -> #VALUE! | FP19: =EK19+FL19/3+FM19/3 -> #VALUE! | FQ19: =EK19 -> #VALUE! | FR19: =FP19-FQ19 -> #VALUE! | FS19: =FN19-FO19 -> #VALUE! | FT19: 26 | FU19: 14
B20: EFX US EQUITY | D20: EFX | E20: 1 | F20: 45810 | H20: {=_xll.BQL($B20, "px_last", "dates=" & _xll.BQL.DATE($D$2))} -> #N/A Connection | I20: 124.1 | J20: -180.8 | K20: 5093.3 | L20: 17.5 | M20: =K20+J20 -> 4912.5 | N20: =I20*H20+M20+L20 -> #VALUE! | O20: 5122.2 | P20: 5265.2 | Q20: 5681.1 | R20: 6074.5 | S20: 6645.2564 | T20: 7203.17 | U20: 7801.8195 | V20: 8448.8615 | W20: 9146.5592 | X20: 0.6 | Y20: 0.6 | Z20: 0.6 | AA20: 0.6 | AB20: 0.6 | AC20: 0.6 | AD20: 0.6 | AE20: 0.6 | AF20: 0.6 | AG20: =X20*O20 -> 3073.32 | AH20: =Y20*P20 -> 3159.12 | AI20: =Z20*Q20 -> 3408.66 | AJ20: =AA20*R20 -> 3644.7 | AK20: =AB20*S20 -> 3987.1538 | AL20: =AC20*T20 -> 4321.902 | AM20: =AD20*U20 -> 4681.0917 | AN20: =AE20*V20 -> 5069.3169 | AO20: =AF20*W20 -> 5487.9355 | AP20: 7.5579886 | AQ20: 6.7110573 | AR20: 7.2946357 | AS20: 7.6526994 | AT20: 8.2610488 | AU20: 9.9529019 | AV20: 11.994757 | AW20: 14.410321 | AX20: 17.275352 | AY20: =AP20 -> 7.5579886 | AZ20: =AQ20 -> 6.7110573 | BA20: =AR20 -> 7.2946357 | BB20: =AS20 -> 7.6526994 | BC20: =AT20 -> 8.2610488 | BD20: =AU20 -> 9.9529019 | BE20: =AV20 -> 11.994757 | BF20: =AW20 -> 14.410321 | BG20: =AX20 -> 17.275352 | BH20: =$N20/Q20 -> #VALUE! | BI20: =$N20/R20 -> #VALUE! | BJ20: =$N20/S20 -> #VALUE! | BK20: =$N20/T20 -> #VALUE! | BL20: =$N20/U20 -> #VALUE! | BM20: =$N20/V20 -> #VALUE! | BN20: =$N20/W20 -> #VALUE! | BO20: =$N20/AK20 -> #VALUE! | BP20: =$N20/AL20 -> #VALUE! | BQ20: =$N20/AM20 -> #VALUE! | BR20: =$N20/AN20 -> #VALUE! | BS20: =$N20/AO20 -> #VALUE! | BT20: =$H20/AT20 -> #VALUE! | BU20: =$H20/AU20 -> #VALUE! | BV20: =$H20/AV20 -> #VALUE! | BW20: =$H20/AW20 -> #VALUE! | BX20: =$H20/AX20 -> #VALUE! | BY20: =$H20/BC20 -> #VALUE! | BZ20: =$H20/BD20 -> #VALUE! | CA20: =$H20/BE20 -> #VALUE! | CB20: =$H20/BF20 -> #VALUE! | CC20: =$H20/BG20 -> #VALUE! | CD20: 20 | CE20: 20 | CF20: 20 | CG20: 20 | CH20: 20 | CN20: =CD20*BD20 -> 199.05804 | CO20: =CE20*BE20 -> 239.89515 | CP20: =CF20*BF20 -> 288.20642 | CQ20: =CG20*BG20 -> 345.50705 | DC20: 121.30785 | DD20: 115.56797 | DE20: 109.43918 | DF20: 103.32806 | DG20: 97.333894 | DO20: 1.9766569 | DP20: 2.1370759 | DQ20: 2.3244586 | DR20: 2.5357917 | DS20: 2.7727135 | DT20: =_xlfn.RRI(DT$2,$H20,CN20+$DO20*$DT$2) -> #VALUE! | DU20: =_xlfn.RRI(DU$2,$H20,CO20+$DO20*$DT$2+SUM($DP20:DP20)) -> #VALUE! | DV20: =_xlfn.RRI(DV$2,$H20,CP20+$DO20*$DT$2+SUM($DP20:DQ20)) -> #VALUE! | DW20: =_xlfn.RRI(DW$2,$H20,CQ20+$DO20*$DT$2+SUM($DP20:DR20)) -> #VALUE! | DX20: =SUM(CN20,$DO20:DO20)/$H20 -> #VALUE! | DY20: =SUM(CO20,$DO20:DP20)/$H20 -> #VALUE! | DZ20: =SUM(CP20,$DO20:DQ20)/$H20 -> #VALUE! | EA20: =SUM(CQ20,$DO20:DR20)/$H20 -> #VALUE! | EB20: {=_xll.BDP(""&$B20&"","CHG_PCT_1M")/100} -> -0.03531822 | EC20: {=_xll.BDP(""&$B20&"","CHG_PCT_3M")/100} -> -0.1838522 | ED20: {=_xll.BDP(""&$B20&"","CHG_PCT_6M")/100} -> -0.1933996 | EE20: =_xlfn.RRI(2+$DT$2,$DT$2*S20+(1-$DT$2)*T20,V20) -> 0.082885985 | EF20: =EG20-EE20 -> 0.056013419 | EG20: =_xlfn.RRI(2+$DT$2,$DT$2*(BC20*DC20)+(1-$DT$2)*(BD20*DD20),(BF20*DF20)) -> 0.1388994 | EH20: =EI20-EG20 -> 0.062679137 | EI20: =ER20+EQ20 -> 0.20157854 | EJ20: =EK20-EI20 -> #VALUE! | EK20: =DV20 -> #VALUE! | EL20: =_xlfn.RRI(3,AK20,AN20) -> 0.083333443 | EM20: =_xlfn.RRI(3,BC20,BF20) -> 0.20377731 | EN20: {=_xll.BDP(B20,"AVG_DAILY_VALUE_TRADED_3M")/10^6} -> 294.55366 | EQ20: =IFERROR(AVERAGE(DP20:DQ20)/H20,0) -> 0 | ER20: =_xlfn.RRI(2+$DT$2,$DT$2*(BC20)+(1-$DT$2)*(BD20),(BF20)) -> 0.20157854 | ES20: =ER20-EG20+EQ20 -> 0.062679137 | EU20: =_xlfn.RRI(2+$DT$2,($DT$2*BY20+(1-$DT$2)*BZ20),CF20) -> #VALUE! | EV20: =EJ20-EU20 -> #VALUE! | FF20: 0.2 | FG20: -0.2 | FH20: =FF20-FG20 -> 0.4 | FI20: =FT20/CF20-1 -> 0.3 | FJ20: =FU20/CF20-1 -> -0.3 | FK20: =FI20-FJ20 -> 0.6 | FL20: =FF20+FG20 -> 0 | FM20: =FJ20+FI20 -> 0 | FN20: =EK20+FF20/3+FI20/3 -> #VALUE! | FO20: =EK20+FG20/3+FJ20/3 -> #VALUE! | FP20: =EK20+FL20/3+FM20/3 -> #VALUE! | FQ20: =EK20 -> #VALUE! | FR20: =FP20-FQ20 -> #VALUE! | FS20: =FN20-FO20 -> #VALUE! | FT20: 26 | FU20: 14
B21: LSEG LN EQUITY | D21: LSEG | E21: 1 | F21: 45994 | H21: {=_xll.BQL($B21, "px_last", "dates=" & _xll.BQL.DATE($D$2))/100} -> #VALUE! | I21: 527 | J21: -3949 | K21: 11804 | M21: =K21+J21 -> 7855 | N21: =I21*H21+M21+L21 -> #VALUE! | O21: 7428 | P21: 8009 | Q21: 8494 | R21: 8986 | S21: 9659.1735 | T21: 10357.271 | U21: 11113.277 | V21: 11932.295 | W21: 12819.889 | X21: 0.87 | Y21: 0.87 | Z21: 0.87 | AA21: 0.87 | AB21: 0.87 | AC21: 0.87 | AD21: 0.87 | AE21: 0.87 | AF21: 0.87 | AG21: =X21*O21 -> 6462.36 | AH21: =Y21*P21 -> 6967.83 | AI21: =Z21*Q21 -> 7389.78 | AJ21: =AA21*R21 -> 7817.82 | AK21: =AB21*S21 -> 8403.4809 | AL21: =AC21*T21 -> 9010.8255 | AM21: =AD21*U21 -> 9668.5511 | AN21: =AE21*V21 -> 10381.096 | AO21: =AF21*W21 -> 11153.304 | AP21: 3.178 | AQ21: 3.239 | AR21: 3.635 | AS21: 4.206 | AT21: 4.6016562 | AU21: 5.1498971 | AV21: 5.9086919 | AW21: 6.7569185 | AX21: 7.707095 | AY21: =AP21 -> 3.178 | AZ21: =AQ21 -> 3.239 | BA21: =AR21 -> 3.635 | BB21: =AS21 -> 4.206 | BC21: =AT21 -> 4.6016562 | BD21: =AU21 -> 5.1498971 | BE21: =AV21 -> 5.9086919 | BF21: =AW21 -> 6.7569185 | BG21: =AX21 -> 7.707095 | BH21: =$N21/Q21 -> #VALUE! | BI21: =$N21/R21 -> #VALUE! | BJ21: =$N21/S21 -> #VALUE! | BK21: =$N21/T21 -> #VALUE! | BL21: =$N21/U21 -> #VALUE! | BM21: =$N21/V21 -> #VALUE! | BN21: =$N21/W21 -> #VALUE! | BO21: =$N21/AK21 -> #VALUE! | BP21: =$N21/AL21 -> #VALUE! | BQ21: =$N21/AM21 -> #VALUE! | BR21: =$N21/AN21 -> #VALUE! | BS21: =$N21/AO21 -> #VALUE! | BT21: =$H21/AT21 -> #VALUE! | BU21: =$H21/AU21 -> #VALUE! | BV21: =$H21/AV21 -> #VALUE! | BW21: =$H21/AW21 -> #VALUE! | BX21: =$H21/AX21 -> #VALUE! | BY21: =$H21/BC21 -> #VALUE! | BZ21: =$H21/BD21 -> #VALUE! | CA21: =$H21/BE21 -> #VALUE! | CB21: =$H21/BF21 -> #VALUE! | CC21: =$H21/BG21 -> #VALUE! | CD21: 22 | CE21: 22 | CF21: 22 | CG21: 22 | CH21: 24 | CN21: =CD21*BD21 -> 113.29774 | CO21: =CE21*BE21 -> 129.99122 | CP21: =CF21*BF21 -> 148.65221 | CQ21: =CG21*BG21 -> 169.55609 | DC21: 509.24246 | DD21: 477.56505 | DE21: 452.12572 | DF21: 429.72617 | DG21: 408.66851 | DO21: 1.6763268 | DP21: 1.9279933 | DQ21: 2.2094085 | DR21: 2.5236533 | DS21: 2.8745861 | DT21: =_xlfn.RRI(DT$2,$H21,CN21+$DO21*$DT$2) -> #VALUE! | DU21: =_xlfn.RRI(DU$2,$H21,CO21+$DO21*$DT$2+SUM($DP21:DP21)) -> #VALUE! | DV21: =_xlfn.RRI(DV$2,$H21,CP21+$DO21*$DT$2+SUM($DP21:DQ21)) -> #VALUE! | DW21: =_xlfn.RRI(DW$2,$H21,CQ21+$DO21*$DT$2+SUM($DP21:DR21)) -> #VALUE! | DX21: =SUM(CN21,$DO21:DO21)/$H21 -> #VALUE! | DY21: =SUM(CO21,$DO21:DP21)/$H21 -> #VALUE! | DZ21: =SUM(CP21,$DO21:DQ21)/$H21 -> #VALUE! | EA21: =SUM(CQ21,$DO21:DR21)/$H21 -> #VALUE! | EB21: {=_xll.BDP(""&$B21&"","CHG_PCT_1M")/100} -> 0.0219075 | EC21: {=_xll.BDP(""&$B21&"","CHG_PCT_3M")/100} -> 0.05050045 | ED21: {=_xll.BDP(""&$B21&"","CHG_PCT_6M")/100} -> 0.08658824 | EE21: =_xlfn.RRI(2+$DT$2,$DT$2*S21+(1-$DT$2)*T21,V21) -> 0.072858405 | EF21: =EG21-EE21 -> 0.0053826734 | EG21: =_xlfn.RRI(2+$DT$2,$DT$2*(BC21*DC21)+(1-$DT$2)*(BD21*DD21),(BF21*DF21)) -> 0.078241079 | EH21: =EI21-EG21 -> 0.060709843 | EI21: =ER21+EQ21 -> 0.13895092 | EJ21: =EK21-EI21 -> #VALUE! | EK21: =DV21 -> #VALUE! | EL21: =_xlfn.RRI(3,AK21,AN21) -> 0.072987509 | EM21: =_xlfn.RRI(3,BC21,BF21) -> 0.13661009 | EN21: {=_xll.BDP(B21,"AVG_DAILY_VALUE_TRADED_3M")/10^6} -> 10396.47 | EQ21: =IFERROR(AVERAGE(DP21:DQ21)/H21,0) -> 0 | ER21: =_xlfn.RRI(2+$DT$2,$DT$2*(BC21)+(1-$DT$2)*(BD21),(BF21)) -> 0.13895092 | ES21: =ER21-EG21+EQ21 -> 0.060709843 | EU21: =_xlfn.RRI(2+$DT$2,($DT$2*BY21+(1-$DT$2)*BZ21),CF21) -> #VALUE! | EV21: =EJ21-EU21 -> #VALUE! | FF21: 0.15 | FG21: -0.15 | FH21: =FF21-FG21 -> 0.3 | FI21: =FT21/CF21-1 -> 0.18181818 | FJ21: =FU21/CF21-1 -> -0.22727273 | FK21: =FI21-FJ21 -> 0.40909091 | FL21: =FF21+FG21 -> 0 | FM21: =FJ21+FI21 -> -0.045454545 | FN21: =EK21+FF21/3+FI21/3 -> #VALUE! | FO21: =EK21+FG21/3+FJ21/3 -> #VALUE! | FP21: =EK21+FL21/3+FM21/3 -> #VALUE! | FQ21: =EK21 -> #VALUE! | FR21: =FP21-FQ21 -> #VALUE! | FS21: =FN21-FO21 -> #VALUE! | FT21: 26 | FU21: 17 | FV21: Set Mendo EPS = adj EPS (SBC <2% revs)
B22: SPGI US EQUITY | D22: SPGI | E22: 1 | F22: 46057 | H22: {=_xll.BQL($B22, "px_last", "dates=" & _xll.BQL.DATE($D$2))} -> #N/A Connection | I22: 304.1025 | J22: -1847 | K22: 11388 | M22: =K22+J22 -> 9541 | N22: =I22*H22+M22+L22 -> #VALUE! | O22: 11843 | P22: 12497 | Q22: 14208 | R22: 15336 | S22: 16719.285 | T22: 18035.782 | U22: 19461.908 | V22: 21007.252 | W22: 22682.276 | X22: 0.7 | Y22: 0.7 | Z22: 0.7 | AA22: 0.7 | AB22: 0.7 | AC22: 0.7 | AD22: 0.7 | AE22: 0.7 | AF22: 0.7 | AG22: =X22*O22 -> 8290.1 | AH22: =Y22*P22 -> 8747.9 | AI22: =Z22*Q22 -> 9945.6 | AJ22: =AA22*R22 -> 10735.2 | AK22: =AB22*S22 -> 11703.5 | AL22: =AC22*T22 -> 12625.048 | AM22: =AD22*U22 -> 13623.336 | AN22: =AE22*V22 -> 14705.077 | AO22: =AF22*W22 -> 15877.593 | AP22: 11.77394 | AQ22: 12.599561 | AR22: 15.703751 | AS22: 18.021314 | AT22: 20.193227 | AU22: 22.779021 | AV22: 25.648626 | AW22: 28.872377 | AX22: 32.492214 | AY22: =AP22 -> 11.77394 | AZ22: =AQ22 -> 12.599561 | BA22: =AR22 -> 15.703751 | BB22: =AS22 -> 18.021314 | BC22: =AT22 -> 20.193227 | BD22: =AU22 -> 22.779021 | BE22: =AV22 -> 25.648626 | BF22: =AW22 -> 28.872377 | BG22: =AX22 -> 32.492214 | BH22: =$N22/Q22 -> #VALUE! | BI22: =$N22/R22 -> #VALUE! | BJ22: =$N22/S22 -> #VALUE! | BK22: =$N22/T22 -> #VALUE! | BL22: =$N22/U22 -> #VALUE! | BM22: =$N22/V22 -> #VALUE! | BN22: =$N22/W22 -> #VALUE! | BO22: =$N22/AK22*0.9 -> #VALUE! | BP22: =$N22/AL22*0.9 -> #VALUE! | BQ22: =$N22/AM22*0.9 -> #VALUE! | BR22: =$N22/AN22*0.9 -> #VALUE! | BS22: =$N22/AO22*0.9 -> #VALUE! | BT22: =$H22/AT22 -> #VALUE! | BU22: =$H22/AU22 -> #VALUE! | BV22: =$H22/AV22 -> #VALUE! | BW22: =$H22/AW22 -> #VALUE! | BX22: =$H22/AX22 -> #VALUE! | BY22: =$H22/BC22 -> #VALUE! | BZ22: =$H22/BD22 -> #VALUE! | CA22: =$H22/BE22 -> #VALUE! | CB22: =$H22/BF22 -> #VALUE! | CC22: =$H22/BG22 -> #VALUE! | CD22: 22 | CE22: 22 | CF22: 22 | CG22: 22 | CH22: 24.5 | CN22: =CD22*BD22 -> 501.13845 | CO22: =CE22*BE22 -> 564.26976 | CP22: =CF22*BF22 -> 635.19228 | CQ22: =CG22*BG22 -> 714.82871 | DC22: 293.77509 | DD22: 283.34014 | DE22: 273.34107 | DF22: 263.77859 | DG22: 254.64132 | DO22: 4.0704 | DP22: 4.314624 | DQ22: 4.5735014 | DR22: 4.8479115 | DS22: 5.1387862 | DT22: =_xlfn.RRI(DT$2,$H22,CN22+$DO22*$DT$2) -> #VALUE! | DU22: =_xlfn.RRI(DU$2,$H22,CO22+$DO22*$DT$2+SUM($DP22:DP22)) -> #VALUE! | DV22: =_xlfn.RRI(DV$2,$H22,CP22+$DO22*$DT$2+SUM($DP22:DQ22)) -> #VALUE! | DW22: =_xlfn.RRI(DW$2,$H22,CQ22+$DO22*$DT$2+SUM($DP22:DR22)) -> #VALUE! | DX22: =SUM(CN22,$DO22:DO22)/$H22 -> #VALUE! | DY22: =SUM(CO22,$DO22:DP22)/$H22 -> #VALUE! | DZ22: =SUM(CP22,$DO22:DQ22)/$H22 -> #VALUE! | EA22: =SUM(CQ22,$DO22:DR22)/$H22 -> #VALUE! | EB22: {=_xll.BDP(""&$B22&"","CHG_PCT_1M")/100} -> 0.005355624 | EC22: {=_xll.BDP(""&$B22&"","CHG_PCT_3M")/100} -> -0.06629672 | ED22: {=_xll.BDP(""&$B22&"","CHG_PCT_6M")/100} -> -0.1416989 | EE22: =_xlfn.RRI(2+$DT$2,$DT$2*S22+(1-$DT$2)*T22,V22) -> 0.078829876 | EF22: =EG22-EE22 -> 0.007444219 | EG22: =_xlfn.RRI(2+$DT$2,$DT$2*(BC22*DC22)+(1-$DT$2)*(BD22*DD22),(BF22*DF22)) -> 0.086274095 | EH22: =EI22-EG22 -> 0.039252141 | EI22: =ER22+EQ22 -> 0.12552624 | EJ22: =EK22-EI22 -> #VALUE! | EK22: =DV22 -> #VALUE! | EL22: =_xlfn.RRI(3,AK22,AN22) -> 0.079072223 | EM22: =_xlfn.RRI(3,BC22,BF22) -> 0.12657196 | EN22: {=_xll.BDP(B22,"AVG_DAILY_VALUE_TRADED_3M")/10^6} -> 849.00768 | EQ22: =IFERROR(AVERAGE(DP22:DQ22)/H22,0) -> 0 | ER22: =_xlfn.RRI(2+$DT$2,$DT$2*(BC22)+(1-$DT$2)*(BD22),(BF22)) -> 0.12552624 | ES22: =ER22-EG22+EQ22 -> 0.039252141 | EU22: =_xlfn.RRI(2+$DT$2,($DT$2*BY22+(1-$DT$2)*BZ22),CF22) -> #VALUE! | EV22: =EJ22-EU22 -> #VALUE! | FF22: 0.15 | FG22: -0.15 | FH22: =FF22-FG22 -> 0.3 | FI22: =FT22/CF22-1 -> 0.18181818 | FJ22: =FU22/CF22-1 -> -0.22727273 | FK22: =FI22-FJ22 -> 0.40909091 | FL22: =FF22+FG22 -> 0 | FM22: =FJ22+FI22 -> -0.045454545 | FN22: =EK22+FF22/3+FI22/3 -> #VALUE! | FO22: =EK22+FG22/3+FJ22/3 -> #VALUE! | FP22: =EK22+FL22/3+FM22/3 -> #VALUE! | FQ22: =EK22 -> #VALUE! | FR22: =FP22-FQ22 -> #VALUE! | FS22: =FN22-FO22 -> #VALUE! | FT22: 26 | FU22: 17
B23: MSCI US EQUITY | D23: MSCI | E23: 1 | F23: 45995 | H23: {=_xll.BQL($B23, "px_last", "dates=" & _xll.BQL.DATE($D$2))} -> #N/A Connection | I23: 73.4 | J23: -385.3 | K23: 6403.8 | M23: =K23+J23 -> 6018.5 | N23: =I23*H23+M23+L23 -> #VALUE! | O23: 2248.598 | P23: 2528.92 | Q23: 2856.128 | R23: 3134.459 | S23: 3563.4271 | T23: 3995.7881 | U23: 4421.833 | V23: 4903.8557 | W23: 5431.2138 | X23: 0.82 | Y23: 0.82 | Z23: 0.82 | AA23: 0.82 | AB23: 0.82 | AC23: 0.82 | AD23: 0.82 | AE23: 0.82 | AF23: 0.82 | AG23: =X23*O23 -> 1843.8504 | AH23: =Y23*P23 -> 2073.7144 | AI23: =Z23*Q23 -> 2342.025 | AJ23: =AA23*R23 -> 2570.2564 | AK23: =AB23*S23 -> 2922.0102 | AL23: =AC23*T23 -> 3276.5463 | AM23: =AD23*U23 -> 3625.9031 | AN23: =AE23*V23 -> 4021.1617 | AO23: =AF23*W23 -> 4453.5953 | AP23: 11.454571 | AQ23: 13.519833 | AR23: 15.200836 | AS23: 17.283992 | AT23: 20.642219 | AU23: 24.577623 | AV23: 28.6984 | AW23: 33.570205 | AX23: 39.147441 | AY23: =AP23 -> 11.454571 | AZ23: =AQ23 -> 13.519833 | BA23: =AR23 -> 15.200836 | BB23: =AS23 -> 17.283992 | BC23: =AT23 -> 20.642219 | BD23: =AU23 -> 24.577623 | BE23: =AV23 -> 28.6984 | BF23: =AW23 -> 33.570205 | BG23: =AX23 -> 39.147441 | BH23: =$N23/Q23 -> #VALUE! | BI23: =$N23/R23 -> #VALUE! | BJ23: =$N23/S23 -> #VALUE! | BK23: =$N23/T23 -> #VALUE! | BL23: =$N23/U23 -> #VALUE! | BM23: =$N23/V23 -> #VALUE! | BN23: =$N23/W23 -> #VALUE! | BO23: =$N23/AK23 -> #VALUE! | BP23: =$N23/AL23 -> #VALUE! | BQ23: =$N23/AM23 -> #VALUE! | BR23: =$N23/AN23 -> #VALUE! | BS23: =$N23/AO23 -> #VALUE! | BT23: =$H23/AT23 -> #VALUE! | BU23: =$H23/AU23 -> #VALUE! | BV23: =$H23/AV23 -> #VALUE! | BW23: =$H23/AW23 -> #VALUE! | BX23: =$H23/AX23 -> #VALUE! | BY23: =$H23/BC23 -> #VALUE! | BZ23: =$H23/BD23 -> #VALUE! | CA23: =$H23/BE23 -> #VALUE! | CB23: =$H23/BF23 -> #VALUE! | CC23: =$H23/BG23 -> #VALUE! | CD23: 27 | CE23: 27 | CF23: 27 | CG23: 27 | CH23: 27 | CN23: =CD23*BD23 -> 663.59583 | CO23: =CE23*BE23 -> 774.8568 | CP23: =CF23*BF23 -> 906.39552 | CQ23: =CG23*BG23 -> 1056.9809 | DC23: 73.57914 | DD23: 71.114174 | DE23: 68.477416 | DF23: 65.921358 | DG23: 63.434977 | DO23: 8.2 | DP23: 9.6246397 | DQ23: 11.232983 | DR23: 13.131373 | DS23: 15.301162 | DT23: =_xlfn.RRI(DT$2,$H23,CN23+$DO23*$DT$2) -> #VALUE! | DU23: =_xlfn.RRI(DU$2,$H23,CO23+$DO23*$DT$2+SUM($DP23:DP23)) -> #VALUE! | DV23: =_xlfn.RRI(DV$2,$H23,CP23+$DO23*$DT$2+SUM($DP23:DQ23)) -> #VALUE! | DW23: =_xlfn.RRI(DW$2,$H23,CQ23+$DO23*$DT$2+SUM($DP23:DR23)) -> #VALUE! | DX23: =SUM(CN23,$DO23:DO23)/$H23 -> #VALUE! | DY23: =SUM(CO23,$DO23:DP23)/$H23 -> #VALUE! | DZ23: =SUM(CP23,$DO23:DQ23)/$H23 -> #VALUE! | EA23: =SUM(CQ23,$DO23:DR23)/$H23 -> #VALUE! | EB23: {=_xll.BDP(""&$B23&"","CHG_PCT_1M")/100} -> 0.04500191 | EC23: {=_xll.BDP(""&$B23&"","CHG_PCT_3M")/100} -> 0.07470489 | ED23: {=_xll.BDP(""&$B23&"","CHG_PCT_6M")/100} -> 0.1394393 | EE23: =_xlfn.RRI(2+$DT$2,$DT$2*S23+(1-$DT$2)*T23,V23) -> 0.11005003 | EF23: =EG23-EE23 -> 0.019630331 | EG23: =_xlfn.RRI(2+$DT$2,$DT$2*(BC23*DC23)+(1-$DT$2)*(BD23*DD23),(BF23*DF23)) -> 0.12968036 | EH23: =EI23-EG23 -> 0.042057543 | EI23: =ER23+EQ23 -> 0.1717379 | EJ23: =EK23-EI23 -> #VALUE! | EK23: =DV23 -> #VALUE! | EL23: =_xlfn.RRI(3,AK23,AN23) -> 0.11230341 | EM23: =_xlfn.RRI(3,BC23,BF23) -> 0.17597802 | EN23: {=_xll.BDP(B23,"AVG_DAILY_VALUE_TRADED_3M")/10^6} -> 353.2687 | EQ23: =IFERROR(AVERAGE(DP23:DQ23)/H23,0) -> 0 | ER23: =_xlfn.RRI(2+$DT$2,$DT$2*(BC23)+(1-$DT$2)*(BD23),(BF23)) -> 0.1717379 | ES23: =ER23-EG23+EQ23 -> 0.042057543 | EU23: =_xlfn.RRI(2+$DT$2,($DT$2*BY23+(1-$DT$2)*BZ23),CF23) -> #VALUE! | EV23: =EJ23-EU23 -> #VALUE! | FF23: 0.2 | FG23: -0.2 | FH23: =FF23-FG23 -> 0.4 | FI23: =FT23/CF23-1 -> 0.11111111 | FJ23: =FU23/CF23-1 -> -0.25925926 | FK23: =FI23-FJ23 -> 0.37037037 | FL23: =FF23+FG23 -> 0 | FM23: =FJ23+FI23 -> -0.14814815 | FN23: =EK23+FF23/3+FI23/3 -> #VALUE! | FO23: =EK23+FG23/3+FJ23/3 -> #VALUE! | FP23: =EK23+FL23/3+FM23/3 -> #VALUE! | FQ23: =EK23 -> #VALUE! | FR23: =FP23-FQ23 -> #VALUE! | FS23: =FN23-FO23 -> #VALUE! | FT23: 30 | FU23: 20 | FV23: Set Mendo EPS = adj EPS (SBC <3% revs)
B24: ABNB US EQUITY | D24: ABNB | E24: 2 | F24: 46068 | H24: {=_xll.BQL($B24, "px_last", "dates=" & _xll.BQL.DATE($D$2))} -> #N/A Connection | I24: {=_xll.BQL(""&B24&"", "CB_IS_ADJ_DILUTED_AVG_SHS/1M", "FPT=Q", "FPO=0Q", "ACT_EST_MAPPING=PRECISE", "FS=MRC", "CURRENCY=USD", "XLFILL=b")} -> 608 | J24: -11014 | K24: 1999 | M24: =K24+J24 -> -9015 | N24: =I24*H24+M24+L24 -> #VALUE! | O24: 8399 | P24: 9917 | Q24: 11102 | R24: 12241 | S24: 14053.594 | T24: 16049.272 | U24: 18609.378 | V24: 21261.992 | W24: 24229.01 | X24: =AG24/O24 -> 0.82154078 | Y24: =AH24/P24 -> 0.82827468 | Z24: =AI24/Q24 -> 0.83084129 | AA24: =AJ24/R24 -> 0.82958909 | AB24: =AK24/S24 -> 0.835 | AC24: =AL24/T24 -> 0.835 | AD24: =AM24/U24 -> 0.835 | AE24: =AN24/V24 -> 0.835 | AF24: =AO24/W24 -> 0.835 | AG24: 6900.121 | AH24: 8214 | AI24: 9224 | AJ24: 10155 | AK24: 11734.751 | AL24: 13401.142 | AM24: 15538.831 | AN24: 17753.763 | AO24: 20231.223 | AP24: 2.4164706 | AQ24: 3.778852 | AR24: 4.1484186 | AS24: 4.1236918 | AT24: 5.0392136 | AU24: 5.9367757 | AV24: 7.4716294 | AW24: 9.213803 | AX24: 11.370692 | AY24: =+AP24 -> 2.4164706 | AZ24: =+AQ24 -> 3.778852 | BA24: =+AR24 -> 4.1484186 | BB24: =+AS24 -> 4.1236918 | BC24: =+AT24 -> 5.0392136 | BD24: =+AU24 -> 5.9367757 | BE24: =+AV24 -> 7.4716294 | BF24: =+AW24 -> 9.213803 | BG24: =+AX24 -> 11.370692 | BH24: =$N24/Q24 -> #VALUE! | BI24: =$N24/R24 -> #VALUE! | BJ24: =$N24/S24 -> #VALUE! | BK24: =$N24/T24 -> #VALUE! | BL24: =$N24/U24 -> #VALUE! | BM24: =$N24/V24 -> #VALUE! | BN24: =$N24/W24 -> #VALUE! | BO24: =$N24/AK24 -> #VALUE! | BP24: =$N24/AL24 -> #VALUE! | BQ24: =$N24/AM24 -> #VALUE! | BR24: =$N24/AN24 -> #VALUE! | BS24: =$N24/AO24 -> #VALUE! | BT24: =$H24/AT24 -> #VALUE! | BU24: =$H24/AU24 -> #VALUE! | BV24: =$H24/AV24 -> #VALUE! | BW24: =$H24/AW24 -> #VALUE! | BX24: =$H24/AX24 -> #VALUE! | BY24: =$H24/BC24 -> #VALUE! | BZ24: =$H24/BD24 -> #VALUE! | CA24: =$H24/BE24 -> #VALUE! | CB24: =$H24/BF24 -> #VALUE! | CC24: =$H24/BG24 -> #VALUE! | CD24: 26 | CE24: 25 | CF24: 24 | CG24: 23 | CH24: 22 | CN24: =CD24*BD24 -> 154.35617 | CO24: =CE24*BE24 -> 186.79074 | CP24: =CF24*BF24 -> 221.13127 | CQ24: =CG24*BG24 -> 261.52592 | DC24: 602.94314 | DD24: 586.00672 | DE24: 568.52002 | DF24: 550.47103 | DG24: 532.31785 | DT24: =_xlfn.RRI(DT$2,$H24,CN24+$DO24*$DT$2) -> #VALUE! | DU24: =_xlfn.RRI(DU$2,$H24,CO24+$DO24*$DT$2+SUM($DP24:DP24)) -> #VALUE! | DV24: =_xlfn.RRI(DV$2,$H24,CP24+$DO24*$DT$2+SUM($DP24:DQ24)) -> #VALUE! | DW24: =_xlfn.RRI(DW$2,$H24,CQ24+$DO24*$DT$2+SUM($DP24:DR24)) -> #VALUE! | DX24: =SUM(CN24,$DO24:DO24)/$H24 -> #VALUE! | DY24: =SUM(CO24,$DO24:DP24)/$H24 -> #VALUE! | DZ24: =SUM(CP24,$DO24:DQ24)/$H24 -> #VALUE! | EA24: =SUM(CQ24,$DO24:DR24)/$H24 -> #VALUE! | EB24: {=_xll.BDP(""&$B24&"","CHG_PCT_1M")/100} -> -0.04088632 | EC24: {=_xll.BDP(""&$B24&"","CHG_PCT_3M")/100} -> 0.01857693 | ED24: {=_xll.BDP(""&$B24&"","CHG_PCT_6M")/100} -> 0.1122449 | EE24: =_xlfn.RRI(2+$DT$2,$DT$2*S24+(1-$DT$2)*T24,V24) -> 0.14804727 | EF24: =EG24-EE24 -> 0.044405115 | EG24: =_xlfn.RRI(2+$DT$2,$DT$2*(BC24*DC24)+(1-$DT$2)*(BD24*DD24),(BF24*DF24)) -> 0.19245239 | EH24: =EI24-EG24 -> 0.036630267 | EI24: =ER24+EQ24 -> 0.22908266 | EJ24: =EK24-EI24 -> #VALUE! | EK24: =DV24 -> #VALUE! | EL24: =_xlfn.RRI(3,AK24,AN24) -> 0.14799196 | EM24: =_xlfn.RRI(3,BC24,BF24) -> 0.22280926 | EN24: {=_xll.BDP(B24,"AVG_DAILY_VALUE_TRADED_3M")/10^6} -> 496.4881 | EQ24: =IFERROR(AVERAGE(DP24:DQ24)/H24,0) -> 0 | ER24: =_xlfn.RRI(2+$DT$2,$DT$2*(BC24)+(1-$DT$2)*(BD24),(BF24)) -> 0.22908266 | ES24: =ER24-EG24+EQ24 -> 0.036630267 | EU24: =_xlfn.RRI(2+$DT$2,($DT$2*BY24+(1-$DT$2)*BZ24),CF24) -> #VALUE! | EV24: =EJ24-EU24 -> #VALUE! | FF24: 0.25 | FG24: -0.1 | FH24: =FF24-FG24 -> 0.35 | FI24: =FT24/CF24-1 -> 0.25 | FJ24: =FU24/CF24-1 -> -0.16666667 | FK24: =FI24-FJ24 -> 0.41666667 | FL24: =FF24+FG24 -> 0.15 | FM24: =FJ24+FI24 -> 0.083333333 | FN24: =EK24+FF24/3+FI24/3 -> #VALUE! | FO24: =EK24+FG24/3+FJ24/3 -> #VALUE! | FP24: =EK24+FL24/3+FM24/3 -> #VALUE! | FQ24: =EK24 -> #VALUE! | FR24: =FP24-FQ24 -> #VALUE! | FS24: =FN24-FO24 -> #VALUE! | FT24: 30 | FU24: 20
D26: Profitable Software
B27: TOST US EQUITY | D27: TOST | E27: 1 | F27: 46119 | H27: {=_xll.BQL($B27, "px_last", "dates=" & _xll.BQL.DATE($D$2))} -> #N/A Connection | I27: 618 | J27: -1770 | K27: 0 | M27: =K27+J27 -> -1770 | N27: =I27*H27+M27+L27 -> #VALUE! | O27: =AG27/X27 -> 836.47059 | P27: =AH27/Y27 -> 1243.5294 | Q27: =AI27/Z27 -> 1667.0588 | R27: =AJ27/AA27 -> 2218.8235 | S27: =AK27/AB27 -> 2766.5202 | T27: =AL27/AC27 -> 3355.8447 | U27: =AM27/AD27 -> 3937.7108 | V27: =AN27/AE27 -> 4525.3813 | W27: =AO27/AF27 -> 5045.1777 | X27: 0.85 | Y27: 0.85 | Z27: 0.85 | AA27: 0.85 | AB27: 0.85 | AC27: 0.85 | AD27: 0.85 | AE27: 0.85 | AF27: 0.85 | AG27: 711 | AH27: 1057 | AI27: 1417 | AJ27: 1886 | AK27: 2351.5422 | AL27: 2852.468 | AM27: 3347.0542 | AN27: 3846.5741 | AO27: 4288.4011 | AS27: 1.0010953 | AT27: 1.2767033 | AU27: 1.5569278 | AV27: 2.0688851 | AW27: 2.6263593 | AX27: 3.0576893 | BB27: 0.50670326 | BC27: 0.76067462 | BD27: 1.0093958 | BE27: 1.4745156 | BF27: 2.0073512 | BG27: 2.5692709 | BO27: =$N27/AK27 -> #VALUE! | BP27: =$N27/AL27 -> #VALUE! | BQ27: =$N27/AM27 -> #VALUE! | BR27: =$N27/AN27 -> #VALUE! | BS27: =$N27/AO27 -> #VALUE! | BU27: =$H27/AU27 -> #VALUE! | BV27: =$H27/AV27 -> #VALUE! | BW27: =$H27/AW27 -> #VALUE! | BX27: =$H27/AX27 -> #VALUE! | BY27: =$H27/BC27 -> #VALUE! | BZ27: =$H27/BD27 -> #VALUE! | CA27: =$H27/BE27 -> #VALUE! | CB27: =$H27/BF27 -> #VALUE! | CC27: =$H27/BG27 -> #VALUE! | CD27: 22 | CE27: 22 | CF27: 22 | CG27: 22 | CH27: 25 | CI27: 48.482082 | CJ27: 56.855636 | CK27: 65.781378 | CL27: 75.385267 | CM27: 84.899722 | CN27: =CD27*BD27 -> 22.206707 | CO27: =CE27*BE27 -> 32.439344 | CP27: =CF27*BF27 -> 44.161726 | CQ27: =CG27*BG27 -> 56.52396 | CX27: =CD27*AL27 -> 62754.297 | CY27: =CE27*AM27 -> 73635.191 | CZ27: =CF27*AN27 -> 84624.631 | DA27: =CG27*AO27 -> 94344.824 | DC27: 609.22541 | DD27: 594.75401 | DE27: 577.90502 | DF27: 559.47181 | DG27: 540.01117 | DH27: -1991 | DI27: -1991 | DJ27: -1991 | DK27: -1991 | DT27: =_xlfn.RRI(DT$2,$H27,CN27+$DO27*$DT$2) -> #VALUE! | DU27: =_xlfn.RRI(DU$2,$H27,CO27+$DO27*$DT$2+SUM($DP27:DP27)) -> #VALUE! | DV27: =_xlfn.RRI(DV$2,$H27,CP27+$DO27*$DT$2+SUM($DP27:DQ27)) -> #VALUE! | DW27: =_xlfn.RRI(DW$2,$H27,CQ27+$DO27*$DT$2+SUM($DP27:DR27)) -> #VALUE! | DX27: =SUM(CN27,$DO27:DO27)/$H27 -> #VALUE! | DY27: =SUM(CO27,$DO27:DP27)/$H27 -> #VALUE! | DZ27: =SUM(CP27,$DO27:DQ27)/$H27 -> #VALUE! | EA27: =SUM(CQ27,$DO27:DR27)/$H27 -> #VALUE! | EB27: {=_xll.BDP(""&$B27&"","CHG_PCT_1M")/100} -> -0.02734528 | EC27: {=_xll.BDP(""&$B27&"","CHG_PCT_3M")/100} -> -0.1956091 | ED27: {=_xll.BDP(""&$B27&"","CHG_PCT_6M")/100} -> -0.2949942 | EE27: =_xlfn.RRI(2+$DT$2,$DT$2*S27+(1-$DT$2)*T27,V27) -> 0.17025048 | EF27: =EG27-EE27 -> 0.17697088 | EG27: =_xlfn.RRI(2+$DT$2,$DT$2*(BC27*DC27)+(1-$DT$2)*(BD27*DD27),(BF27*DF27)) -> 0.34722136 | EH27: =EI27-EG27 -> 0.038970334 | EI27: =ER27+EQ27 -> 0.3861917 | EJ27: =EK27-EI27 -> #VALUE! | EK27: =DV27 -> #VALUE! | EL27: =_xlfn.RRI(3,AK27,AN27) -> 0.17825813 | EM27: =_xlfn.RRI(3,BC27,BF27) -> 0.38189426 | EN27: {=_xll.BDP(B27,"AVG_DAILY_VALUE_TRADED_3M")/10^6} -> 297.08048 | EQ27: =IFERROR(AVERAGE(DP27:DQ27)/H27,0) -> 0 | ER27: =_xlfn.RRI(2+$DT$2,$DT$2*(BC27)+(1-$DT$2)*(BD27),(BF27)) -> 0.3861917 | ES27: =ER27-EG27+EQ27 -> 0.038970334 | EU27: =_xlfn.RRI(2+$DT$2,($DT$2*BY27+(1-$DT$2)*BZ27),CF27) -> #VALUE! | EX27: {=_xll.BQL("TOST US Equity", "IS_RECURRING_REVENUE/1M", "FPT=A", "FPr="&EX5&"", "ACT_EST_MAPPING=PRECISE", "FS=MRC", "CURRENCY=USD", "XLFILL=b")} -> 2321.5151 | EY27: {=_xll.BQL("TOST US Equity", "IS_RECURRING_REVENUE/1M", "FPT=A", "FPr="&EY5&"", "ACT_EST_MAPPING=PRECISE", "FS=MRC", "CURRENCY=USD", "XLFILL=b")} -> 2791.2219 | EZ27: {=_xll.BQL("TOST US Equity", "IS_RECURRING_REVENUE/1M", "FPT=A", "FPr="&EZ5&"", "ACT_EST_MAPPING=PRECISE", "FS=MRC", "CURRENCY=USD", "XLFILL=b")} -> 3340.2101 | FA27: {=_xll.BQL("TOST US Equity", "IS_RECURRING_REVENUE/1M", "FPT=A", "FPr="&FA5&"", "ACT_EST_MAPPING=PRECISE", "FS=MRC", "CURRENCY=USD", "XLFILL=b")} -> 4022.3883 | FB27: =AK27/EX27-1 -> 0.012934264 | FC27: =AL27/EY27-1 -> 0.021942392 | FD27: =AM27/EZ27-1 -> 0.0020490036 | FE27: =AN27/FA27-1 -> -0.043708899 | FF27: 0.08 | FG27: -0.08 | FH27: =FF27-FG27 -> 0.16 | FI27: =FT27/CF27-1 -> -0.54545455 | FJ27: =FU27/CF27-1 -> -0.77272727 | FK27: =FI27-FJ27 -> 0.22727273 | FL27: =FF27+FG27 -> 0 | FM27: =FJ27+FI27 -> -1.3181818 | FN27: =EK27+FF27/3+FI27/3 -> #VALUE! | FO27: =EK27+FG27/3+FJ27/3 -> #VALUE! | FP27: =EK27+FL27/3+FM27/3 -> #VALUE! | FQ27: =EK27 -> #VALUE! | FR27: =FP27-FQ27 -> #VALUE! | FS27: =FN27-FO27 -> #VALUE! | FT27: 10 | FU27: 5
B28: INTU US EQUITY | D28: INTU | F28: 45992 | H28: {=_xll.BQL($B28, "px_last", "dates=" & _xll.BQL.DATE($D$2))} -> #N/A Connection | I28: 282 | J28: -4552 | K28: 5973 | M28: =K28+J28 -> 1421 | N28: =I28*H28+M28+L28 -> #VALUE! | O28: 12726 | P28: 14368 | Q28: 16285 | R28: 18831 | S28: 21322.138 | T28: 23904.037 | U28: 26711.595 | V28: 29878.041 | W28: 33446.623 | X28: 0.8 | Y28: 0.8 | Z28: 0.8 | AA28: 0.8 | AB28: 0.8 | AC28: 0.8 | AD28: 0.8 | AE28: 0.8 | AF28: 0.8 | AG28: =X28*O28 -> 10180.8 | AH28: =Y28*P28 -> 11494.4 | AI28: =Z28*Q28 -> 13028 | AJ28: =AA28*R28 -> 15064.8 | AK28: =AB28*S28 -> 17057.711 | AL28: =AC28*T28 -> 19123.23 | AM28: =AD28*U28 -> 21369.276 | AN28: =AE28*V28 -> 23902.433 | AO28: =AF28*W28 -> 26757.298 | AP28: 12.918746 | AQ28: 15.468286 | AR28: 18.278392 | AS28: 21.815956 | AT28: 25.883023 | AU28: 30.30019 | AV28: 35.409788 | AW28: 41.409192 | AX28: 48.451255 | AY28: 9.9559585 | AZ28: 11.672446 | BA28: 13.820116 | BB28: 16.694312 | BC28: 19.970928 | BD28: 23.797055 | BE28: 28.119115 | BF28: 33.073899 | BG28: 38.910211 | BH28: =$N28/Q28 -> #VALUE! | BI28: =$N28/R28 -> #VALUE! | BJ28: =$N28/S28 -> #VALUE! | BK28: =$N28/T28 -> #VALUE! | BL28: =$N28/U28 -> #VALUE! | BM28: =$N28/V28 -> #VALUE! | BN28: =$N28/W28 -> #VALUE! | BO28: =$N28/AK28 -> #VALUE! | BP28: =$N28/AL28 -> #VALUE! | BQ28: =$N28/AM28 -> #VALUE! | BR28: =$N28/AN28 -> #VALUE! | BS28: =$N28/AO28 -> #VALUE! | BT28: =$H28/AT28 -> #VALUE! | BU28: =$H28/AU28 -> #VALUE! | BV28: =$H28/AV28 -> #VALUE! | BW28: =$H28/AW28 -> #VALUE! | BX28: =$H28/AX28 -> #VALUE! | BY28: =$H28/BC28 -> #VALUE! | BZ28: =$H28/BD28 -> #VALUE! | CA28: =$H28/BE28 -> #VALUE! | CB28: =$H28/BF28 -> #VALUE! | CC28: =$H28/BG28 -> #VALUE! | CD28: 20 | CE28: 20 | CF28: 20 | CG28: 20 | CH28: 25 | CI28: 642.52049 | CJ28: 759.2161 | CK28: 892.99527 | CL28: 1050.5757 | CM28: 1236.1776 | CN28: =CD28*BD28 -> 475.94111 | CO28: =CE28*BE28 -> 562.3823 | CP28: =CF28*BF28 -> 661.47798 | CQ28: =CG28*BG28 -> 778.20422 | DO28: 5.1453945 | DP28: 6.0235018 | DQ28: 7.0392602 | DR28: 8.2319068 | DS28: 9.631828 | DT28: =_xlfn.RRI(DT$2,$H28,CN28+$DO28*$DT$2) -> #VALUE! | DU28: =_xlfn.RRI(DU$2,$H28,CO28+$DO28*$DT$2+SUM($DP28:DP28)) -> #VALUE! | DV28: =_xlfn.RRI(DV$2,$H28,CP28+$DO28*$DT$2+SUM($DP28:DQ28)) -> #VALUE! | DW28: =_xlfn.RRI(DW$2,$H28,CQ28+$DO28*$DT$2+SUM($DP28:DR28)) -> #VALUE! | DX28: =SUM(CN28,$DO28:DO28)/$H28 -> #VALUE! | DY28: =SUM(CO28,$DO28:DP28)/$H28 -> #VALUE! | DZ28: =SUM(CP28,$DO28:DQ28)/$H28 -> #VALUE! | EA28: =SUM(CQ28,$DO28:DR28)/$H28 -> #VALUE! | EB28: {=_xll.BDP(""&$B28&"","CHG_PCT_1M")/100} -> -0.2362292 | EC28: {=_xll.BDP(""&$B28&"","CHG_PCT_3M")/100} -> -0.3709292 | ED28: {=_xll.BDP(""&$B28&"","CHG_PCT_6M")/100} -> -0.5387511 | EN28: {=_xll.BDP(B28,"AVG_DAILY_VALUE_TRADED_3M")/10^6} -> 1592.4419 | EQ28: =IFERROR(AVERAGE(DP28:DQ28)/H28,0) -> 0 | ER28: =_xlfn.RRI(2+$DT$2,$DT$2*(BC28)+(1-$DT$2)*(BD28),(BF28)) -> 0.17991029 | FF28: 0.15 | FG28: -0.2 | FH28: =FF28-FG28 -> 0.35 | FI28: =FT28/CF28-1 -> 0.4 | FJ28: =FU28/CF28-1 -> -0.2 | FK28: =FI28-FJ28 -> 0.6 | FL28: =FF28+FG28 -> -0.05 | FM28: =FJ28+FI28 -> 0.2 | FN28: =EK28+FF28/3+FI28/3 -> 0.18333333 | FO28: =EK28+FG28/3+FJ28/3 -> -0.13333333 | FP28: =EK28+FL28/3+FM28/3 -> 0.05 | FQ28: =EK28 -> 0 | FR28: =FP28-FQ28 -> 0.05 | FS28: =FN28-FO28 -> 0.31666667 | FT28: 28 | FU28: 16
B29: DSY FP EQUITY | D29: DSY FP | F29: 45990 | H29: {=_xll.BQL($B29, "px_last", "dates=" & _xll.BQL.DATE($D$2))} -> #N/A Connection | I29: 1328 | J29: -3910 | K29: =1145+1443 -> 2588 | L29: 5.5 | M29: =K29+J29 -> -1322 | N29: =I29*H29+M29+L29 -> #VALUE! | O29: 5665.5264 | P29: 5951.3991 | Q29: 6213.5794 | R29: 6239.5743 | S29: 6347.1428 | T29: 6759.7071 | U29: 7199.088 | V29: 7703.0242 | W29: 8242.2359 | X29: =AG29/O29 -> 0.83939679 | Y29: =AH29/P29 -> 0.83962637 | Z29: =AI29/Q29 -> 0.83914155 | AA29: =AJ29/R29 -> 0.84040683 | AB29: =AK29/S29 -> 0.84 | AC29: =AL29/T29 -> 0.84 | AD29: =AM29/U29 -> 0.84 | AE29: =AN29/V29 -> 0.84 | AF29: =AO29/W29 -> 0.84 | AG29: 4755.6246 | AH29: 4996.9517 | AI29: 5214.0726 | AJ29: 5243.7809 | AK29: 5331.5999 | AL29: 5678.1539 | AM29: 6047.2339 | AN29: 6470.5403 | AO29: 6923.4781 | AP29: 1.1346955 | AQ29: 1.1952827 | AR29: 1.2788021 | AS29: 1.3076858 | AT29: 1.3362693 | AU29: 1.4388746 | AV29: 1.5697438 | AW29: 1.7210109 | AX29: 1.8709969 | AY29: 1.0342553 | AZ29: 1.0492606 | BA29: 1.1293073 | BB29: 1.1523713 | BC29: 1.1791617 | BD29: 1.2729799 | BE29: 1.3930659 | BF29: 1.5366917 | BG29: 1.6737753 | BH29: =$N29/Q29 -> #VALUE! | BI29: =$N29/R29 -> #VALUE! | BJ29: =$N29/S29 -> #VALUE! | BK29: =$N29/T29 -> #VALUE! | BL29: =$N29/U29 -> #VALUE! | BM29: =$N29/V29 -> #VALUE! | BN29: =$N29/W29 -> #VALUE! | BO29: =$N29/AK29 -> #VALUE! | BP29: =$N29/AL29 -> #VALUE! | BQ29: =$N29/AM29 -> #VALUE! | BR29: =$N29/AN29 -> #VALUE! | BS29: =$N29/AO29 -> #VALUE! | BT29: =$H29/AT29 -> #VALUE! | BU29: =$H29/AU29 -> #VALUE! | BV29: =$H29/AV29 -> #VALUE! | BW29: =$H29/AW29 -> #VALUE! | BX29: =$H29/AX29 -> #VALUE! | BY29: =$H29/BC29 -> #VALUE! | BZ29: =$H29/BD29 -> #VALUE! | CA29: =$H29/BE29 -> #VALUE! | CB29: =$H29/BF29 -> #VALUE! | CC29: =$H29/BG29 -> #VALUE! | CD29: 18 | CE29: 18 | CF29: 18 | CG29: 18 | CH29: 20 | CI29: 39.85318 | CJ29: 45.040971 | CK29: 50.913963 | CL29: 56.580433 | CM29: 63.40104 | CN29: =CD29*BD29+CS29 -> 25.119171 | CO29: =CE29*BE29+CT29 -> 28.258535 | CP29: =CF29*BF29+CU29 -> 31.921218 | CQ29: =CG29*BG29+CV29 -> 35.585643 | CS29: 2.2055325 | CT29: 3.1833496 | CU29: 4.260768 | CV29: 5.457687 | CW29: 6.746216 | DC29: 1328.351 | DD29: 1328.351 | DE29: 1328.351 | DF29: 1328.351 | DG29: 1328.351 | DO29: 0.299 | DP29: 0.34385 | DQ29: 0.3954275 | DR29: 0.45474162 | DS29: 0.52295287 | DT29: =_xlfn.RRI(DT$2,$H29,CN29+$DO29*$DT$2) -> #VALUE! | DU29: =_xlfn.RRI(DU$2,$H29,CO29+$DO29*$DT$2+SUM($DP29:DP29)) -> #VALUE! | DV29: =_xlfn.RRI(DV$2,$H29,CP29+$DO29*$DT$2+SUM($DP29:DQ29)) -> #VALUE! | DW29: =_xlfn.RRI(DW$2,$H29,CQ29+$DO29*$DT$2+SUM($DP29:DR29)) -> #VALUE! | DX29: =SUM(CN29,$DO29:DO29)/$H29 -> #VALUE! | DY29: =SUM(CO29,$DO29:DP29)/$H29 -> #VALUE! | DZ29: =SUM(CP29,$DO29:DQ29)/$H29 -> #VALUE! | EA29: =SUM(CQ29,$DO29:DR29)/$H29 -> #VALUE! | EB29: {=_xll.BDP(""&$B29&"","CHG_PCT_1M")/100} -> 0.008186233 | EC29: {=_xll.BDP(""&$B29&"","CHG_PCT_3M")/100} -> 0.05177472 | ED29: {=_xll.BDP(""&$B29&"","CHG_PCT_6M")/100} -> -0.161846 | EE29: =_xlfn.RRI(2+$DT$2,$DT$2*S29+(1-$DT$2)*T29,V29) -> 0.066746894 | EF29: =EG29-EE29 -> 0.027441661 | EG29: =_xlfn.RRI(2+$DT$2,$DT$2*(BC29*DC29)+(1-$DT$2)*(BD29*DD29),(BF29*DF29)) -> 0.094188555 | EH29: =EI29-EG29 -> -2.220446e-16 | EI29: =ER29+EQ29 -> 0.094188555 | EJ29: =EK29-EI29 -> #VALUE! | EK29: =DV29 -> #VALUE! | EL29: =_xlfn.RRI(3,AK29,AN29) -> 0.066664065 | EM29: =_xlfn.RRI(3,BC29,BF29) -> 0.092289573 | EN29: {=_xll.BDP(B29,"AVG_DAILY_VALUE_TRADED_3M")/10^6} -> 50.92022 | EQ29: =IFERROR(AVERAGE(DP29:DQ29)/H29,0) -> 0 | ER29: =_xlfn.RRI(2+$DT$2,$DT$2*(BC29)+(1-$DT$2)*(BD29),(BF29)) -> 0.094188555 | ES29: =ER29-EG29+EQ29 -> -2.220446e-16 | EX29: {=_xll.BQL("DSY FP Equity", "IS_COMP_EPS_ADJUSTED_OLD", "FPT=A", "FPr="&EX$5&"", "ACT_EST_MAPPING=PRECISE", "FS=MRC", "CURRENCY=EUR", "XLFILL=b")} -> 1.3194737 | EY29: {=_xll.BQL("DSY FP Equity", "IS_COMP_EPS_ADJUSTED_OLD", "FPT=A", "FPr="&EY5&"", "ACT_EST_MAPPING=PRECISE", "FS=MRC", "CURRENCY=EUR", "XLFILL=b")} -> 1.3709091 | EZ29: {=_xll.BQL("DSY FP Equity", "IS_COMP_EPS_ADJUSTED_OLD", "FPT=A", "FPr="&EZ5&"", "ACT_EST_MAPPING=PRECISE", "FS=MRC", "CURRENCY=EUR", "XLFILL=b")} -> 1.4683333 | FA29: {=_xll.BQL("DSY FP Equity", "IS_COMP_EPS_ADJUSTED_OLD", "FPT=A", "FPr="&FA5&"", "ACT_EST_MAPPING=PRECISE", "FS=MRC", "CURRENCY=EUR", "XLFILL=b")} -> 1.565 | FB29: =AT29/EX29-1 -> 0.012729058 | FC29: =AU29/EY29-1 -> 0.049576988 | FD29: =AV29/EZ29-1 -> 0.069064996 | FE29: =AW29/FA29-1 -> 0.099687476 | FF29: 0.1 | FG29: -0.2 | FH29: =FF29-FG29 -> 0.3 | FI29: =FT29/CF29-1 -> 0.55555556 | FJ29: =FU29/CF29-1 -> -0.44444444 | FK29: =FI29-FJ29 -> 1 | FL29: =FF29+FG29 -> -0.1 | FM29: =FJ29+FI29 -> 0.11111111 | FN29: =EK29+FF29/3+FI29/3 -> #VALUE! | FO29: =EK29+FG29/3+FJ29/3 -> #VALUE! | FP29: =EK29+FL29/3+FM29/3 -> #VALUE! | FQ29: =EK29 -> #VALUE! | FR29: =FP29-FQ29 -> #VALUE! | FS29: =FN29-FO29 -> #VALUE! | FT29: 28 | FU29: 10
B30: ADSK US EQUITY | D30: ADSK | E30: 2 | F30: 45987 | H30: {=_xll.BQL($B30, "px_last", "dates=" & _xll.BQL.DATE($D$2))} -> #N/A Connection | I30: {=_xll.BQL(""&B30&"", "CB_IS_ADJ_DILUTED_AVG_SHS/1M", "FPT=Q", "FPO=0Q", "ACT_EST_MAPPING=PRECISE", "FS=MRC", "CURRENCY=USD", "XLFILL=b")} -> 212 | J30: -2236 | K30: 2481 | M30: =K30+J30 -> 245 | N30: =I30*H30+M30+L30 -> #VALUE! | O30: 5005 | P30: 5497 | Q30: 6131 | R30: 7163.5944 | S30: 8033.9295 | T30: 8899.6561 | U30: 9836.7868 | V30: 10567.906 | W30: 11329 | X30: =AG30/O30 -> 0.92387612 | Y30: =AH30/P30 -> 0.92414044 | Z30: =AI30/Q30 -> 0.92692872 | AA30: =AJ30/R30 -> 0.93948959 | AB30: =AK30/S30 -> 0.94497064 | AC30: =AL30/T30 -> 0.94634817 | AD30: =AM30/U30 -> 0.94773818 | AE30: =AN30/V30 -> 0.94773818 | AF30: =AO30/W30 -> 0.94773294 | AG30: 4624 | AH30: 5080 | AI30: 5683 | AJ30: 6730.1223 | AK30: 7591.8275 | AL30: 8422.1732 | AM30: 9322.6985 | AN30: 10015.608 | AO30: 10736.866 | AP30: 6.6284404 | AQ30: 7.6064815 | AR30: 8.4746544 | AS30: 10.251993 | AT30: 12.167684 | AU30: 14.53086 | AV30: 17.248806 | AW30: 19.883967 | AX30: 22.82 | AY30: 4.1156485 | AZ30: 4.9368078 | BA30: 5.9147191 | BB30: 7.5987971 | BC30: 9.4111836 | BD30: 11.687001 | BE30: 14.338177 | BF30: 16.764465 | BG30: 19.352084 | BH30: =$N30/Q30 -> #VALUE! | BI30: =$N30/R30 -> #VALUE! | BJ30: =$N30/S30 -> #VALUE! | BK30: =$N30/T30 -> #VALUE! | BL30: =$N30/U30 -> #VALUE! | BM30: =$N30/V30 -> #VALUE! | BN30: =$N30/W30 -> #VALUE! | BO30: =$N30/AK30 -> #VALUE! | BP30: =$N30/AL30 -> #VALUE! | BQ30: =$N30/AM30 -> #VALUE! | BR30: =$N30/AN30 -> #VALUE! | BS30: =$N30/AO30 -> #VALUE! | BT30: =$H30/AT30 -> #VALUE! | BU30: =$H30/AU30 -> #VALUE! | BV30: =$H30/AV30 -> #VALUE! | BW30: =$H30/AW30 -> #VALUE! | BX30: =$H30/AX30 -> #VALUE! | BY30: =$H30/BC30 -> #VALUE! | BZ30: =$H30/BD30 -> #VALUE! | CA30: =$H30/BE30 -> #VALUE! | CB30: =$H30/BF30 -> #VALUE! | CC30: =$H30/BG30 -> #VALUE! | CD30: 24 | CE30: 22 | CF30: 22 | CG30: 22 | CH30: 24 | CI30: 361.37 | CJ30: 384.69775 | CK30: 448.42554 | CL30: 516.21179 | CM30: 591.48334 | CN30: =CD30*BD30 -> 280.48802 | CO30: =CE30*BE30 -> 315.4399 | CP30: =CF30*BF30 -> 368.81823 | CQ30: =CG30*BG30 -> 425.74584 | CX30: =CN30*DC30+DH30 -> 58480.992 | CY30: =CO30*DD30+DI30 -> 63574.478 | CZ30: =CP30*DE30+DJ30 -> 71704.385 | DA30: =CQ30*DF30+DK30 -> 79757.513 | DC30: 207.80921 | DD30: 200.93044 | DE30: 193.8933 | DF30: 186.88266 | DG30: 180.09898 | DH30: 193 | DI30: 193 | DJ30: 193 | DK30: 193 | DL30: 193 | DT30: =_xlfn.RRI(DT$2,$H30,CN30+$DO30*$DT$2) -> #VALUE! | DU30: =_xlfn.RRI(DU$2,$H30,CO30+$DO30*$DT$2+SUM($DP30:DP30)) -> #VALUE! | DV30: =_xlfn.RRI(DV$2,$H30,CP30+$DO30*$DT$2+SUM($DP30:DQ30)) -> #VALUE! | DW30: =_xlfn.RRI(DW$2,$H30,CQ30+$DO30*$DT$2+SUM($DP30:DR30)) -> #VALUE! | DX30: =SUM(CN30,$DO30:DO30)/$H30 -> #VALUE! | DY30: =SUM(CO30,$DO30:DP30)/$H30 -> #VALUE! | DZ30: =SUM(CP30,$DO30:DQ30)/$H30 -> #VALUE! | EA30: =SUM(CQ30,$DO30:DR30)/$H30 -> #VALUE! | EB30: {=_xll.BDP(""&$B30&"","CHG_PCT_1M")/100} -> -0.06809816 | EC30: {=_xll.BDP(""&$B30&"","CHG_PCT_3M")/100} -> -0.126978 | ED30: {=_xll.BDP(""&$B30&"","CHG_PCT_6M")/100} -> -0.2440028 | EE30: =_xlfn.RRI(2+$DT$2,$DT$2*S30+(1-$DT$2)*T30,V30) -> 0.093067221 | EF30: =EG30-EE30 -> 0.069927881 | EG30: =_xlfn.RRI(2+$DT$2,$DT$2*(BC30*DC30)+(1-$DT$2)*(BD30*DD30),(BF30*DF30)) -> 0.1629951 | EH30: =EI30-EG30 -> 0.041452889 | EI30: =ER30+EQ30 -> 0.20444799 | EJ30: =EK30-EI30 -> #VALUE! | EK30: =DV30 -> #VALUE! | EL30: =_xlfn.RRI(3,AK30,AN30) -> 0.096756779 | EM30: =_xlfn.RRI(3,BC30,BF30) -> 0.21222104 | EN30: {=_xll.BDP(B30,"AVG_DAILY_VALUE_TRADED_3M")/10^6} -> 502.27158 | EQ30: =IFERROR(AVERAGE(DP30:DQ30)/H30,0) -> 0 | ER30: =_xlfn.RRI(2+$DT$2,$DT$2*(BC30)+(1-$DT$2)*(BD30),(BF30)) -> 0.20444799 | ES30: =ER30-EG30+EQ30 -> 0.041452889 | EX30: {=_xll.BQL("ADSK US Equity", "IS_COMP_EPS_EXCL_STOCK_COMP", "FPT=A", "FPr="&EX$5+1&"", "ACT_EST_MAPPING=PRECISE", "FS=MRC", "CURRENCY=USD", "XLFILL=b")} -> 12.595172 | EY30: {=_xll.BQL("ADSK US Equity", "IS_COMP_EPS_EXCL_STOCK_COMP", "FPT=A", "FPr="&EY$5+1&"", "ACT_EST_MAPPING=PRECISE", "FS=MRC", "CURRENCY=USD", "XLFILL=b")} -> 14.222069 | EZ30: {=_xll.BQL("ADSK US Equity", "IS_COMP_EPS_EXCL_STOCK_COMP", "FPT=A", "FPr="&EZ$5+1&"", "ACT_EST_MAPPING=PRECISE", "FS=MRC", "CURRENCY=USD", "XLFILL=b")} -> 16.182857 | FA30: {=_xll.BQL("ADSK US Equity", "IS_COMP_EPS_EXCL_STOCK_COMP", "FPT=A", "FPr="&FA$5+1&"", "ACT_EST_MAPPING=PRECISE", "FS=MRC", "CURRENCY=USD", "XLFILL=b")} -> 18.3825 | FB30: =AT30/EX30-1 -> -0.033940633 | FC30: =AU30/EY30-1 -> 0.0217121 | FD30: =AV30/EZ30-1 -> 0.065869035 | FE30: =AW30/FA30-1 -> 0.081679175 | FF30: 0.15 | FG30: -0.15 | FH30: =FF30-FG30 -> 0.3 | FI30: =FT30/CF30-1 -> 0.27272727 | FJ30: =FU30/CF30-1 -> -0.27272727 | FK30: =FI30-FJ30 -> 0.54545455 | FL30: =FF30+FG30 -> 0 | FM30: =FJ30+FI30 -> 0 | FN30: =EK30+FF30/3+FI30/3 -> #VALUE! | FO30: =EK30+FG30/3+FJ30/3 -> #VALUE! | FP30: =EK30+FL30/3+FM30/3 -> #VALUE! | FQ30: =EK30 -> #VALUE! | FR30: =FP30-FQ30 -> #VALUE! | FS30: =FN30-FO30 -> #VALUE! | FT30: 28 | FU30: 16
B31: CRM US EQUITY | D31: CRM | F31: 45901 | H31: {=_xll.BQL($B31, "px_last", "dates=" & _xll.BQL.DATE($D$2))} -> #N/A Connection | I31: {=_xll.BQL(""&B31&"", "CB_IS_ADJ_DILUTED_AVG_SHS/1M", "FPT=Q", "FPO=0Q", "ACT_EST_MAPPING=PRECISE", "FS=MRC", "CURRENCY=USD", "XLFILL=b")} -> 871 | J31: -11323 | K31: 8438 | M31: =K31+J31 -> -2885 | N31: =I31*H31+M31+L31 -> #VALUE! | O31: 31352 | P31: 34857 | Q31: 37895 | R31: 41116.075 | S31: 44405.361 | T31: 47735.763 | U31: 51077.266 | V31: 54397.289 | W31: 57661.126 | X31: =AG31/O31 -> 0.78227864 | Y31: =AH31/P31 -> 0.7953926 | Z31: =AI31/Q31 -> 0.8053833 | AA31: =AJ31/R31 -> 0.8103833 | AB31: =AK31/S31 -> 0.8153833 | AC31: =AL31/T31 -> 0.8203833 | AD31: =AM31/U31 -> 0.8253833 | AE31: =AN31/V31 -> 0.8303833 | AF31: =AO31/W31 -> 0.8353833 | AG31: 24526 | AH31: 27725 | AI31: 30520 | AJ31: 33319.78 | AK31: 36207.39 | AL31: 39161.623 | AM31: 42158.323 | AN31: 45170.6 | AO31: 48169.142 | AP31: 5.2397192 | AQ31: 8.2184959 | AR31: 10.195072 | AS31: 11.443809 | AT31: 13.152691 | AU31: 14.993792 | AV31: 16.873157 | AW31: 18.777427 | AX31: 20.662041 | AY31: 2.6902649 | AZ31: 6.0517238 | BA31: 7.6461037 | BB31: 8.6561327 | BC31: 10.182366 | BD31: 11.748809 | BE31: 13.351341 | BF31: 14.975576 | BG31: 16.581744 | BO31: =$N31/AK31 -> #VALUE! | BP31: =$N31/AL31 -> #VALUE! | BQ31: =$N31/AM31 -> #VALUE! | BR31: =$N31/AN31 -> #VALUE! | BS31: =$N31/AO31 -> #VALUE! | BT31: =$H31/AT31 -> #VALUE! | BU31: =$H31/AU31 -> #VALUE! | BV31: =$H31/AV31 -> #VALUE! | BW31: =$H31/AW31 -> #VALUE! | BX31: =$H31/AX31 -> #VALUE! | BY31: =$H31/BC31 -> #VALUE! | BZ31: =$H31/BD31 -> #VALUE! | CA31: =$H31/BE31 -> #VALUE! | CB31: =$H31/BF31 -> #VALUE! | CC31: =$H31/BG31 -> #VALUE! | CD31: 20 | CE31: 20 | CF31: 20 | CG31: 20 | CH31: 25 | CI31: 293.72022 | CJ31: 333.78352 | CK31: 374.38941 | CL31: 414.54359 | CM31: 453.06826 | CN31: =CD31*BD31 -> 234.97618 | CO31: =CE31*BE31 -> 267.02682 | CP31: =CF31*BF31 -> 299.51152 | CQ31: =CG31*BG31 -> 331.63487 | DC31: 944.51985 | DD31: 917.9435 | DE31: 893.68138 | DF31: 870.50523 | DG31: 848.74384 | DO31: 1.84 | DP31: 2.116 | DQ31: 2.4334 | DR31: 2.79841 | DS31: 3.2181715 | DT31: =_xlfn.RRI(DT$2,$H31,CN31+$DO31*$DT$2) -> #VALUE! | DU31: =_xlfn.RRI(DU$2,$H31,CO31+$DO31*$DT$2+SUM($DP31:DP31)) -> #VALUE! | DV31: =_xlfn.RRI(DV$2,$H31,CP31+$DO31*$DT$2+SUM($DP31:DQ31)) -> #VALUE! | DW31: =_xlfn.RRI(DW$2,$H31,CQ31+$DO31*$DT$2+SUM($DP31:DR31)) -> #VALUE! | DX31: =SUM(CN31,$DO31:DO31)/$H31 -> #VALUE! | DY31: =SUM(CO31,$DO31:DP31)/$H31 -> #VALUE! | DZ31: =SUM(CP31,$DO31:DQ31)/$H31 -> #VALUE! | EA31: =SUM(CQ31,$DO31:DR31)/$H31 -> #VALUE! | EB31: {=_xll.BDP(""&$B31&"","CHG_PCT_1M")/100} -> 0.00989986 | EC31: {=_xll.BDP(""&$B31&"","CHG_PCT_3M")/100} -> -0.09148484 | ED31: {=_xll.BDP(""&$B31&"","CHG_PCT_6M")/100} -> -0.2924903 | EE31: =_xlfn.RRI(2+$DT$2,$DT$2*S31+(1-$DT$2)*T31,V31) -> 0.068861305 | EF31: =EG31-EE31 -> 0.034633753 | EG31: =_xlfn.RRI(2+$DT$2,$DT$2*(BC31*DC31)+(1-$DT$2)*(BD31*DD31),(BF31*DF31)) -> 0.10349506 | EH31: =EI31-EG31 -> 0.029762229 | EI31: =ER31+EQ31 -> 0.13325729 | EJ31: =EK31-EI31 -> #VALUE! | EK31: =DV31 -> #VALUE! | EN31: {=_xll.BDP(B31,"AVG_DAILY_VALUE_TRADED_3M")/10^6} -> 2599.9004 | EQ31: =IFERROR(AVERAGE(DP31:DQ31)/H31,0) -> 0 | ER31: =_xlfn.RRI(2+$DT$2,$DT$2*(BC31)+(1-$DT$2)*(BD31),(BF31)) -> 0.13325729 | ES31: =ER31-EG31+EQ31 -> 0.029762229 | EX31: {=_xll.BQL("CRM US Equity", "IS_COMP_EPS_EXCL_STOCK_COMP", "FPT=A", "FPr="&EX$5+1&"", "ACT_EST_MAPPING=PRECISE", "FS=MRC", "CURRENCY=USD", "XLFILL=b")} -> 14.105676 | EY31: {=_xll.BQL("CRM US Equity", "IS_COMP_EPS_EXCL_STOCK_COMP", "FPT=A", "FPr="&EY$5+1&"", "ACT_EST_MAPPING=PRECISE", "FS=MRC", "CURRENCY=USD", "XLFILL=b")} -> 15.586304 | EZ31: {=_xll.BQL("CRM US Equity", "IS_COMP_EPS_EXCL_STOCK_COMP", "FPT=A", "FPr="&EZ$5+1&"", "ACT_EST_MAPPING=PRECISE", "FS=MRC", "CURRENCY=USD", "XLFILL=b")} -> 18.108824 | FA31: {=_xll.BQL("CRM US Equity", "IS_COMP_EPS_EXCL_STOCK_COMP", "FPT=A", "FPr="&FA$5+1&"", "ACT_EST_MAPPING=PRECISE", "FS=MRC", "CURRENCY=USD", "XLFILL=b")} -> 21.228333 | FB31: =AT31/EX31-1 -> -0.067560387 | FC31: =AU31/EY31-1 -> -0.03801491 | FD31: =AV31/EZ31-1 -> -0.068235631 | FE31: =AW31/FA31-1 -> -0.11545448 | FF31: 0.15 | FG31: -0.2 | FH31: =FF31-FG31 -> 0.35 | FI31: =FT31/CF31-1 -> 0.2 | FJ31: =FU31/CF31-1 -> -0.2 | FK31: =FI31-FJ31 -> 0.4 | FL31: =FF31+FG31 -> -0.05 | FM31: =FJ31+FI31 -> 0 | FN31: =EK31+FF31/3+FI31/3 -> #VALUE! | FO31: =EK31+FG31/3+FJ31/3 -> #VALUE! | FP31: =EK31+FL31/3+FM31/3 -> #VALUE! | FQ31: =EK31 -> #VALUE! | FR31: =FP31-FQ31 -> #VALUE! | FS31: =FN31-FO31 -> #VALUE! | FT31: 24 | FU31: 16
B32: PTC US EQUITY | D32: PTC | F32: 46138 | H32: {=_xll.BQL($B32, "px_last", "dates=" & _xll.BQL.DATE($D$2))} -> #N/A Connection | I32: {=_xll.BQL(""&B32&"", "CB_IS_ADJ_DILUTED_AVG_SHS/1M", "FPT=Q", "FPO=0Q", "ACT_EST_MAPPING=PRECISE", "FS=MRC", "CURRENCY=USD", "XLFILL=b")} -> 118.553 | J32: -184 | K32: 1197 | M32: =K32+J32 -> 1013 | N32: =I32*H32+M32+L32 -> #VALUE! | O32: 1861.1391 | P32: 2236.1145 | Q32: 2491.0171 | R32: 2655.7864 | S32: 2827.0572 | T32: 3052.9133 | U32: 3290.7754 | V32: 3528.6714 | W32: 3772.9895 | X32: =AG32/O32 -> 0.8185912 | Y32: =AH32/P32 -> 0.82807768 | Z32: =AI32/Q32 -> 0.84503207 | AA32: =AJ32/R32 -> 0.85350513 | AB32: =AK32/S32 -> 0.86080426 | AC32: =AL32/T32 -> 0.86355093 | AD32: =AM32/U32 -> 0.86611888 | AE32: =AN32/V32 -> 0.86841731 | AF32: =AO32/W32 -> 0.87054286 | AG32: 1523.5121 | AH32: 1851.6765 | AI32: 2104.9893 | AJ32: 2266.7274 | AK32: 2433.5428 | AL32: 2636.3462 | AM32: 2850.2027 | AN32: 3064.3594 | AO32: 3284.549 | AR32: 6.1778349 | AS32: 7.3437059 | AT32: 8.3307984 | AU32: 9.6036502 | AV32: 11.021449 | AW32: 12.541703 | AX32: 14.197943 | BA32: 4.7460842 | BB32: 5.8959029 | BC32: 6.7020629 | BD32: 7.8675808 | BE32: 9.1719798 | BF32: 10.574944 | BG32: 12.10871 | BH32: =$N32/Q32 -> #VALUE! | BI32: =$N32/R32 -> #VALUE! | BJ32: =$N32/S32 -> #VALUE! | BK32: =$N32/T32 -> #VALUE! | BL32: =$N32/U32 -> #VALUE! | BM32: =$N32/V32 -> #VALUE! | BN32: =$N32/W32 -> #VALUE! | BO32: =$N32/AK32 -> #VALUE! | BP32: =$N32/AL32 -> #VALUE! | BQ32: =$N32/AM32 -> #VALUE! | BR32: =$N32/AN32 -> #VALUE! | BS32: =$N32/AO32 -> #VALUE! | BT32: =$H32/AT32 -> #VALUE! | BU32: =$H32/AU32 -> #VALUE! | BV32: =$H32/AV32 -> #VALUE! | BW32: =$H32/AW32 -> #VALUE! | BX32: =$H32/AX32 -> #VALUE! | BY32: =$H32/BC32 -> #VALUE! | BZ32: =$H32/BD32 -> #VALUE! | CA32: =$H32/BE32 -> #VALUE! | CB32: =$H32/BF32 -> #VALUE! | CC32: =$H32/BG32 -> #VALUE! | CD32: 22 | CE32: 22 | CF32: 22 | CG32: 22 | CH32: 27 | CI32: 212.87636 | CJ32: 248.9981 | CK32: 289.89951 | CL32: 335.0295 | CM32: 384.35626 | CN32: =CD32*BD32 -> 173.08678 | CO32: =CE32*BE32 -> 201.78356 | CP32: =CF32*BF32 -> 232.64877 | CQ32: =CG32*BG32 -> 266.39161 | DC32: 119.26326 | DD32: 115.58227 | DE32: 111.99245 | DF32: 108.44729 | DG32: 104.9872 | DT32: =_xlfn.RRI(DT$2,$H32,CN32+$DO32*$DT$2) -> #VALUE! | DU32: =_xlfn.RRI(DU$2,$H32,CO32+$DO32*$DT$2+SUM($DP32:DP32)) -> #VALUE! | DV32: =_xlfn.RRI(DV$2,$H32,CP32+$DO32*$DT$2+SUM($DP32:DQ32)) -> #VALUE! | DW32: =_xlfn.RRI(DW$2,$H32,CQ32+$DO32*$DT$2+SUM($DP32:DR32)) -> #VALUE! | DX32: =SUM(CN32,$DO32:DO32)/$H32 -> #VALUE! | DY32: =SUM(CO32,$DO32:DP32)/$H32 -> #VALUE! | DZ32: =SUM(CP32,$DO32:DQ32)/$H32 -> #VALUE! | EA32: =SUM(CQ32,$DO32:DR32)/$H32 -> #VALUE! | EB32: {=_xll.BDP(""&$B32&"","CHG_PCT_1M")/100} -> -0.05912032 | EC32: {=_xll.BDP(""&$B32&"","CHG_PCT_3M")/100} -> -0.1519882 | ED32: {=_xll.BDP(""&$B32&"","CHG_PCT_6M")/100} -> -0.2088757 | EE32: =_xlfn.RRI(2+$DT$2,$DT$2*S32+(1-$DT$2)*T32,V32) -> 0.075836601 | EF32: =EG32-EE32 -> 0.049450629 | EG32: =_xlfn.RRI(2+$DT$2,$DT$2*(BC32*DC32)+(1-$DT$2)*(BD32*DD32),(BF32*DF32)) -> 0.12528723 | EH32: =EI32-EG32 -> 0.035787998 | EI32: =ER32+EQ32 -> 0.16107523 | EJ32: =EK32-EI32 -> #VALUE! | EK32: =DV32 -> #VALUE! | EN32: {=_xll.BDP(B32,"AVG_DAILY_VALUE_TRADED_3M")/10^6} -> 187.60654 | EQ32: =IFERROR(AVERAGE(DP32:DQ32)/H32,0) -> 0 | ER32: =_xlfn.RRI(2+$DT$2,$DT$2*(BC32)+(1-$DT$2)*(BD32),(BF32)) -> 0.16107523 | ES32: =ER32-EG32+EQ32 -> 0.035787998 | FF32: 0.15 | FG32: -0.15 | FH32: =FF32-FG32 -> 0.3 | FI32: =FT32/CF32-1 -> 0.27272727 | FJ32: =FU32/CF32-1 -> -0.27272727 | FK32: =FI32-FJ32 -> 0.54545455 | FL32: =FF32+FG32 -> 0 | FM32: =FJ32+FI32 -> 0 | FN32: =EK32+FF32/3+FI32/3 -> #VALUE! | FO32: =EK32+FG32/3+FJ32/3 -> #VALUE! | FP32: =EK32+FL32/3+FM32/3 -> #VALUE! | FQ32: =EK32 -> #VALUE! | FR32: =FP32-FQ32 -> #VALUE! | FS32: =FN32-FO32 -> #VALUE! | FT32: 28 | FU32: 16
D34: Other TMT
B35: MCHP US Equity | D35: MCHP | F35: 46178 | H35: {=_xll.BQL($B35, "px_last", "dates=" & _xll.BQL.DATE($D$2))} -> #N/A Connection | I35: 566.41788 | J35: =250.7*-1 -> -250.7 | K35: 5366 | M35: =K35+J35 -> 5115.3 | N35: =I35*H35+M35+L35 -> #VALUE! | O35: 8034.25 | P35: 7835.475 | Q35: 5209.8 | R35: 4599.9 | S35: 6199.0237 | T35: 8312.9434 | U35: 9651.2011 | V35: 10781.433 | W35: 12070.706 | X35: 0.67396459 | Y35: 0.66370896 | Z35: 0.60247034 | AA35: 0.55885998 | AB35: 0.62195589 | AC35: 0.65893348 | AD35: 0.66429479 | AE35: 0.66427658 | AF35: 0.6645676 | AG35: =X35*O35 -> 5414.8 | AH35: =Y35*P35 -> 5200.475 | AI35: =Z35*Q35 -> 3138.75 | AJ35: =AA35*R35 -> 2570.7 | AK35: =AB35*S35 -> 3855.5193 | AL35: =AC35*T35 -> 5477.6767 | AM35: =AD35*U35 -> 6411.2427 | AN35: =AE35*V35 -> 7161.8534 | AO35: =AF35*W35 -> 8021.8003 | AP35: 5.6675 | AQ35: 5.195 | AR35: 2.2125 | AS35: 1.3390053 | AT35: 2.8019299 | AU35: 4.7126412 | AV35: 6.0345283 | AW35: 7.205767 | AX35: 8.6296823 | AY35: 5.3437188 | AZ35: 4.8767739 | BA35: 1.842976 | BB35: 0.96454558 | BC35: 2.3672252 | BD35: 4.1978889 | BE35: 5.4574906 | BF35: 6.5688594 | BG35: 7.923145 | BH35: =$N35/Q35 -> #VALUE! | BI35: =$N35/R35 -> #VALUE! | BJ35: =$N35/S35 -> #VALUE! | BK35: =$N35/T35 -> #VALUE! | BL35: =$N35/U35 -> #VALUE! | BM35: =$N35/V35 -> #VALUE! | BN35: =$N35/W35 -> #VALUE! | BO35: =$N35/AK35 -> #VALUE! | BP35: =$N35/AL35 -> #VALUE! | BQ35: =$N35/AM35 -> #VALUE! | BR35: =$N35/AN35 -> #VALUE! | BS35: =$N35/AO35 -> #VALUE! | BT35: =$H35/AT35 -> #VALUE! | BU35: =$H35/AU35 -> #VALUE! | BV35: =$H35/AV35 -> #VALUE! | BW35: =$H35/AW35 -> #VALUE! | BX35: =$H35/AX35 -> #VALUE! | BY35: =$H35/BC35 -> #VALUE! | BZ35: =$H35/BD35 -> #VALUE! | CA35: =$H35/BE35 -> #VALUE! | CB35: =$H35/BF35 -> #VALUE! | CC35: =$H35/BG35 -> #VALUE! | CD35: 20 | CE35: =CD35 -> 20 | CF35: =CE35 -> 20 | CG35: =CF35 -> 20 | CH35: =CG35 -> 20 | CN35: =CD35*BD35+CS35 -> 83.957777 | CO35: =CE35*BE35+CT35 -> 109.14981 | CP35: =CF35*BF35+CU35 -> 131.37719 | CQ35: =CG35*BG35+CV35 -> 158.4629 | DC35: 542.5 | DD35: 542.5 | DE35: 548.77315 | DF35: 536.25053 | DG35: 515.4615 | DH35: 4713.1888 | DI35: 3790.7846 | DJ35: 3655.0317 | DK35: 3700 | DL35: 3700 | DO35: 1.9522 | DP35: 2.14742 | DQ35: 2.362162 | DR35: 2.5983782 | DS35: 2.858216 | DT35: =_xlfn.RRI(DT$2,$H35,CN35+$DO35*$DT$2) -> #VALUE! | DU35: =_xlfn.RRI(DU$2,$H35,CO35+$DO35*$DT$2+SUM($DP35:DP35)) -> #VALUE! | DV35: =_xlfn.RRI(DV$2,$H35,CP35+$DO35*$DT$2+SUM($DP35:DQ35)) -> #VALUE! | DW35: =_xlfn.RRI(DW$2,$H35,CQ35+$DO35*$DT$2+SUM($DP35:DR35)) -> #VALUE! | DX35: =SUM(CN35,$DO35:DO35)/$H35 -> #VALUE! | DY35: =SUM(CO35,$DO35:DP35)/$H35 -> #VALUE! | DZ35: =SUM(CP35,$DO35:DQ35)/$H35 -> #VALUE! | EA35: =SUM(CQ35,$DO35:DR35)/$H35 -> #VALUE! | EB35: {=_xll.BDP(""&$B35&"","CHG_PCT_1M")/100} -> -0.07538598 | EC35: {=_xll.BDP(""&$B35&"","CHG_PCT_3M")/100} -> 0.4145438 | ED35: {=_xll.BDP(""&$B35&"","CHG_PCT_6M")/100} -> 0.3603564 | EE35: =_xlfn.RRI(2+$DT$2,$DT$2*S35+(1-$DT$2)*T35,V35) -> 0.17529349 | EF35: =EG35-EE35 -> 0.14733999 | EG35: =_xlfn.RRI(2+$DT$2,$DT$2*(BC35*DC35)+(1-$DT$2)*(BD35*DD35),(BF35*DF35)) -> 0.32263348 | EH35: =EI35-EG35 -> 0.0060024152 | EI35: =ER35+EQ35 -> 0.32863589 | EJ35: =EK35-EI35 -> #VALUE! | EK35: =DV35 -> #VALUE! | EL35: =_xlfn.RRI(3,AK35,AN35) -> 0.22927066 | EM35: =_xlfn.RRI(3,BC35,BF35) -> 0.40523879 | EN35: {=_xll.BDP(B35,"AVG_DAILY_VALUE_TRADED_3M")/10^6} -> 848.85549 | EQ35: =IFERROR(AVERAGE(DP35:DQ35)/H35,0) -> 0 | ER35: =_xlfn.RRI(2+$DT$2,$DT$2*(BC35)+(1-$DT$2)*(BD35),(BF35)) -> 0.32863589 | FF35: 0.3 | FG35: -0.15 | FH35: =FF35-FG35 -> 0.45 | FI35: =FT35/CF35-1 -> 0.3 | FJ35: =FU35/CF35-1 -> -0.3 | FK35: =FI35-FJ35 -> 0.6 | FL35: =FF35+FG35 -> 0.15 | FM35: =FJ35+FI35 -> 0 | FN35: =EK35+FF35/3+FI35/3 -> #VALUE! | FO35: =EK35+FG35/3+FJ35/3 -> #VALUE! | FP35: =EK35+FL35/3+FM35/3 -> #VALUE! | FQ35: =EK35 -> #VALUE! | FR35: =FP35-FQ35 -> #VALUE! | FS35: =FN35-FO35 -> #VALUE! | FT35: 26 | FU35: 14
B36: SU FP Equity | D36: SU FP | E36: 2 | F36: 46119 | H36: {=_xll.BQL($B36, "px_last", "dates=" & _xll.BQL.DATE($D$2))} -> #N/A Connection | I36: 571 | J36: -256 | K36: 4634 | M36: =K36+J36 -> 4378 | N36: =I36*H36+M36+L36 -> #VALUE! | O36: 34176 | P36: 35902 | Q36: 38153 | R36: 40152 | S36: 43106.592 | T36: 47244.825 | U36: 51166.145 | V36: 54594.277 | W36: 57596.962 | X36: =AG36/O36 -> 0.40601592 | Y36: =AH36/P36 -> 0.41813827 | Z36: =AI36/Q36 -> 0.42638849 | AA36: =AJ36/R36 -> 0.42077605 | AB36: =AK36/S36 -> 0.42327605 | AC36: =AL36/T36 -> 0.42577605 | AD36: =AM36/U36 -> 0.42827605 | AE36: =AN36/V36 -> 0.43077605 | AF36: =AO36/W36 -> 0.43327605 | AG36: 13876 | AH36: 15012 | AI36: 16268 | AJ36: 16895 | AK36: 18245.988 | AL36: 20115.715 | AM36: 21913.235 | AN36: 23517.907 | AO36: 24955.384 | AP36: =AY36 -> 7.3353245 | AQ36: =AZ36 -> 7.4291706 | AR36: =BA36 -> 8.4292358 | AS36: =BB36 -> 8.7645962 | AT36: =BC36 -> 10.118098 | AU36: =BD36 -> 11.686461 | AV36: =BE36 -> 13.168168 | AW36: =BF36 -> 14.56301 | AX36: =BG36 -> 15.956887 | AY36: 7.3353245 | AZ36: 7.4291706 | BA36: 8.4292358 | BB36: 8.7645962 | BC36: 10.118098 | BD36: 11.686461 | BE36: 13.168168 | BF36: 14.56301 | BG36: 15.956887 | BH36: =$N36/Q36 -> #VALUE! | BI36: =$N36/R36 -> #VALUE! | BJ36: =$N36/S36 -> #VALUE! | BK36: =$N36/T36 -> #VALUE! | BL36: =$N36/U36 -> #VALUE! | BM36: =$N36/V36 -> #VALUE! | BN36: =$N36/W36 -> #VALUE! | BO36: =$N36/AK36 -> #VALUE! | BP36: =$N36/AL36 -> #VALUE! | BQ36: =$N36/AM36 -> #VALUE! | BR36: =$N36/AN36 -> #VALUE! | BS36: =$N36/AO36 -> #VALUE! | BY36: =$H36/BC36 -> #VALUE! | BZ36: =$H36/BD36 -> #VALUE! | CA36: =$H36/BE36 -> #VALUE! | CB36: =$H36/BF36 -> #VALUE! | CC36: =$H36/BG36 -> #VALUE! | CD36: 22 | CE36: 22 | CF36: =CE36 -> 22 | CG36: =CF36 -> 22 | CH36: =CG36 -> 22 | CN36: =CD36*BD36+CS36 -> 257.10213 | CO36: =CE36*BE36+CT36 -> 289.69971 | CP36: =CF36*BF36+CU36 -> 320.38623 | CQ36: =CG36*BG36+CV36 -> 351.05152 | DC36: 569.085 | DD36: 569.085 | DE36: 569.085 | DF36: 569.085 | DG36: 569.085 | DO36: 4.2 | DP36: 5.1394414 | DQ36: 5.813801 | DR36: 6.420532 | DS36: 7.0160968 | DT36: =_xlfn.RRI(DT$2,$H36,CN36+$DO36*$DT$2) -> #VALUE! | DU36: =_xlfn.RRI(DU$2,$H36,CO36+$DO36*$DT$2+SUM($DP36:DP36)) -> #VALUE! | DV36: =_xlfn.RRI(DV$2,$H36,CP36+$DO36*$DT$2+SUM($DP36:DQ36)) -> #VALUE! | DW36: =_xlfn.RRI(DW$2,$H36,CQ36+$DO36*$DT$2+SUM($DP36:DR36)) -> #VALUE! | DX36: =SUM(CN36,$DO36:DO36)/$H36 -> #VALUE! | DY36: =SUM(CO36,$DO36:DP36)/$H36 -> #VALUE! | DZ36: =SUM(CP36,$DO36:DQ36)/$H36 -> #VALUE! | EA36: =SUM(CQ36,$DO36:DR36)/$H36 -> #VALUE! | EB36: {=_xll.BDP(""&$B36&"","CHG_PCT_1M")/100} -> -0.00385182 | EC36: {=_xll.BDP(""&$B36&"","CHG_PCT_3M")/100} -> 0.08903146 | ED36: {=_xll.BDP(""&$B36&"","CHG_PCT_6M")/100} -> 0.1428872 | EE36: =_xlfn.RRI(2+$DT$2,$DT$2*S36+(1-$DT$2)*T36,V36) -> 0.079090442 | EF36: =EG36-EE36 -> 0.044427731 | EG36: =_xlfn.RRI(2+$DT$2,$DT$2*(BC36*DC36)+(1-$DT$2)*(BD36*DD36),(BF36*DF36)) -> 0.12351817 | EH36: =EI36-EG36 -> 0 | EI36: =ER36+EQ36 -> 0.12351817 | EJ36: =EK36-EI36 -> #VALUE! | EK36: =DV36 -> #VALUE! | EL36: =_xlfn.RRI(3,AK36,AN36) -> 0.088287802 | EM36: =_xlfn.RRI(3,BC36,BF36) -> 0.12906105 | EN36: {=_xll.BDP(B36,"AVG_DAILY_VALUE_TRADED_3M")/10^6} -> 264.6164 | EQ36: =IFERROR(AVERAGE(DP36:DQ36)/H36,0) -> 0 | ER36: =_xlfn.RRI(2+$DT$2,$DT$2*(BC36)+(1-$DT$2)*(BD36),(BF36)) -> 0.12351817 | EX36: {=_xll.BQL("SU FP Equity", "IS_COMP_EPS_ADJUSTED_OLD", "FPT=A", "FPr="&EX$5&"", "ACT_EST_MAPPING=PRECISE", "FS=MRC", "CURRENCY=EUR", "XLFILL=b")} -> 9.7885 | EY36: {=_xll.BQL("SU FP Equity", "IS_COMP_EPS_ADJUSTED_OLD", "FPT=A", "FPr="&EY$5&"", "ACT_EST_MAPPING=PRECISE", "FS=MRC", "CURRENCY=EUR", "XLFILL=b")} -> 11.448421 | EZ36: {=_xll.BQL("SU FP Equity", "IS_COMP_EPS_ADJUSTED_OLD", "FPT=A", "FPr="&EZ$5&"", "ACT_EST_MAPPING=PRECISE", "FS=MRC", "CURRENCY=EUR", "XLFILL=b")} -> 13.155 | FA36: {=_xll.BQL("SU FP Equity", "IS_COMP_EPS_ADJUSTED_OLD", "FPT=A", "FPr="&FA$5&"", "ACT_EST_MAPPING=PRECISE", "FS=MRC", "CURRENCY=EUR", "XLFILL=b")} -> 14.82 | FB36: =AT36/EX36-1 -> 0.033671978 | FC36: =AU36/EY36-1 -> 0.020792345 | FD36: =AV36/EZ36-1 -> 0.0010010243 | FE36: =AW36/FA36-1 -> -0.017340728 | FF36: 0.15 | FG36: -0.15 | FH36: =FF36-FG36 -> 0.3 | FI36: =FT36/CF36-1 -> 0.27272727 | FJ36: =FU36/CF36-1 -> -0.27272727 | FK36: =FI36-FJ36 -> 0.54545455 | FL36: =FF36+FG36 -> 0 | FM36: =FJ36+FI36 -> 0 | FN36: =EK36+FF36/3+FI36/3 -> #VALUE! | FO36: =EK36+FG36/3+FJ36/3 -> #VALUE! | FP36: =EK36+FL36/3+FM36/3 -> #VALUE! | FQ36: =EK36 -> #VALUE! | FR36: =FP36-FQ36 -> #VALUE! | FS36: =FN36-FO36 -> #VALUE! | FT36: 28 | FU36: 16
B37: ADI US Equity | D37: ADI | E37: 2 | F37: 46119 | H37: {=_xll.BQL($B37, "px_last", "dates=" & _xll.BQL.DATE($D$2))} -> #N/A Connection | I37: 496.709 | J37: -3652.321 | K37: 8591.705 | M37: =K37+J37 -> 4939.384 | N37: =I37*H37+M37+L37 -> #VALUE! | O37: 12062.551 | P37: 11825.809 | Q37: 9692.582 | R37: 11391.574 | S37: 13652.82 | T37: 15832.059 | U37: 16861.143 | V37: 17957.117 | W37: 19124.33 | X37: 0.73416385 | Y37: 0.71914229 | Z37: 0.68198359 | AA37: 0.69524995 | AB37: 0.70431792 | AC37: 0.71060593 | AD37: 0.71301026 | AE37: 0.71526785 | AF37: 0.71738765 | AG37: =X37*O37 -> 8855.8887 | AH37: =Y37*P37 -> 8504.4392 | AI37: =Z37*Q37 -> 6610.1818 | AJ37: =AA37*R37 -> 7919.991 | AK37: =AB37*S37 -> 9615.9257 | AL37: =AC37*T37 -> 11250.355 | AM37: =AD37*U37 -> 12022.168 | AN37: =AE37*V37 -> 12844.149 | AO37: =AF37*W37 -> 13719.558 | AP37: 9.6536192 | AQ37: 9.4699005 | AR37: 6.615 | AS37: 8.1857933 | AT37: 10.648839 | AU37: 13.346218 | AV37: 15.019715 | AW37: 16.794947 | AX37: 18.828812 | AY37: =AP37 -> 9.6536192 | AZ37: =AQ37 -> 9.4699005 | BA37: =AR37 -> 6.615 | BB37: =AS37 -> 8.1857933 | BC37: =AT37 -> 10.648839 | BD37: =AU37 -> 13.346218 | BE37: =AV37 -> 15.019715 | BF37: =AW37 -> 16.794947 | BG37: =AX37 -> 18.828812 | BH37: =$N37/Q37 -> #VALUE! | BI37: =$N37/R37 -> #VALUE! | BJ37: =$N37/S37 -> #VALUE! | BK37: =$N37/T37 -> #VALUE! | BL37: =$N37/U37 -> #VALUE! | BM37: =$N37/V37 -> #VALUE! | BN37: =$N37/W37 -> #VALUE! | BO37: =$N37/AK37 -> #VALUE! | BP37: =$N37/AL37 -> #VALUE! | BQ37: =$N37/AM37 -> #VALUE! | BR37: =$N37/AN37 -> #VALUE! | BS37: =$N37/AO37 -> #VALUE! | BT37: =$H37/AT37 -> #VALUE! | BU37: =$H37/AU37 -> #VALUE! | BV37: =$H37/AV37 -> #VALUE! | BW37: =$H37/AW37 -> #VALUE! | BX37: =$H37/AX37 -> #VALUE! | BY37: =$H37/BC37 -> #VALUE! | BZ37: =$H37/BD37 -> #VALUE! | CA37: =$H37/BE37 -> #VALUE! | CB37: =$H37/BF37 -> #VALUE! | CC37: =$H37/BG37 -> #VALUE! | CD37: 24 | CE37: =CD37 -> 24 | CF37: =CE37 -> 24 | CG37: =CF37 -> 24 | CH37: =CG37 -> 24 | CN37: =CD37*BD37+CS37 -> 320.30924 | CO37: =CE37*BE37+CT37 -> 360.47317 | CP37: =CF37*BF37+CU37 -> 403.07873 | CQ37: =CG37*BG37+CV37 -> 451.89148 | DC37: 489.01211 | DD37: 476.3474 | DE37: 459.37805 | DF37: 441.93829 | DG37: 427.07412 | DH37: 5139.384 | DI37: 5339.384 | DJ37: 7387.9714 | DK37: 7992.7683 | DL37: 8641.1126 | DO37: 4.3503167 | DP37: 4.7853483 | DQ37: 5.2638832 | DR37: 5.7902715 | DS37: 6.3692986 | DT37: =_xlfn.RRI(DT$2,$H37,CN37+$DO37*$DT$2) -> #VALUE! | DU37: =_xlfn.RRI(DU$2,$H37,CO37+$DO37*$DT$2+SUM($DP37:DP37)) -> #VALUE! | DV37: =_xlfn.RRI(DV$2,$H37,CP37+$DO37*$DT$2+SUM($DP37:DQ37)) -> #VALUE! | DW37: =_xlfn.RRI(DW$2,$H37,CQ37+$DO37*$DT$2+SUM($DP37:DR37)) -> #VALUE! | DX37: =SUM(CN37,$DO37:DO37)/$H37 -> #VALUE! | DY37: =SUM(CO37,$DO37:DP37)/$H37 -> #VALUE! | DZ37: =SUM(CP37,$DO37:DQ37)/$H37 -> #VALUE! | EA37: =SUM(CQ37,$DO37:DR37)/$H37 -> #VALUE! | EB37: {=_xll.BDP(""&$B37&"","CHG_PCT_1M")/100} -> -0.0159776 | EC37: {=_xll.BDP(""&$B37&"","CHG_PCT_3M")/100} -> 0.2978215 | ED37: {=_xll.BDP(""&$B37&"","CHG_PCT_6M")/100} -> 0.468366 | EE37: =_xlfn.RRI(2+$DT$2,$DT$2*S37+(1-$DT$2)*T37,V37) -> 0.08383298 | EF37: =EG37-EE37 -> 0.023743543 | EG37: =_xlfn.RRI(2+$DT$2,$DT$2*(BC37*DC37)+(1-$DT$2)*(BD37*DD37),(BF37*DF37)) -> 0.10757652 | EH37: =EI37-EG37 -> 0.038865936 | EI37: =ER37+EQ37 -> 0.14644246 | EJ37: =EK37-EI37 -> #VALUE! | EK37: =DV37 -> #VALUE! | EL37: =_xlfn.RRI(3,AK37,AN37) -> 0.10129772 | EM37: =_xlfn.RRI(3,BC37,BF37) -> 0.16401556 | EN37: {=_xll.BDP(B37,"AVG_DAILY_VALUE_TRADED_3M")/10^6} -> 1479.9409 | EQ37: =IFERROR(AVERAGE(DP37:DQ37)/H37,0) -> 0 | ER37: =_xlfn.RRI(2+$DT$2,$DT$2*(BC37)+(1-$DT$2)*(BD37),(BF37)) -> 0.14644246 | FF37: 0.3 | FG37: -0.2 | FH37: =FF37-FG37 -> 0.5 | FI37: =FT37/CF37-1 -> 0.16666667 | FJ37: =FU37/CF37-1 -> -0.33333333 | FK37: =FI37-FJ37 -> 0.5 | FL37: =FF37+FG37 -> 0.1 | FM37: =FJ37+FI37 -> -0.16666667 | FN37: =EK37+FF37/3+FI37/3 -> #VALUE! | FO37: =EK37+FG37/3+FJ37/3 -> #VALUE! | FP37: =EK37+FL37/3+FM37/3 -> #VALUE! | FQ37: =EK37 -> #VALUE! | FR37: =FP37-FQ37 -> #VALUE! | FS37: =FN37-FO37 -> #VALUE! | FT37: 28 | FU37: 16
D39: Other sectors
B40: COF US Equity | D40: COF | E40: 1 | F40: 45809 | H40: {=_xll.BQL($B40, "px_last", "dates=" & _xll.BQL.DATE($D$2))} -> #N/A Connection | I40: 645.02772 | J40: 0 | K40: 0 | M40: =K40+J40 -> 0 | N40: =I40*H40+M40+L40 -> #VALUE! | Q40: 56411 | R40: 53434 | S40: 62563.761 | T40: 65935.143 | U40: 69230.673 | V40: 72702.35 | W40: 76359.837 | AR40: 14.97727 | AS40: 15.732465 | AT40: 19.948806 | AU40: 24.351434 | AV40: 27.598444 | AW40: 29.976042 | AX40: 33.426452 | BA40: =AR40 -> 14.97727 | BB40: =AS40 -> 15.732465 | BC40: =AT40 -> 19.948806 | BD40: =AU40 -> 24.351434 | BE40: =AV40 -> 27.598444 | BF40: =AW40 -> 29.976042 | BG40: =AX40 -> 33.426452 | BI40: =$N40/R40 -> #VALUE! | BJ40: =$N40/S40 -> #VALUE! | BK40: =$N40/T40 -> #VALUE! | BL40: =$N40/U40 -> #VALUE! | BM40: =$N40/V40 -> #VALUE! | BN40: =$N40/W40 -> #VALUE! | BO40: =IFERROR($N40/AK40,"n/a") -> n/a | BP40: =IFERROR($N40/AL40,"n/a") -> n/a | BQ40: =IFERROR($N40/AM40,"n/a") -> n/a | BR40: =IFERROR($N40/AN40,"n/a") -> n/a | BS40: =IFERROR($N40/AO40,"n/a") -> n/a | BT40: =$H40/AT40 -> #VALUE! | BU40: =$H40/AU40 -> #VALUE! | BV40: =$H40/AV40 -> #VALUE! | BW40: =$H40/AW40 -> #VALUE! | BX40: =$H40/AX40 -> #VALUE! | BY40: =$H40/BC40 -> #VALUE! | BZ40: =$H40/BD40 -> #VALUE! | CA40: =$H40/BE40 -> #VALUE! | CB40: =$H40/BF40 -> #VALUE! | CC40: =$H40/BG40 -> #VALUE! | CD40: 12 | CE40: 12 | CF40: 12 | CG40: 12 | CH40: 12 | CN40: =CD40*BD40+CS40 -> 292.21721 | CO40: =CE40*BE40+CT40 -> 331.18133 | CP40: =CF40*BF40+CU40 -> 359.71251 | CQ40: =CG40*BG40+CV40 -> 401.11743 | DC40: 570.04736 | DD40: 523.90708 | DE40: 492.26483 | DF40: 464.1073 | DG40: 438.03844 | DO40: 2.3598095 | DP40: 2.4502163 | DQ40: 2.5058789 | DR40: 2.5294375 | DS40: 2.5474037 | DT40: =_xlfn.RRI(DT$2,$H40,CN40+$DO40*$DT$2) -> #VALUE! | DU40: =_xlfn.RRI(DU$2,$H40,CO40+$DO40*$DT$2+SUM($DP40:DP40)) -> #VALUE! | DV40: =_xlfn.RRI(DV$2,$H40,CP40+$DO40*$DT$2+SUM($DP40:DQ40)) -> #VALUE! | DW40: =_xlfn.RRI(DW$2,$H40,CQ40+$DO40*$DT$2+SUM($DP40:DR40)) -> #VALUE! | DX40: =SUM(CN40,$DO40:DO40)/$H40 -> #VALUE! | DY40: =SUM(CO40,$DO40:DP40)/$H40 -> #VALUE! | DZ40: =SUM(CP40,$DO40:DQ40)/$H40 -> #VALUE! | EA40: =SUM(CQ40,$DO40:DR40)/$H40 -> #VALUE! | EB40: {=_xll.BDP(""&$B40&"","CHG_PCT_1M")/100} -> -0.04301243 | EC40: {=_xll.BDP(""&$B40&"","CHG_PCT_3M")/100} -> -0.03398863 | ED40: {=_xll.BDP(""&$B40&"","CHG_PCT_6M")/100} -> -0.2136259 | EE40: =_xlfn.RRI(2+$DT$2,$DT$2*S40+(1-$DT$2)*T40,V40) -> 0.050758093 | EF40: =EG40-EE40 -> 0.009304283 | EG40: =_xlfn.RRI(2+$DT$2,$DT$2*(BC40*DC40)+(1-$DT$2)*(BD40*DD40),(BF40*DF40)) -> 0.060062376 | EH40: =EI40-EG40 -> 0.070639709 | EI40: =ER40+EQ40 -> 0.13070209 | EJ40: =EK40-EI40 -> #VALUE! | EK40: =DV40 -> #VALUE! | EL40: =_xlfn.RRI(3,AK40,AN40) -> 0 | EM40: =_xlfn.RRI(3,BC40,BF40) -> 0.14538755 | EN40: {=_xll.BDP(B40,"AVG_DAILY_VALUE_TRADED_3M")/10^6} -> 888.07386 | EQ40: =IFERROR(AVERAGE(DP40:DQ40)/H40,0) -> 0 | ER40: =_xlfn.RRI(2+$DT$2,$DT$2*(BC40)+(1-$DT$2)*(BD40),(BF40)) -> 0.13070209 | ES40: =ER40-EG40+EQ40 -> 0.070639709 | FF40: 0.15 | FG40: -0.15 | FH40: =FF40-FG40 -> 0.3 | FI40: =FT40/CF40-1 -> 0.083333333 | FJ40: =FU40/CF40-1 -> -0.33333333 | FK40: =FI40-FJ40 -> 0.41666667 | FL40: =FF40+FG40 -> 0 | FM40: =FJ40+FI40 -> -0.25 | FN40: =EK40+FF40/3+FI40/3 -> #VALUE! | FO40: =EK40+FG40/3+FJ40/3 -> #VALUE! | FP40: =EK40+FL40/3+FM40/3 -> #VALUE! | FQ40: =EK40 -> #VALUE! | FR40: =FP40-FQ40 -> #VALUE! | FS40: =FN40-FO40 -> #VALUE! | FT40: 13 | FU40: 8
B41: AON US Equity | D41: AON | E41: 1 | F41: 46139 | H41: {=_xll.BQL($B41, "px_last", "dates=" & _xll.BQL.DATE($D$2))} -> #N/A Connection | I41: 216.63014 | J41: -2798 | K41: 15249 | M41: =K41+J41 -> 12451 | N41: =I41*H41+M41+L41 -> #VALUE! | O41: 12479 | P41: 13376 | Q41: 15698 | R41: 17181 | S41: 17997.754 | T41: 18981.82 | U41: 20017.135 | V41: 21106.285 | W41: 22251.981 | X41: 0.48 | Y41: 0.48 | Z41: 0.48 | AA41: 0.48 | AB41: 0.48 | AC41: 0.48 | AD41: 0.48 | AE41: 0.48 | AF41: 0.48 | AG41: =X41*O41 -> 5989.92 | AH41: =Y41*P41 -> 6420.48 | AI41: =Z41*Q41 -> 7535.04 | AJ41: =AA41*R41 -> 8246.88 | AK41: =AB41*S41 -> 8638.922 | AL41: =AC41*T41 -> 9111.2735 | AM41: =AD41*U41 -> 9608.2248 | AN41: =AE41*V41 -> 10131.017 | AO41: =AF41*W41 -> 10680.951 | AP41: 13.391182 | AQ41: 14.141463 | AR41: 15.604706 | AS41: 17.081482 | AT41: 19.260685 | AU41: 22.130311 | AV41: 25.205188 | AW41: 28.526457 | AX41: 32.114173 | AY41: =AP41 -> 13.391182 | AZ41: =AQ41 -> 14.141463 | BA41: =AR41 -> 15.604706 | BB41: =AS41 -> 17.081482 | BC41: =AT41 -> 19.260685 | BD41: =AU41 -> 22.130311 | BE41: =AV41 -> 25.205188 | BF41: =AW41 -> 28.526457 | BG41: =AX41 -> 32.114173 | BH41: =$N41/Q41 -> #VALUE! | BI41: =$N41/R41 -> #VALUE! | BJ41: =$N41/S41 -> #VALUE! | BK41: =$N41/T41 -> #VALUE! | BL41: =$N41/U41 -> #VALUE! | BM41: =$N41/V41 -> #VALUE! | BN41: =$N41/W41 -> #VALUE! | BO41: =$N41/AK41 -> #VALUE! | BP41: =$N41/AL41 -> #VALUE! | BQ41: =$N41/AM41 -> #VALUE! | BR41: =$N41/AN41 -> #VALUE! | BS41: =$N41/AO41 -> #VALUE! | BT41: =$H41/AT41 -> #VALUE! | BU41: =$H41/AU41 -> #VALUE! | BV41: =$H41/AV41 -> #VALUE! | BW41: =$H41/AW41 -> #VALUE! | BX41: =$H41/AX41 -> #VALUE! | BY41: =$H41/BC41 -> #VALUE! | BZ41: =$H41/BD41 -> #VALUE! | CA41: =$H41/BE41 -> #VALUE! | CB41: =$H41/BF41 -> #VALUE! | CC41: =$H41/BG41 -> #VALUE! | CD41: 18 | CE41: 18 | CF41: 18 | CG41: 18 | CH41: 20 | CN41: =CD41*BD41+CS41 -> 398.34561 | CO41: =CE41*BE41+CT41 -> 453.69338 | CP41: =CF41*BF41+CU41 -> 513.47623 | CQ41: =CG41*BG41+CV41 -> 578.05511 | DC41: 210.03211 | DD41: 199.47986 | DE41: 189.2088 | DF41: 179.58405 | DG41: 170.48807 | DO41: 3.0487448 | DP41: 3.201182 | DQ41: 3.3612411 | DR41: 3.5293032 | DS41: 3.7057683 | DT41: =_xlfn.RRI(DT$2,$H41,CN41+$DO41*$DT$2) -> #VALUE! | DU41: =_xlfn.RRI(DU$2,$H41,CO41+$DO41*$DT$2+SUM($DP41:DP41)) -> #VALUE! | DV41: =_xlfn.RRI(DV$2,$H41,CP41+$DO41*$DT$2+SUM($DP41:DQ41)) -> #VALUE! | DW41: =_xlfn.RRI(DW$2,$H41,CQ41+$DO41*$DT$2+SUM($DP41:DR41)) -> #VALUE! | DX41: =SUM(CN41,$DO41:DO41)/$H41 -> #VALUE! | DY41: =SUM(CO41,$DO41:DP41)/$H41 -> #VALUE! | DZ41: =SUM(CP41,$DO41:DQ41)/$H41 -> #VALUE! | EA41: =SUM(CQ41,$DO41:DR41)/$H41 -> #VALUE! | EB41: {=_xll.BDP(""&$B41&"","CHG_PCT_1M")/100} -> 0.04197702 | EC41: {=_xll.BDP(""&$B41&"","CHG_PCT_3M")/100} -> -0.04310043 | ED41: {=_xll.BDP(""&$B41&"","CHG_PCT_6M")/100} -> -0.05087514 | EE41: =_xlfn.RRI(2+$DT$2,$DT$2*S41+(1-$DT$2)*T41,V41) -> 0.054376216 | EF41: =EG41-EE41 -> 0.025516894 | EG41: =_xlfn.RRI(2+$DT$2,$DT$2*(BC41*DC41)+(1-$DT$2)*(BD41*DD41),(BF41*DF41)) -> 0.079893111 | EH41: =EI41-EG41 -> 0.057360635 | EI41: =ER41+EQ41 -> 0.13725375 | EJ41: =EK41-EI41 -> #VALUE! | EK41: =DV41 -> #VALUE! | EL41: =_xlfn.RRI(3,AK41,AN41) -> 0.054543484 | EM41: =_xlfn.RRI(3,BC41,BF41) -> 0.13987887 | EN41: {=_xll.BDP(B41,"AVG_DAILY_VALUE_TRADED_3M")/10^6} -> 451.28925 | EQ41: =IFERROR(AVERAGE(DP41:DQ41)/H41,0) -> 0 | ER41: =_xlfn.RRI(2+$DT$2,$DT$2*(BC41)+(1-$DT$2)*(BD41),(BF41)) -> 0.13725375 | ES41: =ER41-EG41+EQ41 -> 0.057360635 | FF41: 0.1 | FG41: -0.1 | FH41: =FF41-FG41 -> 0.2 | FI41: =FT41/CF41-1 -> 0.22222222 | FJ41: =FU41/CF41-1 -> -0.16666667 | FK41: =FI41-FJ41 -> 0.38888889 | FL41: =FF41+FG41 -> 0 | FM41: =FJ41+FI41 -> 0.055555556 | FN41: =EK41+FF41/3+FI41/3 -> #VALUE! | FO41: =EK41+FG41/3+FJ41/3 -> #VALUE! | FP41: =EK41+FL41/3+FM41/3 -> #VALUE! | FQ41: =EK41 -> #VALUE! | FR41: =FP41-FQ41 -> #VALUE! | FS41: =FN41-FO41 -> #VALUE! | FT41: 22 | FU41: 15
B42: DSV DC Equity | D42: DSV | E42: 1 | F42: 46120 | H42: {=_xll.BQL($B42, "px_last", "dates=" & _xll.BQL.DATE($D$2))} -> #N/A Connection | I42: 236.159 | J42: -13179 | K42: 97935 | M42: =K42+J42 -> 84756 | N42: =I42*H42+M42+L42 -> #VALUE! | Q42: 167106 | R42: 288458.4 | S42: 276504.65 | T42: 279123.69 | U42: 285244.74 | V42: 291551.27 | W42: 298050.43 | AA42: 0.27823739 | AB42: 0.28499667 | AC42: 0.28741232 | AD42: 0.28975499 | AE42: 0.29218038 | AF42: 0.29469036 | AI42: 42974 | AJ42: 80259.912 | AK42: 78802.905 | AL42: 80223.588 | AM42: 82651.087 | AN42: 85185.56 | AO42: 87832.588 | AS42: 50.906381 | AT42: 67.813728 | AU42: 92.547675 | AV42: 107.11499 | AW42: 116.54705 | AX42: 127.07195 | BB42: 50.906381 | BC42: 67.813728 | BD42: 92.547675 | BE42: 107.11499 | BF42: 116.54705 | BG42: 127.07195 | BI42: =$N42/R42 -> #VALUE! | BJ42: =$N42/S42 -> #VALUE! | BK42: =$N42/T42 -> #VALUE! | BL42: =$N42/U42 -> #VALUE! | BM42: =$N42/V42 -> #VALUE! | BN42: =$N42/W42 -> #VALUE! | BO42: =$N42/AK42 -> #VALUE! | BP42: =$N42/AL42 -> #VALUE! | BQ42: =$N42/AM42 -> #VALUE! | BR42: =$N42/AN42 -> #VALUE! | BS42: =$N42/AO42 -> #VALUE! | BT42: =$H42/AT42 -> #VALUE! | BU42: =$H42/AU42 -> #VALUE! | BV42: =$H42/AV42 -> #VALUE! | BW42: =$H42/AW42 -> #VALUE! | BX42: =$H42/AX42 -> #VALUE! | BY42: =$H42/BC42 -> #VALUE! | BZ42: =$H42/BD42 -> #VALUE! | CA42: =$H42/BE42 -> #VALUE! | CB42: =$H42/BF42 -> #VALUE! | CC42: =$H42/BG42 -> #VALUE! | CD42: 21 | CE42: 21 | CF42: 21 | CG42: 21 | CH42: 22 | CN42: =CD42*BD42+CS42 -> 1943.5012 | CO42: =CE42*BE42+CT42 -> 2249.4148 | CP42: =CF42*BF42+CU42 -> 2447.488 | CQ42: =CG42*BG42+CV42 -> 2668.511 | DC42: 236.159 | DD42: 228.54086 | DE42: 217.49764 | DF42: 207.86395 | DG42: 198.71779 | DO42: 7.35 | DP42: 7.7175 | DQ42: 8.103375 | DR42: 8.5085438 | DS42: 8.9339709 | DT42: =_xlfn.RRI(DT$2,$H42,CN42+$DO42*$DT$2) -> #VALUE! | DU42: =_xlfn.RRI(DU$2,$H42,CO42+$DO42*$DT$2+SUM($DP42:DP42)) -> #VALUE! | DV42: =_xlfn.RRI(DV$2,$H42,CP42+$DO42*$DT$2+SUM($DP42:DQ42)) -> #VALUE! | DW42: =_xlfn.RRI(DW$2,$H42,CQ42+$DO42*$DT$2+SUM($DP42:DR42)) -> #VALUE! | DX42: =SUM(CN42,$DO42:DO42)/$H42 -> #VALUE! | DY42: =SUM(CO42,$DO42:DP42)/$H42 -> #VALUE! | DZ42: =SUM(CP42,$DO42:DQ42)/$H42 -> #VALUE! | EA42: =SUM(CQ42,$DO42:DR42)/$H42 -> #VALUE! | EB42: {=_xll.BDP(""&$B42&"","CHG_PCT_1M")/100} -> 0.05101027 | EC42: {=_xll.BDP(""&$B42&"","CHG_PCT_3M")/100} -> -0.04138973 | ED42: {=_xll.BDP(""&$B42&"","CHG_PCT_6M")/100} -> 0.02354839 | EE42: =_xlfn.RRI(2+$DT$2,$DT$2*S42+(1-$DT$2)*T42,V42) -> 0.019261191 | EF42: =EG42-EE42 -> 0.097068413 | EG42: =_xlfn.RRI(2+$DT$2,$DT$2*(BC42*DC42)+(1-$DT$2)*(BD42*DD42),(BF42*DF42)) -> 0.1163296 | EH42: =EI42-EG42 -> 0.049376859 | EI42: =ER42+EQ42 -> 0.16570646 | EJ42: =EK42-EI42 -> #VALUE! | EK42: =DV42 -> #VALUE! | EL42: =_xlfn.RRI(3,AK42,AN42) -> 0.026300603 | EM42: =_xlfn.RRI(3,BC42,BF42) -> 0.19782825 | EN42: {=_xll.BDP(B42,"AVG_DAILY_VALUE_TRADED_3M")/10^6} -> 618.7 | EQ42: =IFERROR(AVERAGE(DP42:DQ42)/H42,0) -> 0 | ER42: =_xlfn.RRI(2+$DT$2,$DT$2*(BC42)+(1-$DT$2)*(BD42),(BF42)) -> 0.16570646 | ES42: =ER42-EG42+EQ42 -> 0.049376859 | EX42: {=_xll.BQL("DSV DC Equity", "IS_COMP_EPS_ADJUSTED_OLD", "FPT=A", "FPO=1A", "ACT_EST_MAPPING=PRECISE", "FS=MRC", "CURRENCY=DKK", "XLFILL=b")} -> 62.582174 | EY42: {=_xll.BQL("DSV DC Equity", "IS_COMP_EPS_ADJUSTED_OLD", "FPT=A", "FPO=2A", "ACT_EST_MAPPING=PRECISE", "FS=MRC", "CURRENCY=DKK", "XLFILL=b")} -> 85.02087 | EZ42: {=_xll.BQL("DSV DC Equity", "IS_COMP_EPS_ADJUSTED_OLD", "FPT=A", "FPO=3A", "ACT_EST_MAPPING=PRECISE", "FS=MRC", "CURRENCY=DKK", "XLFILL=b")} -> 101.14667 | FA42: {=_xll.BQL("DSV DC Equity", "IS_COMP_EPS_ADJUSTED_OLD", "FPT=A", "FPO=4A", "ACT_EST_MAPPING=PRECISE", "FS=MRC", "CURRENCY=DKK", "XLFILL=b")} -> 121.25333 | FB42: =BC42/EX42-1 -> 0.083594961 | FC42: =BD42/EY42-1 -> 0.088528913 | FD42: =BE42/EZ42-1 -> 0.059006641 | FE42: =BF42/FA42-1 -> -0.038813663 | FF42: 0.25 | FG42: -0.15 | FH42: =FF42-FG42 -> 0.4 | FI42: =FT42/CF42-1 -> 0.23809524 | FJ42: =FU42/CF42-1 -> -0.23809524 | FK42: =FI42-FJ42 -> 0.47619048 | FL42: =FF42+FG42 -> 0.1 | FM42: =FJ42+FI42 -> 0 | FN42: =EK42+FF42/3+FI42/3 -> #VALUE! | FO42: =EK42+FG42/3+FJ42/3 -> #VALUE! | FP42: =EK42+FL42/3+FM42/3 -> #VALUE! | FQ42: =EK42 -> #VALUE! | FR42: =FP42-FQ42 -> #VALUE! | FS42: =FN42-FO42 -> #VALUE! | FT42: 26 | FU42: 16
B43: ZTS US Equity | D43: ZTS | F43: 46119 | H43: {=_xll.BQL($B43, "px_last", "dates=" & _xll.BQL.DATE($D$2))} -> #N/A Connection | I43: 443.835 | J43: -2312 | K43: 9042 | M43: =K43+J43 -> 6730 | N43: =I43*H43+M43+L43 -> #VALUE! | O43: 8080 | P43: 8544 | Q43: 9256 | R43: 9467 | S43: 9854.4734 | T43: 10398.411 | U43: 11056.025 | V43: 11971.287 | W43: 13027.292 | X43: 0.6980198 | Y43: 0.70177903 | Z43: 0.70678479 | AA43: 0.71934087 | AB43: 0.72054637 | AC43: 0.72208708 | AD43: 0.72374735 | AE43: 0.72575449 | AF43: 0.72771985 | AG43: =X43*O43 -> 5640 | AH43: =Y43*P43 -> 5996 | AI43: =Z43*Q43 -> 6542 | AJ43: =AA43*R43 -> 6810 | AK43: =AB43*S43 -> 7100.6051 | AL43: =AC43*T43 -> 7508.5585 | AM43: =AD43*U43 -> 8001.7687 | AN43: =AE43*V43 -> 8688.2156 | AO43: =AF43*W43 -> 9480.2188 | AP43: 4.8832339 | AQ43: 5.3147307 | AR43: 5.9212841 | AS43: 6.4145459 | AT43: 6.6244047 | AU43: 7.2631675 | AV43: 8.0798036 | AW43: 9.1971698 | AX43: 10.515169 | AY43: 4.751427 | AZ43: 5.1849448 | BA43: 5.7585752 | BB43: 6.2275395 | BC43: 6.4250916 | BD43: 7.048179 | BE43: 7.84639 | BF43: 8.9391736 | BG43: 10.228619 | BH43: =$N43/Q43 -> #VALUE! | BI43: =$N43/R43 -> #VALUE! | BJ43: =$N43/S43 -> #VALUE! | BK43: =$N43/T43 -> #VALUE! | BL43: =$N43/U43 -> #VALUE! | BM43: =$N43/V43 -> #VALUE! | BN43: =$N43/W43 -> #VALUE! | BO43: =$N43/AK43 -> #VALUE! | BP43: =$N43/AL43 -> #VALUE! | BQ43: =$N43/AM43 -> #VALUE! | BR43: =$N43/AN43 -> #VALUE! | BS43: =$N43/AO43 -> #VALUE! | BT43: =$H43/AT43 -> #VALUE! | BU43: =$H43/AU43 -> #VALUE! | BV43: =$H43/AV43 -> #VALUE! | BW43: =$H43/AW43 -> #VALUE! | BX43: =$H43/AX43 -> #VALUE! | BY43: =$H43/BC43 -> #VALUE! | BZ43: =$H43/BD43 -> #VALUE! | CA43: =$H43/BE43 -> #VALUE! | CB43: =$H43/BF43 -> #VALUE! | CC43: =$H43/BG43 -> #VALUE! | CD43: 17 | CE43: =CD43 -> 17 | CF43: =CE43 -> 17 | CG43: =CF43 -> 17 | CH43: =CG43 -> 17 | CN43: =CD43*BD43+CS43 -> 119.81904 | CO43: =CE43*BE43+CT43 -> 133.38863 | CP43: =CF43*BF43+CU43 -> 151.96595 | CQ43: =CG43*BG43+CV43 -> 173.88653 | DC43: 433.47426 | DD43: 424.05039 | DE43: 415.27758 | DF43: 406.8116 | DG43: 398.58428 | DH43: 6730 | DI43: 6730 | DJ43: 6730 | DK43: 6730 | DL43: 6730 | DO43: 2.3345 | DP43: 2.684675 | DQ43: 3.0873762 | DR43: 3.5504827 | DS43: 4.0830551 | DT43: =_xlfn.RRI(DT$2,$H43,CN43+$DO43*$DT$2) -> #VALUE! | DU43: =_xlfn.RRI(DU$2,$H43,CO43+$DO43*$DT$2+SUM($DP43:DP43)) -> #VALUE! | DV43: =_xlfn.RRI(DV$2,$H43,CP43+$DO43*$DT$2+SUM($DP43:DQ43)) -> #VALUE! | DW43: =_xlfn.RRI(DW$2,$H43,CQ43+$DO43*$DT$2+SUM($DP43:DR43)) -> #VALUE! | DX43: =SUM(CN43,$DO43:DO43)/$H43 -> #VALUE! | DY43: =SUM(CO43,$DO43:DP43)/$H43 -> #VALUE! | DZ43: =SUM(CP43,$DO43:DQ43)/$H43 -> #VALUE! | EA43: =SUM(CQ43,$DO43:DR43)/$H43 -> #VALUE! | EB43: {=_xll.BDP(""&$B43&"","CHG_PCT_1M")/100} -> -0.04768806 | EC43: {=_xll.BDP(""&$B43&"","CHG_PCT_3M")/100} -> -0.3504076 | ED43: {=_xll.BDP(""&$B43&"","CHG_PCT_6M")/100} -> -0.3324306 | EE43: =_xlfn.RRI(2+$DT$2,$DT$2*S43+(1-$DT$2)*T43,V43) -> 0.068912552 | EF43: =EG43-EE43 -> 0.027273815 | EG43: =_xlfn.RRI(2+$DT$2,$DT$2*(BC43*DC43)+(1-$DT$2)*(BD43*DD43),(BF43*DF43)) -> 0.096186367 | EH43: =EI43-EG43 -> 0.02309098 | EI43: =ER43+EQ43 -> 0.11927735 | EJ43: =EK43-EI43 -> #VALUE! | EK43: =DV43 -> #VALUE! | EL43: =_xlfn.RRI(3,AK43,AN43) -> 0.069576233 | EM43: =_xlfn.RRI(3,BC43,BF43) -> 0.1163645 | EN43: {=_xll.BDP(B43,"AVG_DAILY_VALUE_TRADED_3M")/10^6} -> 560.08838 | EQ43: =IFERROR(AVERAGE(DP43:DQ43)/H43,0) -> 0 | ER43: =_xlfn.RRI(2+$DT$2,$DT$2*(BC43)+(1-$DT$2)*(BD43),(BF43)) -> 0.11927735 | ES43: =ER43-EG43+EQ43 -> 0.02309098 | FF43: 0.2 | FG43: -0.25 | FH43: =FF43-FG43 -> 0.45 | FI43: =FT43/CF43-1 -> 0.41176471 | FJ43: =FU43/CF43-1 -> -0.11764706 | FK43: =FI43-FJ43 -> 0.52941176 | FL43: =FF43+FG43 -> -0.05 | FM43: =FJ43+FI43 -> 0.29411765 | FN43: =EK43+FF43/3+FI43/3 -> #VALUE! | FO43: =EK43+FG43/3+FJ43/3 -> #VALUE! | FP43: =EK43+FL43/3+FM43/3 -> #VALUE! | FQ43: =EK43 -> #VALUE! | FR43: =FP43-FQ43 -> #VALUE! | FS43: =FN43-FO43 -> #VALUE! | FT43: 24 | FU43: 15
B44: WING US Equity | D44: WING | F44: 46139 | H44: {=_xll.BQL($B44, "px_last", "dates=" & _xll.BQL.DATE($D$2))} -> #N/A Connection | I44: 28.074 | J44: -222.566 | K44: 1209.094 | M44: =K44+J44 -> 986.528 | N44: =I44*H44+M44+L44 -> #VALUE! | O44: 357.521 | P44: 460.055 | Q44: 625.807 | R44: 696.853 | S44: 778.76669 | T44: 919.23366 | U44: 1078.8701 | V44: 1258.6672 | W44: 1459.6536 | AP44: 1.8477141 | AQ44: 2.4811678 | AR44: 3.7247811 | AS44: 4.1483008 | AT44: 4.6123604 | AU44: 5.975037 | AV44: 7.6104083 | AW44: 9.55656 | AX44: 11.856499 | AY44: 1.8477141 | AZ44: 2.4811678 | BA44: 3.7247811 | BB44: 4.1483008 | BC44: 4.6123604 | BD44: 5.975037 | BE44: 7.6104083 | BF44: 9.55656 | BG44: 11.856499 | BH44: =$N44/Q44 -> #VALUE! | BI44: =$N44/R44 -> #VALUE! | BJ44: =$N44/S44 -> #VALUE! | BK44: =$N44/T44 -> #VALUE! | BL44: =$N44/U44 -> #VALUE! | BM44: =$N44/V44 -> #VALUE! | BN44: =$N44/W44 -> #VALUE! | BO44: =IFERROR($N44/AK44,"n/a") -> n/a | BP44: =IFERROR($N44/AL44,"n/a") -> n/a | BQ44: =$N44/AM44 -> #VALUE! | BR44: =$N44/AN44 -> #VALUE! | BS44: =$N44/AO44 -> #VALUE! | BT44: =$H44/AT44 -> #VALUE! | BU44: =$H44/AU44 -> #VALUE! | BV44: =$H44/AV44 -> #VALUE! | BW44: =$H44/AW44 -> #VALUE! | BX44: =$H44/AX44 -> #VALUE! | BY44: =$H44/BC44 -> #VALUE! | BZ44: =$H44/BD44 -> #VALUE! | CA44: =$H44/BE44 -> #VALUE! | CB44: =$H44/BF44 -> #VALUE! | CC44: =$H44/BG44 -> #VALUE! | CD44: 22 | CE44: 22 | CF44: 22 | CG44: 22 | CH44: 24 | CN44: =CD44*BD44 -> 131.45081 | CO44: =CE44*BE44 -> 167.42898 | CP44: =CF44*BF44 -> 210.24432 | CQ44: =CG44*BG44 -> 260.84298 | DC44: 27.751065 | DD44: 27.356287 | DE44: 26.895951 | DF44: 26.377227 | DG44: 25.807803 | DO44: 1.311 | DP44: 1.50765 | DQ44: 1.7337975 | DR44: 1.9938671 | DS44: 2.2929472 | DT44: =_xlfn.RRI(DT$2,$H44,CN44+$DO44*$DT$2) -> #VALUE! | DU44: =_xlfn.RRI(DU$2,$H44,CO44+$DO44*$DT$2+SUM($DP44:DP44)) -> #VALUE! | DV44: =_xlfn.RRI(DV$2,$H44,CP44+$DO44*$DT$2+SUM($DP44:DQ44)) -> #VALUE! | DW44: =_xlfn.RRI(DW$2,$H44,CQ44+$DO44*$DT$2+SUM($DP44:DR44)) -> #VALUE! | DX44: =SUM(CN44,$DO44:DO44)/$H44 -> #VALUE! | DY44: =SUM(CO44,$DO44:DP44)/$H44 -> #VALUE! | DZ44: =SUM(CP44,$DO44:DQ44)/$H44 -> #VALUE! | EA44: =SUM(CQ44,$DO44:DR44)/$H44 -> #VALUE! | EB44: {=_xll.BDP(""&$B44&"","CHG_PCT_1M")/100} -> 0.1235444 | EC44: {=_xll.BDP(""&$B44&"","CHG_PCT_3M")/100} -> -0.3642711 | ED44: {=_xll.BDP(""&$B44&"","CHG_PCT_6M")/100} -> -0.4076438 | EE44: =_xlfn.RRI(2+$DT$2,$DT$2*S44+(1-$DT$2)*T44,V44) -> 0.17081653 | EF44: =EG44-EE44 -> 0.075004582 | EG44: =_xlfn.RRI(2+$DT$2,$DT$2*(BC44*DC44)+(1-$DT$2)*(BD44*DD44),(BF44*DF44)) -> 0.24582111 | EH44: =EI44-EG44 -> 0.021386881 | EI44: =ER44+EQ44 -> 0.26720799 | EJ44: =EK44-EI44 -> #VALUE! | EK44: =DV44 -> #VALUE! | EL44: =_xlfn.RRI(3,AK44,AN44) -> 0 | EM44: =_xlfn.RRI(3,BC44,BF44) -> 0.27485107 | EN44: {=_xll.BDP(B44,"AVG_DAILY_VALUE_TRADED_3M")/10^6} -> 218.65602 | EQ44: =IFERROR(AVERAGE(DP44:DQ44)/H44,0) -> 0 | ER44: =_xlfn.RRI(2+$DT$2,$DT$2*(BC44)+(1-$DT$2)*(BD44),(BF44)) -> 0.26720799 | ES44: =ER44-EG44+EQ44 -> 0.021386881 | EX44: {=_xll.BQL("WING US Equity", "IS_COMP_EPS_ADJUSTED_OLD", "FPT=A", "FPO=1A", "ACT_EST_MAPPING=PRECISE", "FS=MRC", "CURRENCY=USD", "XLFILL=b")} -> 4.5739394 | EY44: {=_xll.BQL("WING US Equity", "IS_COMP_EPS_ADJUSTED_OLD", "FPT=A", "FPO=2A", "ACT_EST_MAPPING=PRECISE", "FS=MRC", "CURRENCY=USD", "XLFILL=b")} -> 5.5684848 | EZ44: {=_xll.BQL("WING US Equity", "IS_COMP_EPS_ADJUSTED_OLD", "FPT=A", "FPO=3A", "ACT_EST_MAPPING=PRECISE", "FS=MRC", "CURRENCY=USD", "XLFILL=b")} -> 6.9135294 | FA44: {=_xll.BQL("WING US Equity", "IS_COMP_EPS_ADJUSTED_OLD", "FPT=A", "FPO=4A", "ACT_EST_MAPPING=PRECISE", "FS=MRC", "CURRENCY=USD", "XLFILL=b")} -> 8.275 | FB44: =BC44/EX44-1 -> 0.0083999885 | FC44: =BD44/EY44-1 -> 0.073009467 | FD44: =BE44/EZ44-1 -> 0.10079929 | FE44: =BF44/FA44-1 -> 0.1548713 | FF44: 0.2 | FG44: -0.15 | FH44: =FF44-FG44 -> 0.35 | FI44: =FT44/CF44-1 -> 0.36363636 | FJ44: =FU44/CF44-1 -> -0.090909091 | FK44: =FI44-FJ44 -> 0.45454545 | FL44: =FF44+FG44 -> 0.05 | FM44: =FJ44+FI44 -> 0.27272727 | FN44: =EK44+FF44/3+FI44/3 -> #VALUE! | FO44: =EK44+FG44/3+FJ44/3 -> #VALUE! | FP44: =EK44+FL44/3+FM44/3 -> #VALUE! | FQ44: =EK44 -> #VALUE! | FR44: =FP44-FQ44 -> #VALUE! | FS44: =FN44-FO44 -> #VALUE! | FT44: 30 | FU44: 20
D46: Unprofitable Software
B47: PCOR US EQUITY | D47: PCOR | F47: 46119 | H47: {=_xll.BQL($B47, "px_last", "dates=" & _xll.BQL.DATE($D$2))} -> #N/A Connection | I47: 161.46556 | J47: -811 | K47: 28 | M47: =K47+J47 -> -783 | N47: =I47*H47+M47+L47 -> #VALUE! | O47: 720.203 | P47: 950.01 | Q47: 1151.708 | R47: 1322.509 | S47: 1507.6603 | T47: 1703.6561 | U47: 1908.0948 | V47: 2127.5257 | W47: 2361.5536 | X47: =AG47/O47 -> 0.83556442 | Y47: =AH47/P47 -> 0.85259629 | Z47: =AI47/Q47 -> 0.85752899 | AA47: =AJ47/R47 -> 0.83613042 | AB47: =AK47/S47 -> 0.84928708 | AC47: =AL47/T47 -> 0.85529973 | AD47: =AM47/U47 -> 0.85933919 | AE47: =AN47/V47 -> 0.86341685 | AF47: =AO47/W47 -> 0.86753328 | AG47: 601.776 | AH47: 809.975 | AI47: 987.623 | AJ47: 1105.79 | AK47: 1280.4364 | AL47: 1457.1366 | AM47: 1639.7007 | AN47: 1836.9416 | AO47: 2048.7263 | AQ47: 0.2860091 | AR47: 0.88947488 | AS47: 1.3067373 | AT47: 1.5666595 | AU47: 2.231158 | AV47: 2.9986834 | AW47: 3.935053 | AX47: 5.2472299 | BA47: -0.32076479 | BB47: -0.20239665 | BC47: 0.34626651 | BD47: 0.90715357 | BE47: 1.5690342 | BF47: 2.3974072 | BG47: 3.5235657 | BH47: =$N47/Q47 -> #VALUE! | BI47: =$N47/R47 -> #VALUE! | BJ47: =$N47/S47 -> #VALUE! | BK47: =$N47/T47 -> #VALUE! | BL47: =$N47/U47 -> #VALUE! | BM47: =$N47/V47 -> #VALUE! | BN47: =$N47/W47 -> #VALUE! | BO47: =$N47/AK47 -> #VALUE! | BP47: =$N47/AL47 -> #VALUE! | BQ47: =$N47/AM47 -> #VALUE! | BR47: =$N47/AN47 -> #VALUE! | BS47: =$N47/AO47 -> #VALUE! | BY47: n/a | BZ47: =$H47/BD47 -> #VALUE! | CA47: =$H47/BE47 -> #VALUE! | CB47: =$H47/BF47 -> #VALUE! | CC47: =$H47/BG47 -> #VALUE! | CD47: 8 | CE47: 7 | CF47: 7 | CG47: 7 | CH47: 7 | CI47: 92.895312 | CJ47: 105.12151 | CK47: 118.98665 | CL47: 135.2034 | CM47: 152.60938 | CN47: =(CX47-DH47)/DC47 -> 77.506566 | CO47: =(CY47-DI47)/DD47 -> 78.045916 | CP47: =(CZ47-DJ47)/DE47 -> 89.154683 | CQ47: =(DA47-DK47)/DF47 -> 101.91876 | CX47: =CD47*AL47 -> 11657.093 | CY47: =CE47*AM47 -> 11477.905 | CZ47: =CF47*AN47 -> 12858.591 | DA47: =CG47*AO47 -> 14341.084 | DC47: 160.49986 | DD47: 157.09476 | DE47: 153.007 | DF47: 148.39058 | DG47: 143.41422 | DH47: -782.7 | DI47: -782.7 | DJ47: -782.7 | DK47: -782.7 | DL47: -782.7 | DT47: =_xlfn.RRI(DT$2,$H47,CN47+$DO47*$DT$2) -> #VALUE! | DU47: =_xlfn.RRI(DU$2,$H47,CO47+$DO47*$DT$2+SUM($DP47:DP47)) -> #VALUE! | DV47: =_xlfn.RRI(DV$2,$H47,CP47+$DO47*$DT$2+SUM($DP47:DQ47)) -> #VALUE! | DW47: =_xlfn.RRI(DW$2,$H47,CQ47+$DO47*$DT$2+SUM($DP47:DR47)) -> #VALUE! | DX47: =SUM(CN47,$DO47:DO47)/$H47 -> #VALUE! | DY47: =SUM(CO47,$DO47:DP47)/$H47 -> #VALUE! | DZ47: =SUM(CP47,$DO47:DQ47)/$H47 -> #VALUE! | EA47: =SUM(CQ47,$DO47:DR47)/$H47 -> #VALUE! | EB47: {=_xll.BDP(""&$B47&"","CHG_PCT_1M")/100} -> -0.1146772 | EC47: {=_xll.BDP(""&$B47&"","CHG_PCT_3M")/100} -> -0.1995588 | ED47: {=_xll.BDP(""&$B47&"","CHG_PCT_6M")/100} -> -0.3912763 | EE47: =_xlfn.RRI(2+$DT$2,$DT$2*S47+(1-$DT$2)*T47,V47) -> 0.11940702 | EH47: =-_xlfn.RRI(2+$DT$2,$DT$2*DC47+(1-$DT$2)*DD47,DF47) -> 0.026620729 | EI47: =EH47+EE47 -> 0.14602775 | EJ47: =EK47-EI47 -> #VALUE! | EK47: =DV47 -> #VALUE! | EL47: =_xlfn.RRI(3,AK47,AN47) -> 0.12783555 | EM47: n/a | EN47: {=_xll.BDP(B47,"AVG_DAILY_VALUE_TRADED_3M")/10^6} -> 129.05309 | EQ47: =IFERROR(AVERAGE(DP47:DQ47)/H47,0) -> 0 | ER47: =_xlfn.RRI(2+$DT$2,$DT$2*(BC47)+(1-$DT$2)*(BD47),(BF47)) -> 0.72542693 | ES47: =ER47-EG47+EQ47 -> 0.72542693 | EU47: =_xlfn.RRI(2+$DT$2,($DT$2*BY47+(1-$DT$2)*BZ47),CF47) -> #VALUE! | EX47: {=_xll.BQL("PCOR US Equity", "IS_COMP_SALES/1M", "FPT=A", "FPr="&EX5&"", "ACT_EST_MAPPING=PRECISE", "FS=MRC", "CURRENCY=USD", "XLFILL=b")} -> 1502.9091 | EY47: {=_xll.BQL("PCOR US Equity", "IS_COMP_SALES/1M", "FPT=A", "FPr="&EY5&"", "ACT_EST_MAPPING=PRECISE", "FS=MRC", "CURRENCY=USD", "XLFILL=b")} -> 1699.8182 | EZ47: {=_xll.BQL("PCOR US Equity", "IS_COMP_SALES/1M", "FPT=A", "FPr="&EZ5&"", "ACT_EST_MAPPING=PRECISE", "FS=MRC", "CURRENCY=USD", "XLFILL=b")} -> 1941.5 | FA47: {=_xll.BQL("PCOR US Equity", "IS_COMP_SALES/1M", "FPT=A", "FPr="&FA5&"", "ACT_EST_MAPPING=PRECISE", "FS=MRC", "CURRENCY=USD", "XLFILL=b")} -> 2128.5 | FB47: =S47/EX47-1 -> 0.003161315 | FC47: =T47/EY47-1 -> 0.0022578368 | FD47: =U47/EZ47-1 -> -0.017205859 | FE47: =V47/FA47-1 -> -0.00045772613 | FF47: 0.07 | FG47: -0.06 | FH47: =FF47-FG47 -> 0.13 | FI47: =FT47/CF47-1 -> 0.42857143 | FJ47: =FU47/CF47-1 -> -0.28571429 | FK47: =FI47-FJ47 -> 0.71428571 | FL47: =FF47+FG47 -> 0.01 | FM47: =FJ47+FI47 -> 0.14285714 | FN47: =EK47+FF47/3+FI47/3 -> #VALUE! | FO47: =EK47+FG47/3+FJ47/3 -> #VALUE! | FP47: =EK47+FL47/3+FM47/3 -> #VALUE! | FQ47: =EK47 -> #VALUE! | FR47: =FP47-FQ47 -> #VALUE! | FS47: =FN47-FO47 -> #VALUE! | FT47: 10 | FU47: 5
B48: TTAN US EQUITY | D48: TTAN | F48: 46119 | H48: {=_xll.BQL($B48, "px_last", "dates=" & _xll.BQL.DATE($D$2))} -> #N/A Connection | I48: 94.113302 | J48: -429.352 | M48: =K48+J48 -> -429.352 | N48: =I48*H48+M48+L48 -> #VALUE! | O48: 467.734 | P48: 614.341 | Q48: 771.878 | R48: 960.965 | S48: 1170.4399 | T48: 1410.8055 | U48: 1660.2376 | V48: 1947.3317 | W48: 2257.7347 | AG48: 297.192 | AH48: 417.619 | AI48: 543.259 | AJ48: 711.483 | AK48: 879.37455 | AL48: 1078.9008 | AM48: 1288.1882 | AN48: 1530.7204 | AO48: 1795.2715 | AP48: -5.2035863 | AQ48: -2.2611508 | AR48: 0.39239782 | AS48: 1.100849 | AT48: 1.7962606 | AU48: 2.7051749 | AV48: 3.8034995 | AW48: 5.1971525 | AX48: 6.861089 | AY48: -7.1522428 | AZ48: -5.5200758 | BA48: -3.0958693 | BB48: -0.94337005 | BC48: -0.49851227 | BD48: 0.2427629 | BE48: 1.2372221 | BF48: 2.4508639 | BG48: 3.8433139 | BH48: =$N48/Q48 -> #VALUE! | BI48: =$N48/R48 -> #VALUE! | BJ48: =$N48/S48 -> #VALUE! | BK48: =$N48/T48 -> #VALUE! | BL48: =$N48/U48 -> #VALUE! | BM48: =$N48/V48 -> #VALUE! | BN48: =$N48/W48 -> #VALUE! | BO48: =$N48/AK48 -> #VALUE! | BP48: =$N48/AL48 -> #VALUE! | BQ48: =$N48/AM48 -> #VALUE! | BR48: =$N48/AN48 -> #VALUE! | BS48: =$N48/AO48 -> #VALUE! | BT48: =$H48/AT48 -> #VALUE! | BU48: =$H48/AU48 -> #VALUE! | BV48: =$H48/AV48 -> #VALUE! | BW48: =$H48/AW48 -> #VALUE! | BX48: =$H48/AX48 -> #VALUE! | BY48: n/a | BZ48: =$H48/BD48 -> #VALUE! | CA48: =$H48/BE48 -> #VALUE! | CB48: =$H48/BF48 -> #VALUE! | CC48: =$H48/BG48 -> #VALUE! | CD48: 7 | CE48: 7 | CF48: 7 | CG48: 7 | CH48: 8 | CN48: =(CX48-DH48)/DC48 -> 84.532908 | CO48: =(CY48-DI48)/DD48 -> 99.85447 | CP48: =(CZ48-DJ48)/DE48 -> 118.70166 | CQ48: =(DA48-DK48)/DF48 -> 140.85552 | CX48: =CD48*AL48 -> 7552.3059 | CY48: =CE48*AM48 -> 9017.3172 | CZ48: =CF48*AN48 -> 10715.043 | DA48: =CG48*AO48 -> 12566.901 | DC48: 94.420718 | DD48: 94.60437 | DE48: 93.885754 | DF48: 92.26655 | DG48: 89.868677 | DH48: -429.352 | DI48: -429.352 | DJ48: -429.352 | DK48: -429.352 | DL48: -429.352 | DT48: =_xlfn.RRI(DT$2,$H48,CN48+$DO48*$DT$2) -> #VALUE! | DU48: =_xlfn.RRI(DU$2,$H48,CO48+$DO48*$DT$2+SUM($DP48:DP48)) -> #VALUE! | DV48: =_xlfn.RRI(DV$2,$H48,CP48+$DO48*$DT$2+SUM($DP48:DQ48)) -> #VALUE! | DW48: =_xlfn.RRI(DW$2,$H48,CQ48+$DO48*$DT$2+SUM($DP48:DR48)) -> #VALUE! | DX48: =SUM(CN48,$DO48:DO48)/$H48 -> #VALUE! | DY48: =SUM(CO48,$DO48:DP48)/$H48 -> #VALUE! | DZ48: =SUM(CP48,$DO48:DQ48)/$H48 -> #VALUE! | EA48: =SUM(CQ48,$DO48:DR48)/$H48 -> #VALUE! | EB48: {=_xll.BDP(""&$B48&"","CHG_PCT_1M")/100} -> 0.1548223 | EC48: {=_xll.BDP(""&$B48&"","CHG_PCT_3M")/100} -> -0.1223628 | ED48: {=_xll.BDP(""&$B48&"","CHG_PCT_6M")/100} -> -0.3261755 | EE48: =_xlfn.RRI(2+$DT$2,$DT$2*S48+(1-$DT$2)*T48,V48) -> 0.17946088 | EH48: =-_xlfn.RRI(2+$DT$2,$DT$2*DC48+(1-$DT$2)*DD48,DF48) -> 0.0093105571 | EI48: =EH48+EE48 -> 0.18877143 | EJ48: =EK48-EI48 -> #VALUE! | EK48: =DV48 -> #VALUE! | EL48: =_xlfn.RRI(3,AK48,AN48) -> 0.20293084 | EM48: n/a | EN48: {=_xll.BDP(B48,"AVG_DAILY_VALUE_TRADED_3M")/10^6} -> 86.634592 | EQ48: =IFERROR(AVERAGE(DP48:DQ48)/H48,0) -> 0 | ER48: =_xlfn.RRI(2+$DT$2,$DT$2*(BC48)+(1-$DT$2)*(BD48),(BF48)) -> #NUM! | ES48: =ER48-EG48+EQ48 -> #NUM! | EU48: =_xlfn.RRI(2+$DT$2,($DT$2*BY48+(1-$DT$2)*BZ48),CF48) -> #VALUE! | EX48: {=_xll.BQL("TTAN US Equity", "IS_COMP_SALES/1M", "FPT=A", "FPr="&EX5+1&"", "ACT_EST_MAPPING=PRECISE", "FS=MRC", "CURRENCY=USD", "XLFILL=b")} -> 1136.9412 | EY48: {=_xll.BQL("TTAN US Equity", "IS_COMP_SALES/1M", "FPT=A", "FPr="&EY5+1&"", "ACT_EST_MAPPING=PRECISE", "FS=MRC", "CURRENCY=USD", "XLFILL=b")} -> 1302.8333 | EZ48: {=_xll.BQL("TTAN US Equity", "IS_COMP_SALES/1M", "FPT=A", "FPr="&EZ5+1&"", "ACT_EST_MAPPING=PRECISE", "FS=MRC", "CURRENCY=USD", "XLFILL=b")} -> 1509.6667 | FA48: {=_xll.BQL("TTAN US Equity", "IS_COMP_SALES/1M", "FPT=A", "FPr="&FA5+1&"", "ACT_EST_MAPPING=PRECISE", "FS=MRC", "CURRENCY=USD", "XLFILL=b")} -> 1787 | FB48: =S48/EX48-1 -> 0.029463937 | FC48: =T48/EY48-1 -> 0.082874882 | FD48: =U48/EZ48-1 -> 0.099737856 | FE48: =V48/FA48-1 -> 0.089721173 | FF48: 0.1 | FG48: -0.1 | FH48: =FF48-FG48 -> 0.2 | FI48: =FT48/CF48-1 -> 0.28571429 | FJ48: =FU48/CF48-1 -> -0.42857143 | FK48: =FI48-FJ48 -> 0.71428571 | FL48: =FF48+FG48 -> 0 | FM48: =FJ48+FI48 -> -0.14285714 | FN48: =EK48+FF48/3+FI48/3 -> #VALUE! | FO48: =EK48+FG48/3+FJ48/3 -> #VALUE! | FP48: =EK48+FL48/3+FM48/3 -> #VALUE! | FQ48: =EK48 -> #VALUE! | FR48: =FP48-FQ48 -> #VALUE! | FS48: =FN48-FO48 -> #VALUE! | FT48: 9 | FU48: 4
B49: GWRE US EQUITY | D49: GWRE | F49: 46054 | H49: {=_xll.BQL($B49, "px_last", "dates=" & _xll.BQL.DATE($D$2))} -> #N/A Connection | I49: 86.451737 | J49: -1410.456 | K49: 704.5 | M49: =K49+J49 -> -705.956 | N49: =I49*H49+M49+L49 -> #VALUE! | O49: 612.749 | P49: 752.474 | Q49: 971.543 | R49: 1188.6634 | S49: 1394.7843 | T49: 1657.5923 | U49: 1941.5146 | V49: 2243.9025 | W49: 2585.5299 | X49: 0.69387302 | Y49: 0.7458364 | Z49: 0.78985644 | AA49: 0.80051716 | AB49: 0.80154868 | AC49: 0.80545121 | AD49: 0.80912615 | AE49: 0.8140254 | AF49: 0.82065591 | AG49: =X49*O49 -> 425.17 | AH49: =Y49*P49 -> 561.2225 | AI49: =Z49*Q49 -> 767.3795 | AJ49: =AA49*R49 -> 951.54545 | AK49: =AB49*S49 -> 1117.9876 | AL49: =AC49*T49 -> 1335.1098 | AM49: =AD49*U49 -> 1570.9303 | AN49: =AE49*V49 -> 1826.5936 | AO49: =AF49*W49 -> 2121.8304 | AP49: -0.077699242 | AQ49: 0.83215138 | AR49: 1.9816448 | AS49: 2.695467 | AT49: 3.2782003 | AU49: 4.478262 | AV49: 6.0385589 | AW49: 8.130041 | AX49: 10.871194 | AY49: -0.97359042 | AZ49: -0.22880869 | BA49: 0.43081056 | BB49: 1.1166603 | BC49: 1.6426499 | BD49: 2.7167351 | BE49: 4.1543467 | BF49: 6.1252537 | BG49: 8.6079473 | BH49: =$N49/Q49 -> #VALUE! | BI49: =$N49/R49 -> #VALUE! | BJ49: =$N49/S49 -> #VALUE! | BK49: =$N49/T49 -> #VALUE! | BL49: =$N49/U49 -> #VALUE! | BM49: =$N49/V49 -> #VALUE! | BN49: =$N49/W49 -> #VALUE! | BO49: =$N49/AK49*0.9 -> #VALUE! | BP49: =$N49/AL49*0.9 -> #VALUE! | BQ49: =$N49/AM49*0.9 -> #VALUE! | BR49: =$N49/AN49*0.9 -> #VALUE! | BS49: =$N49/AO49*0.9 -> #VALUE! | BT49: =$H49/AT49 -> #VALUE! | BU49: =$H49/AU49 -> #VALUE! | BV49: =$H49/AV49 -> #VALUE! | BW49: =$H49/AW49 -> #VALUE! | BX49: =$H49/AX49 -> #VALUE! | BY49: n/a | BZ49: =$H49/BD49 -> #VALUE! | CA49: =$H49/BE49 -> #VALUE! | CB49: =$H49/BF49 -> #VALUE! | CC49: =$H49/BG49 -> #VALUE! | CD49: 8.5 | CE49: 8.5 | CF49: 8.5 | CG49: 8.5 | CH49: 8.5 | CN49: =(CX49-DH49)/DC49 -> 140.37143 | CO49: =(CY49-DI49)/DD49 -> 166.39691 | CP49: =(CZ49-DJ49)/DE49 -> 196.51477 | CQ49: =(DA49-DK49)/DF49 -> 233.87844 | CX49: =CD49*AL49 -> 11348.433 | CY49: =CE49*AM49 -> 13352.907 | CZ49: =CF49*AN49 -> 15526.046 | DA49: =CG49*AO49 -> 18035.559 | DC49: 85.874944 | DD49: 84.489929 | DE49: 82.599401 | DF49: 80.133573 | DH49: -705.956 | DI49: -705.956 | DJ49: -705.956 | DK49: -705.956 | DT49: =_xlfn.RRI(DT$2,$H49,CN49+$DO49*$DT$2) -> #VALUE! | DU49: =_xlfn.RRI(DU$2,$H49,CO49+$DO49*$DT$2+SUM($DP49:DP49)) -> #VALUE! | DV49: =_xlfn.RRI(DV$2,$H49,CP49+$DO49*$DT$2+SUM($DP49:DQ49)) -> #VALUE! | DW49: =_xlfn.RRI(DW$2,$H49,CQ49+$DO49*$DT$2+SUM($DP49:DR49)) -> #VALUE! | DX49: =SUM(CN49,$DO49:DO49)/$H49 -> #VALUE! | DY49: =SUM(CO49,$DO49:DP49)/$H49 -> #VALUE! | DZ49: =SUM(CP49,$DO49:DQ49)/$H49 -> #VALUE! | EA49: =SUM(CQ49,$DO49:DR49)/$H49 -> #VALUE! | EB49: {=_xll.BDP(""&$B49&"","CHG_PCT_1M")/100} -> -0.06847235 | EC49: {=_xll.BDP(""&$B49&"","CHG_PCT_3M")/100} -> -0.2362764 | ED49: {=_xll.BDP(""&$B49&"","CHG_PCT_6M")/100} -> -0.3554723 | EE49: =_xlfn.RRI(2+$DT$2,$DT$2*S49+(1-$DT$2)*T49,V49) -> 0.16720543 | EK49: =DV49 -> #VALUE! | EL49: =_xlfn.RRI(3,AK49,AN49) -> 0.17779125 | EM49: =_xlfn.RRI(3,BC49,BF49) -> 0.55069489 | EN49: {=_xll.BDP(B49,"AVG_DAILY_VALUE_TRADED_3M")/10^6} -> 217.82213 | EQ49: =IFERROR(AVERAGE(DP49:DQ49)/H49,0) -> 0 | ER49: =_xlfn.RRI(2+$DT$2,$DT$2*(BC49)+(1-$DT$2)*(BD49),(BF49)) -> 0.5148128 | ES49: =ER49-EG49+EQ49 -> 0.5148128 | EU49: =_xlfn.RRI(2+$DT$2,($DT$2*BY49+(1-$DT$2)*BZ49),CF49) -> #VALUE! | FF49: 0.1 | FG49: -0.1 | FH49: =FF49-FG49 -> 0.2 | FI49: =FT49/CF49-1 -> 0.41176471 | FJ49: =FU49/CF49-1 -> -0.29411765 | FK49: =FI49-FJ49 -> 0.70588235 | FL49: =FF49+FG49 -> 0 | FM49: =FJ49+FI49 -> 0.11764706 | FN49: =EK49+FF49/3+FI49/3 -> #VALUE! | FO49: =EK49+FG49/3+FJ49/3 -> #VALUE! | FP49: =EK49+FL49/3+FM49/3 -> #VALUE! | FQ49: =EK49 -> #VALUE! | FR49: =FP49-FQ49 -> #VALUE! | FS49: =FN49-FO49 -> #VALUE! | FT49: 12 | FU49: 6 | FV49: Mendo GP = Fully Ramped ARR basis GP; GWRE uses Jul FYE, CY calculated using avg.
B50: IOT US Equity | D50: IOT | F50: 46119 | H50: {=_xll.BQL($B50, "px_last", "dates=" & _xll.BQL.DATE($D$2))} -> #N/A Connection | I50: 584 | M50: =K50+J50 -> 0 | N50: =I50*H50+M50+L50 -> #VALUE! | O50: 652.545 | P50: 937.385 | Q50: 1249.199 | R50: 1597 | S50: 2015.4619 | T50: 2499.0955 | U50: 3043.4161 | V50: 3647.0294 | W50: 4306.7083 | X50: 0.73459302 | Y50: 0.75004187 | Z50: 0.77347724 | AA50: 0.77457733 | AB50: 0.77570322 | AC50: 0.77653475 | AD50: 0.77715451 | AE50: 0.77762546 | AF50: 0.77798918 | AG50: =X50*O50 -> 479.355 | AH50: =Y50*P50 -> 703.078 | AI50: =Z50*Q50 -> 966.227 | AJ50: =AA50*R50 -> 1237 | AK50: =AB50*S50 -> 1563.4003 | AL50: =AC50*T50 -> 1940.6345 | AM50: =AD50*U50 -> 2365.2045 | AN50: =AE50*V50 -> 2836.023 | AO50: =AF50*W50 -> 3350.5725 | AP50: -0.1262777 | AQ50: 0.067343595 | AR50: 0.25699685 | AS50: 0.50684932 | AT50: 0.64130837 | AU50: 0.93597582 | AV50: 1.2984003 | AW50: 1.7374877 | AX50: 2.2625348 | AY50: -0.4811044 | AZ50: -0.50959752 | BA50: -0.26787207 | BB50: -0.073630137 | BC50: -0.014882745 | BD50: 0.19679475 | BE50: 0.46873863 | BF50: 0.80881649 | BG50: 1.2253431 | BH50: =$N50/Q50 -> #VALUE! | BI50: =$N50/R50 -> #VALUE! | BJ50: =$N50/S50 -> #VALUE! | BK50: =$N50/T50 -> #VALUE! | BL50: =$N50/U50 -> #VALUE! | BM50: =$N50/V50 -> #VALUE! | BN50: =$N50/W50 -> #VALUE! | BO50: =$N50/AK50 -> #VALUE! | BP50: =$N50/AL50 -> #VALUE! | BQ50: =$N50/AM50 -> #VALUE! | BR50: =$N50/AN50 -> #VALUE! | BS50: =$N50/AO50 -> #VALUE! | BT50: =$H50/AT50 -> #VALUE! | BU50: =$H50/AU50 -> #VALUE! | BV50: =$H50/AV50 -> #VALUE! | BW50: =$H50/AW50 -> #VALUE! | BX50: =$H50/AX50 -> #VALUE! | BY50: n/a | BZ50: =$H50/BD50 -> #VALUE! | CA50: =$H50/BE50 -> #VALUE! | CB50: =$H50/BF50 -> #VALUE! | CC50: =$H50/BG50 -> #VALUE! | CD50: 7 | CE50: 7 | CF50: 7 | CG50: 7 | CH50: 10 | CN50: =CD50*AL50/DD50+CS50 -> 23.38374 | CO50: =CE50*AM50/DE50+CT50 -> 28.846648 | CP50: =CF50*AN50/DF50+CU50 -> 35.223593 | CQ50: =CG50*AO50/DG50+CV50 -> 42.622405 | DC50: 584.30247 | DD50: 580.93536 | DE50: 573.94647 | DF50: 563.60408 | DG50: 550.27415 | DT50: =_xlfn.RRI(DT$2,$H50,CN50+$DO50*$DT$2) -> #VALUE! | DU50: =_xlfn.RRI(DU$2,$H50,CO50+$DO50*$DT$2+SUM($DP50:DP50)) -> #VALUE! | DV50: =_xlfn.RRI(DV$2,$H50,CP50+$DO50*$DT$2+SUM($DP50:DQ50)) -> #VALUE! | DW50: =_xlfn.RRI(DW$2,$H50,CQ50+$DO50*$DT$2+SUM($DP50:DR50)) -> #VALUE! | DX50: =SUM(CN50,$DO50:DO50)/$H50 -> #VALUE! | DY50: =SUM(CO50,$DO50:DP50)/$H50 -> #VALUE! | DZ50: =SUM(CP50,$DO50:DQ50)/$H50 -> #VALUE! | EA50: =SUM(CQ50,$DO50:DR50)/$H50 -> #VALUE! | EB50: {=_xll.BDP(""&$B50&"","CHG_PCT_1M")/100} -> 0.1529926 | EC50: {=_xll.BDP(""&$B50&"","CHG_PCT_3M")/100} -> -0.0302602 | ED50: {=_xll.BDP(""&$B50&"","CHG_PCT_6M")/100} -> -0.2164076 | EE50: =_xlfn.RRI(2+$DT$2,$DT$2*S50+(1-$DT$2)*T50,V50) -> 0.21221245 | EF50: n/a | EG50: n/a | EH50: n/a | EI50: n/a | EJ50: n/a | EK50: =DV50 -> #VALUE! | EL50: =_xlfn.RRI(3,AK50,AN50) -> 0.21958811 | EM50: n/a | EN50: {=_xll.BDP(B50,"AVG_DAILY_VALUE_TRADED_3M")/10^6} -> 223.49102 | EQ50: =IFERROR(AVERAGE(DP50:DQ50)/H50,0) -> 0 | ER50: =_xlfn.RRI(2+$DT$2,$DT$2*(BC50)+(1-$DT$2)*(BD50),(BF50)) -> 1.4882402 | ES50: =ER50-EG50+EQ50 -> #VALUE! | EU50: =_xlfn.RRI(2+$DT$2,($DT$2*BY50+(1-$DT$2)*BZ50),CF50) -> #VALUE! | FF50: 0.15 | FG50: -0.15 | FH50: =FF50-FG50 -> 0.3 | FI50: =FT50/CF50-1 -> 0.42857143 | FJ50: =FU50/CF50-1 -> -0.21428571 | FK50: =FI50-FJ50 -> 0.64285714 | FL50: =FF50+FG50 -> 0 | FM50: =FJ50+FI50 -> 0.21428571 | FN50: =EK50+FF50/3+FI50/3 -> #VALUE! | FO50: =EK50+FG50/3+FJ50/3 -> #VALUE! | FP50: =EK50+FL50/3+FM50/3 -> #VALUE! | FQ50: =EK50 -> #VALUE! | FR50: =FP50-FQ50 -> #VALUE! | FS50: =FN50-FO50 -> #VALUE! | FT50: 10 | FU50: 5.5
B51: FROG US Equity | D51: FROG | F51: 46119 | H51: {=_xll.BQL($B51, "px_last", "dates=" & _xll.BQL.DATE($D$2))} -> #N/A Connection | I51: 121.849 | M51: =K51+J51 -> 0 | N51: =I51*H51+M51+L51 -> #VALUE! | O51: 280.04 | P51: 349.886 | Q51: 428.488 | R51: 531.84 | S51: 665.41555 | T51: 826.13258 | U51: 1017.0984 | V51: 1241.1346 | W51: 1500.5796 | X51: 0.83985145 | Y51: 0.83739275 | Z51: 0.83796046 | AA51: 0.83345743 | AB51: 0.82674118 | AC51: 0.82153892 | AD51: 0.81749487 | AE51: 0.81433688 | AF51: 0.81185808 | AG51: =X51*O51 -> 235.192 | AH51: =Y51*P51 -> 292.992 | AI51: =Z51*Q51 -> 359.056 | AJ51: =AA51*R51 -> 443.266 | AK51: =AB51*S51 -> 550.12644 | AL51: =AC51*T51 -> 678.70007 | AM51: =AD51*U51 -> 831.47271 | AN51: =AE51*V51 -> 1010.7017 | AO51: =AF51*W51 -> 1218.2577 | AP51: 0.035418991 | AQ51: 0.51477076 | AR51: 0.64781768 | AS51: 0.82052376 | AT51: 0.97873873 | AU51: 1.3183562 | AV51: 1.7754967 | AW51: 2.3788924 | AX51: 3.162259 | AY51: -0.61937459 | AZ51: -0.35809342 | BA51: -0.48959373 | BB51: -0.46514128 | BC51: -0.30251127 | BD51: -0.11451466 | BE51: 0.17248503 | BF51: 0.58446619 | BG51: 1.1519037 | BH51: =$N51/Q51 -> #VALUE! | BI51: =$N51/R51 -> #VALUE! | BJ51: =$N51/S51 -> #VALUE! | BK51: =$N51/T51 -> #VALUE! | BL51: =$N51/U51 -> #VALUE! | BM51: =$N51/V51 -> #VALUE! | BN51: =$N51/W51 -> #VALUE! | BO51: =$N51/AK51 -> #VALUE! | BP51: =$N51/AL51 -> #VALUE! | BQ51: =$N51/AM51 -> #VALUE! | BR51: =$N51/AN51 -> #VALUE! | BS51: =$N51/AO51 -> #VALUE! | BT51: =$H51/AT51 -> #VALUE! | BU51: =$H51/AU51 -> #VALUE! | BV51: =$H51/AV51 -> #VALUE! | BW51: =$H51/AW51 -> #VALUE! | BX51: =$H51/AX51 -> #VALUE! | BY51: n/a | BZ51: n/a | CA51: =$H51/BE51 -> #VALUE! | CB51: =$H51/BF51 -> #VALUE! | CC51: =$H51/BG51 -> #VALUE! | CD51: 7 | CE51: 7 | CF51: 7 | CG51: 7 | CH51: 6 | CN51: =CD51*(T51/DD51)+CS51 -> 45.081325 | CO51: =CE51*(U51/DE51)+CT51 -> 55.659525 | CP51: =CF51*(V51/DF51)+CU51 -> 68.487062 | CQ51: =CG51*(W51/DG51)+CV51 -> 83.989038 | DC51: 128 | DD51: 128.27769 | DE51: 127.91501 | DF51: 126.85523 | DG51: 125.06462 | DT51: =_xlfn.RRI(DT$2,$H51,CN51+$DO51*$DT$2) -> #VALUE! | DU51: =_xlfn.RRI(DU$2,$H51,CO51+$DO51*$DT$2+SUM($DP51:DP51)) -> #VALUE! | DV51: =_xlfn.RRI(DV$2,$H51,CP51+$DO51*$DT$2+SUM($DP51:DQ51)) -> #VALUE! | DW51: =_xlfn.RRI(DW$2,$H51,CQ51+$DO51*$DT$2+SUM($DP51:DR51)) -> #VALUE! | DX51: =SUM(CN51,$DO51:DO51)/$H51 -> #VALUE! | DY51: =SUM(CO51,$DO51:DP51)/$H51 -> #VALUE! | DZ51: =SUM(CP51,$DO51:DQ51)/$H51 -> #VALUE! | EA51: =SUM(CQ51,$DO51:DR51)/$H51 -> #VALUE! | EB51: {=_xll.BDP(""&$B51&"","CHG_PCT_1M")/100} -> 0.2297661 | EC51: {=_xll.BDP(""&$B51&"","CHG_PCT_3M")/100} -> 1.137472 | ED51: {=_xll.BDP(""&$B51&"","CHG_PCT_6M")/100} -> 0.3393023 | EE51: =_xlfn.RRI(2+$DT$2,$DT$2*S51+(1-$DT$2)*T51,V51) -> 0.22635441 | EF51: n/a | EG51: n/a | EH51: n/a | EI51: n/a | EJ51: n/a | EK51: =DV51 -> #VALUE! | EL51: =_xlfn.RRI(3,AK51,AN51) -> 0.22476703 | EM51: n/a | EN51: {=_xll.BDP(B51,"AVG_DAILY_VALUE_TRADED_3M")/10^6} -> 152.34379 | EQ51: =IFERROR(AVERAGE(DP51:DQ51)/H51,0) -> 0 | ER51: =_xlfn.RRI(2+$DT$2,$DT$2*(BC51)+(1-$DT$2)*(BD51),(BF51)) -> #NUM! | ES51: =ER51-EG51+EQ51 -> #NUM! | EU51: =_xlfn.RRI(2+$DT$2,($DT$2*BY51+(1-$DT$2)*BZ51),CF51) -> #VALUE! | FF51: 0.2 | FG51: -0.15 | FH51: =FF51-FG51 -> 0.35 | FI51: =FT51/CF51-1 -> 0.28571429 | FJ51: =FU51/CF51-1 -> -0.28571429 | FK51: =FI51-FJ51 -> 0.57142857 | FL51: =FF51+FG51 -> 0.05 | FM51: =FJ51+FI51 -> 0 | FN51: =EK51+FF51/3+FI51/3 -> #VALUE! | FO51: =EK51+FG51/3+FJ51/3 -> #VALUE! | FP51: =EK51+FL51/3+FM51/3 -> #VALUE! | FQ51: =EK51 -> #VALUE! | FR51: =FP51-FQ51 -> #VALUE! | FS51: =FN51-FO51 -> #VALUE! | FT51: 9 | FU51: 5
D53: Index
B54: B500XM7T INDEX | D54: B500XM7T | BY54: {=_xll.BDP($D54&" Index","best_pe_ratio","best_fperiod_override="&(BY$5-2025)&"fy")} -> 20.634287 | BZ54: {=_xll.BDP($D54&" Index","best_pe_ratio","best_fperiod_override="&(BZ$5-2025)&"fy")} -> 17.858564 | CA54: {=_xll.BDP($D54&" Index","best_pe_ratio","best_fperiod_override="&(CA$5-2025)&"fy")} -> 16.206752 | EB54: {=_xll.BDP(""&$B54&"","CHG_PCT_1M")/100} -> 0.03230227 | EC54: {=_xll.BDP(""&$B54&"","CHG_PCT_3M")/100} -> 0.1015597 | ED54: {=_xll.BDP(""&$B54&"","CHG_PCT_6M")/100} -> 0.1180842
B55: SPX INDEX | D55: SPX | BY55: {=_xll.BDP($D55&" Index","best_pe_ratio","best_fperiod_override="&(BY$5-2025)&"fy")} -> 21.819136 | BZ55: {=_xll.BDP($D55&" Index","best_pe_ratio","best_fperiod_override="&(BZ$5-2025)&"fy")} -> 18.832115 | CA55: {=_xll.BDP($D55&" Index","best_pe_ratio","best_fperiod_override="&(CA$5-2025)&"fy")} -> 16.765531 | EB55: {=_xll.BDP(""&$B55&"","CHG_PCT_1M")/100} -> 0.00573325 | EC55: {=_xll.BDP(""&$B55&"","CHG_PCT_3M")/100} -> 0.1040546 | ED55: {=_xll.BDP(""&$B55&"","CHG_PCT_6M")/100} -> 0.08688227

Sheet Sheet1
B2: 46161 | M2: Revs | V2: GM | AE2: Adj GP | AN2: Adj EPS | AW2: Mendo EPS | BF2: EV / Revs | BM2: EV / GP | BR2: P/E (Adj, Ex SBC) | BW2: Mendo P/E | CB2: Target Multiple (Mendo EPS or GP) | CC2: Target Multiple (Mendo EPS or GP) | CE2: Target Mult (GP or P/E) | CH2: Target Px (old, hardcoded) | CM2: Derived Target Px for IRR calc | CR2: Net Cash per Share | CW2: EV | DB2: WADSO | DG2: Net Debt | DN2: DPS | DS2: IRR | DT2: IRR | DW2: MoM | EA2: Recent Performance | ED2: NTM - YE28 IRR Decomp | EK2: '26-'29 CAGR
B3: Company | C3: Port | D3: Update | E3: Update by | F3: Px | G3: Shares | H3: Cash | I3: Debt | J3: Min Int | K3: Net Debt | L3: EV | M3: 2022 | N3: 2023 | O3: 2024 | P3: 2025 | Q3: 2026 | R3: 2027 | S3: 2028 | T3: 2029 | U3: 2030 | V3: 2022 | W3: 2023 | X3: 2024 | Y3: 2025 | Z3: 2026 | AA3: 2027 | AB3: 2028 | AC3: 2029 | AD3: 2030 | AE3: 2022 | AF3: 2023 | AG3: 2024 | AH3: 2025 | AI3: 2026 | AJ3: 2027 | AK3: 2028 | AL3: 2029 | AM3: 2030 | AN3: 2022 | AO3: 2023 | AP3: 2024 | AQ3: 2025 | AR3: 2026 | AS3: 2027 | AT3: 2028 | AU3: 2029 | AV3: 2030 | AW3: 2022 | AX3: 2023 | AY3: 2024 | AZ3: 2025 | BA3: 2026 | BB3: 2027 | BC3: 2028 | BD3: 2029 | BE3: 2030 | BF3: 2024 | BG3: 2025 | BH3: 2026 | BI3: 2027 | BJ3: 2028 | BK3: 2029 | BL3: 2030 | BM3: 2026 | BN3: 2027 | BO3: 2028 | BP3: 2029 | BQ3: 2030 | BR3: 2026 | BS3: 2027 | BT3: 2028 | BU3: 2029 | BV3: 2030 | BW3: 2026 | BX3: 2027 | BY3: 2028 | BZ3: 2029 | CA3: 2030 | CB3: Metric | CC3: 2026 | CD3: 2027 | CE3: 2028 | CF3: 2029 | CG3: 2030 | CH3: 2026 | CI3: 2027 | CJ3: 2028 | CK3: 2029 | CL3: 2030 | CM3: 2026 | CN3: 2027 | CO3: 2028 | CP3: 2029 | CQ3: 2030 | CR3: 2026 | CS3: 2027 | CT3: 2028 | CU3: 2029 | CV3: 2030 | CW3: 2026 | CX3: 2027 | CY3: 2028 | CZ3: 2029 | DA3: 2030 | DB3: 2026 | DC3: 2027 | DD3: 2028 | DE3: 2029 | DF3: 2030 | DG3: 2026 | DH3: 2027 | DI3: 2028 | DJ3: 2029 | DK3: 2030 | DN3: 2026 | DO3: 2027 | DP3: 2028 | DQ3: 2029 | DR3: 2030 | DS3: 2026 | DT3: 2027 | DU3: 2028 | DV3: 2029 | DW3: 2026 | DX3: 2027 | DY3: 2028 | DZ3: 2029 | EA3: 1M | EB3: 3M | EC3: 6M | ED3: Revs | EE3: Margin | EF3: Mendo NI | EG3: Yield | EH3: EPS + Divs | EI3: Multiple | EJ3: Return | EK3: GP | EL3: mEPS
B4: TMSC | D4: 46140 | F4: 2205 | G4: 25930 | H4: -3192142.3 | I4: 1036072.4 | K4: -2156069.9 | L4: 55019580 | M4: 2263891.3 | N4: 2161735.8 | O4: 2894307.7 | P4: 3809054.3 | Q4: 5039894.5 | R4: 6594728.5 | S4: 8633128.7 | T4: 10355421 | U4: 12283063 | V4: 0.59559167 | W4: 0.54359585 | X4: 0.56122352 | Y4: 0.59891349 | Z4: 0.66920044 | AA4: 0.66322768 | AB4: 0.65343679 | AC4: 0.62939631 | AD4: 0.61454739 | AE4: 1348354.8 | AF4: 1175110.6 | AG4: 1624353.6 | AH4: 2281294 | AI4: 3372699.6 | AJ4: 4373806.4 | AK4: 5641203.9 | AL4: 6517663.5 | AM4: 7548524.5 | AN4: 39.204375 | AO4: 32.338218 | AP4: 45.247501 | AQ4: 66.248221 | AR4: 94.04858 | AS4: 122.02141 | AT4: 157.5557 | AU4: 182.32036 | AV4: 211.90932 | AW4: 39.204375 | AX4: 32.338218 | AY4: 45.247501 | AZ4: 66.248221 | BA4: 94.04858 | BB4: 122.02141 | BC4: 157.5557 | BD4: 182.32036 | BE4: 211.90932 | BF4: 19.009582 | BG4: 14.44442 | BH4: 10.916812 | BI4: 8.3429637 | BJ4: 6.3730754 | BK4: 5.3131188 | BL4: 4.4793045 | BM4: 16.313217 | BN4: 12.579336 | BO4: 9.7531628 | BP4: 8.441611 | BQ4: 7.2887861 | BR4: 23.44533 | BS4: 18.0706 | BT4: 13.995051 | BU4: 12.094097 | BV4: 10.405394 | BW4: 23.44533 | BX4: 18.0706 | BY4: 13.995051 | BZ4: 12.094097 | CA4: 10.405394 | CC4: 20 | CD4: 20 | CE4: 20 | CF4: 20 | CG4: 18 | CM4: 2558.166 | CN4: 3322.4769 | CO4: 3888.5981 | CP4: 4566.6877 | CR4: 117.73782 | CS4: 171.36295 | CT4: 242.19095 | CU4: 328.50126 | CV4: 431.59469 | DB4: 25931 | DC4: 25931 | DD4: 25931 | DE4: 25931 | DF4: 25931 | DN4: 22.501022 | DO4: 28.126277 | DP4: 35.157847 | DQ4: 43.947308 | DR4: 54.934135 | DS4: 0.28236731 | DT4: 0.29819309 | DU4: 0.2512085 | DV4: 0.23170919 | DW4: 1.1703705 | DX4: 1.5297525 | DY4: 1.8024414 | DZ4: 2.1298957 | EA4: 0.0862069 | EB4: 0.151436 | EC4: 0.5806452 | ED4: 0.26179136 | EE4: -0.025932014 | EF4: 0.23585935 | EG4: 0.041935738 | EH4: 0.27779508 | EI4: -0.026586582 | EJ4: 0.2512085 | EK4: 0.24557942 | EL4: 0.24688856
B5: ORCL | C5: 2 | D5: 46016 | F5: 184.4149 | G5: 2922 | H5: -19766 | I5: 108075 | J5: 506 | K5: 88309 | L5: 627675.34 | M5: 46823.167 | N5: 51708.083 | O5: 55549.833 | P5: 62562.083 | Q5: 77012.5 | R5: 103966.33 | S5: 130624.99 | T5: 149866.65 | U5: 167111.32 | V5: 0.76192697 | W5: 0.73268847 | X5: 0.72284795 | Y5: 0.68592365 | Z5: 0.63612969 | AA5: 0.56715623 | AB5: 0.54624472 | AC5: 0.55 | AD5: 0.55 | AE5: 35675.833 | AF5: 37885.917 | AG5: 40154.083 | AH5: 42912.812 | AI5: 48989.938 | AJ5: 58965.153 | AK5: 71353.209 | AL5: 82426.659 | AM5: 91911.225 | AN5: 5.0327385 | AO5: 5.3817054 | AP5: 5.8366619 | AQ5: 6.1956217 | AR5: 7.1496288 | AS5: 8.6706219 | AT5: 10.806073 | AU5: 12.978162 | AV5: 15.177568 | AW5: 4.0793636 | AX5: 4.2709302 | AY5: 4.5984827 | AZ5: 4.88448 | BA5: 5.6197485 | BB5: 6.5941229 | BC5: 8.1840838 | BD5: 9.9518601 | BE5: 11.758517 | BF5: 11.29932 | BG5: 10.03284 | BH5: 8.1503047 | BI5: 6.0372942 | BJ5: 4.8051706 | BK5: 4.1882255 | BL5: 3.7560313 | BM5: 12.812332 | BN5: 10.644852 | BO5: 8.796736 | BP5: 7.6149555 | BQ5: 6.8291478 | BR5: 25.793633 | BS5: 21.268936 | BT5: 17.065858 | BU5: 14.209631 | BV5: 12.150491 | BW5: 32.815508 | BX5: 27.966555 | BY5: 22.533359 | BZ5: 18.530697 | CA5: 15.683517 | CC5: 22 | CD5: 22 | CE5: 22 | CF5: 22 | CG5: 27 | CH5: 178.04132 | CI5: 220.97026 | CJ5: 268.70022 | CK5: 317.47995 | CM5: 145.0707 | CN5: 180.04984 | CO5: 218.94092 | CP5: 258.68737 | DB5: 2876.5202 | DC5: 2915.0938 | DD5: 2942.9543 | DE5: 2921.0293 | DF5: 2857.4352 | DN5: 1.9529574 | DO5: 2.0588007 | DP5: 2.3470286 | DQ5: 2.5646852 | DS5: -0.31212684 | DT5: -0.0036780882 | DU5: 0.078089342 | DV5: 0.10750787 | DW5: 0.79724394 | DX5: 0.99808422 | DY5: 1.2217001 | DZ5: 1.4511346 | EA5: 0.05235349 | EB5: 0.1768558 | EC5: -0.1831464 | ED5: 0.22927265 | EE5: -0.0109222 | EF5: 0.21835045 | EG5: 0.0074187422 | EH5: 0.22576919 | EI5: -0.14767985 | EJ5: 0.078089342 | EK5: 0.18937901 | EL5: 0.20984331
B6: FROG | D6: 46119 | F6: 68.050003 | G6: 121.849 | K6: 0 | L6: 8291.8248 | M6: 280.04 | N6: 349.886 | O6: 428.488 | P6: 531.84 | Q6: 665.41555 | R6: 826.13258 | S6: 1017.0984 | T6: 1241.1346 | U6: 1500.5796 | V6: 0.83985145 | W6: 0.83739275 | X6: 0.83796046 | Y6: 0.83345743 | Z6: 0.82674118 | AA6: 0.82153892 | AB6: 0.81749487 | AC6: 0.81433688 | AD6: 0.81185808 | AE6: 235.192 | AF6: 292.992 | AG6: 359.056 | AH6: 443.266 | AI6: 550.12644 | AJ6: 678.70007 | AK6: 831.47271 | AL6: 1010.7017 | AM6: 1218.2577 | AN6: 0.035418991 | AO6: 0.51477076 | AP6: 0.64781768 | AQ6: 0.82052376 | AR6: 0.97873873 | AS6: 1.3183562 | AT6: 1.7754967 | AU6: 2.3788924 | AV6: 3.162259 | AW6: -0.61937459 | AX6: -0.35809342 | AY6: -0.48959373 | AZ6: -0.46514128 | BA6: -0.30251127 | BB6: -0.11451466 | BC6: 0.17248503 | BD6: 0.58446619 | BE6: 1.1519037 | BF6: 19.351358 | BG6: 15.590826 | BH6: 12.461123 | BI6: 10.036918 | BJ6: 8.1524314 | BK6: 6.6808427 | BL6: 5.5257482 | BM6: 15.07258 | BN6: 12.217215 | BO6: 9.9724558 | BP6: 8.2040282 | BQ6: 6.8062981 | BR6: 69.528262 | BS6: 51.617311 | BT6: 38.327305 | BU6: 28.605751 | BV6: 21.519428 | BW6: n/a | BX6: n/a | BY6: 394.52701 | BZ6: 116.43103 | CA6: 59.076123 | CC6: 7 | CD6: 7 | CE6: 7 | CF6: 7 | CG6: 6 | CM6: 45.081325 | CN6: 55.659525 | CO6: 68.487062 | CP6: 83.989038 | DB6: 128 | DC6: 128.27769 | DD6: 127.91501 | DE6: 126.85523 | DF6: 125.06462 | DS6: -0.48574414 | DT6: -0.11673553 | DU6: 0.0024472979 | DV6: 0.059870543 | DW6: 0.66247351 | DX6: 0.81792097 | DY6: 1.0064226 | DZ6: 1.2342253 | EA6: 0.5423844 | EB6: 0.3531517 | EC6: 0.11814 | ED6: 0.22679692 | EE6: n/a | EF6: n/a | EG6: n/a | EH6: n/a | EI6: n/a | EJ6: 0.0024472979 | EK6: 0.22476703 | EL6: n/a
B7: IOT | D7: 46119 | F7: 31.25 | G7: 584 | K7: 0 | L7: 18250 | M7: 652.545 | N7: 937.385 | O7: 1249.199 | P7: 1597 | Q7: 2015.4619 | R7: 2499.0955 | S7: 3043.4161 | T7: 3647.0294 | U7: 4306.7083 | V7: 0.73459302 | W7: 0.75004187 | X7: 0.77347724 | Y7: 0.77457733 | Z7: 0.77570322 | AA7: 0.77653475 | AB7: 0.77715451 | AC7: 0.77762546 | AD7: 0.77798918 | AE7: 479.355 | AF7: 703.078 | AG7: 966.227 | AH7: 1237 | AI7: 1563.4003 | AJ7: 1940.6345 | AK7: 2365.2045 | AL7: 2836.023 | AM7: 3350.5725 | AN7: -0.1262777 | AO7: 0.067343595 | AP7: 0.25699685 | AQ7: 0.50684932 | AR7: 0.64130837 | AS7: 0.93597582 | AT7: 1.2984003 | AU7: 1.7374877 | AV7: 2.2625348 | AW7: -0.4811044 | AX7: -0.50959752 | AY7: -0.26787207 | AZ7: -0.073630137 | BA7: -0.014882745 | BB7: 0.19679475 | BC7: 0.46873863 | BD7: 0.80881649 | BE7: 1.2253431 | BF7: 14.609362 | BG7: 11.427677 | BH7: 9.0549961 | BI7: 7.3026422 | BJ7: 5.9965511 | BK7: 5.0040726 | BL7: 4.2375751 | BM7: 11.673274 | BN7: 9.4041409 | BO7: 7.7160346 | BP7: 6.4350678 | BQ7: 5.4468304 | BR7: 48.728508 | BS7: 33.387615 | BT7: 24.068078 | BU7: 17.985739 | BV7: 13.811942 | BW7: n/a | BX7: 158.79489 | BY7: 66.668284 | BZ7: 38.6367 | CA7: 25.50306 | CC7: 7 | CD7: 7 | CE7: 7 | CF7: 7 | CG7: 10 | CM7: 23.38374 | CN7: 28.846648 | CO7: 35.223593 | CP7: 42.622405 | DB7: 584.30247 | DC7: 580.93536 | DD7: 573.94647 | DE7: 563.60408 | DF7: 550.27415 | DS7: -0.37395191 | DT7: -0.048222108 | DU7: 0.046760453 | DV7: 0.089538774 | DW7: 0.74827967 | DX7: 0.92309274 | DY7: 1.127155 | DZ7: 1.363917 | EA7: 0.02286085 | EB7: 0.1686567 | EC7: -0.1407408 | ED7: 0.21293735 | EE7: n/a | EF7: n/a | EG7: n/a | EH7: n/a | EI7: n/a | EJ7: 0.046760453 | EK7: 0.21958811 | EL7: n/a
B8: MCHP | D8: 46119 | F8: 91.875 | G8: 566.41788 | H8: -250.7 | I8: 5366 | K8: 5115.3 | L8: 57154.943 | M8: 8034.25 | N8: 7835.475 | O8: 5209.8 | P8: 4507.3709 | Q8: 5696.8212 | R8: 8093.4529 | S8: 9312.8626 | T8: 10284.115 | U8: 11715.82 | V8: 0.67843388 | W8: 0.65828356 | X8: 0.57020174 | Y8: 0.5703747 | Z8: 0.64826825 | AA8: 0.67069849 | AB8: 0.6678242 | AC8: 0.66558694 | AD8: 0.66386262 | AE8: 5450.7074 | AF8: 5157.9644 | AG8: 2970.6371 | AH8: 2570.8903 | AI8: 3693.0683 | AJ8: 5428.2666 | AK8: 6219.355 | AL8: 6844.9727 | AM8: 7777.6948 | AN8: 5.6675 | AO8: 5.195 | AP8: 2.2125 | AQ8: 1.3482914 | AR8: 2.5475875 | AS8: 4.6130732 | AT8: 5.684263 | AU8: 6.5062783 | AV8: 7.6602042 | AW8: 5.3680144 | AX8: 4.8992851 | AY8: 1.8543936 | AZ8: 0.97340059 | BA8: 2.1235228 | BB8: 4.099978 | BC8: 5.1266802 | BD8: 5.9210093 | BE8: 7.0466053 | BF8: 10.97066 | BG8: 12.680328 | BH8: 10.032778 | BI8: 7.0618738 | BJ8: 6.1372046 | BK8: 5.5575946 | BL8: 4.8784416 | BM8: 15.476276 | BN8: 10.529133 | BO8: 9.1898505 | BP8: 8.3499154 | BQ8: 7.348571 | BR8: 36.06353 | BS8: 19.916224 | BT8: 16.163045 | BU8: 14.120976 | BV8: 11.993806 | BW8: 43.26537 | BX8: 22.408657 | BY8: 17.920954 | BZ8: 15.51678 | CA8: 13.038193 | CC8: 20 | CD8: 20 | CE8: 20 | CF8: 20 | CG8: 20 | CM8: 81.99956 | CN8: 102.5336 | CO8: 118.42019 | CP8: 140.93211 | DB8: 537.3 | DC8: 537.3 | DD8: 549.08629 | DE8: 543.66703 | DF8: 531.92173 | DG8: 4832.1612 | DH8: 4019.5209 | DI8: 3717.7957 | DJ8: 3700 | DK8: 3700 | DN8: 1.9522 | DO8: 2.14742 | DP8: 2.362162 | DQ8: 2.5983782 | DR8: 2.858216 | DS8: -0.14787429 | DT8: 0.091638938 | DU8: 0.12177221 | DV8: 0.14346108 | DW8: 0.91376065 | DX8: 1.1606337 | DY8: 1.3592595 | DZ8: 1.6325689 | EA8: 0.168423 | EB8: 0.1926516 | EC8: 0.8115158 | ED8: 0.18387138 | EE8: 0.13948446 | EF8: 0.32335584 | EG8: 0.018603197 | EH8: 0.34195903 | EI8: -0.22018682 | EJ8: 0.12177221 | EK8: 0.22836696 | EL8: 0.40749309
B9: TTAN | D9: 46119 | F9: 62.549999 | G9: 94.113302 | H9: -429.352 | K9: -429.352 | L9: 5457.435 | M9: 467.734 | N9: 614.341 | O9: 771.878 | P9: 960.965 | Q9: 1170.4399 | R9: 1410.8055 | S9: 1660.2376 | T9: 1947.3317 | U9: 2257.7347 | AE9: 297.192 | AF9: 417.619 | AG9: 543.259 | AH9: 711.483 | AI9: 879.37455 | AJ9: 1078.9008 | AK9: 1288.1882 | AL9: 1530.7204 | AM9: 1795.2715 | AN9: -5.2035863 | AO9: -2.2611508 | AP9: 0.39239782 | AQ9: 1.100849 | AR9: 1.7962606 | AS9: 2.7051749 | AT9: 3.8034995 | AU9: 5.1971525 | AV9: 6.861089 | AW9: -7.1522428 | AX9: -5.5200758 | AY9: -3.0958693 | AZ9: -0.94337005 | BA9: -0.49851227 | BB9: 0.2427629 | BC9: 1.2372221 | BD9: 2.4508639 | BE9: 3.8433139 | BF9: 7.0703336 | BG9: 5.6791194 | BH9: 4.6627211 | BI9: 3.8683114 | BJ9: 3.287141 | BK9: 2.8025194 | BL9: 2.4172171 | BM9: 6.2060415 | BN9: 5.0583286 | BO9: 4.23652 | BP9: 3.5652722 | BQ9: 3.0398939 | BR9: 34.82234 | BS9: 23.12235 | BT9: 16.445381 | BU9: 12.035437 | BV9: 9.1166285 | BW9: n/a | BX9: 257.65881 | BY9: 50.556807 | BZ9: 25.521613 | CA9: 16.275017 | CB9: GP | CC9: 7 | CD9: 7 | CE9: 7 | CF9: 7 | CG9: 8 | CM9: 84.532908 | CN9: 99.85447 | CO9: 118.70166 | CP9: 140.85552 | CW9: 7552.3059 | CX9: 9017.3172 | CY9: 10715.043 | CZ9: 12566.901 | DB9: 94.420718 | DC9: 94.60437 | DD9: 93.885754 | DE9: 92.26655 | DF9: 89.868677 | DG9: -429.352 | DH9: -429.352 | DI9: -429.352 | DJ9: -429.352 | DK9: -429.352 | DS9: 0.62646741 | DT9: 0.33493106 | DU9: 0.27710847 | DV9: 0.25144183 | DW9: 1.3514454 | DX9: 1.5963944 | DY9: 1.8977084 | DZ9: 2.2518868 | EA9: -0.0273674 | EB9: -0.06613919 | EC9: -0.2748667 | ED9: 0.1801213 | EG9: 0.0090529563 | EH9: 0.18917426 | EI9: 0.087934212 | EJ9: 0.27710847 | EK9: 0.20293084 | EL9: n/a
B10: MSFT | C10: 1 | D10: 46119 | F10: 424.66501 | G10: 7460 | H10: -89462 | I10: 63127 | K10: -26335 | L10: 3141666 | M10: 204094 | N10: 227582 | O10: 261803 | P10: 305440 | Q10: 356800.78 | R10: 418430.46 | S10: 491728.15 | T10: 575920.69 | U10: 670017.49 | V10: 0.6815977 | W10: 0.69748486 | X10: 0.69409059 | Y10: 0.68589248 | Z10: 0.68339248 | AA10: 0.68089248 | AB10: 0.67839248 | AC10: 0.67589248 | AD10: 0.67339248 | AE10: 139110 | AF10: 158735 | AG10: 181715 | AH10: 209499 | AI10: 243834.97 | AJ10: 284906.16 | AK10: 333584.68 | AL10: 389260.47 | AM10: 451184.74 | AN10: 9.1199413 | AO10: 11.056696 | AP10: 12.415501 | AQ10: 15.949195 | AR10: 18.277836 | AS10: 21.13818 | AT10: 24.860954 | AU10: 30.196774 | AV10: 36.555023 | AW10: 9.1199413 | AX10: 11.056696 | AY10: 12.415501 | AZ10: 15.949195 | BA10: 18.277836 | BB10: 21.13818 | BC10: 24.860954 | BD10: 30.196774 | BE10: 36.555023 | BF10: 12.000114 | BG10: 10.285706 | BH10: 8.8050983 | BI10: 7.5082152 | BJ10: 6.3890301 | BK10: 5.4550323 | BL10: 4.6889313 | BM10: 12.884394 | BN10: 11.02702 | BO10: 9.4178964 | BP10: 8.070858 | BQ10: 6.9631477 | BR10: 23.233878 | BS10: 20.089951 | BT10: 17.081606 | BU10: 14.063258 | BV10: 11.617145 | BW10: 23.233878 | BX10: 20.089951 | BY10: 17.081606 | BZ10: 14.063258 | CA10: 11.617145 | CC10: 24 | CD10: 24 | CE10: 24 | CF10: 24 | CG10: 24 | CM10: 543.48941 | CN10: 632.905 | CO10: 761.24215 | CP10: 914.51529 | CR10: 36.173085 | CS10: 36.24212 | CT10: 36.51958 | CU10: 37.194743 | CV10: 38.054831 | DB10: 7464.1132 | DC10: 7449.8954 | DD10: 7393.2942 | DE10: 7259.0903 | DF10: 7095.0257 | DG10: -26335 | DH10: -26335 | DI10: -26335 | DJ10: -26335 | DK10: -26335 | DN10: 3.828 | DO10: 4.2108 | DP10: 4.63188 | DQ10: 5.095068 | DR10: 5.6045748 | DS10: 0.50001477 | DT10: 0.28765427 | DU10: 0.25661324 | DV10: 0.2421406 | DW10: 1.2888215 | DX10: 1.5092927 | DY10: 1.8224078 | DZ10: 2.1953328 | EA10: 0.004555433 | EB10: 0.06589371 | EC10: -0.1281081 | ED10: 0.17172814 | EE10: 0.00090035848 | EF10: 0.1726285 | EG10: 0.050861804 | EH10: 0.2234903 | EI10: 0.033122937 | EJ10: 0.25661324 | EK10: 0.16873155 | EL10: 0.18216635
B11: TOST | C11: 1 | D11: 46119 | F11: 23.245001 | G11: 618 | H11: -1770 | I11: 0 | K11: -1770 | L11: 12595.411 | M11: 836.47059 | N11: 1243.5294 | O11: 1667.0588 | P11: 2218.8235 | Q11: 2766.5202 | R11: 3355.8447 | S11: 3937.7108 | T11: 4525.3813 | U11: 5045.1777 | V11: 0.85 | W11: 0.85 | X11: 0.85 | Y11: 0.85 | Z11: 0.85 | AA11: 0.85 | AB11: 0.85 | AC11: 0.85 | AD11: 0.85 | AE11: 711 | AF11: 1057 | AG11: 1417 | AH11: 1886 | AI11: 2351.5422 | AJ11: 2852.468 | AK11: 3347.0542 | AL11: 3846.5741 | AM11: 4288.4011 | AQ11: 1.0010953 | AR11: 1.2767033 | AS11: 1.5569278 | AT11: 2.0688851 | AU11: 2.6263593 | AV11: 3.0576893 | AZ11: 0.50670326 | BA11: 0.76067462 | BB11: 1.0093958 | BC11: 1.4745156 | BD11: 2.0073512 | BE11: 2.5692709 | BM11: 5.3562341 | BN11: 4.4156185 | BO11: 3.7631332 | BP11: 3.2744489 | BQ11: 2.9370878 | BS11: 14.930044 | BT11: 11.23552 | BU11: 8.8506552 | BV11: 7.6021461 | BW11: 30.558402 | BX11: 23.028629 | BY11: 15.764499 | BZ11: 11.579937 | CA11: 9.0473141 | CB11: Recur GP | CC11: 25 | CD11: 25 | CE11: 25 | CF11: 25 | CG11: 25 | CH11: 48.482082 | CI11: 56.855636 | CJ11: 65.781378 | CK11: 75.385267 | CL11: 84.899722 | CM11: 25.234895 | CN11: 36.862891 | CO11: 50.18378 | CP11: 64.231773 | CW11: 71311.701 | CX11: 83676.354 | CY11: 96164.354 | CZ11: 107210.03 | DB11: 609.22541 | DC11: 594.75401 | DD11: 577.90502 | DE11: 559.47181 | DF11: 540.01117 | DG11: -1991 | DH11: -1991 | DI11: -1991 | DJ11: -1991 | DS11: 0.14185707 | DT11: 0.32947424 | DU11: 0.34156026 | DV11: 0.32424095 | DW11: 1.0856052 | DX11: 1.5858417 | DY11: 2.1589063 | DZ11: 2.763251 | EA11: -0.2006534 | EB11: -0.1590087 | EC11: -0.2945372 | ED11: 0.17129201 | EE11: 0.17485787 | EF11: 0.34614988 | EG11: 0.038820263 | EH11: 0.38497014 | EI11: -0.043409878 | EJ11: 0.34156026 | EK11: 0.17825813 | EL11: 0.38189426
B12: WING | D12: 46139 | F12: 127.085 | G12: 28.074 | H12: -222.566 | I12: 1209.094 | K12: 986.528 | L12: 4554.3123 | M12: 357.521 | N12: 460.055 | O12: 625.807 | P12: 696.853 | Q12: 778.76669 | R12: 919.23366 | S12: 1078.8701 | T12: 1258.6672 | U12: 1459.6536 | AN12: 1.8477141 | AO12: 2.4811678 | AP12: 3.7247811 | AQ12: 4.1483008 | AR12: 4.6123604 | AS12: 5.975037 | AT12: 7.6104083 | AU12: 9.55656 | AV12: 11.856499 | AW12: 1.8477141 | AX12: 2.4811678 | AY12: 3.7247811 | AZ12: 4.1483008 | BA12: 4.6123604 | BB12: 5.975037 | BC12: 7.6104083 | BD12: 9.55656 | BE12: 11.856499 | BF12: 7.2775029 | BG12: 6.5355423 | BH12: 5.8481087 | BI12: 4.9544664 | BJ12: 4.2213721 | BK12: 3.618361 | BL12: 3.1201323 | BM12: n/a | BN12: n/a | BO12: #DIV/0! | BP12: #DIV/0! | BQ12: #DIV/0! | BR12: 27.553137 | BS12: 21.269324 | BT12: 16.698841 | BU12: 13.298195 | BV12: 10.718594 | BW12: 27.553137 | BX12: 21.269324 | BY12: 16.698841 | BZ12: 13.298195 | CA12: 10.718594 | CC12: 24 | CD12: 24 | CE12: 24 | CF12: 24 | CG12: 24 | CM12: 143.40089 | CN12: 182.6498 | CO12: 229.35744 | CP12: 284.55598 | DB12: 27.751065 | DC12: 27.356287 | DD12: 26.895951 | DE12: 26.377227 | DF12: 25.807803 | DN12: 1.311 | DO12: 1.50765 | DP12: 1.7337975 | DQ12: 1.9938671 | DR12: 2.2929472 | DS12: 0.22653649 | DT12: 0.26087349 | DU12: 0.2612612 | DV12: 0.25675515 | DW12: 1.1387016 | DX12: 1.4594047 | DY12: 1.8405783 | DZ12: 2.290611 | EA12: -0.3527299 | EB12: -0.5111927 | EC12: -0.4517945 | ED12: 0.17109203 | EE12: 0.07555818 | EF12: 0.24665021 | EG12: 0.034088044 | EH12: 0.28073825 | EI12: -0.019477049 | EJ12: 0.2612612 | EK12: 0 | EL12: 0.27485107
B13: GWRE | D13: 46054 | F13: 141.17999 | G13: 86.451737 | H13: -1410.456 | I13: 704.5 | K13: -705.956 | L13: 11499.3 | M13: 612.749 | N13: 752.474 | O13: 971.543 | P13: 1188.6634 | Q13: 1394.7843 | R13: 1657.5923 | S13: 1941.5146 | T13: 2243.9025 | U13: 2585.5299 | V13: 0.69387302 | W13: 0.7458364 | X13: 0.78985644 | Y13: 0.80051716 | Z13: 0.80154868 | AA13: 0.80545121 | AB13: 0.80912615 | AC13: 0.8140254 | AD13: 0.82065591 | AE13: 425.17 | AF13: 561.2225 | AG13: 767.3795 | AH13: 951.54545 | AI13: 1117.9876 | AJ13: 1335.1098 | AK13: 1570.9303 | AL13: 1826.5936 | AM13: 2121.8304 | AN13: -0.077699242 | AO13: 0.83215138 | AP13: 1.9816448 | AQ13: 2.695467 | AR13: 3.2782003 | AS13: 4.478262 | AT13: 6.0385589 | AU13: 8.130041 | AV13: 10.871194 | AW13: -0.97359042 | AX13: -0.22880869 | AY13: 0.43081056 | AZ13: 1.1166603 | BA13: 1.6426499 | BB13: 2.7167351 | BC13: 4.1543467 | BD13: 6.1252537 | BE13: 8.6079473 | BF13: 11.83612 | BG13: 9.6741429 | BH13: 8.2445001 | BI13: 6.9373508 | BJ13: 5.9228498 | BK13: 5.1246877 | BL13: 4.4475601 | BM13: 9.2571421 | BN13: 7.7516995 | BO13: 6.5880516 | BP13: 5.6659398 | BQ13: 4.8775668 | BR13: 43.06631 | BS13: 31.525622 | BT13: 23.379749 | BU13: 17.365225 | BV13: 12.986613 | BW13: n/a | BX13: 51.966786 | BY13: 33.983681 | BZ13: 23.04884 | CA13: 16.401122 | CB13: Mendo GP | CC13: 8.5 | CD13: 8.5 | CE13: 8.5 | CF13: 8.5 | CG13: 8.5 | CM13: 140.37143 | CN13: 166.39691 | CO13: 196.51477 | CP13: 233.87844 | CW13: 11348.433 | CX13: 13352.907 | CY13: 15526.046 | CZ13: 18035.559 | DB13: 85.874944 | DC13: 84.489929 | DD13: 82.599401 | DE13: 80.133573 | DG13: -705.956 | DH13: -705.956 | DI13: -705.956 | DJ13: -705.956 | DS13: -0.0092333062 | DT13: 0.10682566 | DU13: 0.13457908 | DV13: 0.14966402 | DW13: 0.99427284 | DX13: 1.1786154 | DY13: 1.3919449 | DZ13: 1.6565976 | EA13: 0.005842116 | EB13: 0.09577774 | EC13: -0.3402187 | ED13: 0.16775 | EJ13: 0.13457908 | EK13: 0.17779125 | EL13: 0.55069489
B14: META (incl. GenAI) | D14: 46139 | F14: 605.70001 | G14: 2573.7761 | H14: -84819 | I14: 85081 | K14: 262 | L14: 1559198.2 | M14: 116608 | N14: 134902 | O14: 164500 | P14: 200965 | Q14: 252369.84 | R14: 301648.93 | S14: 347539.27 | T14: 394733.56 | U14: 453608.37 | AE14: 0 | AF14: 0 | AG14: 0 | AH14: 0 | AI14: 0 | AJ14: 0 | AK14: 0 | AL14: 0 | AM14: 0 | AN14: 10.440785 | AO14: 16.379135 | AP14: 24.207034 | AQ14: 29.015803 | AR14: 30.163709 | AS14: 38.02961 | AT14: 46.790913 | AU14: 58.401463 | AV14: 75.389148 | AW14: 10.440785 | AX14: 16.379135 | AY14: 24.207034 | AZ14: 29.015803 | BA14: 30.163709 | BB14: 38.02961 | BC14: 46.790913 | BD14: 58.401463 | BE14: 75.389148 | BF14: 9.4784085 | BG14: 7.758556 | BH14: 6.1782271 | BI14: 5.1689168 | BJ14: 4.4863943 | BK14: 3.9500016 | BL14: 3.4373224 | BM14: n/a | BN14: n/a | BO14: #DIV/0! | BP14: #DIV/0! | BQ14: #DIV/0! | BR14: 20.080422 | BS14: 15.927063 | BT14: 12.944821 | BU14: 10.371316 | BV14: 8.034313 | BW14: 20.080422 | BX14: 15.927063 | BY14: 12.944821 | BZ14: 10.371316 | CA14: 8.034313 | CC14: 19 | CD14: 19 | CE14: 19 | CF14: 19 | CG14: 20 | CM14: 722.56259 | CN14: 889.02735 | CO14: 1109.6278 | CP14: 1432.3938 | DB14: 2573.7761 | DC14: 2565.3705 | DD14: 2524.5024 | DE14: 2456.3036 | DF14: 2359.3103 | DN14: 2.205 | DO14: 2.31525 | DP14: 2.4310125 | DQ14: 2.5525631 | DR14: 2.6801913 | DS14: 0.3337221 | DT14: 0.27067758 | DU14: 0.26267997 | DV14: 0.27059782 | DW14: 1.1965785 | DX14: 1.4752313 | DY14: 1.8434523 | DZ14: 2.3805475 | EA14: -0.1203253 | EB14: -0.06060986 | EC14: 0.02605365 | ED14: 0.15419088 | EE14: 0.065765025 | EF14: 0.21995591 | EG14: 0.025196102 | EH14: 0.24515201 | EI14: 0.01752796 | EJ14: 0.26267997 | EK14: 0 | EL14: 0.24636811
B15: GOOG | C15: 2 | D15: 46120 | F15: 386.54999 | G15: 12230 | H15: -126843 | I15: 66967 | K15: -59876 | L15: 4667630.4 | M15: 282836 | N15: 307394 | O15: 350018 | P15: 402836 | Q15: 474201.19 | R15: 547000.07 | S15: 627861.63 | T15: 715818.21 | U15: 803490.68 | V15: 0.55379443 | W15: 0.56625048 | X15: 0.58200435 | Y15: 0.59652315 | Z15: 0.60130017 | AA15: 0.60309319 | AB15: 0.60681934 | AC15: 0.61614806 | AD15: 0.62285471 | AE15: 156633 | AF15: 174062 | AG15: 203712 | AH15: 240301 | AI15: 285137.25 | AJ15: 329892.01 | AK15: 380998.59 | AL15: 441050 | AM15: 500457.95 | AN15: 4.5574892 | AO15: 5.8005817 | AP15: 8.0435446 | AQ15: 10.807032 | AR15: 10.430843 | AS15: 12.047233 | AT15: 14.174341 | AU15: 17.360857 | AV15: 20.696308 | AW15: 4.9626111 | AX15: 5.968244 | AY15: 7.7855708 | AZ15: 8.6659035 | BA15: 10.430843 | BB15: 12.047233 | BC15: 14.174341 | BD15: 17.360857 | BE15: 20.696308 | BF15: 13.335401 | BG15: 11.586925 | BH15: 9.8431435 | BI15: 8.533144 | BJ15: 7.4341704 | BK15: 6.5206924 | BL15: 5.8091904 | BM15: 16.369767 | BN15: 14.148964 | BO15: 12.251044 | BP15: 10.582996 | BQ15: 9.3267184 | BR15: 37.058366 | BS15: 32.086206 | BT15: 27.271108 | BU15: 22.265605 | BV15: 18.677244 | BW15: 37.058366 | BX15: 32.086206 | BY15: 27.271108 | BZ15: 22.265605 | CA15: 18.677244 | CC15: 24 | CD15: 24 | CE15: 24 | CF15: 24 | CG15: 24 | CM15: 289.13359 | CN15: 340.18418 | CO15: 416.66057 | CP15: 496.71138 | DB15: 12230 | DC15: 12230 | DD15: 12155.112 | DE15: 11921.29 | DF15: 11635.202 | DN15: 0.83 | DO15: 0.83 | DP15: 0.83 | DQ15: 0.83 | DR15: 0.83 | DS15: -0.37255304 | DT15: -0.073626554 | DU15: 0.031099677 | DV15: 0.073526556 | DW15: 0.75013219 | DX15: 0.88434664 | DY15: 1.0843373 | DZ15: 1.2935749 | EA15: 0.1389216 | EB15: 0.2733891 | EC15: 0.3193283 | ED15: 0.14514317 | EE15: 0.031723403 | EF15: 0.17686658 | EG15: 0.013690977 | EH15: 0.19055755 | EI15: -0.15945788 | EJ15: 0.031099677 | EK15: 0.1564973 | EL15: 0.18508797
B16: META (Core) | D16: 46139 | F16: 605.70001 | G16: 2573.7761 | H16: -84819 | I16: 85081 | K16: 262 | L16: 1559198.2 | M16: 116608 | N16: 134902 | O16: 164500 | P16: 200965 | Q16: 248522.91 | R16: 295151.32 | S16: 335415.23 | T16: 371309.47 | U16: 403354.04 | AE16: 0 | AF16: 0 | AG16: 0 | AH16: 0 | AI16: 0 | AJ16: 0 | AK16: 0 | AL16: 0 | AM16: 0 | AN16: 11.527294 | AO16: 17.776263 | AP16: 26.860056 | AQ16: 37.091372 | AR16: 43.244244 | AS16: 54.069647 | AT16: 64.737817 | AU16: 76.123334 | AV16: 87.688622 | AW16: 11.527294 | AX16: 17.776263 | AY16: 26.860056 | AZ16: 37.091372 | BA16: 43.244244 | BB16: 54.069647 | BC16: 64.737817 | BD16: 76.123334 | BE16: 87.688622 | BF16: 9.4784085 | BG16: 7.758556 | BH16: 6.273861 | BI16: 5.2827079 | BJ16: 4.6485611 | BK16: 4.1991878 | BL16: 3.8655822 | BM16: n/a | BN16: n/a | BO16: #DIV/0! | BP16: #DIV/0! | BQ16: #DIV/0! | BR16: 14.006489 | BS16: 11.202219 | BT16: 9.3562007 | BU16: 7.9568246 | BV16: 6.9073957 | BW16: 14.006489 | BX16: 11.202219 | BY16: 9.3562007 | BZ16: 7.9568246 | CA16: 6.9073957 | CC16: 19 | CD16: 19 | CE16: 19 | CF16: 19 | CG16: 20 | CM16: 1027.3233 | CN16: 1230.0185 | CO16: 1446.3433 | CP16: 1666.0838 | DB16: 2573.7761 | DC16: 2565.3705 | DD16: 2524.5024 | DE16: 2456.3036 | DF16: 2359.3103 | DN16: 2.205 | DO16: 2.31525 | DP16: 2.4310125 | DQ16: 2.5525631 | DR16: 2.6801913 | DS16: 1.3523542 | DT16: 0.5516998 | DU16: 0.39644723 | DV16: 0.32446973 | DW16: 1.699733 | DX16: 2.0382017 | DY16: 2.3993637 | DZ16: 2.7663655 | EA16: -0.1203253 | EB16: -0.06060986 | EC16: 0.02605365 | ED16: 0.13535276 | EE16: 0.042678215 | EF16: 0.17803097 | EG16: 0.02446792 | EH16: 0.20249889 | EI16: 0.19394834 | EJ16: 0.39644723 | EK16: 0 | EL16: 0.20743334
B17: ABNB | C17: 2 | D17: 46068 | F17: 132.47501 | G17: 608 | H17: -11014 | I17: 1999 | K17: -9015 | L17: 71529.804 | M17: 8399 | N17: 9917 | O17: 11102 | P17: 12241 | Q17: 13606.373 | R17: 15272.943 | S17: 17277.307 | T17: 19431.57 | U17: 21648.865 | V17: 0.82154078 | W17: 0.82827468 | X17: 0.83084129 | Y17: 0.82958909 | Z17: 0.82958909 | AA17: 0.82958909 | AB17: 0.82958909 | AC17: 0.82958909 | AD17: 0.82958909 | AE17: 6900.121 | AF17: 8214 | AG17: 9224 | AH17: 10155 | AI17: 11287.698 | AJ17: 12670.266 | AK17: 14333.065 | AL17: 16120.218 | AM17: 17959.662 | AN17: 2.4164706 | AO17: 3.778852 | AP17: 4.1484186 | AQ17: 4.2619583 | AR17: 4.9188101 | AS17: 5.6859834 | AT17: 6.9655912 | AU17: 8.5476451 | AV17: 10.230472 | AW17: 2.4164706 | AX17: 3.778852 | AY17: 4.1484186 | AZ17: 4.2619583 | BA17: 4.9188101 | BB17: 5.6859834 | BC17: 6.9655912 | BD17: 8.5476451 | BE17: 10.230472 | BF17: 6.4429656 | BG17: 5.8434608 | BH17: 5.257081 | BI17: 4.683433 | BJ17: 4.1401015 | BK17: 3.6811129 | BL17: 3.3040902 | BM17: 6.3369698 | BN17: 5.6454853 | BO17: 4.9905449 | BP17: 4.4372726 | BQ17: 3.9828033 | BR17: 26.932328 | BS17: 23.298522 | BT17: 19.018487 | BU17: 15.498421 | BV17: 12.949061 | BW17: 26.932328 | BX17: 23.298522 | BY17: 19.018487 | BZ17: 15.498421 | CA17: 12.949061 | CC17: 24 | CD17: 24 | CE17: 24 | CF17: 24 | CG17: 23 | CM17: 136.4636 | CN17: 167.17419 | CO17: 205.14348 | CP17: 245.53134 | DB17: 602.94314 | DC17: 586.00672 | DD17: 568.52002 | DE17: 550.47103 | DF17: 532.31785 | DS17: 0.049074709 | DT17: 0.15451376 | DU17: 0.18171497 | DV17: 0.18588478 | DW17: 1.0301083 | DX17: 1.26193 | DY17: 1.5485448 | DZ17: 1.8534163 | EA17: -0.06411164 | EB17: 0.05297673 | EC17: 0.1575935 | ED17: 0.12597821 | EE17: 0.045971945 | EF17: 0.17195016 | EG17: 0.036028903 | EH17: 0.20797906 | EI17: -0.02626409 | EJ17: 0.18171497 | EK17: 0.12612995 | EL17: 0.20225191
B18: PCOR | C18: 1 | D18: 46119 | F18: 47.790001 | G18: 161.46556 | H18: -811 | I18: 28 | K18: -783 | L18: 6933.4392 | M18: 720.203 | N18: 950.01 | O18: 1151.708 | P18: 1322.509 | Q18: 1507.6603 | R18: 1703.6561 | S18: 1908.0948 | T18: 2127.5257 | U18: 2361.5536 | V18: 0.83556442 | W18: 0.85259629 | X18: 0.85752899 | Y18: 0.83613042 | Z18: 0.84928708 | AA18: 0.85529973 | AB18: 0.85933919 | AC18: 0.86341685 | AD18: 0.86753328 | AE18: 601.776 | AF18: 809.975 | AG18: 987.623 | AH18: 1105.79 | AI18: 1280.4364 | AJ18: 1457.1366 | AK18: 1639.7007 | AL18: 1836.9416 | AM18: 2048.7263 | AO18: 0.2860091 | AP18: 0.88947488 | AQ18: 1.3067373 | AR18: 1.5666595 | AS18: 2.231158 | AT18: 2.9986834 | AU18: 3.935053 | AV18: 5.2472299 | AY18: -0.32076479 | AZ18: -0.20239665 | BA18: 0.34626651 | BB18: 0.90715357 | BC18: 1.5690342 | BD18: 2.3974072 | BE18: 3.5235657 | BF18: 6.0201364 | BG18: 5.2426405 | BH18: 4.5988075 | BI18: 4.0697411 | BJ18: 3.6336974 | BK18: 3.2589214 | BL18: 2.9359653 | BM18: 5.4149033 | BN18: 4.758263 | BO18: 4.2284787 | BP18: 3.7744473 | BQ18: 3.3842682 | BW18: n/a | BX18: 52.681269 | BY18: 30.458228 | BZ18: 19.934036 | CA18: 13.562966 | CB18: GP | CC18: 7 | CD18: 7 | CE18: 7 | CF18: 7 | CG18: 7 | CH18: 92.895312 | CI18: 105.12151 | CJ18: 118.98665 | CK18: 135.2034 | CL18: 152.60938 | CM18: 68.427826 | CN18: 78.045916 | CO18: 89.154683 | CP18: 101.91876 | CW18: 10199.956 | CX18: 11477.905 | CY18: 12858.591 | CZ18: 14341.084 | DB18: 160.49986 | DC18: 157.09476 | DD18: 153.007 | DE18: 148.39058 | DF18: 143.41422 | DG18: -782.7 | DH18: -782.7 | DI18: -782.7 | DJ18: -782.7 | DK18: -782.7 | DS18: 0.78557647 | DT18: 0.35380571 | DU18: 0.26880223 | DV18: 0.23276901 | DW18: 1.431844 | DX18: 1.6331014 | DY18: 1.865551 | DZ18: 2.1326377 | EA18: -0.137987 | EB18: -0.08131489 | EC18: -0.3338444 | ED18: 0.11968033 | EG18: 0.026495745 | EH18: 0.14617607 | EI18: 0.12262615 | EJ18: 0.26880223 | EK18: 0.12783555 | EL18: n/a
B19: AMZN | C19: 1 | D19: 46120 | F19: 260.35501 | G19: 10827 | H19: -123329 | I19: 178547 | K19: 55218 | L19: 2874081.7 | M19: 513983 | N19: 574785 | O19: 637959 | P19: 716924 | Q19: 817469.18 | R19: 928320.74 | S19: 1044416 | T19: 1153879.7 | U19: 1265801 | V19: 0.4380534 | W19: 0.46982089 | X19: 0.48854393 | Y19: 0.50285665 | Z19: 0.52586233 | AA19: 0.54940611 | AB19: 0.56879977 | AC19: 0.58047854 | AD19: 0.58999333 | AE19: 225152 | AF19: 270046 | AG19: 311671 | AH19: 360510 | AI19: 429876.24 | AJ19: 510025.09 | AK19: 594063.59 | AL19: 669802.4 | AM19: 746814.14 | AN19: -0.26715085 | AO19: 2.8998284 | AP19: 5.5263502 | AQ19: 7.1737323 | AR19: 7.3680359 | AS19: 9.512152 | AT19: 12.252122 | AU19: 15.255782 | AV19: 19.175997 | AW19: 1.3825694 | AX19: 2.8115707 | AY19: 5.7456394 | AZ19: 5.8183246 | BA19: 7.3680359 | BB19: 9.512152 | BC19: 12.252122 | BD19: 15.255782 | BE19: 19.175997 | BF19: 4.5051198 | BG19: 4.0089071 | BH19: 3.5158288 | BI19: 3.0960008 | BJ19: 2.7518553 | BK19: 2.4907984 | BL19: 2.2705636 | BM19: 6.6858351 | BN19: 5.6351771 | BO19: 4.8380034 | BP19: 4.2909397 | BQ19: 3.8484565 | BR19: 35.335741 | BS19: 27.370779 | BT19: 21.249788 | BU19: 17.06599 | BV19: 13.577131 | BW19: 35.335741 | BX19: 27.370779 | BY19: 21.249788 | BZ19: 17.06599 | CA19: 13.577131 | CC19: 26 | CD19: 26 | CE19: 26 | CF19: 26 | CG19: 24 | CM19: 247.31595 | CN19: 318.55518 | CO19: 396.65032 | CP19: 498.57591 | DB19: 10827 | DC19: 10788.313 | DD19: 10587.029 | DE19: 10192.759 | DF19: 9738.2353 | DS19: -0.079630524 | DT19: 0.13269529 | DU19: 0.17438061 | DV19: 0.19664114 | DW19: 0.94991816 | DX19: 1.2235416 | DY19: 1.5234979 | DZ19: 1.9149849 | EA19: 0.03903258 | EB19: 0.2708191 | EC19: 0.1690691 | ED19: 0.11892824 | EE19: 0.12131374 | EF19: 0.24024198 | EG19: 0.028149706 | EH19: 0.26839168 | EI19: -0.09401107 | EJ19: 0.17438061 | EK19: 0.15931401 | EL19: 0.27456184
B20: CSGP | C20: 1 | D20: 45689 | F20: 33.855 | G20: 419.6 | H20: -1633 | I20: 992.5 | K20: -640.5 | L20: 13565.058 | M20: 2182.399 | N20: 2455 | O20: 2736.2 | P20: 3236.027 | Q20: 3800 | R20: 4267.3 | S20: 4781.923 | T20: 5335.7805 | U20: 5922.7164 | V20: 0.8 | W20: 0.8 | X20: 0.8 | Y20: 0.8 | Z20: 0.8 | AA20: 0.8 | AB20: 0.8 | AC20: 0.8 | AD20: 0.8 | AE20: 1745.9192 | AF20: 1964 | AG20: 2188.96 | AH20: 2588.8216 | AI20: 3040 | AJ20: 3413.84 | AK20: 3825.5384 | AL20: 4268.6244 | AM20: 4738.1731 | AN20: 1.2726523 | AO20: 1.2241337 | AP20: 0.74254941 | AQ20: 0.8294196 | AR20: 1.1224162 | AS20: 1.7627063 | AT20: 2.5071929 | AU20: 3.3694004 | AV20: 4.3626189 | AW20: 1.2726523 | AX20: 1.2241337 | AY20: 0.74254941 | AZ20: 0.8294196 | BA20: 1.1224162 | BB20: 1.7627063 | BC20: 2.5071929 | BD20: 3.3694004 | BE20: 4.3626189 | BF20: 4.9576266 | BG20: 4.1918865 | BH20: 3.5697521 | BI20: 3.1788386 | BJ20: 2.836737 | BK20: 2.5422818 | BL20: 2.290344 | BM20: 4.4621901 | BN20: 3.9735482 | BO20: 3.5459212 | BP20: 3.1778523 | BQ20: 2.86293 | BR20: 30.162607 | BS20: 19.206262 | BT20: 13.503149 | BU20: 10.047782 | BV20: 7.7602469 | BW20: 30.162607 | BX20: 19.206262 | BY20: 13.503149 | BZ20: 10.047782 | CA20: 7.7602469 | CC20: 22 | CD20: 22 | CE20: 22 | CF20: 22 | CG20: 22 | CM20: 38.77954 | CN20: 55.158244 | CO20: 74.126808 | CP20: 95.977615 | DB20: 414.18387 | DC20: 401.21459 | DD20: 388.58912 | DE20: 377.61046 | DF20: 368.06379 | DN20: 0 | DO20: 0 | DP20: 0 | DQ20: 0 | DR20: 0 | DS20: 0.24524569 | DT20: 0.35183281 | DU20: 0.34879608 | DV20: 0.3336486 | DW20: 1.1454598 | DX20: 1.6292496 | DY20: 2.189538 | DZ20: 2.8349614 | EA20: -0.1476586 | EB20: -0.3100672 | EC20: -0.4872008 | ED20: 0.11864892 | EE20: 0.25196592 | EF20: 0.37061485 | EG20: 0.040861189 | EH20: 0.41147603 | EI20: -0.062679958 | EJ20: 0.34879608 | EK20: 0.11979396 | EL20: 0.44255671
B21: SAP | C21: 1 | D21: 45688 | F21: 158.42 | G21: 1169 | H21: -9609 | I21: 11446 | K21: 1837 | L21: 187029.98 | M21: 29520 | N21: 31207 | O21: 34176 | P21: 36800 | Q21: 40273.14 | R21: 45307.135 | S21: 50851.13 | T21: 56381.116 | U21: 62355.58 | V21: 0.74261518 | W21: 0.72429263 | X21: 0.73182935 | Y21: 0.73764946 | Z21: 0.7380271 | AA21: 0.73982573 | AB21: 0.74211568 | AC21: 0.74533219 | AD21: 0.74935858 | AE21: 21922 | AF21: 22603 | AG21: 25011 | AH21: 27145.5 | AI21: 29722.669 | AJ21: 33519.384 | AK21: 37737.421 | AL21: 42022.661 | AM21: 46726.689 | AN21: 4.0161702 | AO21: 3.6754237 | AP21: 4.479661 | AQ21: 6.0991489 | AR21: 7.1545717 | AS21: 8.5750357 | AT21: 10.465866 | AU21: 12.432473 | AV21: 14.872587 | AW21: 4.0161702 | AX21: 3.6754237 | AY21: 4.479661 | AZ21: 6.0991489 | BA21: 7.1545717 | BB21: 8.5750357 | BC21: 10.465866 | BD21: 12.432473 | BE21: 14.872587 | BF21: 5.4725532 | BG21: 5.0823364 | BH21: 4.6440376 | BI21: 4.1280469 | BJ21: 3.6779906 | BK21: 3.317245 | BL21: 2.9994104 | BM21: 6.2925029 | BN21: 5.5797558 | BO21: 4.956088 | BP21: 4.4506934 | BQ21: 4.0026371 | BR21: 22.142485 | BS21: 18.474558 | BT21: 15.136826 | BU21: 12.742437 | BV21: 10.651812 | BW21: 22.142485 | BX21: 18.474558 | BY21: 15.136826 | BZ21: 12.742437 | CA21: 10.651812 | CC21: 22 | CD21: 22 | CE21: 22 | CF21: 22 | CG21: 24 | CM21: 188.65079 | CN21: 230.24906 | CO21: 273.5144 | CP21: 327.19691 | CW21: 220789.28 | CX21: 263601.12 | CY21: 305681.97 | CZ21: 356154.29 | DB21: 1160.6221 | DC21: 1136.8738 | DD21: 1110.892 | DE21: 1082.887 | DF21: 1053.2432 | DG21: 1837 | DH21: 1837 | DI21: 1837 | DJ21: 1837 | DK21: 1837 | DN21: 2.8618287 | DO21: 3.4300143 | DP21: 4.1863466 | DQ21: 4.9729891 | DR21: 5.9490347 | DS21: 0.34603502 | DT21: 0.27727001 | DU21: 0.24780694 | DV21: 0.23649042 | DW21: 1.2088917 | DX21: 1.4931253 | DY21: 1.7926562 | DZ21: 2.1629093 | EA21: 0.01408087 | EB21: -0.07203939 | EC21: -0.2290024 | ED21: 0.1170612 | EE21: 0.056450039 | EF21: 0.17351123 | EG21: 0.051508787 | EH21: 0.22502002 | EI21: 0.022786915 | EJ21: 0.24780694 | EK21: 0.12235932 | EL21: 0.20224032
B22: MSCI | C22: 1 | D22: 45995 | F22: 589.35999 | G22: 73.4 | H22: -385.3 | I22: 6403.8 | K22: 6018.5 | L22: 49277.523 | M22: 2248.598 | N22: 2528.92 | O22: 2856.128 | P22: 3134.459 | Q22: 3521.8781 | R22: 3909.2528 | S22: 4325.7773 | T22: 4796.6952 | U22: 5311.721 | V22: 0.82 | W22: 0.82 | X22: 0.82 | Y22: 0.82 | Z22: 0.82 | AA22: 0.82 | AB22: 0.82 | AC22: 0.82 | AD22: 0.82 | AE22: 1843.8504 | AF22: 2073.7144 | AG22: 2342.025 | AH22: 2570.2564 | AI22: 2887.94 | AJ22: 3205.5873 | AK22: 3547.1374 | AL22: 3933.2901 | AM22: 4355.6113 | AN22: 11.454571 | AO22: 13.519833 | AP22: 15.200836 | AQ22: 17.283992 | AR22: 20.298701 | AS22: 23.825327 | AT22: 27.806702 | AU22: 32.506076 | AV22: 37.877281 | AW22: 11.454571 | AX22: 13.519833 | AY22: 15.200836 | AZ22: 17.283992 | BA22: 20.298701 | BB22: 23.825327 | BC22: 27.806702 | BD22: 32.506076 | BE22: 37.877281 | BF22: 17.253261 | BG22: 15.721221 | BH22: 13.991831 | BI22: 12.605356 | BJ22: 11.3916 | BK22: 10.273224 | BL22: 9.2771293 | BM22: 17.063209 | BN22: 15.372385 | BO22: 13.892195 | BP22: 12.528322 | BQ22: 11.313572 | BR22: 29.03437 | BS22: 24.736701 | BT22: 21.19489 | BU22: 18.130764 | BV22: 15.559722 | BW22: 29.03437 | BX22: 24.736701 | BY22: 21.19489 | BZ22: 18.130764 | CA22: 15.559722 | CB22: Adj EPS | CC22: 27 | CD22: 27 | CE22: 27 | CF22: 27 | CG22: 27 | CM22: 643.28383 | CN22: 750.78095 | CO22: 877.66404 | CP22: 1022.6866 | DB22: 73.57914 | DC22: 71.114174 | DD22: 68.477416 | DE22: 65.921358 | DF22: 63.434977 | DN22: 8.2 | DO22: 9.6246397 | DP22: 11.232983 | DQ22: 13.131373 | DR22: 15.301162 | DS22: 0.16659861 | DT22: 0.17525241 | DU22: 0.17722652 | DV22: 0.17661829 | DW22: 1.105409 | DX22: 1.304136 | DY22: 1.5384853 | DZ22: 1.8068339 | EA22: 0.0366019 | EB22: 0.08914844 | EC22: 0.05319961 | ED22: 0.10769772 | EE22: 0.018400271 | EF22: 0.126098 | EG22: 0.059625905 | EH22: 0.1857239 | EI22: -0.0084973776 | EJ22: 0.17722652 | EK22: 0.10846658 | EL22: 0.16994496
B23: EFX | C23: 1 | D23: 45689 | F23: 163.575 | G23: 125.1 | H23: -169.9 | I23: 5010.5 | J23: 17.5 | K23: 4840.6 | L23: 25321.332 | M23: 5122.2 | N23: 5265.2 | O23: 5681.1 | P23: 6058.8157 | Q23: 6592.0376 | R23: 7271.8069 | S23: 8040.8758 | T23: 8913.6 | U23: 9907.0218 | V23: 0.6 | W23: 0.6 | X23: 0.6 | Y23: 0.6 | Z23: 0.6 | AA23: 0.6 | AB23: 0.6 | AC23: 0.6 | AD23: 0.6 | AE23: 3073.32 | AF23: 3159.12 | AG23: 3408.66 | AH23: 3635.2894 | AI23: 3955.2226 | AJ23: 4363.0841 | AK23: 4824.5255 | AL23: 5348.16 | AM23: 5944.2131 | AN23: 7.5636659 | AO23: 6.7110573 | AP23: 7.2866293 | AQ23: 7.6486704 | AR23: 9.2053868 | AS23: 11.430042 | AT23: 14.091333 | AU23: 17.43175 | AV23: 21.468127 | AW23: 7.5636659 | AX23: 6.7110573 | AY23: 7.2866293 | AZ23: 7.6486704 | BA23: 9.2053868 | BB23: 11.430042 | BC23: 14.091333 | BD23: 17.43175 | BE23: 21.468127 | BF23: 4.4571178 | BG23: 4.1792544 | BH23: 3.8411996 | BI23: 3.4821238 | BJ23: 3.1490764 | BK23: 2.8407526 | BL23: 2.5558975 | BM23: 6.4019993 | BN23: 5.8035397 | BO23: 5.2484607 | BP23: 4.7345876 | BQ23: 4.2598292 | BR23: 17.769486 | BS23: 14.310971 | BT23: 11.608199 | BU23: 9.3837393 | BV23: 7.6194351 | BW23: 17.769486 | BX23: 14.310971 | BY23: 11.608199 | BZ23: 9.3837393 | CA23: 7.6194351 | CC23: 20 | CD23: 20 | CE23: 20 | CF23: 20 | CG23: 20 | CM23: 228.60084 | CN23: 281.82666 | CO23: 348.635 | CP23: 429.36253 | DB23: 119.58966 | DC23: 113.88804 | DD23: 107.73848 | DE23: 101.37715 | DF23: 94.919032 | DN23: 1.9697019 | DO23: 2.0681869 | DP23: 2.1715963 | DQ23: 2.2801761 | DR23: 2.3941849 | DS23: 0.73179457 | DT23: 0.40937851 | DU23: 0.34293887 | DV23: 0.3120354 | DW23: 1.4095708 | DX23: 1.7476054 | DY23: 2.1693076 | DZ23: 2.6767672 | EA23: -0.1663694 | EB23: -0.1624424 | EC23: -0.2069475 | ED23: 0.10571077 | EE23: 0.062006232 | EF23: 0.167717 | EG23: 0.079126238 | EH23: 0.24684324 | EI23: 0.096095629 | EJ23: 0.34293887 | EK23: 0.10580315 | EL23: 0.23718026
B24: WDAY | C24: 1 | D24: 45991 | F24: 132.075 | G24: 263.411 | H24: -8017 | I24: 2984 | K24: -5033 | L24: 29757.007 | M24: 6215.818 | N24: 7258.753 | O24: 8446 | P24: 9552 | Q24: 10723.337 | R24: 11959.266 | S24: 13226.36 | T24: 14542.97 | U24: 15876.671 | V24: 0.76955632 | W24: 0.79683535 | X24: 0.78886878 | Y24: 0.79169571 | Z24: 0.80060817 | AA24: 0.80656338 | AB24: 0.81225976 | AC24: 0.81644821 | AD24: 0.82046166 | AE24: 4783.422 | AF24: 5784.031 | AG24: 6662.7857 | AH24: 7562.2774 | AI24: 8585.1913 | AJ24: 9645.9061 | AK24: 10743.24 | AL24: 11873.582 | AM24: 13026.2 | AO24: 5.6577043 | AP24: 7.13432 | AQ24: 9.0770109 | AR24: 10.410325 | AS24: 13.111934 | AT24: 15.687176 | AU24: 18.590369 | AV24: 21.987373 | AX24: 1.3596545 | AY24: 2.6061784 | AZ24: 4.2675468 | BA24: 5.5610566 | BB24: 7.7961783 | BC24: 9.9297272 | BD24: 12.341413 | BE24: 15.25191 | BF24: 3.5232071 | BG24: 3.1152646 | BH24: 2.7749763 | BI24: 2.4881968 | BJ24: 2.2498259 | BK24: 2.0461437 | BL24: 1.8742599 | BM24: 3.4660855 | BN24: 3.0849364 | BO24: 2.7698355 | BP24: 2.5061525 | BQ24: 2.2843967 | BR24: 12.686923 | BS24: 10.072885 | BT24: 8.419297 | BU24: 7.1044851 | BV24: 6.0068567 | BW24: 23.749982 | BX24: 16.940992 | BY24: 13.300969 | BZ24: 10.701773 | CA24: 8.6595707 | CB24: Revenue | CC24: 22 | CD24: 22 | CE24: 22 | CF24: 22 | CG24: 20 | CM24: 180.93166 | CN24: 228.34968 | CO24: 281.87397 | CP24: 346.43357 | CR24: 9.4157415 | CS24: 9.8956805 | CT24: 10.362889 | CU24: 10.891539 | CV24: 11.486062 | CW24: 46054.855 | CX24: 57106.681 | CY24: 67502.046 | CZ24: 79648.601 | DB24: 268.117 | DC24: 260.83979 | DD24: 248.1891 | DE24: 236.99955 | DF24: 225.49614 | DG24: -2456 | DH24: -2456 | DI24: -2456 | DJ24: -2456 | DK24: -2456 | DS24: 0.66251973 | DT24: 0.40233624 | DU24: 0.33567687 | DV24: 0.30531913 | DW24: 1.3699161 | DX24: 1.7289395 | DY24: 2.1341963 | DZ24: 2.6230064 | EA24: 0.0665832 | EB24: -0.05674192 | EC24: -0.4100107 | ED24: 0.10509137 | EE24: 0.12576663 | EF24: 0.230858 | EG24: 0.083103279 | EH24: 0.31396128 | EI24: 0.021715588 | EJ24: 0.33567687 | EK24: 0.11415067 | EL24: 0.30437516
B25: ADSK | C25: 2 | D25: 45987 | F25: 247.03 | G25: 214 | H25: -2236 | I25: 2481 | K25: 245 | L25: 53109.42 | M25: 5005 | N25: 5497 | O25: 6131 | P25: 7163.5944 | Q25: 8033.9295 | R25: 8899.6561 | S25: 9836.7868 | T25: 10567.906 | U25: 11329 | V25: 0.92387612 | W25: 0.92414044 | X25: 0.92692872 | Y25: 0.93948959 | Z25: 0.94497064 | AA25: 0.94634817 | AB25: 0.94773818 | AC25: 0.94773818 | AD25: 0.94773294 | AE25: 4624 | AF25: 5080 | AG25: 5683 | AH25: 6730.1223 | AI25: 7591.8275 | AJ25: 8422.1732 | AK25: 9322.6985 | AL25: 10015.608 | AM25: 10736.866 | AN25: 6.6284404 | AO25: 7.6064815 | AP25: 8.4746544 | AQ25: 10.251993 | AR25: 12.167684 | AS25: 14.53086 | AT25: 17.248806 | AU25: 19.883967 | AV25: 22.82 | AW25: 4.1156485 | AX25: 4.9368078 | AY25: 5.9147191 | AZ25: 7.5987971 | BA25: 9.4111836 | BB25: 11.687001 | BC25: 14.338177 | BD25: 16.764465 | BE25: 19.352084 | BF25: 8.66244 | BG25: 7.4137949 | BH25: 6.6106405 | BI25: 5.9675811 | BJ25: 5.3990618 | BK25: 5.0255387 | BL25: 4.6879177 | BM25: 6.9956041 | BN25: 6.3059045 | BO25: 5.6967862 | BP25: 5.3026656 | BQ25: 4.9464544 | BR25: 20.302137 | BS25: 17.00037 | BT25: 14.321571 | BU25: 12.423577 | BV25: 10.825153 | BW25: 26.248558 | BX25: 21.13716 | BY25: 17.228829 | BZ25: 14.735334 | CA25: 12.765034 | CB25: Mendo EPS | CC25: 24 | CD25: 24 | CE25: 24 | CF25: 24 | CG25: 24 | CH25: 361.37 | CI25: 384.69775 | CJ25: 448.42554 | CK25: 516.21179 | CL25: 591.48334 | CM25: 280.48802 | CN25: 344.11625 | CO25: 402.34716 | CP25: 464.45001 | CW25: 58480.992 | CX25: 69336.43 | CY25: 78205.42 | CZ25: 86990.651 | DB25: 207.80921 | DC25: 200.93044 | DD25: 193.8933 | DE25: 186.88266 | DF25: 180.09898 | DG25: 193 | DH25: 193 | DI25: 193 | DJ25: 193 | DK25: 193 | DS25: 0.22770293 | DT25: 0.22717505 | DU25: 0.20471586 | DV25: 0.19058415 | DW25: 1.1354411 | DX25: 1.393014 | DY25: 1.6287381 | DZ25: 1.8801361 | EA25: 0.02070075 | EB25: 0.07826274 | EC25: -0.1516536 | ED25: 0.093424514 | EE25: 0.070492242 | EF25: 0.16391676 | EG25: 0.041472414 | EH25: 0.20538917 | EI25: -0.0006733091 | EJ25: 0.20471586 | EK25: 0.096756779 | EL25: 0.21222104
B26: ADI | C26: 2 | D26: 46119 | F26: 419.92999 | G26: 496.709 | H26: -3652.321 | I26: 8591.705 | K26: 4939.384 | L26: 213522.39 | M26: 12062.551 | N26: 11825.809 | O26: 9692.582 | P26: 11391.574 | Q26: 13652.82 | R26: 15832.059 | S26: 16861.143 | T26: 17957.117 | U26: 19124.33 | V26: 0.73416385 | W26: 0.71914229 | X26: 0.68198359 | Y26: 0.69524995 | Z26: 0.70431792 | AA26: 0.71060593 | AB26: 0.71301026 | AC26: 0.71526785 | AD26: 0.71738765 | AE26: 8855.8887 | AF26: 8504.4392 | AG26: 6610.1818 | AH26: 7919.991 | AI26: 9615.9257 | AJ26: 11250.355 | AK26: 12022.168 | AL26: 12844.149 | AM26: 13719.558 | AN26: 9.6536192 | AO26: 9.4699005 | AP26: 6.615 | AQ26: 8.1857933 | AR26: 10.648839 | AS26: 13.346218 | AT26: 15.019715 | AU26: 16.794947 | AV26: 18.828812 | AW26: 9.6536192 | AX26: 9.4699005 | AY26: 6.615 | AZ26: 8.1857933 | BA26: 10.648839 | BB26: 13.346218 | BC26: 15.019715 | BD26: 16.794947 | BE26: 18.828812 | BF26: 22.029464 | BG26: 18.743889 | BH26: 15.639435 | BI26: 13.48671 | BJ26: 12.663578 | BK26: 11.890683 | BL26: 11.164961 | BM26: 22.205079 | BN26: 18.979169 | BO26: 17.760723 | BP26: 16.624098 | BQ26: 15.563358 | BR26: 39.434343 | BS26: 31.464343 | BT26: 27.958585 | BU26: 25.003353 | BV26: 22.302522 | BW26: 39.434343 | BX26: 31.464343 | BY26: 27.958585 | BZ26: 25.003353 | CA26: 22.302522 | CC26: 24 | CD26: 24 | CE26: 24 | CF26: 24 | CG26: 24 | CM26: 320.30924 | CN26: 360.47317 | CO26: 403.07873 | CP26: 451.89148 | DB26: 489.01211 | DC26: 476.3474 | DD26: 459.37805 | DE26: 441.93829 | DF26: 427.07412 | DG26: 5139.384 | DH26: 5339.384 | DI26: 7387.9714 | DJ26: 7992.7683 | DK26: 8641.1126 | DN26: 4.3503167 | DO26: 4.7853483 | DP26: 5.2638832 | DQ26: 5.7902715 | DR26: 6.3692986 | DS26: -0.34546548 | DT26: -0.078365269 | DU26: -0.0037467089 | DV26: 0.031871233 | DW26: 0.77312781 | DX26: 0.88016775 | DY26: 0.99416162 | DZ26: 1.1241905 | EA26: 0.130677 | EB26: 0.2163047 | EC26: 0.8087425 | ED26: 0.085562563 | EE26: 0.024573286 | EF26: 0.11013585 | EG26: 0.050721854 | EH26: 0.1608577 | EI26: -0.16460441 | EJ26: -0.0037467089 | EK26: 0.10129772 | EL26: 0.16401556
B27: TRU | C27: 1 | D27: 45689 | F27: 68.120003 | G27: 197.2 | H27: -749.9 | I27: 5120.1 | J27: 105.1 | K27: 4370.2 | L27: 17908.565 | M27: 3710 | N27: 3831.4 | O27: 4183.8 | P27: 4544.1737 | Q27: 4888.6712 | R27: 5267.245 | S27: 5690.0897 | T27: 6163.7654 | U27: 6647.7197 | V27: 0.6 | W27: 0.6 | X27: 0.6 | Y27: 0.6 | Z27: 0.6 | AA27: 0.6 | AB27: 0.6 | AC27: 0.6 | AD27: 0.6 | AE27: 2226 | AF27: 2298.84 | AG27: 2510.28 | AH27: 2726.5042 | AI27: 2933.2027 | AJ27: 3160.347 | AK27: 3414.0538 | AL27: 3698.2592 | AM27: 3988.6318 | AN27: 3.294088 | AO27: 2.96698 | AP27: 3.4410971 | AQ27: 3.742421 | AR27: 4.3515835 | AS27: 5.1963949 | AT27: 6.1913685 | AU27: 7.3896916 | AV27: 8.7315557 | AW27: 3.294088 | AX27: 2.96698 | AY27: 3.4410971 | AZ27: 3.742421 | BA27: 4.3515835 | BB27: 5.1963949 | BC27: 6.1913685 | BD27: 7.3896916 | BE27: 8.7315557 | BF27: 4.2804543 | BG27: 3.9409948 | BH27: 3.6632786 | BI27: 3.399987 | BJ27: 3.1473255 | BK27: 2.9054585 | BL27: 2.693941 | BM27: 6.1054643 | BN27: 5.666645 | BO27: 5.2455425 | BP27: 4.8424308 | BQ27: 4.4899016 | BR27: 15.654072 | BS27: 13.109089 | BT27: 11.002414 | BU27: 9.2182471 | BV27: 7.8015883 | BW27: 15.654072 | BX27: 13.109089 | BY27: 11.002414 | BZ27: 9.2182471 | CA27: 7.8015883 | CC27: 20 | CD27: 20 | CE27: 20 | CF27: 20 | CG27: 20 | CH27: 103.9279 | CI27: 130.01874 | CJ27: 162.57321 | CK27: 192.09422 | CM27: 103.9279 | CN27: 123.82737 | CO27: 147.79383 | CP27: 174.63111 | DB27: 190.35636 | DC27: 180.30633 | DD27: 169.6049 | DE27: 159.4025 | DF27: 149.64171 | DN27: 0.88330717 | DO27: 1.0311127 | DP27: 1.2092732 | DQ27: 1.4281018 | DS27: 0.99514036 | DT27: 0.4577699 | DU27: 0.35371817 | DV27: 0.30565675 | DW27: 1.538626 | DX27: 1.8458865 | DY27: 2.2154656 | DZ27: 2.6304008 | EA27: -0.1294569 | EB27: -0.1050972 | EC27: -0.1680508 | ED27: 0.080465498 | EE27: 0.042332788 | EF27: 0.12279829 | EG27: 0.084830051 | EH27: 0.20762834 | EI27: 0.14608983 | EJ27: 0.35371817 | EK27: 0.08031836 | EL27: 0.1930528
B28: SU FP | C28: 2 | D28: 46119 | F28: 256.45001 | G28: 571 | H28: -256 | I28: 4634 | K28: 4378 | L28: 150810.96 | M28: 34176 | N28: 35902 | O28: 38153 | P28: 40152 | Q28: 43106.592 | R28: 47244.825 | S28: 51166.145 | T28: 54594.277 | U28: 57596.962 | V28: 0.40601592 | W28: 0.41813827 | X28: 0.42638849 | Y28: 0.42077605 | Z28: 0.42327605 | AA28: 0.42577605 | AB28: 0.42827605 | AC28: 0.43077605 | AD28: 0.43327605 | AE28: 13876 | AF28: 15012 | AG28: 16268 | AH28: 16895 | AI28: 18245.988 | AJ28: 20115.715 | AK28: 21913.235 | AL28: 23517.907 | AM28: 24955.384 | AN28: 7.3353245 | AO28: 7.4291706 | AP28: 8.4292358 | AQ28: 8.7645962 | AR28: 10.118098 | AS28: 11.686461 | AT28: 13.168168 | AU28: 14.56301 | AV28: 15.956887 | AW28: 7.3353245 | AX28: 7.4291706 | AY28: 8.4292358 | AZ28: 8.7645962 | BA28: 10.118098 | BB28: 11.686461 | BC28: 13.168168 | BD28: 14.56301 | BE28: 15.956887 | BF28: 3.9527942 | BG28: 3.7560011 | BH28: 3.498559 | BI28: 3.1921159 | BJ28: 2.9474754 | BK28: 2.762395 | BL28: 2.6183839 | BM28: 8.2654311 | BN28: 7.4971711 | BO28: 6.882186 | BP28: 6.4126011 | BQ28: 6.0432232 | BW28: 25.345673 | BX28: 21.944199 | BY28: 19.474995 | BZ28: 17.609684 | CA28: 16.071431 | CB28: Mendo EPS | CC28: 22 | CD28: 22 | CE28: 22 | CF28: 22 | CG28: 22 | CM28: 257.10213 | CN28: 289.69971 | CO28: 320.38623 | CP28: 351.05152 | DB28: 569.085 | DC28: 569.085 | DD28: 569.085 | DE28: 569.085 | DF28: 569.085 | DN28: 4.2 | DO28: 5.1394414 | DP28: 5.813801 | DQ28: 6.420532 | DR28: 7.0160968 | DS28: 0.020564085 | DT28: 0.095899986 | DU28: 0.10606152 | DV28: 0.1074391 | DW28: 1.0189203 | DX28: 1.1660719 | DY28: 1.3084011 | DZ28: 1.4530134 | EA28: -0.07949038 | EB28: -0.01098903 | EC28: 0.1289613 | ED28: 0.079493751 | EE28: 0.044781166 | EF28: 0.12427492 | EG28: 0.021355512 | EH28: 0.14563043 | EI28: -0.039568904 | EJ28: 0.10606152 | EK28: 0.088287802 | EL28: 0.12906105
B29: SPGI | C29: 1 | D29: 46057 | F29: 416.60999 | G29: 304.1025 | H29: -1847 | I29: 11388 | K29: 9541 | L29: 136233.14 | M29: 11843 | N29: 12497 | O29: 14208 | P29: 15336 | Q29: 16719.285 | R29: 18035.782 | S29: 19461.908 | T29: 21007.252 | U29: 22682.276 | V29: 0.7 | W29: 0.7 | X29: 0.7 | Y29: 0.7 | Z29: 0.7 | AA29: 0.7 | AB29: 0.7 | AC29: 0.7 | AD29: 0.7 | AE29: 8290.1 | AF29: 8747.9 | AG29: 9945.6 | AH29: 10735.2 | AI29: 11703.5 | AJ29: 12625.048 | AK29: 13623.336 | AL29: 14705.077 | AM29: 15877.593 | AN29: 11.77394 | AO29: 12.599561 | AP29: 15.703751 | AQ29: 18.021314 | AR29: 20.193227 | AS29: 22.779021 | AT29: 25.648626 | AU29: 28.872377 | AV29: 32.492214 | AW29: 11.77394 | AX29: 12.599561 | AY29: 15.703751 | AZ29: 18.021314 | BA29: 20.193227 | BB29: 22.779021 | BC29: 25.648626 | BD29: 28.872377 | BE29: 32.492214 | BF29: 9.588481 | BG29: 8.883225 | BH29: 8.1482633 | BI29: 7.553492 | BJ29: 6.9999887 | BK29: 6.4850527 | BL29: 6.0061493 | BM29: 10.476338 | BN29: 9.7116325 | BO29: 8.9999855 | BP29: 8.337925 | BQ29: 7.722192 | BR29: 20.631175 | BS29: 18.289197 | BT29: 16.242975 | BU29: 14.429362 | BV29: 12.82184 | BW29: 20.631175 | BX29: 18.289197 | BY29: 16.242975 | BZ29: 14.429362 | CA29: 12.82184 | CC29: 22 | CD29: 22 | CE29: 22 | CF29: 22 | CG29: 24.5 | CM29: 501.13845 | CN29: 564.26976 | CO29: 635.19228 | CP29: 714.82871 | DB29: 293.77509 | DC29: 283.34014 | DD29: 273.34107 | DE29: 263.77859 | DF29: 254.64132 | DN29: 4.0704 | DO29: 4.314624 | DP29: 4.5735014 | DQ29: 4.8479115 | DR29: 5.1387862 | DS29: 0.35859649 | DT29: 0.21507256 | DU29: 0.18273635 | DV29: 0.16811189 | DW29: 1.2126662 | DX29: 1.3745585 | DY29: 1.5557736 | DZ29: 1.7585636 | EA29: -0.05858962 | EB29: -7.203165e-05 | EC29: -0.1511002 | ED29: 0.078839713 | EE29: 0.0074883845 | EF29: 0.086328097 | EG29: 0.049953424 | EH29: 0.13628152 | EI29: 0.046454825 | EJ29: 0.18273635 | EK29: 0.079072223 | EL29: 0.12657196
